Workbook

Sheet Start here
B2: paid in yellow · Paycheck Payoff Planner
B3: Your debt-free date, and a clear amount to move every payday. One paycheck at a time.
B5: How it works
B6: 1. Setup: how often you're paid, your next payday, and how much you can put toward the plan each payday.
B7: 2. Debts: one row per debt (up to 50): balance, interest rate, monthly minimum and due day. The due day is on your statement.
B8: 3. This payday: the exact amounts to move this payday, debt by debt. Pay them, then type Paid on that row of the Plan tab.
B9: 4. Progress: your debt-free date, what you've paid off, and the interest you avoid compared with paying only minimums.
B11: The cells to fill in
B12: White cells with a dark border are yours to type in. Everything else does the math. The example numbers are there to show the format: replace them with yours.
B14: How the plan pays
B15: Every debt gets its full monthly minimum on the payday before its due date. Your money for the plan fills your yearly bills, then your buffer, then goes to one debt at a time.
B16: When a debt is gone, its minimum keeps going: it joins the extra for the next debt. Balances only move by what you actually pay, plus interest.
... B31: one paycheck at a time

Sheet Setup
B2: Setup
B3: Fill in the white cells. You can change them any time.
B5: Currency symbol | C5: $ | E5: Any symbol: $, £, €, MAD...
B7: How often you're paid | C7: Every 2 weeks | E7: Every week · Every 2 weeks · Twice a month · Every month
B8: Your next payday | C8: 46325 | E8: The plan starts on this payday.
B9: Twice a month only: your other pay day | E9: For example 15, or 31 for the last day. Leave empty to use the usual pairing.
B11: Money for the plan each payday (on top of minimums) | C11: 100 | E11: Even 20 matters. You can change it any time.
B13: Buffer: set aside now | C13: 300 | E13: Money for surprises. Empty is fine.
B14: Buffer goal | C14: 500 | E14: A plain separate account or an envelope.
B16: Payoff order | C16: PaidInYellow order | E16: PaidInYellow order (smallest first, growing debts first) · Biggest interest first · My own order
B18: Yearly bills (optional)
B19: Bills that come once a year, saved a little each payday.
B20: Bill | C20: Per year | D20: Month needed
B21: Gifts and holidays | C21: 240 | D21: December
B32: Total per year | C32: =SUM(C21:C30) -> 240
B35: Worked out for you
B36: Paydays per year | C36: =IF(C7="Every week",52,IF(C7="Every 2 weeks",26,IF(C7="Twice a month",24,12))) -> 26
B37: Yearly bills per payday | C37: =C32/C36 -> 9.2307692
B38: Other pay day used | C38: =IF(C9>0,C9,IF(DAY(C8)<=15,DAY(C8)+15,IF(DAY(C8)=DAY(EOMONTH(C8,0)),15,DAY(C8)-15))) -> 15
B39: First pay day of the month | C39: =MIN(DAY(C8),C38) -> 15
B40: Second pay day of the month | C40: =MAX(DAY(C8),C38) -> 30
B41: Plan starts on the second one | C41: =IF(DAY(C8)=C39,0,1) -> 1

Sheet Debts
B2: Debts
B3: One row per debt. Balance, rate and minimum are on your statement. Due day is the day of the month it's due.
A5: # | B5: Name | C5: Type | D5: Balance | E5: Rate % | F5: Monthly minimum | G5: Due day | H5: My order | I5: Grows? | J5: Sort key | K5: Order | L5: Gone by | M5: Status | N5: Minimums only: months | O5: Minimums only: interest
A6: 1 | B6: Card A | C6: Credit card | D6: 500 | E6: 24 | F6: 25 | G6: 10 | I6: =IF(AND(D6>0,E6>0,F6<=D6*E6/1200),"Grows","") | J6: =IF(N(D6)<=0,5000000000000000,IF(Setup!$C$16="Biggest interest first",ROUND((100-E6)*1000,0)*10000000000+ROUND(D6*100,0),IF(Setup!$C$16="My own order",IF(H6>0,H6,999),IF(I6="Grows",ROUND((100-E6)*1000,0),1000000+ROUND(D6*100,0))))) -> 1050000 | K6: =COUNTIF($J$6:$J$55,"<"&J6)+COUNTIFS($J$6:$J$55,J6,$A$6:$A$55,"<"&A6)+1 -> 1 | L6: =IF(N(D6)<=0,"",IFERROR(INDEX(Plan!$B$9:$B$528,COUNTIF(INDEX(BalBlock,0,K6),">0.005")+1),"More than 20 years")) -> 46423 | M6: =IF(N(D6)<=0,"",IF(INDEX(BalNow,1,K6)<0.005,"PAID","")) | N6: =IF(N(D6)<=0,"",IF(N(F6)<=0,"Never ends",IF(AND(E6>0,F6<=D6*E6/1200),"Never ends",IF(N(E6)=0,D6/F6,NPER(E6/1200,-F6,D6))))) -> 25.795851 | O6: =IF(ISNUMBER(N6),F6*N6-D6,"") -> 144.89628
A7: 2 | B7: Card B | C7: Credit card | D7: 1200 | E7: 18 | F7: 40 | G7: 20 | I7: =IF(AND(D7>0,E7>0,F7<=D7*E7/1200),"Grows","") | J7: =IF(N(D7)<=0,5000000000000000,IF(Setup!$C$16="Biggest interest first",ROUND((100-E7)*1000,0)*10000000000+ROUND(D7*100,0),IF(Setup!$C$16="My own order",IF(H7>0,H7,999),IF(I7="Grows",ROUND((100-E7)*1000,0),1000000+ROUND(D7*100,0))))) -> 1120000 | K7: =COUNTIF($J$6:$J$55,"<"&J7)+COUNTIFS($J$6:$J$55,J7,$A$6:$A$55,"<"&A7)+1 -> 2 | L7: =IF(N(D7)<=0,"",IFERROR(INDEX(Plan!$B$9:$B$528,COUNTIF(INDEX(BalBlock,0,K7),">0.005")+1),"More than 20 years")) -> 46549 | M7: =IF(N(D7)<=0,"",IF(INDEX(BalNow,1,K7)<0.005,"PAID","")) | N7: =IF(N(D7)<=0,"",IF(N(F7)<=0,"Never ends",IF(AND(E7>0,F7<=D7*E7/1200),"Never ends",IF(N(E7)=0,D7/F7,NPER(E7/1200,-F7,D7))))) -> 40.153977 | O7: =IF(ISNUMBER(N7),F7*N7-D7,"") -> 406.15907
A8: 3 | I8: =IF(AND(D8>0,E8>0,F8<=D8*E8/1200),"Grows","") | J8: =IF(N(D8)<=0,5000000000000000,IF(Setup!$C$16="Biggest interest first",ROUND((100-E8)*1000,0)*10000000000+ROUND(D8*100,0),IF(Setup!$C$16="My own order",IF(H8>0,H8,999),IF(I8="Grows",ROUND((100-E8)*1000,0),1000000+ROUND(D8*100,0))))) -> 5e+15 | K8: =COUNTIF($J$6:$J$55,"<"&J8)+COUNTIFS($J$6:$J$55,J8,$A$6:$A$55,"<"&A8)+1 -> 3 | L8: =IF(N(D8)<=0,"",IFERROR(INDEX(Plan!$B$9:$B$528,COUNTIF(INDEX(BalBlock,0,K8),">0.005")+1),"More than 20 years")) | M8: =IF(N(D8)<=0,"",IF(INDEX(BalNow,1,K8)<0.005,"PAID","")) | N8: =IF(N(D8)<=0,"",IF(N(F8)<=0,"Never ends",IF(AND(E8>0,F8<=D8*E8/1200),"Never ends",IF(N(E8)=0,D8/F8,NPER(E8/1200,-F8,D8))))) | O8: =IF(ISNUMBER(N8),F8*N8-D8,"")
A9: 4 | I9: =IF(AND(D9>0,E9>0,F9<=D9*E9/1200),"Grows","") | J9: =IF(N(D9)<=0,5000000000000000,IF(Setup!$C$16="Biggest interest first",ROUND((100-E9)*1000,0)*10000000000+ROUND(D9*100,0),IF(Setup!$C$16="My own order",IF(H9>0,H9,999),IF(I9="Grows",ROUND((100-E9)*1000,0),1000000+ROUND(D9*100,0))))) -> 5e+15 | K9: =COUNTIF($J$6:$J$55,"<"&J9)+COUNTIFS($J$6:$J$55,J9,$A$6:$A$55,"<"&A9)+1 -> 4 | L9: =IF(N(D9)<=0,"",IFERROR(INDEX(Plan!$B$9:$B$528,COUNTIF(INDEX(BalBlock,0,K9),">0.005")+1),"More than 20 years")) | M9: =IF(N(D9)<=0,"",IF(INDEX(BalNow,1,K9)<0.005,"PAID","")) | N9: =IF(N(D9)<=0,"",IF(N(F9)<=0,"Never ends",IF(AND(E9>0,F9<=D9*E9/1200),"Never ends",IF(N(E9)=0,D9/F9,NPER(E9/1200,-F9,D9))))) | O9: =IF(ISNUMBER(N9),F9*N9-D9,"")
A10: 5 | I10: =IF(AND(D10>0,E10>0,F10<=D10*E10/1200),"Grows","") | J10: =IF(N(D10)<=0,5000000000000000,IF(Setup!$C$16="Biggest interest first",ROUND((100-E10)*1000,0)*10000000000+ROUND(D10*100,0),IF(Setup!$C$16="My own order",IF(H10>0,H10,999),IF(I10="Grows",ROUND((100-E10)*1000,0),1000000+ROUND(D10*100,0))))) -> 5e+15 | K10: =COUNTIF($J$6:$J$55,"<"&J10)+COUNTIFS($J$6:$J$55,J10,$A$6:$A$55,"<"&A10)+1 -> 5 | L10: =IF(N(D10)<=0,"",IFERROR(INDEX(Plan!$B$9:$B$528,COUNTIF(INDEX(BalBlock,0,K10),">0.005")+1),"More than 20 years")) | M10: =IF(N(D10)<=0,"",IF(INDEX(BalNow,1,K10)<0.005,"PAID","")) | N10: =IF(N(D10)<=0,"",IF(N(F10)<=0,"Never ends",IF(AND(E10>0,F10<=D10*E10/1200),"Never ends",IF(N(E10)=0,D10/F10,NPER(E10/1200,-F10,D10))))) | O10: =IF(ISNUMBER(N10),F10*N10-D10,"")
A11: 6 | I11: =IF(AND(D11>0,E11>0,F11<=D11*E11/1200),"Grows","") | J11: =IF(N(D11)<=0,5000000000000000,IF(Setup!$C$16="Biggest interest first",ROUND((100-E11)*1000,0)*10000000000+ROUND(D11*100,0),IF(Setup!$C$16="My own order",IF(H11>0,H11,999),IF(I11="Grows",ROUND((100-E11)*1000,0),1000000+ROUND(D11*100,0))))) -> 5e+15 | K11: =COUNTIF($J$6:$J$55,"<"&J11)+COUNTIFS($J$6:$J$55,J11,$A$6:$A$55,"<"&A11)+1 -> 6 | L11: =IF(N(D11)<=0,"",IFERROR(INDEX(Plan!$B$9:$B$528,COUNTIF(INDEX(BalBlock,0,K11),">0.005")+1),"More than 20 years")) | M11: =IF(N(D11)<=0,"",IF(INDEX(BalNow,1,K11)<0.005,"PAID","")) | N11: =IF(N(D11)<=0,"",IF(N(F11)<=0,"Never ends",IF(AND(E11>0,F11<=D11*E11/1200),"Never ends",IF(N(E11)=0,D11/F11,NPER(E11/1200,-F11,D11))))) | O11: =IF(ISNUMBER(N11),F11*N11-D11,"")
A12: 7 | I12: =IF(AND(D12>0,E12>0,F12<=D12*E12/1200),"Grows","") | J12: =IF(N(D12)<=0,5000000000000000,IF(Setup!$C$16="Biggest interest first",ROUND((100-E12)*1000,0)*10000000000+ROUND(D12*100,0),IF(Setup!$C$16="My own order",IF(H12>0,H12,999),IF(I12="Grows",ROUND((100-E12)*1000,0),1000000+ROUND(D12*100,0))))) -> 5e+15 | K12: =COUNTIF($J$6:$J$55,"<"&J12)+COUNTIFS($J$6:$J$55,J12,$A$6:$A$55,"<"&A12)+1 -> 7 | L12: =IF(N(D12)<=0,"",IFERROR(INDEX(Plan!$B$9:$B$528,COUNTIF(INDEX(BalBlock,0,K12),">0.005")+1),"More than 20 years")) | M12: =IF(N(D12)<=0,"",IF(INDEX(BalNow,1,K12)<0.005,"PAID","")) | N12: =IF(N(D12)<=0,"",IF(N(F12)<=0,"Never ends",IF(AND(E12>0,F12<=D12*E12/1200),"Never ends",IF(N(E12)=0,D12/F12,NPER(E12/1200,-F12,D12))))) | O12: =IF(ISNUMBER(N12),F12*N12-D12,"")
A13: 8 | I13: =IF(AND(D13>0,E13>0,F13<=D13*E13/1200),"Grows","") | J13: =IF(N(D13)<=0,5000000000000000,IF(Setup!$C$16="Biggest interest first",ROUND((100-E13)*1000,0)*10000000000+ROUND(D13*100,0),IF(Setup!$C$16="My own order",IF(H13>0,H13,999),IF(I13="Grows",ROUND((100-E13)*1000,0),1000000+ROUND(D13*100,0))))) -> 5e+15 | K13: =COUNTIF($J$6:$J$55,"<"&J13)+COUNTIFS($J$6:$J$55,J13,$A$6:$A$55,"<"&A13)+1 -> 8 | L13: =IF(N(D13)<=0,"",IFERROR(INDEX(Plan!$B$9:$B$528,COUNTIF(INDEX(BalBlock,0,K13),">0.005")+1),"More than 20 years")) | M13: =IF(N(D13)<=0,"",IF(INDEX(BalNow,1,K13)<0.005,"PAID","")) | N13: =IF(N(D13)<=0,"",IF(N(F13)<=0,"Never ends",IF(AND(E13>0,F13<=D13*E13/1200),"Never ends",IF(N(E13)=0,D13/F13,NPER(E13/1200,-F13,D13))))) | O13: =IF(ISNUMBER(N13),F13*N13-D13,"")
A14: 9 | I14: =IF(AND(D14>0,E14>0,F14<=D14*E14/1200),"Grows","") | J14: =IF(N(D14)<=0,5000000000000000,IF(Setup!$C$16="Biggest interest first",ROUND((100-E14)*1000,0)*10000000000+ROUND(D14*100,0),IF(Setup!$C$16="My own order",IF(H14>0,H14,999),IF(I14="Grows",ROUND((100-E14)*1000,0),1000000+ROUND(D14*100,0))))) -> 5e+15 | K14: =COUNTIF($J$6:$J$55,"<"&J14)+COUNTIFS($J$6:$J$55,J14,$A$6:$A$55,"<"&A14)+1 -> 9 | L14: =IF(N(D14)<=0,"",IFERROR(INDEX(Plan!$B$9:$B$528,COUNTIF(INDEX(BalBlock,0,K14),">0.005")+1),"More than 20 years")) | M14: =IF(N(D14)<=0,"",IF(INDEX(BalNow,1,K14)<0.005,"PAID","")) | N14: =IF(N(D14)<=0,"",IF(N(F14)<=0,"Never ends",IF(AND(E14>0,F14<=D14*E14/1200),"Never ends",IF(N(E14)=0,D14/F14,NPER(E14/1200,-F14,D14))))) | O14: =IF(ISNUMBER(N14),F14*N14-D14,"")
A15: 10 | I15: =IF(AND(D15>0,E15>0,F15<=D15*E15/1200),"Grows","") | J15: =IF(N(D15)<=0,5000000000000000,IF(Setup!$C$16="Biggest interest first",ROUND((100-E15)*1000,0)*10000000000+ROUND(D15*100,0),IF(Setup!$C$16="My own order",IF(H15>0,H15,999),IF(I15="Grows",ROUND((100-E15)*1000,0),1000000+ROUND(D15*100,0))))) -> 5e+15 | K15: =COUNTIF($J$6:$J$55,"<"&J15)+COUNTIFS($J$6:$J$55,J15,$A$6:$A$55,"<"&A15)+1 -> 10 | L15: =IF(N(D15)<=0,"",IFERROR(INDEX(Plan!$B$9:$B$528,COUNTIF(INDEX(BalBlock,0,K15),">0.005")+1),"More than 20 years")) | M15: =IF(N(D15)<=0,"",IF(INDEX(BalNow,1,K15)<0.005,"PAID","")) | N15: =IF(N(D15)<=0,"",IF(N(F15)<=0,"Never ends",IF(AND(E15>0,F15<=D15*E15/1200),"Never ends",IF(N(E15)=0,D15/F15,NPER(E15/1200,-F15,D15))))) | O15: =IF(ISNUMBER(N15),F15*N15-D15,"")
A16: 11 | I16: =IF(AND(D16>0,E16>0,F16<=D16*E16/1200),"Grows","") | J16: =IF(N(D16)<=0,5000000000000000,IF(Setup!$C$16="Biggest interest first",ROUND((100-E16)*1000,0)*10000000000+ROUND(D16*100,0),IF(Setup!$C$16="My own order",IF(H16>0,H16,999),IF(I16="Grows",ROUND((100-E16)*1000,0),1000000+ROUND(D16*100,0))))) -> 5e+15 | K16: =COUNTIF($J$6:$J$55,"<"&J16)+COUNTIFS($J$6:$J$55,J16,$A$6:$A$55,"<"&A16)+1 -> 11 | L16: =IF(N(D16)<=0,"",IFERROR(INDEX(Plan!$B$9:$B$528,COUNTIF(INDEX(BalBlock,0,K16),">0.005")+1),"More than 20 years")) | M16: =IF(N(D16)<=0,"",IF(INDEX(BalNow,1,K16)<0.005,"PAID","")) | N16: =IF(N(D16)<=0,"",IF(N(F16)<=0,"Never ends",IF(AND(E16>0,F16<=D16*E16/1200),"Never ends",IF(N(E16)=0,D16/F16,NPER(E16/1200,-F16,D16))))) | O16: =IF(ISNUMBER(N16),F16*N16-D16,"")
A17: 12 | I17: =IF(AND(D17>0,E17>0,F17<=D17*E17/1200),"Grows","") | J17: =IF(N(D17)<=0,5000000000000000,IF(Setup!$C$16="Biggest interest first",ROUND((100-E17)*1000,0)*10000000000+ROUND(D17*100,0),IF(Setup!$C$16="My own order",IF(H17>0,H17,999),IF(I17="Grows",ROUND((100-E17)*1000,0),1000000+ROUND(D17*100,0))))) -> 5e+15 | K17: =COUNTIF($J$6:$J$55,"<"&J17)+COUNTIFS($J$6:$J$55,J17,$A$6:$A$55,"<"&A17)+1 -> 12 | L17: =IF(N(D17)<=0,"",IFERROR(INDEX(Plan!$B$9:$B$528,COUNTIF(INDEX(BalBlock,0,K17),">0.005")+1),"More than 20 years")) | M17: =IF(N(D17)<=0,"",IF(INDEX(BalNow,1,K17)<0.005,"PAID","")) | N17: =IF(N(D17)<=0,"",IF(N(F17)<=0,"Never ends",IF(AND(E17>0,F17<=D17*E17/1200),"Never ends",IF(N(E17)=0,D17/F17,NPER(E17/1200,-F17,D17))))) | O17: =IF(ISNUMBER(N17),F17*N17-D17,"")
A18: 13 | I18: =IF(AND(D18>0,E18>0,F18<=D18*E18/1200),"Grows","") | J18: =IF(N(D18)<=0,5000000000000000,IF(Setup!$C$16="Biggest interest first",ROUND((100-E18)*1000,0)*10000000000+ROUND(D18*100,0),IF(Setup!$C$16="My own order",IF(H18>0,H18,999),IF(I18="Grows",ROUND((100-E18)*1000,0),1000000+ROUND(D18*100,0))))) -> 5e+15 | K18: =COUNTIF($J$6:$J$55,"<"&J18)+COUNTIFS($J$6:$J$55,J18,$A$6:$A$55,"<"&A18)+1 -> 13 | L18: =IF(N(D18)<=0,"",IFERROR(INDEX(Plan!$B$9:$B$528,COUNTIF(INDEX(BalBlock,0,K18),">0.005")+1),"More than 20 years")) | M18: =IF(N(D18)<=0,"",IF(INDEX(BalNow,1,K18)<0.005,"PAID","")) | N18: =IF(N(D18)<=0,"",IF(N(F18)<=0,"Never ends",IF(AND(E18>0,F18<=D18*E18/1200),"Never ends",IF(N(E18)=0,D18/F18,NPER(E18/1200,-F18,D18))))) | O18: =IF(ISNUMBER(N18),F18*N18-D18,"")
A19: 14 | I19: =IF(AND(D19>0,E19>0,F19<=D19*E19/1200),"Grows","") | J19: =IF(N(D19)<=0,5000000000000000,IF(Setup!$C$16="Biggest interest first",ROUND((100-E19)*1000,0)*10000000000+ROUND(D19*100,0),IF(Setup!$C$16="My own order",IF(H19>0,H19,999),IF(I19="Grows",ROUND((100-E19)*1000,0),1000000+ROUND(D19*100,0))))) -> 5e+15 | K19: =COUNTIF($J$6:$J$55,"<"&J19)+COUNTIFS($J$6:$J$55,J19,$A$6:$A$55,"<"&A19)+1 -> 14 | L19: =IF(N(D19)<=0,"",IFERROR(INDEX(Plan!$B$9:$B$528,COUNTIF(INDEX(BalBlock,0,K19),">0.005")+1),"More than 20 years")) | M19: =IF(N(D19)<=0,"",IF(INDEX(BalNow,1,K19)<0.005,"PAID","")) | N19: =IF(N(D19)<=0,"",IF(N(F19)<=0,"Never ends",IF(AND(E19>0,F19<=D19*E19/1200),"Never ends",IF(N(E19)=0,D19/F19,NPER(E19/1200,-F19,D19))))) | O19: =IF(ISNUMBER(N19),F19*N19-D19,"")
... A55: 50 | I55: =IF(AND(D55>0,E55>0,F55<=D55*E55/1200),"Grows","") | J55: =IF(N(D55)<=0,5000000000000000,IF(Setup!$C$16="Biggest interest first",ROUND((100-E55)*1000,0)*10000000000+ROUND(D55*100,0),IF(Setup!$C$16="My own order",IF(H55>0,H55,999),IF(I55="Grows",ROUND((100-E55)*1000,0),1000000+ROUND(D55*100,0))))) -> 5e+15 | K55: =COUNTIF($J$6:$J$55,"<"&J55)+COUNTIFS($J$6:$J$55,J55,$A$6:$A$55,"<"&A55)+1 -> 50 | L55: =IF(N(D55)<=0,"",IFERROR(INDEX(Plan!$B$9:$B$528,COUNTIF(INDEX(BalBlock,0,K55),">0.005")+1),"More than 20 years")) | M55: =IF(N(D55)<=0,"",IF(INDEX(BalNow,1,K55)<0.005,"PAID","")) | N55: =IF(N(D55)<=0,"",IF(N(F55)<=0,"Never ends",IF(AND(E55>0,F55<=D55*E55/1200),"Never ends",IF(N(E55)=0,D55/F55,NPER(E55/1200,-F55,D55))))) | O55: =IF(ISNUMBER(N55),F55*N55-D55,"")
B57: Total | D57: =SUM(D6:D55) -> 1700 | F57: =SUM(F6:F55) -> 65

Sheet This payday
H1: row | I1: =IFERROR(MATCH(1,Plan!$W$9:$W$528,0),0) -> 1
B2: This payday | I2: =IF(I1=0,0,INDEX(Plan!$A$9:$A$528,I1)) -> 1
B3: =IF($I$1=0,IF(Plan!$T$528<0.005,"You're debt-free. Keep your buffer and yearly bills going.","All planned paydays are marked Paid."),"Payday "&TEXT(INDEX(Plan!$B$9:$B$528,$I$1),"ddd d mmm yyyy")) -> Payday Fri 30 Oct 2026
B5: MOVE
B6: =IF($I$1=0,"",Setup!$C$5&TEXT(INDEX(Plan!$R$9:$R$528,$I$1),"#,##0")) -> $125
B8: =IF($I$1=0,"",IF(INDEX(Plan!$Q$9:$Q$528,$I$1)>0.005,"The extra "&Setup!$C$5&TEXT(INDEX(Plan!$Q$9:$Q$528,$I$1),"#,##0")&" goes to "&INDEX(Plan!$U$9:$U$528,$I$1)&".",IF(INDEX(Plan!$K$9:$K$528,$I$1)>0.005,"Your buffer fills first. Extra for your debts starts once it reaches "&Setup!$C$5&TEXT(Setup!$C$14,"#,##0")&".",""))) -> Your buffer fills first. Extra for your debts starts once it reaches $500.
B10: What | C10: Bill | D10: Extra | E10: Due | F10: Total
B11: =IFERROR(INDEX(Helpers!$C$2:$C$51,MATCH(1,$C$64:$AZ$64,0)),"") -> Card A | C11: =IFERROR(INDEX($C$61:$AZ$61,MATCH(1,$C$64:$AZ$64,0)),"") -> 25 | D11: =IFERROR(INDEX($C$62:$AZ$62,MATCH(1,$C$64:$AZ$64,0)),"") -> 0 | E11: =IFERROR(INDEX($C$65:$AZ$65,MATCH(1,$C$64:$AZ$64,0)),"") -> 46336 | F11: =IF(B11="","",N(C11)+N(D11)) -> 25
B12: =IFERROR(INDEX(Helpers!$C$2:$C$51,MATCH(2,$C$64:$AZ$64,0)),"") | C12: =IFERROR(INDEX($C$61:$AZ$61,MATCH(2,$C$64:$AZ$64,0)),"") | D12: =IFERROR(INDEX($C$62:$AZ$62,MATCH(2,$C$64:$AZ$64,0)),"") | E12: =IFERROR(INDEX($C$65:$AZ$65,MATCH(2,$C$64:$AZ$64,0)),"") | F12: =IF(B12="","",N(C12)+N(D12))
B13: =IFERROR(INDEX(Helpers!$C$2:$C$51,MATCH(3,$C$64:$AZ$64,0)),"") | C13: =IFERROR(INDEX($C$61:$AZ$61,MATCH(3,$C$64:$AZ$64,0)),"") | D13: =IFERROR(INDEX($C$62:$AZ$62,MATCH(3,$C$64:$AZ$64,0)),"") | E13: =IFERROR(INDEX($C$65:$AZ$65,MATCH(3,$C$64:$AZ$64,0)),"") | F13: =IF(B13="","",N(C13)+N(D13))
B14: =IFERROR(INDEX(Helpers!$C$2:$C$51,MATCH(4,$C$64:$AZ$64,0)),"") | C14: =IFERROR(INDEX($C$61:$AZ$61,MATCH(4,$C$64:$AZ$64,0)),"") | D14: =IFERROR(INDEX($C$62:$AZ$62,MATCH(4,$C$64:$AZ$64,0)),"") | E14: =IFERROR(INDEX($C$65:$AZ$65,MATCH(4,$C$64:$AZ$64,0)),"") | F14: =IF(B14="","",N(C14)+N(D14))
B15: =IFERROR(INDEX(Helpers!$C$2:$C$51,MATCH(5,$C$64:$AZ$64,0)),"") | C15: =IFERROR(INDEX($C$61:$AZ$61,MATCH(5,$C$64:$AZ$64,0)),"") | D15: =IFERROR(INDEX($C$62:$AZ$62,MATCH(5,$C$64:$AZ$64,0)),"") | E15: =IFERROR(INDEX($C$65:$AZ$65,MATCH(5,$C$64:$AZ$64,0)),"") | F15: =IF(B15="","",N(C15)+N(D15))
B16: =IFERROR(INDEX(Helpers!$C$2:$C$51,MATCH(6,$C$64:$AZ$64,0)),"") | C16: =IFERROR(INDEX($C$61:$AZ$61,MATCH(6,$C$64:$AZ$64,0)),"") | D16: =IFERROR(INDEX($C$62:$AZ$62,MATCH(6,$C$64:$AZ$64,0)),"") | E16: =IFERROR(INDEX($C$65:$AZ$65,MATCH(6,$C$64:$AZ$64,0)),"") | F16: =IF(B16="","",N(C16)+N(D16))
B17: =IFERROR(INDEX(Helpers!$C$2:$C$51,MATCH(7,$C$64:$AZ$64,0)),"") | C17: =IFERROR(INDEX($C$61:$AZ$61,MATCH(7,$C$64:$AZ$64,0)),"") | D17: =IFERROR(INDEX($C$62:$AZ$62,MATCH(7,$C$64:$AZ$64,0)),"") | E17: =IFERROR(INDEX($C$65:$AZ$65,MATCH(7,$C$64:$AZ$64,0)),"") | F17: =IF(B17="","",N(C17)+N(D17))
B18: =IFERROR(INDEX(Helpers!$C$2:$C$51,MATCH(8,$C$64:$AZ$64,0)),"") | C18: =IFERROR(INDEX($C$61:$AZ$61,MATCH(8,$C$64:$AZ$64,0)),"") | D18: =IFERROR(INDEX($C$62:$AZ$62,MATCH(8,$C$64:$AZ$64,0)),"") | E18: =IFERROR(INDEX($C$65:$AZ$65,MATCH(8,$C$64:$AZ$64,0)),"") | F18: =IF(B18="","",N(C18)+N(D18))
B19: =IFERROR(INDEX(Helpers!$C$2:$C$51,MATCH(9,$C$64:$AZ$64,0)),"") | C19: =IFERROR(INDEX($C$61:$AZ$61,MATCH(9,$C$64:$AZ$64,0)),"") | D19: =IFERROR(INDEX($C$62:$AZ$62,MATCH(9,$C$64:$AZ$64,0)),"") | E19: =IFERROR(INDEX($C$65:$AZ$65,MATCH(9,$C$64:$AZ$64,0)),"") | F19: =IF(B19="","",N(C19)+N(D19))
B20: =IFERROR(INDEX(Helpers!$C$2:$C$51,MATCH(10,$C$64:$AZ$64,0)),"") | C20: =IFERROR(INDEX($C$61:$AZ$61,MATCH(10,$C$64:$AZ$64,0)),"") | D20: =IFERROR(INDEX($C$62:$AZ$62,MATCH(10,$C$64:$AZ$64,0)),"") | E20: =IFERROR(INDEX($C$65:$AZ$65,MATCH(10,$C$64:$AZ$64,0)),"") | F20: =IF(B20="","",N(C20)+N(D20))
B21: =IFERROR(INDEX(Helpers!$C$2:$C$51,MATCH(11,$C$64:$AZ$64,0)),"") | C21: =IFERROR(INDEX($C$61:$AZ$61,MATCH(11,$C$64:$AZ$64,0)),"") | D21: =IFERROR(INDEX($C$62:$AZ$62,MATCH(11,$C$64:$AZ$64,0)),"") | E21: =IFERROR(INDEX($C$65:$AZ$65,MATCH(11,$C$64:$AZ$64,0)),"") | F21: =IF(B21="","",N(C21)+N(D21))
B22: =IFERROR(INDEX(Helpers!$C$2:$C$51,MATCH(12,$C$64:$AZ$64,0)),"") | C22: =IFERROR(INDEX($C$61:$AZ$61,MATCH(12,$C$64:$AZ$64,0)),"") | D22: =IFERROR(INDEX($C$62:$AZ$62,MATCH(12,$C$64:$AZ$64,0)),"") | E22: =IFERROR(INDEX($C$65:$AZ$65,MATCH(12,$C$64:$AZ$64,0)),"") | F22: =IF(B22="","",N(C22)+N(D22))
B23: =IFERROR(INDEX(Helpers!$C$2:$C$51,MATCH(13,$C$64:$AZ$64,0)),"") | C23: =IFERROR(INDEX($C$61:$AZ$61,MATCH(13,$C$64:$AZ$64,0)),"") | D23: =IFERROR(INDEX($C$62:$AZ$62,MATCH(13,$C$64:$AZ$64,0)),"") | E23: =IFERROR(INDEX($C$65:$AZ$65,MATCH(13,$C$64:$AZ$64,0)),"") | F23: =IF(B23="","",N(C23)+N(D23))
B24: =IFERROR(INDEX(Helpers!$C$2:$C$51,MATCH(14,$C$64:$AZ$64,0)),"") | C24: =IFERROR(INDEX($C$61:$AZ$61,MATCH(14,$C$64:$AZ$64,0)),"") | D24: =IFERROR(INDEX($C$62:$AZ$62,MATCH(14,$C$64:$AZ$64,0)),"") | E24: =IFERROR(INDEX($C$65:$AZ$65,MATCH(14,$C$64:$AZ$64,0)),"") | F24: =IF(B24="","",N(C24)+N(D24))
B25: =IFERROR(INDEX(Helpers!$C$2:$C$51,MATCH(15,$C$64:$AZ$64,0)),"") | C25: =IFERROR(INDEX($C$61:$AZ$61,MATCH(15,$C$64:$AZ$64,0)),"") | D25: =IFERROR(INDEX($C$62:$AZ$62,MATCH(15,$C$64:$AZ$64,0)),"") | E25: =IFERROR(INDEX($C$65:$AZ$65,MATCH(15,$C$64:$AZ$64,0)),"") | F25: =IF(B25="","",N(C25)+N(D25))
B26: =IFERROR(INDEX(Helpers!$C$2:$C$51,MATCH(16,$C$64:$AZ$64,0)),"") | C26: =IFERROR(INDEX($C$61:$AZ$61,MATCH(16,$C$64:$AZ$64,0)),"") | D26: =IFERROR(INDEX($C$62:$AZ$62,MATCH(16,$C$64:$AZ$64,0)),"") | E26: =IFERROR(INDEX($C$65:$AZ$65,MATCH(16,$C$64:$AZ$64,0)),"") | F26: =IF(B26="","",N(C26)+N(D26))
B27: Yearly bills pot | F27: =IF($I$1=0,"",INDEX(Plan!$J$9:$J$528,$I$1)) -> 9.2307692
B28: Buffer | F28: =IF($I$1=0,"",INDEX(Plan!$K$9:$K$528,$I$1)) -> 90.769231
B29: Total to move | F29: =IF($I$1=0,"",INDEX(Plan!$R$9:$R$528,$I$1)) -> 125
B31: =IF($I$1=0,"","When it's done, type Paid in column D of the Plan tab, on payday #"&$I$2&". The next payday then shows here.") -> When it's done, type Paid in column D of the Plan tab, on payday #1. The next payday then shows here.
B33: one paycheck at a time
B59: helpers
C60: =IF($I$1=0,INDEX(Plan!$FT$9:$FT$528,520),IF($I$1=1,Plan!FT$8,INDEX(Plan!$FT$9:$FT$528,$I$1-1))) -> 500 | D60: =IF($I$1=0,INDEX(Plan!$FU$9:$FU$528,520),IF($I$1=1,Plan!FU$8,INDEX(Plan!$FU$9:$FU$528,$I$1-1))) -> 1200 | E60: =IF($I$1=0,INDEX(Plan!$FV$9:$FV$528,520),IF($I$1=1,Plan!FV$8,INDEX(Plan!$FV$9:$FV$528,$I$1-1))) -> 0 | F60: =IF($I$1=0,INDEX(Plan!$FW$9:$FW$528,520),IF($I$1=1,Plan!FW$8,INDEX(Plan!$FW$9:$FW$528,$I$1-1))) -> 0 | G60: =IF($I$1=0,INDEX(Plan!$FX$9:$FX$528,520),IF($I$1=1,Plan!FX$8,INDEX(Plan!$FX$9:$FX$528,$I$1-1))) -> 0 | H60: =IF($I$1=0,INDEX(Plan!$FY$9:$FY$528,520),IF($I$1=1,Plan!FY$8,INDEX(Plan!$FY$9:$FY$528,$I$1-1))) -> 0 | I60: =IF($I$1=0,INDEX(Plan!$FZ$9:$FZ$528,520),IF($I$1=1,Plan!FZ$8,INDEX(Plan!$FZ$9:$FZ$528,$I$1-1))) -> 0 | J60: =IF($I$1=0,INDEX(Plan!$GA$9:$GA$528,520),IF($I$1=1,Plan!GA$8,INDEX(Plan!$GA$9:$GA$528,$I$1-1))) -> 0 | K60: =IF($I$1=0,INDEX(Plan!$GB$9:$GB$528,520),IF($I$1=1,Plan!GB$8,INDEX(Plan!$GB$9:$GB$528,$I$1-1))) -> 0 | L60: =IF($I$1=0,INDEX(Plan!$GC$9:$GC$528,520),IF($I$1=1,Plan!GC$8,INDEX(Plan!$GC$9:$GC$528,$I$1-1))) -> 0 | M60: =IF($I$1=0,INDEX(Plan!$GD$9:$GD$528,520),IF($I$1=1,Plan!GD$8,INDEX(Plan!$GD$9:$GD$528,$I$1-1))) -> 0 | N60: =IF($I$1=0,INDEX(Plan!$GE$9:$GE$528,520),IF($I$1=1,Plan!GE$8,INDEX(Plan!$GE$9:$GE$528,$I$1-1))) -> 0 | O60: =IF($I$1=0,INDEX(Plan!$GF$9:$GF$528,520),IF($I$1=1,Plan!GF$8,INDEX(Plan!$GF$9:$GF$528,$I$1-1))) -> 0 | P60: =IF($I$1=0,INDEX(Plan!$GG$9:$GG$528,520),IF($I$1=1,Plan!GG$8,INDEX(Plan!$GG$9:$GG$528,$I$1-1))) -> 0 | Q60: =IF($I$1=0,INDEX(Plan!$GH$9:$GH$528,520),IF($I$1=1,Plan!GH$8,INDEX(Plan!$GH$9:$GH$528,$I$1-1))) -> 0 | R60: =IF($I$1=0,INDEX(Plan!$GI$9:$GI$528,520),IF($I$1=1,Plan!GI$8,INDEX(Plan!$GI$9:$GI$528,$I$1-1))) -> 0 | S60: =IF($I$1=0,INDEX(Plan!$GJ$9:$GJ$528,520),IF($I$1=1,Plan!GJ$8,INDEX(Plan!$GJ$9:$GJ$528,$I$1-1))) -> 0 | T60: =IF($I$1=0,INDEX(Plan!$GK$9:$GK$528,520),IF($I$1=1,Plan!GK$8,INDEX(Plan!$GK$9:$GK$528,$I$1-1))) -> 0 | U60: =IF($I$1=0,INDEX(Plan!$GL$9:$GL$528,520),IF($I$1=1,Plan!GL$8,INDEX(Plan!$GL$9:$GL$528,$I$1-1))) -> 0 | V60: =IF($I$1=0,INDEX(Plan!$GM$9:$GM$528,520),IF($I$1=1,Plan!GM$8,INDEX(Plan!$GM$9:$GM$528,$I$1-1))) -> 0 | W60: =IF($I$1=0,INDEX(Plan!$GN$9:$GN$528,520),IF($I$1=1,Plan!GN$8,INDEX(Plan!$GN$9:$GN$528,$I$1-1))) -> 0 | X60: =IF($I$1=0,INDEX(Plan!$GO$9:$GO$528,520),IF($I$1=1,Plan!GO$8,INDEX(Plan!$GO$9:$GO$528,$I$1-1))) -> 0 | Y60: =IF($I$1=0,INDEX(Plan!$GP$9:$GP$528,520),IF($I$1=1,Plan!GP$8,INDEX(Plan!$GP$9:$GP$528,$I$1-1))) -> 0 | Z60: =IF($I$1=0,INDEX(Plan!$GQ$9:$GQ$528,520),IF($I$1=1,Plan!GQ$8,INDEX(Plan!$GQ$9:$GQ$528,$I$1-1))) -> 0 | AA60: =IF($I$1=0,INDEX(Plan!$GR$9:$GR$528,520),IF($I$1=1,Plan!GR$8,INDEX(Plan!$GR$9:$GR$528,$I$1-1))) -> 0 | AB60: =IF($I$1=0,INDEX(Plan!$GS$9:$GS$528,520),IF($I$1=1,Plan!GS$8,INDEX(Plan!$GS$9:$GS$528,$I$1-1))) -> 0 | AC60: =IF($I$1=0,INDEX(Plan!$GT$9:$GT$528,520),IF($I$1=1,Plan!GT$8,INDEX(Plan!$GT$9:$GT$528,$I$1-1))) -> 0 | AD60: =IF($I$1=0,INDEX(Plan!$GU$9:$GU$528,520),IF($I$1=1,Plan!GU$8,INDEX(Plan!$GU$9:$GU$528,$I$1-1))) -> 0 | AE60: =IF($I$1=0,INDEX(Plan!$GV$9:$GV$528,520),IF($I$1=1,Plan!GV$8,INDEX(Plan!$GV$9:$GV$528,$I$1-1))) -> 0 | AF60: =IF($I$1=0,INDEX(Plan!$GW$9:$GW$528,520),IF($I$1=1,Plan!GW$8,INDEX(Plan!$GW$9:$GW$528,$I$1-1))) -> 0 | AG60: =IF($I$1=0,INDEX(Plan!$GX$9:$GX$528,520),IF($I$1=1,Plan!GX$8,INDEX(Plan!$GX$9:$GX$528,$I$1-1))) -> 0 | AH60: =IF($I$1=0,INDEX(Plan!$GY$9:$GY$528,520),IF($I$1=1,Plan!GY$8,INDEX(Plan!$GY$9:$GY$528,$I$1-1))) -> 0 | AI60: =IF($I$1=0,INDEX(Plan!$GZ$9:$GZ$528,520),IF($I$1=1,Plan!GZ$8,INDEX(Plan!$GZ$9:$GZ$528,$I$1-1))) -> 0 | AJ60: =IF($I$1=0,INDEX(Plan!$HA$9:$HA$528,520),IF($I$1=1,Plan!HA$8,INDEX(Plan!$HA$9:$HA$528,$I$1-1))) -> 0 | AK60: =IF($I$1=0,INDEX(Plan!$HB$9:$HB$528,520),IF($I$1=1,Plan!HB$8,INDEX(Plan!$HB$9:$HB$528,$I$1-1))) -> 0 | AL60: =IF($I$1=0,INDEX(Plan!$HC$9:$HC$528,520),IF($I$1=1,Plan!HC$8,INDEX(Plan!$HC$9:$HC$528,$I$1-1))) -> 0 | AM60: =IF($I$1=0,INDEX(Plan!$HD$9:$HD$528,520),IF($I$1=1,Plan!HD$8,INDEX(Plan!$HD$9:$HD$528,$I$1-1))) -> 0 | AN60: =IF($I$1=0,INDEX(Plan!$HE$9:$HE$528,520),IF($I$1=1,Plan!HE$8,INDEX(Plan!$HE$9:$HE$528,$I$1-1))) -> 0 | AO60: =IF($I$1=0,INDEX(Plan!$HF$9:$HF$528,520),IF($I$1=1,Plan!HF$8,INDEX(Plan!$HF$9:$HF$528,$I$1-1))) -> 0 | AP60: =IF($I$1=0,INDEX(Plan!$HG$9:$HG$528,520),IF($I$1=1,Plan!HG$8,INDEX(Plan!$HG$9:$HG$528,$I$1-1))) -> 0 | AQ60: =IF($I$1=0,INDEX(Plan!$HH$9:$HH$528,520),IF($I$1=1,Plan!HH$8,INDEX(Plan!$HH$9:$HH$528,$I$1-1))) -> 0 | AR60: =IF($I$1=0,INDEX(Plan!$HI$9:$HI$528,520),IF($I$1=1,Plan!HI$8,INDEX(Plan!$HI$9:$HI$528,$I$1-1))) -> 0 | AS60: =IF($I$1=0,INDEX(Plan!$HJ$9:$HJ$528,520),IF($I$1=1,Plan!HJ$8,INDEX(Plan!$HJ$9:$HJ$528,$I$1-1))) -> 0 | AT60: =IF($I$1=0,INDEX(Plan!$HK$9:$HK$528,520),IF($I$1=1,Plan!HK$8,INDEX(Plan!$HK$9:$HK$528,$I$1-1))) -> 0 | AU60: =IF($I$1=0,INDEX(Plan!$HL$9:$HL$528,520),IF($I$1=1,Plan!HL$8,INDEX(Plan!$HL$9:$HL$528,$I$1-1))) -> 0 | AV60: =IF($I$1=0,INDEX(Plan!$HM$9:$HM$528,520),IF($I$1=1,Plan!HM$8,INDEX(Plan!$HM$9:$HM$528,$I$1-1))) -> 0 | AW60: =IF($I$1=0,INDEX(Plan!$HN$9:$HN$528,520),IF($I$1=1,Plan!HN$8,INDEX(Plan!$HN$9:$HN$528,$I$1-1))) -> 0 | AX60: =IF($I$1=0,INDEX(Plan!$HO$9:$HO$528,520),IF($I$1=1,Plan!HO$8,INDEX(Plan!$HO$9:$HO$528,$I$1-1))) -> 0 | AY60: =IF($I$1=0,INDEX(Plan!$HP$9:$HP$528,520),IF($I$1=1,Plan!HP$8,INDEX(Plan!$HP$9:$HP$528,$I$1-1))) -> 0 | AZ60: =IF($I$1=0,INDEX(Plan!$HQ$9:$HQ$528,520),IF($I$1=1,Plan!HQ$8,INDEX(Plan!$HQ$9:$HQ$528,$I$1-1))) -> 0
C61: =IF($I$1=0,0,INDEX(Plan!$BX$9:$BX$528,$I$1)) -> 25 | D61: =IF($I$1=0,0,INDEX(Plan!$BY$9:$BY$528,$I$1)) -> 0 | E61: =IF($I$1=0,0,INDEX(Plan!$BZ$9:$BZ$528,$I$1)) -> 0 | F61: =IF($I$1=0,0,INDEX(Plan!$CA$9:$CA$528,$I$1)) -> 0 | G61: =IF($I$1=0,0,INDEX(Plan!$CB$9:$CB$528,$I$1)) -> 0 | H61: =IF($I$1=0,0,INDEX(Plan!$CC$9:$CC$528,$I$1)) -> 0 | I61: =IF($I$1=0,0,INDEX(Plan!$CD$9:$CD$528,$I$1)) -> 0 | J61: =IF($I$1=0,0,INDEX(Plan!$CE$9:$CE$528,$I$1)) -> 0 | K61: =IF($I$1=0,0,INDEX(Plan!$CF$9:$CF$528,$I$1)) -> 0 | L61: =IF($I$1=0,0,INDEX(Plan!$CG$9:$CG$528,$I$1)) -> 0 | M61: =IF($I$1=0,0,INDEX(Plan!$CH$9:$CH$528,$I$1)) -> 0 | N61: =IF($I$1=0,0,INDEX(Plan!$CI$9:$CI$528,$I$1)) -> 0 | O61: =IF($I$1=0,0,INDEX(Plan!$CJ$9:$CJ$528,$I$1)) -> 0 | P61: =IF($I$1=0,0,INDEX(Plan!$CK$9:$CK$528,$I$1)) -> 0 | Q61: =IF($I$1=0,0,INDEX(Plan!$CL$9:$CL$528,$I$1)) -> 0 | R61: =IF($I$1=0,0,INDEX(Plan!$CM$9:$CM$528,$I$1)) -> 0 | S61: =IF($I$1=0,0,INDEX(Plan!$CN$9:$CN$528,$I$1)) -> 0 | T61: =IF($I$1=0,0,INDEX(Plan!$CO$9:$CO$528,$I$1)) -> 0 | U61: =IF($I$1=0,0,INDEX(Plan!$CP$9:$CP$528,$I$1)) -> 0 | V61: =IF($I$1=0,0,INDEX(Plan!$CQ$9:$CQ$528,$I$1)) -> 0 | W61: =IF($I$1=0,0,INDEX(Plan!$CR$9:$CR$528,$I$1)) -> 0 | X61: =IF($I$1=0,0,INDEX(Plan!$CS$9:$CS$528,$I$1)) -> 0 | Y61: =IF($I$1=0,0,INDEX(Plan!$CT$9:$CT$528,$I$1)) -> 0 | Z61: =IF($I$1=0,0,INDEX(Plan!$CU$9:$CU$528,$I$1)) -> 0 | AA61: =IF($I$1=0,0,INDEX(Plan!$CV$9:$CV$528,$I$1)) -> 0 | AB61: =IF($I$1=0,0,INDEX(Plan!$CW$9:$CW$528,$I$1)) -> 0 | AC61: =IF($I$1=0,0,INDEX(Plan!$CX$9:$CX$528,$I$1)) -> 0 | AD61: =IF($I$1=0,0,INDEX(Plan!$CY$9:$CY$528,$I$1)) -> 0 | AE61: =IF($I$1=0,0,INDEX(Plan!$CZ$9:$CZ$528,$I$1)) -> 0 | AF61: =IF($I$1=0,0,INDEX(Plan!$DA$9:$DA$528,$I$1)) -> 0 | AG61: =IF($I$1=0,0,INDEX(Plan!$DB$9:$DB$528,$I$1)) -> 0 | AH61: =IF($I$1=0,0,INDEX(Plan!$DC$9:$DC$528,$I$1)) -> 0 | AI61: =IF($I$1=0,0,INDEX(Plan!$DD$9:$DD$528,$I$1)) -> 0 | AJ61: =IF($I$1=0,0,INDEX(Plan!$DE$9:$DE$528,$I$1)) -> 0 | AK61: =IF($I$1=0,0,INDEX(Plan!$DF$9:$DF$528,$I$1)) -> 0 | AL61: =IF($I$1=0,0,INDEX(Plan!$DG$9:$DG$528,$I$1)) -> 0 | AM61: =IF($I$1=0,0,INDEX(Plan!$DH$9:$DH$528,$I$1)) -> 0 | AN61: =IF($I$1=0,0,INDEX(Plan!$DI$9:$DI$528,$I$1)) -> 0 | AO61: =IF($I$1=0,0,INDEX(Plan!$DJ$9:$DJ$528,$I$1)) -> 0 | AP61: =IF($I$1=0,0,INDEX(Plan!$DK$9:$DK$528,$I$1)) -> 0 | AQ61: =IF($I$1=0,0,INDEX(Plan!$DL$9:$DL$528,$I$1)) -> 0 | AR61: =IF($I$1=0,0,INDEX(Plan!$DM$9:$DM$528,$I$1)) -> 0 | AS61: =IF($I$1=0,0,INDEX(Plan!$DN$9:$DN$528,$I$1)) -> 0 | AT61: =IF($I$1=0,0,INDEX(Plan!$DO$9:$DO$528,$I$1)) -> 0 | AU61: =IF($I$1=0,0,INDEX(Plan!$DP$9:$DP$528,$I$1)) -> 0 | AV61: =IF($I$1=0,0,INDEX(Plan!$DQ$9:$DQ$528,$I$1)) -> 0 | AW61: =IF($I$1=0,0,INDEX(Plan!$DR$9:$DR$528,$I$1)) -> 0 | AX61: =IF($I$1=0,0,INDEX(Plan!$DS$9:$DS$528,$I$1)) -> 0 | AY61: =IF($I$1=0,0,INDEX(Plan!$DT$9:$DT$528,$I$1)) -> 0 | AZ61: =IF($I$1=0,0,INDEX(Plan!$DU$9:$DU$528,$I$1)) -> 0
C62: =IF($I$1=0,0,INDEX(Plan!$DV$9:$DV$528,$I$1)) -> 0 | D62: =IF($I$1=0,0,INDEX(Plan!$DW$9:$DW$528,$I$1)) -> 0 | E62: =IF($I$1=0,0,INDEX(Plan!$DX$9:$DX$528,$I$1)) -> 0 | F62: =IF($I$1=0,0,INDEX(Plan!$DY$9:$DY$528,$I$1)) -> 0 | G62: =IF($I$1=0,0,INDEX(Plan!$DZ$9:$DZ$528,$I$1)) -> 0 | H62: =IF($I$1=0,0,INDEX(Plan!$EA$9:$EA$528,$I$1)) -> 0 | I62: =IF($I$1=0,0,INDEX(Plan!$EB$9:$EB$528,$I$1)) -> 0 | J62: =IF($I$1=0,0,INDEX(Plan!$EC$9:$EC$528,$I$1)) -> 0 | K62: =IF($I$1=0,0,INDEX(Plan!$ED$9:$ED$528,$I$1)) -> 0 | L62: =IF($I$1=0,0,INDEX(Plan!$EE$9:$EE$528,$I$1)) -> 0 | M62: =IF($I$1=0,0,INDEX(Plan!$EF$9:$EF$528,$I$1)) -> 0 | N62: =IF($I$1=0,0,INDEX(Plan!$EG$9:$EG$528,$I$1)) -> 0 | O62: =IF($I$1=0,0,INDEX(Plan!$EH$9:$EH$528,$I$1)) -> 0 | P62: =IF($I$1=0,0,INDEX(Plan!$EI$9:$EI$528,$I$1)) -> 0 | Q62: =IF($I$1=0,0,INDEX(Plan!$EJ$9:$EJ$528,$I$1)) -> 0 | R62: =IF($I$1=0,0,INDEX(Plan!$EK$9:$EK$528,$I$1)) -> 0 | S62: =IF($I$1=0,0,INDEX(Plan!$EL$9:$EL$528,$I$1)) -> 0 | T62: =IF($I$1=0,0,INDEX(Plan!$EM$9:$EM$528,$I$1)) -> 0 | U62: =IF($I$1=0,0,INDEX(Plan!$EN$9:$EN$528,$I$1)) -> 0 | V62: =IF($I$1=0,0,INDEX(Plan!$EO$9:$EO$528,$I$1)) -> 0 | W62: =IF($I$1=0,0,INDEX(Plan!$EP$9:$EP$528,$I$1)) -> 0 | X62: =IF($I$1=0,0,INDEX(Plan!$EQ$9:$EQ$528,$I$1)) -> 0 | Y62: =IF($I$1=0,0,INDEX(Plan!$ER$9:$ER$528,$I$1)) -> 0 | Z62: =IF($I$1=0,0,INDEX(Plan!$ES$9:$ES$528,$I$1)) -> 0 | AA62: =IF($I$1=0,0,INDEX(Plan!$ET$9:$ET$528,$I$1)) -> 0 | AB62: =IF($I$1=0,0,INDEX(Plan!$EU$9:$EU$528,$I$1)) -> 0 | AC62: =IF($I$1=0,0,INDEX(Plan!$EV$9:$EV$528,$I$1)) -> 0 | AD62: =IF($I$1=0,0,INDEX(Plan!$EW$9:$EW$528,$I$1)) -> 0 | AE62: =IF($I$1=0,0,INDEX(Plan!$EX$9:$EX$528,$I$1)) -> 0 | AF62: =IF($I$1=0,0,INDEX(Plan!$EY$9:$EY$528,$I$1)) -> 0 | AG62: =IF($I$1=0,0,INDEX(Plan!$EZ$9:$EZ$528,$I$1)) -> 0 | AH62: =IF($I$1=0,0,INDEX(Plan!$FA$9:$FA$528,$I$1)) -> 0 | AI62: =IF($I$1=0,0,INDEX(Plan!$FB$9:$FB$528,$I$1)) -> 0 | AJ62: =IF($I$1=0,0,INDEX(Plan!$FC$9:$FC$528,$I$1)) -> 0 | AK62: =IF($I$1=0,0,INDEX(Plan!$FD$9:$FD$528,$I$1)) -> 0 | AL62: =IF($I$1=0,0,INDEX(Plan!$FE$9:$FE$528,$I$1)) -> 0 | AM62: =IF($I$1=0,0,INDEX(Plan!$FF$9:$FF$528,$I$1)) -> 0 | AN62: =IF($I$1=0,0,INDEX(Plan!$FG$9:$FG$528,$I$1)) -> 0 | AO62: =IF($I$1=0,0,INDEX(Plan!$FH$9:$FH$528,$I$1)) -> 0 | AP62: =IF($I$1=0,0,INDEX(Plan!$FI$9:$FI$528,$I$1)) -> 0 | AQ62: =IF($I$1=0,0,INDEX(Plan!$FJ$9:$FJ$528,$I$1)) -> 0 | AR62: =IF($I$1=0,0,INDEX(Plan!$FK$9:$FK$528,$I$1)) -> 0 | AS62: =IF($I$1=0,0,INDEX(Plan!$FL$9:$FL$528,$I$1)) -> 0 | AT62: =IF($I$1=0,0,INDEX(Plan!$FM$9:$FM$528,$I$1)) -> 0 | AU62: =IF($I$1=0,0,INDEX(Plan!$FN$9:$FN$528,$I$1)) -> 0 | AV62: =IF($I$1=0,0,INDEX(Plan!$FO$9:$FO$528,$I$1)) -> 0 | AW62: =IF($I$1=0,0,INDEX(Plan!$FP$9:$FP$528,$I$1)) -> 0 | AX62: =IF($I$1=0,0,INDEX(Plan!$FQ$9:$FQ$528,$I$1)) -> 0 | AY62: =IF($I$1=0,0,INDEX(Plan!$FR$9:$FR$528,$I$1)) -> 0 | AZ62: =IF($I$1=0,0,INDEX(Plan!$FS$9:$FS$528,$I$1)) -> 0
C63: =IF(C61+C62>0.005,1,0) -> 1 | D63: =IF(D61+D62>0.005,1,0) -> 0 | E63: =IF(E61+E62>0.005,1,0) -> 0 | F63: =IF(F61+F62>0.005,1,0) -> 0 | G63: =IF(G61+G62>0.005,1,0) -> 0 | H63: =IF(H61+H62>0.005,1,0) -> 0 | I63: =IF(I61+I62>0.005,1,0) -> 0 | J63: =IF(J61+J62>0.005,1,0) -> 0 | ... AZ63: =IF(AZ61+AZ62>0.005,1,0) -> 0
C64: =C63 -> 1 | D64: =C64+D63 -> 1 | E64: =D64+E63 -> 1 | F64: =E64+F63 -> 1 | G64: =F64+G63 -> 1 | H64: =G64+H63 -> 1 | I64: =H64+I63 -> 1 | J64: =I64+J63 -> 1 | K64: =J64+K63 -> 1 | ... AZ64: =AY64+AZ63 -> 1
C65: =IF(OR($I$1=0,Helpers!$F$2=""),"",IF(AND(DATE(YEAR(INDEX(Plan!$B$9:$B$528,$I$1)),MONTH(INDEX(Plan!$B$9:$B$528,$I$1)),MIN(Helpers!$F$2,DAY(EOMONTH(INDEX(Plan!$B$9:$B$528,$I$1),0))))>=INDEX(Plan!$B$9:$B$528,$I$1),DATE(YEAR(INDEX(Plan!$B$9:$B$528,$I$1)),MONTH(INDEX(Plan!$B$9:$B$528,$I$1)),MIN(Helpers!$F$2,DAY(EOMONTH(INDEX(Plan!$B$9:$B$528,$I$1),0))))<INDEX(Plan!$C$9:$C$528,$I$1)),DATE(YEAR(INDEX(Plan!$B$9:$B$528,$I$1)),MONTH(INDEX(Plan!$B$9:$B$528,$I$1)),MIN(Helpers!$F$2,DAY(EOMONTH(INDEX(Plan!$B$9:$B$528,$I$1),0)))),IF(AND(DATE(YEAR(INDEX(Plan!$B$9:$B$528,$I$1)),MONTH(INDEX(Plan!$B$9:$B$528,$I$1))+1,MIN(Helpers!$F$2,DAY(EOMONTH(INDEX(Plan!$B$9:$B$528,$I$1),1))))>=INDEX(Plan!$B$9:$B$528,$I$1),DATE(YEAR(INDEX(Plan!$B$9:$B$528,$I$1)),MONTH(INDEX(Plan!$B$9:$B$528,$I$1))+1,MIN(Helpers!$F$2,DAY(EOMONTH(INDEX(Plan!$B$9:$B$528,$I$1),1))))<INDEX(Plan!$C$9:$C$528,$I$1)),DATE(YEAR(INDEX(Plan!$B$9:$B$528,$I$1)),MONTH(INDEX(Plan!$B$9:$B$528,$I$1))+1,MIN(Helpers!$F$2,DAY(EOMONTH(INDEX(Plan!$B$9:$B$528,$I$1),1)))),""))) -> 46336 | D65: =IF(OR($I$1=0,Helpers!$F$3=""),"",IF(AND(DATE(YEAR(INDEX(Plan!$B$9:$B$528,$I$1)),MONTH(INDEX(Plan!$B$9:$B$528,$I$1)),MIN(Helpers!$F$3,DAY(EOMONTH(INDEX(Plan!$B$9:$B$528,$I$1),0))))>=INDEX(Plan!$B$9:$B$528,$I$1),DATE(YEAR(INDEX(Plan!$B$9:$B$528,$I$1)),MONTH(INDEX(Plan!$B$9:$B$528,$I$1)),MIN(Helpers!$F$3,DAY(EOMONTH(INDEX(Plan!$B$9:$B$528,$I$1),0))))<INDEX(Plan!$C$9:$C$528,$I$1)),DATE(YEAR(INDEX(Plan!$B$9:$B$528,$I$1)),MONTH(INDEX(Plan!$B$9:$B$528,$I$1)),MIN(Helpers!$F$3,DAY(EOMONTH(INDEX(Plan!$B$9:$B$528,$I$1),0)))),IF(AND(DATE(YEAR(INDEX(Plan!$B$9:$B$528,$I$1)),MONTH(INDEX(Plan!$B$9:$B$528,$I$1))+1,MIN(Helpers!$F$3,DAY(EOMONTH(INDEX(Plan!$B$9:$B$528,$I$1),1))))>=INDEX(Plan!$B$9:$B$528,$I$1),DATE(YEAR(INDEX(Plan!$B$9:$B$528,$I$1)),MONTH(INDEX(Plan!$B$9:$B$528,$I$1))+1,MIN(Helpers!$F$3,DAY(EOMONTH(INDEX(Plan!$B$9:$B$528,$I$1),1))))<INDEX(Plan!$C$9:$C$528,$I$1)),DATE(YEAR(INDEX(Plan!$B$9:$B$528,$I$1)),MONTH(INDEX(Plan!$B$9:$B$528,$I$1))+1,MIN(Helpers!$F$3,DAY(EOMONTH(INDEX(Plan!$B$9:$B$528,$I$1),1)))),""))) | E65: =IF(OR($I$1=0,Helpers!$F$4=""),"",IF(AND(DATE(YEAR(INDEX(Plan!$B$9:$B$528,$I$1)),MONTH(INDEX(Plan!$B$9:$B$528,$I$1)),MIN(Helpers!$F$4,DAY(EOMONTH(INDEX(Plan!$B$9:$B$528,$I$1),0))))>=INDEX(Plan!$B$9:$B$528,$I$1),DATE(YEAR(INDEX(Plan!$B$9:$B$528,$I$1)),MONTH(INDEX(Plan!$B$9:$B$528,$I$1)),MIN(Helpers!$F$4,DAY(EOMONTH(INDEX(Plan!$B$9:$B$528,$I$1),0))))<INDEX(Plan!$C$9:$C$528,$I$1)),DATE(YEAR(INDEX(Plan!$B$9:$B$528,$I$1)),MONTH(INDEX(Plan!$B$9:$B$528,$I$1)),MIN(Helpers!$F$4,DAY(EOMONTH(INDEX(Plan!$B$9:$B$528,$I$1),0)))),IF(AND(DATE(YEAR(INDEX(Plan!$B$9:$B$528,$I$1)),MONTH(INDEX(Plan!$B$9:$B$528,$I$1))+1,MIN(Helpers!$F$4,DAY(EOMONTH(INDEX(Plan!$B$9:$B$528,$I$1),1))))>=INDEX(Plan!$B$9:$B$528,$I$1),DATE(YEAR(INDEX(Plan!$B$9:$B$528,$I$1)),MONTH(INDEX(Plan!$B$9:$B$528,$I$1))+1,MIN(Helpers!$F$4,DAY(EOMONTH(INDEX(Plan!$B$9:$B$528,$I$1),1))))<INDEX(Plan!$C$9:$C$528,$I$1)),DATE(YEAR(INDEX(Plan!$B$9:$B$528,$I$1)),MONTH(INDEX(Plan!$B$9:$B$528,$I$1))+1,MIN(Helpers!$F$4,DAY(EOMONTH(INDEX(Plan!$B$9:$B$528,$I$1),1)))),""))) | F65: =IF(OR($I$1=0,Helpers!$F$5=""),"",IF(AND(DATE(YEAR(INDEX(Plan!$B$9:$B$528,$I$1)),MONTH(INDEX(Plan!$B$9:$B$528,$I$1)),MIN(Helpers!$F$5,DAY(EOMONTH(INDEX(Plan!$B$9:$B$528,$I$1),0))))>=INDEX(Plan!$B$9:$B$528,$I$1),DATE(YEAR(INDEX(Plan!$B$9:$B$528,$I$1)),MONTH(INDEX(Plan!$B$9:$B$528,$I$1)),MIN(Helpers!$F$5,DAY(EOMONTH(INDEX(Plan!$B$9:$B$528,$I$1),0))))<INDEX(Plan!$C$9:$C$528,$I$1)),DATE(YEAR(INDEX(Plan!$B$9:$B$528,$I$1)),MONTH(INDEX(Plan!$B$9:$B$528,$I$1)),MIN(Helpers!$F$5,DAY(EOMONTH(INDEX(Plan!$B$9:$B$528,$I$1),0)))),IF(AND(DATE(YEAR(INDEX(Plan!$B$9:$B$528,$I$1)),MONTH(INDEX(Plan!$B$9:$B$528,$I$1))+1,MIN(Helpers!$F$5,DAY(EOMONTH(INDEX(Plan!$B$9:$B$528,$I$1),1))))>=INDEX(Plan!$B$9:$B$528,$I$1),DATE(YEAR(INDEX(Plan!$B$9:$B$528,$I$1)),MONTH(INDEX(Plan!$B$9:$B$528,$I$1))+1,MIN(Helpers!$F$5,DAY(EOMONTH(INDEX(Plan!$B$9:$B$528,$I$1),1))))<INDEX(Plan!$C$9:$C$528,$I$1)),DATE(YEAR(INDEX(Plan!$B$9:$B$528,$I$1)),MONTH(INDEX(Plan!$B$9:$B$528,$I$1))+1,MIN(Helpers!$F$5,DAY(EOMONTH(INDEX(Plan!$B$9:$B$528,$I$1),1)))),""))) | G65: =IF(OR($I$1=0,Helpers!$F$6=""),"",IF(AND(DATE(YEAR(INDEX(Plan!$B$9:$B$528,$I$1)),MONTH(INDEX(Plan!$B$9:$B$528,$I$1)),MIN(Helpers!$F$6,DAY(EOMONTH(INDEX(Plan!$B$9:$B$528,$I$1),0))))>=INDEX(Plan!$B$9:$B$528,$I$1),DATE(YEAR(INDEX(Plan!$B$9:$B$528,$I$1)),MONTH(INDEX(Plan!$B$9:$B$528,$I$1)),MIN(Helpers!$F$6,DAY(EOMONTH(INDEX(Plan!$B$9:$B$528,$I$1),0))))<INDEX(Plan!$C$9:$C$528,$I$1)),DATE(YEAR(INDEX(Plan!$B$9:$B$528,$I$1)),MONTH(INDEX(Plan!$B$9:$B$528,$I$1)),MIN(Helpers!$F$6,DAY(EOMONTH(INDEX(Plan!$B$9:$B$528,$I$1),0)))),IF(AND(DATE(YEAR(INDEX(Plan!$B$9:$B$528,$I$1)),MONTH(INDEX(Plan!$B$9:$B$528,$I$1))+1,MIN(Helpers!$F$6,DAY(EOMONTH(INDEX(Plan!$B$9:$B$528,$I$1),1))))>=INDEX(Plan!$B$9:$B$528,$I$1),DATE(YEAR(INDEX(Plan!$B$9:$B$528,$I$1)),MONTH(INDEX(Plan!$B$9:$B$528,$I$1))+1,MIN(Helpers!$F$6,DAY(EOMONTH(INDEX(Plan!$B$9:$B$528,$I$1),1))))<INDEX(Plan!$C$9:$C$528,$I$1)),DATE(YEAR(INDEX(Plan!$B$9:$B$528,$I$1)),MONTH(INDEX(Plan!$B$9:$B$528,$I$1))+1,MIN(Helpers!$F$6,DAY(EOMONTH(INDEX(Plan!$B$9:$B$528,$I$1),1)))),""))) | H65: =IF(OR($I$1=0,Helpers!$F$7=""),"",IF(AND(DATE(YEAR(INDEX(Plan!$B$9:$B$528,$I$1)),MONTH(INDEX(Plan!$B$9:$B$528,$I$1)),MIN(Helpers!$F$7,DAY(EOMONTH(INDEX(Plan!$B$9:$B$528,$I$1),0))))>=INDEX(Plan!$B$9:$B$528,$I$1),DATE(YEAR(INDEX(Plan!$B$9:$B$528,$I$1)),MONTH(INDEX(Plan!$B$9:$B$528,$I$1)),MIN(Helpers!$F$7,DAY(EOMONTH(INDEX(Plan!$B$9:$B$528,$I$1),0))))<INDEX(Plan!$C$9:$C$528,$I$1)),DATE(YEAR(INDEX(Plan!$B$9:$B$528,$I$1)),MONTH(INDEX(Plan!$B$9:$B$528,$I$1)),MIN(Helpers!$F$7,DAY(EOMONTH(INDEX(Plan!$B$9:$B$528,$I$1),0)))),IF(AND(DATE(YEAR(INDEX(Plan!$B$9:$B$528,$I$1)),MONTH(INDEX(Plan!$B$9:$B$528,$I$1))+1,MIN(Helpers!$F$7,DAY(EOMONTH(INDEX(Plan!$B$9:$B$528,$I$1),1))))>=INDEX(Plan!$B$9:$B$528,$I$1),DATE(YEAR(INDEX(Plan!$B$9:$B$528,$I$1)),MONTH(INDEX(Plan!$B$9:$B$528,$I$1))+1,MIN(Helpers!$F$7,DAY(EOMONTH(INDEX(Plan!$B$9:$B$528,$I$1),1))))<INDEX(Plan!$C$9:$C$528,$I$1)),DATE(YEAR(INDEX(Plan!$B$9:$B$528,$I$1)),MONTH(INDEX(Plan!$B$9:$B$528,$I$1))+1,MIN(Helpers!$F$7,DAY(EOMONTH(INDEX(Plan!$B$9:$B$528,$I$1),1)))),""))) | I65: =IF(OR($I$1=0,Helpers!$F$8=""),"",IF(AND(DATE(YEAR(INDEX(Plan!$B$9:$B$528,$I$1)),MONTH(INDEX(Plan!$B$9:$B$528,$I$1)),MIN(Helpers!$F$8,DAY(EOMONTH(INDEX(Plan!$B$9:$B$528,$I$1),0))))>=INDEX(Plan!$B$9:$B$528,$I$1),DATE(YEAR(INDEX(Plan!$B$9:$B$528,$I$1)),MONTH(INDEX(Plan!$B$9:$B$528,$I$1)),MIN(Helpers!$F$8,DAY(EOMONTH(INDEX(Plan!$B$9:$B$528,$I$1),0))))<INDEX(Plan!$C$9:$C$528,$I$1)),DATE(YEAR(INDEX(Plan!$B$9:$B$528,$I$1)),MONTH(INDEX(Plan!$B$9:$B$528,$I$1)),MIN(Helpers!$F$8,DAY(EOMONTH(INDEX(Plan!$B$9:$B$528,$I$1),0)))),IF(AND(DATE(YEAR(INDEX(Plan!$B$9:$B$528,$I$1)),MONTH(INDEX(Plan!$B$9:$B$528,$I$1))+1,MIN(Helpers!$F$8,DAY(EOMONTH(INDEX(Plan!$B$9:$B$528,$I$1),1))))>=INDEX(Plan!$B$9:$B$528,$I$1),DATE(YEAR(INDEX(Plan!$B$9:$B$528,$I$1)),MONTH(INDEX(Plan!$B$9:$B$528,$I$1))+1,MIN(Helpers!$F$8,DAY(EOMONTH(INDEX(Plan!$B$9:$B$528,$I$1),1))))<INDEX(Plan!$C$9:$C$528,$I$1)),DATE(YEAR(INDEX(Plan!$B$9:$B$528,$I$1)),MONTH(INDEX(Plan!$B$9:$B$528,$I$1))+1,MIN(Helpers!$F$8,DAY(EOMONTH(INDEX(Plan!$B$9:$B$528,$I$1),1)))),""))) | J65: =IF(OR($I$1=0,Helpers!$F$9=""),"",IF(AND(DATE(YEAR(INDEX(Plan!$B$9:$B$528,$I$1)),MONTH(INDEX(Plan!$B$9:$B$528,$I$1)),MIN(Helpers!$F$9,DAY(EOMONTH(INDEX(Plan!$B$9:$B$528,$I$1),0))))>=INDEX(Plan!$B$9:$B$528,$I$1),DATE(YEAR(INDEX(Plan!$B$9:$B$528,$I$1)),MONTH(INDEX(Plan!$B$9:$B$528,$I$1)),MIN(Helpers!$F$9,DAY(EOMONTH(INDEX(Plan!$B$9:$B$528,$I$1),0))))<INDEX(Plan!$C$9:$C$528,$I$1)),DATE(YEAR(INDEX(Plan!$B$9:$B$528,$I$1)),MONTH(INDEX(Plan!$B$9:$B$528,$I$1)),MIN(Helpers!$F$9,DAY(EOMONTH(INDEX(Plan!$B$9:$B$528,$I$1),0)))),IF(AND(DATE(YEAR(INDEX(Plan!$B$9:$B$528,$I$1)),MONTH(INDEX(Plan!$B$9:$B$528,$I$1))+1,MIN(Helpers!$F$9,DAY(EOMONTH(INDEX(Plan!$B$9:$B$528,$I$1),1))))>=INDEX(Plan!$B$9:$B$528,$I$1),DATE(YEAR(INDEX(Plan!$B$9:$B$528,$I$1)),MONTH(INDEX(Plan!$B$9:$B$528,$I$1))+1,MIN(Helpers!$F$9,DAY(EOMONTH(INDEX(Plan!$B$9:$B$528,$I$1),1))))<INDEX(Plan!$C$9:$C$528,$I$1)),DATE(YEAR(INDEX(Plan!$B$9:$B$528,$I$1)),MONTH(INDEX(Plan!$B$9:$B$528,$I$1))+1,MIN(Helpers!$F$9,DAY(EOMONTH(INDEX(Plan!$B$9:$B$528,$I$1),1)))),""))) | K65: =IF(OR($I$1=0,Helpers!$F$10=""),"",IF(AND(DATE(YEAR(INDEX(Plan!$B$9:$B$528,$I$1)),MONTH(INDEX(Plan!$B$9:$B$528,$I$1)),MIN(Helpers!$F$10,DAY(EOMONTH(INDEX(Plan!$B$9:$B$528,$I$1),0))))>=INDEX(Plan!$B$9:$B$528,$I$1),DATE(YEAR(INDEX(Plan!$B$9:$B$528,$I$1)),MONTH(INDEX(Plan!$B$9:$B$528,$I$1)),MIN(Helpers!$F$10,DAY(EOMONTH(INDEX(Plan!$B$9:$B$528,$I$1),0))))<INDEX(Plan!$C$9:$C$528,$I$1)),DATE(YEAR(INDEX(Plan!$B$9:$B$528,$I$1)),MONTH(INDEX(Plan!$B$9:$B$528,$I$1)),MIN(Helpers!$F$10,DAY(EOMONTH(INDEX(Plan!$B$9:$B$528,$I$1),0)))),IF(AND(DATE(YEAR(INDEX(Plan!$B$9:$B$528,$I$1)),MONTH(INDEX(Plan!$B$9:$B$528,$I$1))+1,MIN(Helpers!$F$10,DAY(EOMONTH(INDEX(Plan!$B$9:$B$528,$I$1),1))))>=INDEX(Plan!$B$9:$B$528,$I$1),DATE(YEAR(INDEX(Plan!$B$9:$B$528,$I$1)),MONTH(INDEX(Plan!$B$9:$B$528,$I$1))+1,MIN(Helpers!$F$10,DAY(EOMONTH(INDEX(Plan!$B$9:$B$528,$I$1),1))))<INDEX(Plan!$C$9:$C$528,$I$1)),DATE(YEAR(INDEX(Plan!$B$9:$B$528,$I$1)),MONTH(INDEX(Plan!$B$9:$B$528,$I$1))+1,MIN(Helpers!$F$10,DAY(EOMONTH(INDEX(Plan!$B$9:$B$528,$I$1),1)))),""))) | L65: =IF(OR($I$1=0,Helpers!$F$11=""),"",IF(AND(DATE(YEAR(INDEX(Plan!$B$9:$B$528,$I$1)),MONTH(INDEX(Plan!$B$9:$B$528,$I$1)),MIN(Helpers!$F$11,DAY(EOMONTH(INDEX(Plan!$B$9:$B$528,$I$1),0))))>=INDEX(Plan!$B$9:$B$528,$I$1),DATE(YEAR(INDEX(Plan!$B$9:$B$528,$I$1)),MONTH(INDEX(Plan!$B$9:$B$528,$I$1)),MIN(Helpers!$F$11,DAY(EOMONTH(INDEX(Plan!$B$9:$B$528,$I$1),0))))<INDEX(Plan!$C$9:$C$528,$I$1)),DATE(YEAR(INDEX(Plan!$B$9:$B$528,$I$1)),MONTH(INDEX(Plan!$B$9:$B$528,$I$1)),MIN(Helpers!$F$11,DAY(EOMONTH(INDEX(Plan!$B$9:$B$528,$I$1),0)))),IF(AND(DATE(YEAR(INDEX(Plan!$B$9:$B$528,$I$1)),MONTH(INDEX(Plan!$B$9:$B$528,$I$1))+1,MIN(Helpers!$F$11,DAY(EOMONTH(INDEX(Plan!$B$9:$B$528,$I$1),1))))>=INDEX(Plan!$B$9:$B$528,$I$1),DATE(YEAR(INDEX(Plan!$B$9:$B$528,$I$1)),MONTH(INDEX(Plan!$B$9:$B$528,$I$1))+1,MIN(Helpers!$F$11,DAY(EOMONTH(INDEX(Plan!$B$9:$B$528,$I$1),1))))<INDEX(Plan!$C$9:$C$528,$I$1)),DATE(YEAR(INDEX(Plan!$B$9:$B$528,$I$1)),MONTH(INDEX(Plan!$B$9:$B$528,$I$1))+1,MIN(Helpers!$F$11,DAY(EOMONTH(INDEX(Plan!$B$9:$B$528,$I$1),1)))),""))) | M65: =IF(OR($I$1=0,Helpers!$F$12=""),"",IF(AND(DATE(YEAR(INDEX(Plan!$B$9:$B$528,$I$1)),MONTH(INDEX(Plan!$B$9:$B$528,$I$1)),MIN(Helpers!$F$12,DAY(EOMONTH(INDEX(Plan!$B$9:$B$528,$I$1),0))))>=INDEX(Plan!$B$9:$B$528,$I$1),DATE(YEAR(INDEX(Plan!$B$9:$B$528,$I$1)),MONTH(INDEX(Plan!$B$9:$B$528,$I$1)),MIN(Helpers!$F$12,DAY(EOMONTH(INDEX(Plan!$B$9:$B$528,$I$1),0))))<INDEX(Plan!$C$9:$C$528,$I$1)),DATE(YEAR(INDEX(Plan!$B$9:$B$528,$I$1)),MONTH(INDEX(Plan!$B$9:$B$528,$I$1)),MIN(Helpers!$F$12,DAY(EOMONTH(INDEX(Plan!$B$9:$B$528,$I$1),0)))),IF(AND(DATE(YEAR(INDEX(Plan!$B$9:$B$528,$I$1)),MONTH(INDEX(Plan!$B$9:$B$528,$I$1))+1,MIN(Helpers!$F$12,DAY(EOMONTH(INDEX(Plan!$B$9:$B$528,$I$1),1))))>=INDEX(Plan!$B$9:$B$528,$I$1),DATE(YEAR(INDEX(Plan!$B$9:$B$528,$I$1)),MONTH(INDEX(Plan!$B$9:$B$528,$I$1))+1,MIN(Helpers!$F$12,DAY(EOMONTH(INDEX(Plan!$B$9:$B$528,$I$1),1))))<INDEX(Plan!$C$9:$C$528,$I$1)),DATE(YEAR(INDEX(Plan!$B$9:$B$528,$I$1)),MONTH(INDEX(Plan!$B$9:$B$528,$I$1))+1,MIN(Helpers!$F$12,DAY(EOMONTH(INDEX(Plan!$B$9:$B$528,$I$1),1)))),""))) | N65: =IF(OR($I$1=0,Helpers!$F$13=""),"",IF(AND(DATE(YEAR(INDEX(Plan!$B$9:$B$528,$I$1)),MONTH(INDEX(Plan!$B$9:$B$528,$I$1)),MIN(Helpers!$F$13,DAY(EOMONTH(INDEX(Plan!$B$9:$B$528,$I$1),0))))>=INDEX(Plan!$B$9:$B$528,$I$1),DATE(YEAR(INDEX(Plan!$B$9:$B$528,$I$1)),MONTH(INDEX(Plan!$B$9:$B$528,$I$1)),MIN(Helpers!$F$13,DAY(EOMONTH(INDEX(Plan!$B$9:$B$528,$I$1),0))))<INDEX(Plan!$C$9:$C$528,$I$1)),DATE(YEAR(INDEX(Plan!$B$9:$B$528,$I$1)),MONTH(INDEX(Plan!$B$9:$B$528,$I$1)),MIN(Helpers!$F$13,DAY(EOMONTH(INDEX(Plan!$B$9:$B$528,$I$1),0)))),IF(AND(DATE(YEAR(INDEX(Plan!$B$9:$B$528,$I$1)),MONTH(INDEX(Plan!$B$9:$B$528,$I$1))+1,MIN(Helpers!$F$13,DAY(EOMONTH(INDEX(Plan!$B$9:$B$528,$I$1),1))))>=INDEX(Plan!$B$9:$B$528,$I$1),DATE(YEAR(INDEX(Plan!$B$9:$B$528,$I$1)),MONTH(INDEX(Plan!$B$9:$B$528,$I$1))+1,MIN(Helpers!$F$13,DAY(EOMONTH(INDEX(Plan!$B$9:$B$528,$I$1),1))))<INDEX(Plan!$C$9:$C$528,$I$1)),DATE(YEAR(INDEX(Plan!$B$9:$B$528,$I$1)),MONTH(INDEX(Plan!$B$9:$B$528,$I$1))+1,MIN(Helpers!$F$13,DAY(EOMONTH(INDEX(Plan!$B$9:$B$528,$I$1),1)))),""))) | O65: =IF(OR($I$1=0,Helpers!$F$14=""),"",IF(AND(DATE(YEAR(INDEX(Plan!$B$9:$B$528,$I$1)),MONTH(INDEX(Plan!$B$9:$B$528,$I$1)),MIN(Helpers!$F$14,DAY(EOMONTH(INDEX(Plan!$B$9:$B$528,$I$1),0))))>=INDEX(Plan!$B$9:$B$528,$I$1),DATE(YEAR(INDEX(Plan!$B$9:$B$528,$I$1)),MONTH(INDEX(Plan!$B$9:$B$528,$I$1)),MIN(Helpers!$F$14,DAY(EOMONTH(INDEX(Plan!$B$9:$B$528,$I$1),0))))<INDEX(Plan!$C$9:$C$528,$I$1)),DATE(YEAR(INDEX(Plan!$B$9:$B$528,$I$1)),MONTH(INDEX(Plan!$B$9:$B$528,$I$1)),MIN(Helpers!$F$14,DAY(EOMONTH(INDEX(Plan!$B$9:$B$528,$I$1),0)))),IF(AND(DATE(YEAR(INDEX(Plan!$B$9:$B$528,$I$1)),MONTH(INDEX(Plan!$B$9:$B$528,$I$1))+1,MIN(Helpers!$F$14,DAY(EOMONTH(INDEX(Plan!$B$9:$B$528,$I$1),1))))>=INDEX(Plan!$B$9:$B$528,$I$1),DATE(YEAR(INDEX(Plan!$B$9:$B$528,$I$1)),MONTH(INDEX(Plan!$B$9:$B$528,$I$1))+1,MIN(Helpers!$F$14,DAY(EOMONTH(INDEX(Plan!$B$9:$B$528,$I$1),1))))<INDEX(Plan!$C$9:$C$528,$I$1)),DATE(YEAR(INDEX(Plan!$B$9:$B$528,$I$1)),MONTH(INDEX(Plan!$B$9:$B$528,$I$1))+1,MIN(Helpers!$F$14,DAY(EOMONTH(INDEX(Plan!$B$9:$B$528,$I$1),1)))),""))) | P65: =IF(OR($I$1=0,Helpers!$F$15=""),"",IF(AND(DATE(YEAR(INDEX(Plan!$B$9:$B$528,$I$1)),MONTH(INDEX(Plan!$B$9:$B$528,$I$1)),MIN(Helpers!$F$15,DAY(EOMONTH(INDEX(Plan!$B$9:$B$528,$I$1),0))))>=INDEX(Plan!$B$9:$B$528,$I$1),DATE(YEAR(INDEX(Plan!$B$9:$B$528,$I$1)),MONTH(INDEX(Plan!$B$9:$B$528,$I$1)),MIN(Helpers!$F$15,DAY(EOMONTH(INDEX(Plan!$B$9:$B$528,$I$1),0))))<INDEX(Plan!$C$9:$C$528,$I$1)),DATE(YEAR(INDEX(Plan!$B$9:$B$528,$I$1)),MONTH(INDEX(Plan!$B$9:$B$528,$I$1)),MIN(Helpers!$F$15,DAY(EOMONTH(INDEX(Plan!$B$9:$B$528,$I$1),0)))),IF(AND(DATE(YEAR(INDEX(Plan!$B$9:$B$528,$I$1)),MONTH(INDEX(Plan!$B$9:$B$528,$I$1))+1,MIN(Helpers!$F$15,DAY(EOMONTH(INDEX(Plan!$B$9:$B$528,$I$1),1))))>=INDEX(Plan!$B$9:$B$528,$I$1),DATE(YEAR(INDEX(Plan!$B$9:$B$528,$I$1)),MONTH(INDEX(Plan!$B$9:$B$528,$I$1))+1,MIN(Helpers!$F$15,DAY(EOMONTH(INDEX(Plan!$B$9:$B$528,$I$1),1))))<INDEX(Plan!$C$9:$C$528,$I$1)),DATE(YEAR(INDEX(Plan!$B$9:$B$528,$I$1)),MONTH(INDEX(Plan!$B$9:$B$528,$I$1))+1,MIN(Helpers!$F$15,DAY(EOMONTH(INDEX(Plan!$B$9:$B$528,$I$1),1)))),""))) | Q65: =IF(OR($I$1=0,Helpers!$F$16=""),"",IF(AND(DATE(YEAR(INDEX(Plan!$B$9:$B$528,$I$1)),MONTH(INDEX(Plan!$B$9:$B$528,$I$1)),MIN(Helpers!$F$16,DAY(EOMONTH(INDEX(Plan!$B$9:$B$528,$I$1),0))))>=INDEX(Plan!$B$9:$B$528,$I$1),DATE(YEAR(INDEX(Plan!$B$9:$B$528,$I$1)),MONTH(INDEX(Plan!$B$9:$B$528,$I$1)),MIN(Helpers!$F$16,DAY(EOMONTH(INDEX(Plan!$B$9:$B$528,$I$1),0))))<INDEX(Plan!$C$9:$C$528,$I$1)),DATE(YEAR(INDEX(Plan!$B$9:$B$528,$I$1)),MONTH(INDEX(Plan!$B$9:$B$528,$I$1)),MIN(Helpers!$F$16,DAY(EOMONTH(INDEX(Plan!$B$9:$B$528,$I$1),0)))),IF(AND(DATE(YEAR(INDEX(Plan!$B$9:$B$528,$I$1)),MONTH(INDEX(Plan!$B$9:$B$528,$I$1))+1,MIN(Helpers!$F$16,DAY(EOMONTH(INDEX(Plan!$B$9:$B$528,$I$1),1))))>=INDEX(Plan!$B$9:$B$528,$I$1),DATE(YEAR(INDEX(Plan!$B$9:$B$528,$I$1)),MONTH(INDEX(Plan!$B$9:$B$528,$I$1))+1,MIN(Helpers!$F$16,DAY(EOMONTH(INDEX(Plan!$B$9:$B$528,$I$1),1))))<INDEX(Plan!$C$9:$C$528,$I$1)),DATE(YEAR(INDEX(Plan!$B$9:$B$528,$I$1)),MONTH(INDEX(Plan!$B$9:$B$528,$I$1))+1,MIN(Helpers!$F$16,DAY(EOMONTH(INDEX(Plan!$B$9:$B$528,$I$1),1)))),""))) | R65: =IF(OR($I$1=0,Helpers!$F$17=""),"",IF(AND(DATE(YEAR(INDEX(Plan!$B$9:$B$528,$I$1)),MONTH(INDEX(Plan!$B$9:$B$528,$I$1)),MIN(Helpers!$F$17,DAY(EOMONTH(INDEX(Plan!$B$9:$B$528,$I$1),0))))>=INDEX(Plan!$B$9:$B$528,$I$1),DATE(YEAR(INDEX(Plan!$B$9:$B$528,$I$1)),MONTH(INDEX(Plan!$B$9:$B$528,$I$1)),MIN(Helpers!$F$17,DAY(EOMONTH(INDEX(Plan!$B$9:$B$528,$I$1),0))))<INDEX(Plan!$C$9:$C$528,$I$1)),DATE(YEAR(INDEX(Plan!$B$9:$B$528,$I$1)),MONTH(INDEX(Plan!$B$9:$B$528,$I$1)),MIN(Helpers!$F$17,DAY(EOMONTH(INDEX(Plan!$B$9:$B$528,$I$1),0)))),IF(AND(DATE(YEAR(INDEX(Plan!$B$9:$B$528,$I$1)),MONTH(INDEX(Plan!$B$9:$B$528,$I$1))+1,MIN(Helpers!$F$17,DAY(EOMONTH(INDEX(Plan!$B$9:$B$528,$I$1),1))))>=INDEX(Plan!$B$9:$B$528,$I$1),DATE(YEAR(INDEX(Plan!$B$9:$B$528,$I$1)),MONTH(INDEX(Plan!$B$9:$B$528,$I$1))+1,MIN(Helpers!$F$17,DAY(EOMONTH(INDEX(Plan!$B$9:$B$528,$I$1),1))))<INDEX(Plan!$C$9:$C$528,$I$1)),DATE(YEAR(INDEX(Plan!$B$9:$B$528,$I$1)),MONTH(INDEX(Plan!$B$9:$B$528,$I$1))+1,MIN(Helpers!$F$17,DAY(EOMONTH(INDEX(Plan!$B$9:$B$528,$I$1),1)))),""))) | S65: =IF(OR($I$1=0,Helpers!$F$18=""),"",IF(AND(DATE(YEAR(INDEX(Plan!$B$9:$B$528,$I$1)),MONTH(INDEX(Plan!$B$9:$B$528,$I$1)),MIN(Helpers!$F$18,DAY(EOMONTH(INDEX(Plan!$B$9:$B$528,$I$1),0))))>=INDEX(Plan!$B$9:$B$528,$I$1),DATE(YEAR(INDEX(Plan!$B$9:$B$528,$I$1)),MONTH(INDEX(Plan!$B$9:$B$528,$I$1)),MIN(Helpers!$F$18,DAY(EOMONTH(INDEX(Plan!$B$9:$B$528,$I$1),0))))<INDEX(Plan!$C$9:$C$528,$I$1)),DATE(YEAR(INDEX(Plan!$B$9:$B$528,$I$1)),MONTH(INDEX(Plan!$B$9:$B$528,$I$1)),MIN(Helpers!$F$18,DAY(EOMONTH(INDEX(Plan!$B$9:$B$528,$I$1),0)))),IF(AND(DATE(YEAR(INDEX(Plan!$B$9:$B$528,$I$1)),MONTH(INDEX(Plan!$B$9:$B$528,$I$1))+1,MIN(Helpers!$F$18,DAY(EOMONTH(INDEX(Plan!$B$9:$B$528,$I$1),1))))>=INDEX(Plan!$B$9:$B$528,$I$1),DATE(YEAR(INDEX(Plan!$B$9:$B$528,$I$1)),MONTH(INDEX(Plan!$B$9:$B$528,$I$1))+1,MIN(Helpers!$F$18,DAY(EOMONTH(INDEX(Plan!$B$9:$B$528,$I$1),1))))<INDEX(Plan!$C$9:$C$528,$I$1)),DATE(YEAR(INDEX(Plan!$B$9:$B$528,$I$1)),MONTH(INDEX(Plan!$B$9:$B$528,$I$1))+1,MIN(Helpers!$F$18,DAY(EOMONTH(INDEX(Plan!$B$9:$B$528,$I$1),1)))),""))) | T65: =IF(OR($I$1=0,Helpers!$F$19=""),"",IF(AND(DATE(YEAR(INDEX(Plan!$B$9:$B$528,$I$1)),MONTH(INDEX(Plan!$B$9:$B$528,$I$1)),MIN(Helpers!$F$19,DAY(EOMONTH(INDEX(Plan!$B$9:$B$528,$I$1),0))))>=INDEX(Plan!$B$9:$B$528,$I$1),DATE(YEAR(INDEX(Plan!$B$9:$B$528,$I$1)),MONTH(INDEX(Plan!$B$9:$B$528,$I$1)),MIN(Helpers!$F$19,DAY(EOMONTH(INDEX(Plan!$B$9:$B$528,$I$1),0))))<INDEX(Plan!$C$9:$C$528,$I$1)),DATE(YEAR(INDEX(Plan!$B$9:$B$528,$I$1)),MONTH(INDEX(Plan!$B$9:$B$528,$I$1)),MIN(Helpers!$F$19,DAY(EOMONTH(INDEX(Plan!$B$9:$B$528,$I$1),0)))),IF(AND(DATE(YEAR(INDEX(Plan!$B$9:$B$528,$I$1)),MONTH(INDEX(Plan!$B$9:$B$528,$I$1))+1,MIN(Helpers!$F$19,DAY(EOMONTH(INDEX(Plan!$B$9:$B$528,$I$1),1))))>=INDEX(Plan!$B$9:$B$528,$I$1),DATE(YEAR(INDEX(Plan!$B$9:$B$528,$I$1)),MONTH(INDEX(Plan!$B$9:$B$528,$I$1))+1,MIN(Helpers!$F$19,DAY(EOMONTH(INDEX(Plan!$B$9:$B$528,$I$1),1))))<INDEX(Plan!$C$9:$C$528,$I$1)),DATE(YEAR(INDEX(Plan!$B$9:$B$528,$I$1)),MONTH(INDEX(Plan!$B$9:$B$528,$I$1))+1,MIN(Helpers!$F$19,DAY(EOMONTH(INDEX(Plan!$B$9:$B$528,$I$1),1)))),""))) | U65: =IF(OR($I$1=0,Helpers!$F$20=""),"",IF(AND(DATE(YEAR(INDEX(Plan!$B$9:$B$528,$I$1)),MONTH(INDEX(Plan!$B$9:$B$528,$I$1)),MIN(Helpers!$F$20,DAY(EOMONTH(INDEX(Plan!$B$9:$B$528,$I$1),0))))>=INDEX(Plan!$B$9:$B$528,$I$1),DATE(YEAR(INDEX(Plan!$B$9:$B$528,$I$1)),MONTH(INDEX(Plan!$B$9:$B$528,$I$1)),MIN(Helpers!$F$20,DAY(EOMONTH(INDEX(Plan!$B$9:$B$528,$I$1),0))))<INDEX(Plan!$C$9:$C$528,$I$1)),DATE(YEAR(INDEX(Plan!$B$9:$B$528,$I$1)),MONTH(INDEX(Plan!$B$9:$B$528,$I$1)),MIN(Helpers!$F$20,DAY(EOMONTH(INDEX(Plan!$B$9:$B$528,$I$1),0)))),IF(AND(DATE(YEAR(INDEX(Plan!$B$9:$B$528,$I$1)),MONTH(INDEX(Plan!$B$9:$B$528,$I$1))+1,MIN(Helpers!$F$20,DAY(EOMONTH(INDEX(Plan!$B$9:$B$528,$I$1),1))))>=INDEX(Plan!$B$9:$B$528,$I$1),DATE(YEAR(INDEX(Plan!$B$9:$B$528,$I$1)),MONTH(INDEX(Plan!$B$9:$B$528,$I$1))+1,MIN(Helpers!$F$20,DAY(EOMONTH(INDEX(Plan!$B$9:$B$528,$I$1),1))))<INDEX(Plan!$C$9:$C$528,$I$1)),DATE(YEAR(INDEX(Plan!$B$9:$B$528,$I$1)),MONTH(INDEX(Plan!$B$9:$B$528,$I$1))+1,MIN(Helpers!$F$20,DAY(EOMONTH(INDEX(Plan!$B$9:$B$528,$I$1),1)))),""))) | V65: =IF(OR($I$1=0,Helpers!$F$21=""),"",IF(AND(DATE(YEAR(INDEX(Plan!$B$9:$B$528,$I$1)),MONTH(INDEX(Plan!$B$9:$B$528,$I$1)),MIN(Helpers!$F$21,DAY(EOMONTH(INDEX(Plan!$B$9:$B$528,$I$1),0))))>=INDEX(Plan!$B$9:$B$528,$I$1),DATE(YEAR(INDEX(Plan!$B$9:$B$528,$I$1)),MONTH(INDEX(Plan!$B$9:$B$528,$I$1)),MIN(Helpers!$F$21,DAY(EOMONTH(INDEX(Plan!$B$9:$B$528,$I$1),0))))<INDEX(Plan!$C$9:$C$528,$I$1)),DATE(YEAR(INDEX(Plan!$B$9:$B$528,$I$1)),MONTH(INDEX(Plan!$B$9:$B$528,$I$1)),MIN(Helpers!$F$21,DAY(EOMONTH(INDEX(Plan!$B$9:$B$528,$I$1),0)))),IF(AND(DATE(YEAR(INDEX(Plan!$B$9:$B$528,$I$1)),MONTH(INDEX(Plan!$B$9:$B$528,$I$1))+1,MIN(Helpers!$F$21,DAY(EOMONTH(INDEX(Plan!$B$9:$B$528,$I$1),1))))>=INDEX(Plan!$B$9:$B$528,$I$1),DATE(YEAR(INDEX(Plan!$B$9:$B$528,$I$1)),MONTH(INDEX(Plan!$B$9:$B$528,$I$1))+1,MIN(Helpers!$F$21,DAY(EOMONTH(INDEX(Plan!$B$9:$B$528,$I$1),1))))<INDEX(Plan!$C$9:$C$528,$I$1)),DATE(YEAR(INDEX(Plan!$B$9:$B$528,$I$1)),MONTH(INDEX(Plan!$B$9:$B$528,$I$1))+1,MIN(Helpers!$F$21,DAY(EOMONTH(INDEX(Plan!$B$9:$B$528,$I$1),1)))),""))) | W65: =IF(OR($I$1=0,Helpers!$F$22=""),"",IF(AND(DATE(YEAR(INDEX(Plan!$B$9:$B$528,$I$1)),MONTH(INDEX(Plan!$B$9:$B$528,$I$1)),MIN(Helpers!$F$22,DAY(EOMONTH(INDEX(Plan!$B$9:$B$528,$I$1),0))))>=INDEX(Plan!$B$9:$B$528,$I$1),DATE(YEAR(INDEX(Plan!$B$9:$B$528,$I$1)),MONTH(INDEX(Plan!$B$9:$B$528,$I$1)),MIN(Helpers!$F$22,DAY(EOMONTH(INDEX(Plan!$B$9:$B$528,$I$1),0))))<INDEX(Plan!$C$9:$C$528,$I$1)),DATE(YEAR(INDEX(Plan!$B$9:$B$528,$I$1)),MONTH(INDEX(Plan!$B$9:$B$528,$I$1)),MIN(Helpers!$F$22,DAY(EOMONTH(INDEX(Plan!$B$9:$B$528,$I$1),0)))),IF(AND(DATE(YEAR(INDEX(Plan!$B$9:$B$528,$I$1)),MONTH(INDEX(Plan!$B$9:$B$528,$I$1))+1,MIN(Helpers!$F$22,DAY(EOMONTH(INDEX(Plan!$B$9:$B$528,$I$1),1))))>=INDEX(Plan!$B$9:$B$528,$I$1),DATE(YEAR(INDEX(Plan!$B$9:$B$528,$I$1)),MONTH(INDEX(Plan!$B$9:$B$528,$I$1))+1,MIN(Helpers!$F$22,DAY(EOMONTH(INDEX(Plan!$B$9:$B$528,$I$1),1))))<INDEX(Plan!$C$9:$C$528,$I$1)),DATE(YEAR(INDEX(Plan!$B$9:$B$528,$I$1)),MONTH(INDEX(Plan!$B$9:$B$528,$I$1))+1,MIN(Helpers!$F$22,DAY(EOMONTH(INDEX(Plan!$B$9:$B$528,$I$1),1)))),""))) | X65: =IF(OR($I$1=0,Helpers!$F$23=""),"",IF(AND(DATE(YEAR(INDEX(Plan!$B$9:$B$528,$I$1)),MONTH(INDEX(Plan!$B$9:$B$528,$I$1)),MIN(Helpers!$F$23,DAY(EOMONTH(INDEX(Plan!$B$9:$B$528,$I$1),0))))>=INDEX(Plan!$B$9:$B$528,$I$1),DATE(YEAR(INDEX(Plan!$B$9:$B$528,$I$1)),MONTH(INDEX(Plan!$B$9:$B$528,$I$1)),MIN(Helpers!$F$23,DAY(EOMONTH(INDEX(Plan!$B$9:$B$528,$I$1),0))))<INDEX(Plan!$C$9:$C$528,$I$1)),DATE(YEAR(INDEX(Plan!$B$9:$B$528,$I$1)),MONTH(INDEX(Plan!$B$9:$B$528,$I$1)),MIN(Helpers!$F$23,DAY(EOMONTH(INDEX(Plan!$B$9:$B$528,$I$1),0)))),IF(AND(DATE(YEAR(INDEX(Plan!$B$9:$B$528,$I$1)),MONTH(INDEX(Plan!$B$9:$B$528,$I$1))+1,MIN(Helpers!$F$23,DAY(EOMONTH(INDEX(Plan!$B$9:$B$528,$I$1),1))))>=INDEX(Plan!$B$9:$B$528,$I$1),DATE(YEAR(INDEX(Plan!$B$9:$B$528,$I$1)),MONTH(INDEX(Plan!$B$9:$B$528,$I$1))+1,MIN(Helpers!$F$23,DAY(EOMONTH(INDEX(Plan!$B$9:$B$528,$I$1),1))))<INDEX(Plan!$C$9:$C$528,$I$1)),DATE(YEAR(INDEX(Plan!$B$9:$B$528,$I$1)),MONTH(INDEX(Plan!$B$9:$B$528,$I$1))+1,MIN(Helpers!$F$23,DAY(EOMONTH(INDEX(Plan!$B$9:$B$528,$I$1),1)))),""))) | Y65: =IF(OR($I$1=0,Helpers!$F$24=""),"",IF(AND(DATE(YEAR(INDEX(Plan!$B$9:$B$528,$I$1)),MONTH(INDEX(Plan!$B$9:$B$528,$I$1)),MIN(Helpers!$F$24,DAY(EOMONTH(INDEX(Plan!$B$9:$B$528,$I$1),0))))>=INDEX(Plan!$B$9:$B$528,$I$1),DATE(YEAR(INDEX(Plan!$B$9:$B$528,$I$1)),MONTH(INDEX(Plan!$B$9:$B$528,$I$1)),MIN(Helpers!$F$24,DAY(EOMONTH(INDEX(Plan!$B$9:$B$528,$I$1),0))))<INDEX(Plan!$C$9:$C$528,$I$1)),DATE(YEAR(INDEX(Plan!$B$9:$B$528,$I$1)),MONTH(INDEX(Plan!$B$9:$B$528,$I$1)),MIN(Helpers!$F$24,DAY(EOMONTH(INDEX(Plan!$B$9:$B$528,$I$1),0)))),IF(AND(DATE(YEAR(INDEX(Plan!$B$9:$B$528,$I$1)),MONTH(INDEX(Plan!$B$9:$B$528,$I$1))+1,MIN(Helpers!$F$24,DAY(EOMONTH(INDEX(Plan!$B$9:$B$528,$I$1),1))))>=INDEX(Plan!$B$9:$B$528,$I$1),DATE(YEAR(INDEX(Plan!$B$9:$B$528,$I$1)),MONTH(INDEX(Plan!$B$9:$B$528,$I$1))+1,MIN(Helpers!$F$24,DAY(EOMONTH(INDEX(Plan!$B$9:$B$528,$I$1),1))))<INDEX(Plan!$C$9:$C$528,$I$1)),DATE(YEAR(INDEX(Plan!$B$9:$B$528,$I$1)),MONTH(INDEX(Plan!$B$9:$B$528,$I$1))+1,MIN(Helpers!$F$24,DAY(EOMONTH(INDEX(Plan!$B$9:$B$528,$I$1),1)))),""))) | Z65: =IF(OR($I$1=0,Helpers!$F$25=""),"",IF(AND(DATE(YEAR(INDEX(Plan!$B$9:$B$528,$I$1)),MONTH(INDEX(Plan!$B$9:$B$528,$I$1)),MIN(Helpers!$F$25,DAY(EOMONTH(INDEX(Plan!$B$9:$B$528,$I$1),0))))>=INDEX(Plan!$B$9:$B$528,$I$1),DATE(YEAR(INDEX(Plan!$B$9:$B$528,$I$1)),MONTH(INDEX(Plan!$B$9:$B$528,$I$1)),MIN(Helpers!$F$25,DAY(EOMONTH(INDEX(Plan!$B$9:$B$528,$I$1),0))))<INDEX(Plan!$C$9:$C$528,$I$1)),DATE(YEAR(INDEX(Plan!$B$9:$B$528,$I$1)),MONTH(INDEX(Plan!$B$9:$B$528,$I$1)),MIN(Helpers!$F$25,DAY(EOMONTH(INDEX(Plan!$B$9:$B$528,$I$1),0)))),IF(AND(DATE(YEAR(INDEX(Plan!$B$9:$B$528,$I$1)),MONTH(INDEX(Plan!$B$9:$B$528,$I$1))+1,MIN(Helpers!$F$25,DAY(EOMONTH(INDEX(Plan!$B$9:$B$528,$I$1),1))))>=INDEX(Plan!$B$9:$B$528,$I$1),DATE(YEAR(INDEX(Plan!$B$9:$B$528,$I$1)),MONTH(INDEX(Plan!$B$9:$B$528,$I$1))+1,MIN(Helpers!$F$25,DAY(EOMONTH(INDEX(Plan!$B$9:$B$528,$I$1),1))))<INDEX(Plan!$C$9:$C$528,$I$1)),DATE(YEAR(INDEX(Plan!$B$9:$B$528,$I$1)),MONTH(INDEX(Plan!$B$9:$B$528,$I$1))+1,MIN(Helpers!$F$25,DAY(EOMONTH(INDEX(Plan!$B$9:$B$528,$I$1),1)))),""))) | AA65: =IF(OR($I$1=0,Helpers!$F$26=""),"",IF(AND(DATE(YEAR(INDEX(Plan!$B$9:$B$528,$I$1)),MONTH(INDEX(Plan!$B$9:$B$528,$I$1)),MIN(Helpers!$F$26,DAY(EOMONTH(INDEX(Plan!$B$9:$B$528,$I$1),0))))>=INDEX(Plan!$B$9:$B$528,$I$1),DATE(YEAR(INDEX(Plan!$B$9:$B$528,$I$1)),MONTH(INDEX(Plan!$B$9:$B$528,$I$1)),MIN(Helpers!$F$26,DAY(EOMONTH(INDEX(Plan!$B$9:$B$528,$I$1),0))))<INDEX(Plan!$C$9:$C$528,$I$1)),DATE(YEAR(INDEX(Plan!$B$9:$B$528,$I$1)),MONTH(INDEX(Plan!$B$9:$B$528,$I$1)),MIN(Helpers!$F$26,DAY(EOMONTH(INDEX(Plan!$B$9:$B$528,$I$1),0)))),IF(AND(DATE(YEAR(INDEX(Plan!$B$9:$B$528,$I$1)),MONTH(INDEX(Plan!$B$9:$B$528,$I$1))+1,MIN(Helpers!$F$26,DAY(EOMONTH(INDEX(Plan!$B$9:$B$528,$I$1),1))))>=INDEX(Plan!$B$9:$B$528,$I$1),DATE(YEAR(INDEX(Plan!$B$9:$B$528,$I$1)),MONTH(INDEX(Plan!$B$9:$B$528,$I$1))+1,MIN(Helpers!$F$26,DAY(EOMONTH(INDEX(Plan!$B$9:$B$528,$I$1),1))))<INDEX(Plan!$C$9:$C$528,$I$1)),DATE(YEAR(INDEX(Plan!$B$9:$B$528,$I$1)),MONTH(INDEX(Plan!$B$9:$B$528,$I$1))+1,MIN(Helpers!$F$26,DAY(EOMONTH(INDEX(Plan!$B$9:$B$528,$I$1),1)))),""))) | AB65: =IF(OR($I$1=0,Helpers!$F$27=""),"",IF(AND(DATE(YEAR(INDEX(Plan!$B$9:$B$528,$I$1)),MONTH(INDEX(Plan!$B$9:$B$528,$I$1)),MIN(Helpers!$F$27,DAY(EOMONTH(INDEX(Plan!$B$9:$B$528,$I$1),0))))>=INDEX(Plan!$B$9:$B$528,$I$1),DATE(YEAR(INDEX(Plan!$B$9:$B$528,$I$1)),MONTH(INDEX(Plan!$B$9:$B$528,$I$1)),MIN(Helpers!$F$27,DAY(EOMONTH(INDEX(Plan!$B$9:$B$528,$I$1),0))))<INDEX(Plan!$C$9:$C$528,$I$1)),DATE(YEAR(INDEX(Plan!$B$9:$B$528,$I$1)),MONTH(INDEX(Plan!$B$9:$B$528,$I$1)),MIN(Helpers!$F$27,DAY(EOMONTH(INDEX(Plan!$B$9:$B$528,$I$1),0)))),IF(AND(DATE(YEAR(INDEX(Plan!$B$9:$B$528,$I$1)),MONTH(INDEX(Plan!$B$9:$B$528,$I$1))+1,MIN(Helpers!$F$27,DAY(EOMONTH(INDEX(Plan!$B$9:$B$528,$I$1),1))))>=INDEX(Plan!$B$9:$B$528,$I$1),DATE(YEAR(INDEX(Plan!$B$9:$B$528,$I$1)),MONTH(INDEX(Plan!$B$9:$B$528,$I$1))+1,MIN(Helpers!$F$27,DAY(EOMONTH(INDEX(Plan!$B$9:$B$528,$I$1),1))))<INDEX(Plan!$C$9:$C$528,$I$1)),DATE(YEAR(INDEX(Plan!$B$9:$B$528,$I$1)),MONTH(INDEX(Plan!$B$9:$B$528,$I$1))+1,MIN(Helpers!$F$27,DAY(EOMONTH(INDEX(Plan!$B$9:$B$528,$I$1),1)))),""))) | AC65: =IF(OR($I$1=0,Helpers!$F$28=""),"",IF(AND(DATE(YEAR(INDEX(Plan!$B$9:$B$528,$I$1)),MONTH(INDEX(Plan!$B$9:$B$528,$I$1)),MIN(Helpers!$F$28,DAY(EOMONTH(INDEX(Plan!$B$9:$B$528,$I$1),0))))>=INDEX(Plan!$B$9:$B$528,$I$1),DATE(YEAR(INDEX(Plan!$B$9:$B$528,$I$1)),MONTH(INDEX(Plan!$B$9:$B$528,$I$1)),MIN(Helpers!$F$28,DAY(EOMONTH(INDEX(Plan!$B$9:$B$528,$I$1),0))))<INDEX(Plan!$C$9:$C$528,$I$1)),DATE(YEAR(INDEX(Plan!$B$9:$B$528,$I$1)),MONTH(INDEX(Plan!$B$9:$B$528,$I$1)),MIN(Helpers!$F$28,DAY(EOMONTH(INDEX(Plan!$B$9:$B$528,$I$1),0)))),IF(AND(DATE(YEAR(INDEX(Plan!$B$9:$B$528,$I$1)),MONTH(INDEX(Plan!$B$9:$B$528,$I$1))+1,MIN(Helpers!$F$28,DAY(EOMONTH(INDEX(Plan!$B$9:$B$528,$I$1),1))))>=INDEX(Plan!$B$9:$B$528,$I$1),DATE(YEAR(INDEX(Plan!$B$9:$B$528,$I$1)),MONTH(INDEX(Plan!$B$9:$B$528,$I$1))+1,MIN(Helpers!$F$28,DAY(EOMONTH(INDEX(Plan!$B$9:$B$528,$I$1),1))))<INDEX(Plan!$C$9:$C$528,$I$1)),DATE(YEAR(INDEX(Plan!$B$9:$B$528,$I$1)),MONTH(INDEX(Plan!$B$9:$B$528,$I$1))+1,MIN(Helpers!$F$28,DAY(EOMONTH(INDEX(Plan!$B$9:$B$528,$I$1),1)))),""))) | AD65: =IF(OR($I$1=0,Helpers!$F$29=""),"",IF(AND(DATE(YEAR(INDEX(Plan!$B$9:$B$528,$I$1)),MONTH(INDEX(Plan!$B$9:$B$528,$I$1)),MIN(Helpers!$F$29,DAY(EOMONTH(INDEX(Plan!$B$9:$B$528,$I$1),0))))>=INDEX(Plan!$B$9:$B$528,$I$1),DATE(YEAR(INDEX(Plan!$B$9:$B$528,$I$1)),MONTH(INDEX(Plan!$B$9:$B$528,$I$1)),MIN(Helpers!$F$29,DAY(EOMONTH(INDEX(Plan!$B$9:$B$528,$I$1),0))))<INDEX(Plan!$C$9:$C$528,$I$1)),DATE(YEAR(INDEX(Plan!$B$9:$B$528,$I$1)),MONTH(INDEX(Plan!$B$9:$B$528,$I$1)),MIN(Helpers!$F$29,DAY(EOMONTH(INDEX(Plan!$B$9:$B$528,$I$1),0)))),IF(AND(DATE(YEAR(INDEX(Plan!$B$9:$B$528,$I$1)),MONTH(INDEX(Plan!$B$9:$B$528,$I$1))+1,MIN(Helpers!$F$29,DAY(EOMONTH(INDEX(Plan!$B$9:$B$528,$I$1),1))))>=INDEX(Plan!$B$9:$B$528,$I$1),DATE(YEAR(INDEX(Plan!$B$9:$B$528,$I$1)),MONTH(INDEX(Plan!$B$9:$B$528,$I$1))+1,MIN(Helpers!$F$29,DAY(EOMONTH(INDEX(Plan!$B$9:$B$528,$I$1),1))))<INDEX(Plan!$C$9:$C$528,$I$1)),DATE(YEAR(INDEX(Plan!$B$9:$B$528,$I$1)),MONTH(INDEX(Plan!$B$9:$B$528,$I$1))+1,MIN(Helpers!$F$29,DAY(EOMONTH(INDEX(Plan!$B$9:$B$528,$I$1),1)))),""))) | AE65: =IF(OR($I$1=0,Helpers!$F$30=""),"",IF(AND(DATE(YEAR(INDEX(Plan!$B$9:$B$528,$I$1)),MONTH(INDEX(Plan!$B$9:$B$528,$I$1)),MIN(Helpers!$F$30,DAY(EOMONTH(INDEX(Plan!$B$9:$B$528,$I$1),0))))>=INDEX(Plan!$B$9:$B$528,$I$1),DATE(YEAR(INDEX(Plan!$B$9:$B$528,$I$1)),MONTH(INDEX(Plan!$B$9:$B$528,$I$1)),MIN(Helpers!$F$30,DAY(EOMONTH(INDEX(Plan!$B$9:$B$528,$I$1),0))))<INDEX(Plan!$C$9:$C$528,$I$1)),DATE(YEAR(INDEX(Plan!$B$9:$B$528,$I$1)),MONTH(INDEX(Plan!$B$9:$B$528,$I$1)),MIN(Helpers!$F$30,DAY(EOMONTH(INDEX(Plan!$B$9:$B$528,$I$1),0)))),IF(AND(DATE(YEAR(INDEX(Plan!$B$9:$B$528,$I$1)),MONTH(INDEX(Plan!$B$9:$B$528,$I$1))+1,MIN(Helpers!$F$30,DAY(EOMONTH(INDEX(Plan!$B$9:$B$528,$I$1),1))))>=INDEX(Plan!$B$9:$B$528,$I$1),DATE(YEAR(INDEX(Plan!$B$9:$B$528,$I$1)),MONTH(INDEX(Plan!$B$9:$B$528,$I$1))+1,MIN(Helpers!$F$30,DAY(EOMONTH(INDEX(Plan!$B$9:$B$528,$I$1),1))))<INDEX(Plan!$C$9:$C$528,$I$1)),DATE(YEAR(INDEX(Plan!$B$9:$B$528,$I$1)),MONTH(INDEX(Plan!$B$9:$B$528,$I$1))+1,MIN(Helpers!$F$30,DAY(EOMONTH(INDEX(Plan!$B$9:$B$528,$I$1),1)))),""))) | AF65: =IF(OR($I$1=0,Helpers!$F$31=""),"",IF(AND(DATE(YEAR(INDEX(Plan!$B$9:$B$528,$I$1)),MONTH(INDEX(Plan!$B$9:$B$528,$I$1)),MIN(Helpers!$F$31,DAY(EOMONTH(INDEX(Plan!$B$9:$B$528,$I$1),0))))>=INDEX(Plan!$B$9:$B$528,$I$1),DATE(YEAR(INDEX(Plan!$B$9:$B$528,$I$1)),MONTH(INDEX(Plan!$B$9:$B$528,$I$1)),MIN(Helpers!$F$31,DAY(EOMONTH(INDEX(Plan!$B$9:$B$528,$I$1),0))))<INDEX(Plan!$C$9:$C$528,$I$1)),DATE(YEAR(INDEX(Plan!$B$9:$B$528,$I$1)),MONTH(INDEX(Plan!$B$9:$B$528,$I$1)),MIN(Helpers!$F$31,DAY(EOMONTH(INDEX(Plan!$B$9:$B$528,$I$1),0)))),IF(AND(DATE(YEAR(INDEX(Plan!$B$9:$B$528,$I$1)),MONTH(INDEX(Plan!$B$9:$B$528,$I$1))+1,MIN(Helpers!$F$31,DAY(EOMONTH(INDEX(Plan!$B$9:$B$528,$I$1),1))))>=INDEX(Plan!$B$9:$B$528,$I$1),DATE(YEAR(INDEX(Plan!$B$9:$B$528,$I$1)),MONTH(INDEX(Plan!$B$9:$B$528,$I$1))+1,MIN(Helpers!$F$31,DAY(EOMONTH(INDEX(Plan!$B$9:$B$528,$I$1),1))))<INDEX(Plan!$C$9:$C$528,$I$1)),DATE(YEAR(INDEX(Plan!$B$9:$B$528,$I$1)),MONTH(INDEX(Plan!$B$9:$B$528,$I$1))+1,MIN(Helpers!$F$31,DAY(EOMONTH(INDEX(Plan!$B$9:$B$528,$I$1),1)))),""))) | AG65: =IF(OR($I$1=0,Helpers!$F$32=""),"",IF(AND(DATE(YEAR(INDEX(Plan!$B$9:$B$528,$I$1)),MONTH(INDEX(Plan!$B$9:$B$528,$I$1)),MIN(Helpers!$F$32,DAY(EOMONTH(INDEX(Plan!$B$9:$B$528,$I$1),0))))>=INDEX(Plan!$B$9:$B$528,$I$1),DATE(YEAR(INDEX(Plan!$B$9:$B$528,$I$1)),MONTH(INDEX(Plan!$B$9:$B$528,$I$1)),MIN(Helpers!$F$32,DAY(EOMONTH(INDEX(Plan!$B$9:$B$528,$I$1),0))))<INDEX(Plan!$C$9:$C$528,$I$1)),DATE(YEAR(INDEX(Plan!$B$9:$B$528,$I$1)),MONTH(INDEX(Plan!$B$9:$B$528,$I$1)),MIN(Helpers!$F$32,DAY(EOMONTH(INDEX(Plan!$B$9:$B$528,$I$1),0)))),IF(AND(DATE(YEAR(INDEX(Plan!$B$9:$B$528,$I$1)),MONTH(INDEX(Plan!$B$9:$B$528,$I$1))+1,MIN(Helpers!$F$32,DAY(EOMONTH(INDEX(Plan!$B$9:$B$528,$I$1),1))))>=INDEX(Plan!$B$9:$B$528,$I$1),DATE(YEAR(INDEX(Plan!$B$9:$B$528,$I$1)),MONTH(INDEX(Plan!$B$9:$B$528,$I$1))+1,MIN(Helpers!$F$32,DAY(EOMONTH(INDEX(Plan!$B$9:$B$528,$I$1),1))))<INDEX(Plan!$C$9:$C$528,$I$1)),DATE(YEAR(INDEX(Plan!$B$9:$B$528,$I$1)),MONTH(INDEX(Plan!$B$9:$B$528,$I$1))+1,MIN(Helpers!$F$32,DAY(EOMONTH(INDEX(Plan!$B$9:$B$528,$I$1),1)))),""))) | AH65: =IF(OR($I$1=0,Helpers!$F$33=""),"",IF(AND(DATE(YEAR(INDEX(Plan!$B$9:$B$528,$I$1)),MONTH(INDEX(Plan!$B$9:$B$528,$I$1)),MIN(Helpers!$F$33,DAY(EOMONTH(INDEX(Plan!$B$9:$B$528,$I$1),0))))>=INDEX(Plan!$B$9:$B$528,$I$1),DATE(YEAR(INDEX(Plan!$B$9:$B$528,$I$1)),MONTH(INDEX(Plan!$B$9:$B$528,$I$1)),MIN(Helpers!$F$33,DAY(EOMONTH(INDEX(Plan!$B$9:$B$528,$I$1),0))))<INDEX(Plan!$C$9:$C$528,$I$1)),DATE(YEAR(INDEX(Plan!$B$9:$B$528,$I$1)),MONTH(INDEX(Plan!$B$9:$B$528,$I$1)),MIN(Helpers!$F$33,DAY(EOMONTH(INDEX(Plan!$B$9:$B$528,$I$1),0)))),IF(AND(DATE(YEAR(INDEX(Plan!$B$9:$B$528,$I$1)),MONTH(INDEX(Plan!$B$9:$B$528,$I$1))+1,MIN(Helpers!$F$33,DAY(EOMONTH(INDEX(Plan!$B$9:$B$528,$I$1),1))))>=INDEX(Plan!$B$9:$B$528,$I$1),DATE(YEAR(INDEX(Plan!$B$9:$B$528,$I$1)),MONTH(INDEX(Plan!$B$9:$B$528,$I$1))+1,MIN(Helpers!$F$33,DAY(EOMONTH(INDEX(Plan!$B$9:$B$528,$I$1),1))))<INDEX(Plan!$C$9:$C$528,$I$1)),DATE(YEAR(INDEX(Plan!$B$9:$B$528,$I$1)),MONTH(INDEX(Plan!$B$9:$B$528,$I$1))+1,MIN(Helpers!$F$33,DAY(EOMONTH(INDEX(Plan!$B$9:$B$528,$I$1),1)))),""))) | AI65: =IF(OR($I$1=0,Helpers!$F$34=""),"",IF(AND(DATE(YEAR(INDEX(Plan!$B$9:$B$528,$I$1)),MONTH(INDEX(Plan!$B$9:$B$528,$I$1)),MIN(Helpers!$F$34,DAY(EOMONTH(INDEX(Plan!$B$9:$B$528,$I$1),0))))>=INDEX(Plan!$B$9:$B$528,$I$1),DATE(YEAR(INDEX(Plan!$B$9:$B$528,$I$1)),MONTH(INDEX(Plan!$B$9:$B$528,$I$1)),MIN(Helpers!$F$34,DAY(EOMONTH(INDEX(Plan!$B$9:$B$528,$I$1),0))))<INDEX(Plan!$C$9:$C$528,$I$1)),DATE(YEAR(INDEX(Plan!$B$9:$B$528,$I$1)),MONTH(INDEX(Plan!$B$9:$B$528,$I$1)),MIN(Helpers!$F$34,DAY(EOMONTH(INDEX(Plan!$B$9:$B$528,$I$1),0)))),IF(AND(DATE(YEAR(INDEX(Plan!$B$9:$B$528,$I$1)),MONTH(INDEX(Plan!$B$9:$B$528,$I$1))+1,MIN(Helpers!$F$34,DAY(EOMONTH(INDEX(Plan!$B$9:$B$528,$I$1),1))))>=INDEX(Plan!$B$9:$B$528,$I$1),DATE(YEAR(INDEX(Plan!$B$9:$B$528,$I$1)),MONTH(INDEX(Plan!$B$9:$B$528,$I$1))+1,MIN(Helpers!$F$34,DAY(EOMONTH(INDEX(Plan!$B$9:$B$528,$I$1),1))))<INDEX(Plan!$C$9:$C$528,$I$1)),DATE(YEAR(INDEX(Plan!$B$9:$B$528,$I$1)),MONTH(INDEX(Plan!$B$9:$B$528,$I$1))+1,MIN(Helpers!$F$34,DAY(EOMONTH(INDEX(Plan!$B$9:$B$528,$I$1),1)))),""))) | AJ65: =IF(OR($I$1=0,Helpers!$F$35=""),"",IF(AND(DATE(YEAR(INDEX(Plan!$B$9:$B$528,$I$1)),MONTH(INDEX(Plan!$B$9:$B$528,$I$1)),MIN(Helpers!$F$35,DAY(EOMONTH(INDEX(Plan!$B$9:$B$528,$I$1),0))))>=INDEX(Plan!$B$9:$B$528,$I$1),DATE(YEAR(INDEX(Plan!$B$9:$B$528,$I$1)),MONTH(INDEX(Plan!$B$9:$B$528,$I$1)),MIN(Helpers!$F$35,DAY(EOMONTH(INDEX(Plan!$B$9:$B$528,$I$1),0))))<INDEX(Plan!$C$9:$C$528,$I$1)),DATE(YEAR(INDEX(Plan!$B$9:$B$528,$I$1)),MONTH(INDEX(Plan!$B$9:$B$528,$I$1)),MIN(Helpers!$F$35,DAY(EOMONTH(INDEX(Plan!$B$9:$B$528,$I$1),0)))),IF(AND(DATE(YEAR(INDEX(Plan!$B$9:$B$528,$I$1)),MONTH(INDEX(Plan!$B$9:$B$528,$I$1))+1,MIN(Helpers!$F$35,DAY(EOMONTH(INDEX(Plan!$B$9:$B$528,$I$1),1))))>=INDEX(Plan!$B$9:$B$528,$I$1),DATE(YEAR(INDEX(Plan!$B$9:$B$528,$I$1)),MONTH(INDEX(Plan!$B$9:$B$528,$I$1))+1,MIN(Helpers!$F$35,DAY(EOMONTH(INDEX(Plan!$B$9:$B$528,$I$1),1))))<INDEX(Plan!$C$9:$C$528,$I$1)),DATE(YEAR(INDEX(Plan!$B$9:$B$528,$I$1)),MONTH(INDEX(Plan!$B$9:$B$528,$I$1))+1,MIN(Helpers!$F$35,DAY(EOMONTH(INDEX(Plan!$B$9:$B$528,$I$1),1)))),""))) | AK65: =IF(OR($I$1=0,Helpers!$F$36=""),"",IF(AND(DATE(YEAR(INDEX(Plan!$B$9:$B$528,$I$1)),MONTH(INDEX(Plan!$B$9:$B$528,$I$1)),MIN(Helpers!$F$36,DAY(EOMONTH(INDEX(Plan!$B$9:$B$528,$I$1),0))))>=INDEX(Plan!$B$9:$B$528,$I$1),DATE(YEAR(INDEX(Plan!$B$9:$B$528,$I$1)),MONTH(INDEX(Plan!$B$9:$B$528,$I$1)),MIN(Helpers!$F$36,DAY(EOMONTH(INDEX(Plan!$B$9:$B$528,$I$1),0))))<INDEX(Plan!$C$9:$C$528,$I$1)),DATE(YEAR(INDEX(Plan!$B$9:$B$528,$I$1)),MONTH(INDEX(Plan!$B$9:$B$528,$I$1)),MIN(Helpers!$F$36,DAY(EOMONTH(INDEX(Plan!$B$9:$B$528,$I$1),0)))),IF(AND(DATE(YEAR(INDEX(Plan!$B$9:$B$528,$I$1)),MONTH(INDEX(Plan!$B$9:$B$528,$I$1))+1,MIN(Helpers!$F$36,DAY(EOMONTH(INDEX(Plan!$B$9:$B$528,$I$1),1))))>=INDEX(Plan!$B$9:$B$528,$I$1),DATE(YEAR(INDEX(Plan!$B$9:$B$528,$I$1)),MONTH(INDEX(Plan!$B$9:$B$528,$I$1))+1,MIN(Helpers!$F$36,DAY(EOMONTH(INDEX(Plan!$B$9:$B$528,$I$1),1))))<INDEX(Plan!$C$9:$C$528,$I$1)),DATE(YEAR(INDEX(Plan!$B$9:$B$528,$I$1)),MONTH(INDEX(Plan!$B$9:$B$528,$I$1))+1,MIN(Helpers!$F$36,DAY(EOMONTH(INDEX(Plan!$B$9:$B$528,$I$1),1)))),""))) | AL65: =IF(OR($I$1=0,Helpers!$F$37=""),"",IF(AND(DATE(YEAR(INDEX(Plan!$B$9:$B$528,$I$1)),MONTH(INDEX(Plan!$B$9:$B$528,$I$1)),MIN(Helpers!$F$37,DAY(EOMONTH(INDEX(Plan!$B$9:$B$528,$I$1),0))))>=INDEX(Plan!$B$9:$B$528,$I$1),DATE(YEAR(INDEX(Plan!$B$9:$B$528,$I$1)),MONTH(INDEX(Plan!$B$9:$B$528,$I$1)),MIN(Helpers!$F$37,DAY(EOMONTH(INDEX(Plan!$B$9:$B$528,$I$1),0))))<INDEX(Plan!$C$9:$C$528,$I$1)),DATE(YEAR(INDEX(Plan!$B$9:$B$528,$I$1)),MONTH(INDEX(Plan!$B$9:$B$528,$I$1)),MIN(Helpers!$F$37,DAY(EOMONTH(INDEX(Plan!$B$9:$B$528,$I$1),0)))),IF(AND(DATE(YEAR(INDEX(Plan!$B$9:$B$528,$I$1)),MONTH(INDEX(Plan!$B$9:$B$528,$I$1))+1,MIN(Helpers!$F$37,DAY(EOMONTH(INDEX(Plan!$B$9:$B$528,$I$1),1))))>=INDEX(Plan!$B$9:$B$528,$I$1),DATE(YEAR(INDEX(Plan!$B$9:$B$528,$I$1)),MONTH(INDEX(Plan!$B$9:$B$528,$I$1))+1,MIN(Helpers!$F$37,DAY(EOMONTH(INDEX(Plan!$B$9:$B$528,$I$1),1))))<INDEX(Plan!$C$9:$C$528,$I$1)),DATE(YEAR(INDEX(Plan!$B$9:$B$528,$I$1)),MONTH(INDEX(Plan!$B$9:$B$528,$I$1))+1,MIN(Helpers!$F$37,DAY(EOMONTH(INDEX(Plan!$B$9:$B$528,$I$1),1)))),""))) | AM65: =IF(OR($I$1=0,Helpers!$F$38=""),"",IF(AND(DATE(YEAR(INDEX(Plan!$B$9:$B$528,$I$1)),MONTH(INDEX(Plan!$B$9:$B$528,$I$1)),MIN(Helpers!$F$38,DAY(EOMONTH(INDEX(Plan!$B$9:$B$528,$I$1),0))))>=INDEX(Plan!$B$9:$B$528,$I$1),DATE(YEAR(INDEX(Plan!$B$9:$B$528,$I$1)),MONTH(INDEX(Plan!$B$9:$B$528,$I$1)),MIN(Helpers!$F$38,DAY(EOMONTH(INDEX(Plan!$B$9:$B$528,$I$1),0))))<INDEX(Plan!$C$9:$C$528,$I$1)),DATE(YEAR(INDEX(Plan!$B$9:$B$528,$I$1)),MONTH(INDEX(Plan!$B$9:$B$528,$I$1)),MIN(Helpers!$F$38,DAY(EOMONTH(INDEX(Plan!$B$9:$B$528,$I$1),0)))),IF(AND(DATE(YEAR(INDEX(Plan!$B$9:$B$528,$I$1)),MONTH(INDEX(Plan!$B$9:$B$528,$I$1))+1,MIN(Helpers!$F$38,DAY(EOMONTH(INDEX(Plan!$B$9:$B$528,$I$1),1))))>=INDEX(Plan!$B$9:$B$528,$I$1),DATE(YEAR(INDEX(Plan!$B$9:$B$528,$I$1)),MONTH(INDEX(Plan!$B$9:$B$528,$I$1))+1,MIN(Helpers!$F$38,DAY(EOMONTH(INDEX(Plan!$B$9:$B$528,$I$1),1))))<INDEX(Plan!$C$9:$C$528,$I$1)),DATE(YEAR(INDEX(Plan!$B$9:$B$528,$I$1)),MONTH(INDEX(Plan!$B$9:$B$528,$I$1))+1,MIN(Helpers!$F$38,DAY(EOMONTH(INDEX(Plan!$B$9:$B$528,$I$1),1)))),""))) | AN65: =IF(OR($I$1=0,Helpers!$F$39=""),"",IF(AND(DATE(YEAR(INDEX(Plan!$B$9:$B$528,$I$1)),MONTH(INDEX(Plan!$B$9:$B$528,$I$1)),MIN(Helpers!$F$39,DAY(EOMONTH(INDEX(Plan!$B$9:$B$528,$I$1),0))))>=INDEX(Plan!$B$9:$B$528,$I$1),DATE(YEAR(INDEX(Plan!$B$9:$B$528,$I$1)),MONTH(INDEX(Plan!$B$9:$B$528,$I$1)),MIN(Helpers!$F$39,DAY(EOMONTH(INDEX(Plan!$B$9:$B$528,$I$1),0))))<INDEX(Plan!$C$9:$C$528,$I$1)),DATE(YEAR(INDEX(Plan!$B$9:$B$528,$I$1)),MONTH(INDEX(Plan!$B$9:$B$528,$I$1)),MIN(Helpers!$F$39,DAY(EOMONTH(INDEX(Plan!$B$9:$B$528,$I$1),0)))),IF(AND(DATE(YEAR(INDEX(Plan!$B$9:$B$528,$I$1)),MONTH(INDEX(Plan!$B$9:$B$528,$I$1))+1,MIN(Helpers!$F$39,DAY(EOMONTH(INDEX(Plan!$B$9:$B$528,$I$1),1))))>=INDEX(Plan!$B$9:$B$528,$I$1),DATE(YEAR(INDEX(Plan!$B$9:$B$528,$I$1)),MONTH(INDEX(Plan!$B$9:$B$528,$I$1))+1,MIN(Helpers!$F$39,DAY(EOMONTH(INDEX(Plan!$B$9:$B$528,$I$1),1))))<INDEX(Plan!$C$9:$C$528,$I$1)),DATE(YEAR(INDEX(Plan!$B$9:$B$528,$I$1)),MONTH(INDEX(Plan!$B$9:$B$528,$I$1))+1,MIN(Helpers!$F$39,DAY(EOMONTH(INDEX(Plan!$B$9:$B$528,$I$1),1)))),""))) | AO65: =IF(OR($I$1=0,Helpers!$F$40=""),"",IF(AND(DATE(YEAR(INDEX(Plan!$B$9:$B$528,$I$1)),MONTH(INDEX(Plan!$B$9:$B$528,$I$1)),MIN(Helpers!$F$40,DAY(EOMONTH(INDEX(Plan!$B$9:$B$528,$I$1),0))))>=INDEX(Plan!$B$9:$B$528,$I$1),DATE(YEAR(INDEX(Plan!$B$9:$B$528,$I$1)),MONTH(INDEX(Plan!$B$9:$B$528,$I$1)),MIN(Helpers!$F$40,DAY(EOMONTH(INDEX(Plan!$B$9:$B$528,$I$1),0))))<INDEX(Plan!$C$9:$C$528,$I$1)),DATE(YEAR(INDEX(Plan!$B$9:$B$528,$I$1)),MONTH(INDEX(Plan!$B$9:$B$528,$I$1)),MIN(Helpers!$F$40,DAY(EOMONTH(INDEX(Plan!$B$9:$B$528,$I$1),0)))),IF(AND(DATE(YEAR(INDEX(Plan!$B$9:$B$528,$I$1)),MONTH(INDEX(Plan!$B$9:$B$528,$I$1))+1,MIN(Helpers!$F$40,DAY(EOMONTH(INDEX(Plan!$B$9:$B$528,$I$1),1))))>=INDEX(Plan!$B$9:$B$528,$I$1),DATE(YEAR(INDEX(Plan!$B$9:$B$528,$I$1)),MONTH(INDEX(Plan!$B$9:$B$528,$I$1))+1,MIN(Helpers!$F$40,DAY(EOMONTH(INDEX(Plan!$B$9:$B$528,$I$1),1))))<INDEX(Plan!$C$9:$C$528,$I$1)),DATE(YEAR(INDEX(Plan!$B$9:$B$528,$I$1)),MONTH(INDEX(Plan!$B$9:$B$528,$I$1))+1,MIN(Helpers!$F$40,DAY(EOMONTH(INDEX(Plan!$B$9:$B$528,$I$1),1)))),""))) | AP65: =IF(OR($I$1=0,Helpers!$F$41=""),"",IF(AND(DATE(YEAR(INDEX(Plan!$B$9:$B$528,$I$1)),MONTH(INDEX(Plan!$B$9:$B$528,$I$1)),MIN(Helpers!$F$41,DAY(EOMONTH(INDEX(Plan!$B$9:$B$528,$I$1),0))))>=INDEX(Plan!$B$9:$B$528,$I$1),DATE(YEAR(INDEX(Plan!$B$9:$B$528,$I$1)),MONTH(INDEX(Plan!$B$9:$B$528,$I$1)),MIN(Helpers!$F$41,DAY(EOMONTH(INDEX(Plan!$B$9:$B$528,$I$1),0))))<INDEX(Plan!$C$9:$C$528,$I$1)),DATE(YEAR(INDEX(Plan!$B$9:$B$528,$I$1)),MONTH(INDEX(Plan!$B$9:$B$528,$I$1)),MIN(Helpers!$F$41,DAY(EOMONTH(INDEX(Plan!$B$9:$B$528,$I$1),0)))),IF(AND(DATE(YEAR(INDEX(Plan!$B$9:$B$528,$I$1)),MONTH(INDEX(Plan!$B$9:$B$528,$I$1))+1,MIN(Helpers!$F$41,DAY(EOMONTH(INDEX(Plan!$B$9:$B$528,$I$1),1))))>=INDEX(Plan!$B$9:$B$528,$I$1),DATE(YEAR(INDEX(Plan!$B$9:$B$528,$I$1)),MONTH(INDEX(Plan!$B$9:$B$528,$I$1))+1,MIN(Helpers!$F$41,DAY(EOMONTH(INDEX(Plan!$B$9:$B$528,$I$1),1))))<INDEX(Plan!$C$9:$C$528,$I$1)),DATE(YEAR(INDEX(Plan!$B$9:$B$528,$I$1)),MONTH(INDEX(Plan!$B$9:$B$528,$I$1))+1,MIN(Helpers!$F$41,DAY(EOMONTH(INDEX(Plan!$B$9:$B$528,$I$1),1)))),""))) | AQ65: =IF(OR($I$1=0,Helpers!$F$42=""),"",IF(AND(DATE(YEAR(INDEX(Plan!$B$9:$B$528,$I$1)),MONTH(INDEX(Plan!$B$9:$B$528,$I$1)),MIN(Helpers!$F$42,DAY(EOMONTH(INDEX(Plan!$B$9:$B$528,$I$1),0))))>=INDEX(Plan!$B$9:$B$528,$I$1),DATE(YEAR(INDEX(Plan!$B$9:$B$528,$I$1)),MONTH(INDEX(Plan!$B$9:$B$528,$I$1)),MIN(Helpers!$F$42,DAY(EOMONTH(INDEX(Plan!$B$9:$B$528,$I$1),0))))<INDEX(Plan!$C$9:$C$528,$I$1)),DATE(YEAR(INDEX(Plan!$B$9:$B$528,$I$1)),MONTH(INDEX(Plan!$B$9:$B$528,$I$1)),MIN(Helpers!$F$42,DAY(EOMONTH(INDEX(Plan!$B$9:$B$528,$I$1),0)))),IF(AND(DATE(YEAR(INDEX(Plan!$B$9:$B$528,$I$1)),MONTH(INDEX(Plan!$B$9:$B$528,$I$1))+1,MIN(Helpers!$F$42,DAY(EOMONTH(INDEX(Plan!$B$9:$B$528,$I$1),1))))>=INDEX(Plan!$B$9:$B$528,$I$1),DATE(YEAR(INDEX(Plan!$B$9:$B$528,$I$1)),MONTH(INDEX(Plan!$B$9:$B$528,$I$1))+1,MIN(Helpers!$F$42,DAY(EOMONTH(INDEX(Plan!$B$9:$B$528,$I$1),1))))<INDEX(Plan!$C$9:$C$528,$I$1)),DATE(YEAR(INDEX(Plan!$B$9:$B$528,$I$1)),MONTH(INDEX(Plan!$B$9:$B$528,$I$1))+1,MIN(Helpers!$F$42,DAY(EOMONTH(INDEX(Plan!$B$9:$B$528,$I$1),1)))),""))) | AR65: =IF(OR($I$1=0,Helpers!$F$43=""),"",IF(AND(DATE(YEAR(INDEX(Plan!$B$9:$B$528,$I$1)),MONTH(INDEX(Plan!$B$9:$B$528,$I$1)),MIN(Helpers!$F$43,DAY(EOMONTH(INDEX(Plan!$B$9:$B$528,$I$1),0))))>=INDEX(Plan!$B$9:$B$528,$I$1),DATE(YEAR(INDEX(Plan!$B$9:$B$528,$I$1)),MONTH(INDEX(Plan!$B$9:$B$528,$I$1)),MIN(Helpers!$F$43,DAY(EOMONTH(INDEX(Plan!$B$9:$B$528,$I$1),0))))<INDEX(Plan!$C$9:$C$528,$I$1)),DATE(YEAR(INDEX(Plan!$B$9:$B$528,$I$1)),MONTH(INDEX(Plan!$B$9:$B$528,$I$1)),MIN(Helpers!$F$43,DAY(EOMONTH(INDEX(Plan!$B$9:$B$528,$I$1),0)))),IF(AND(DATE(YEAR(INDEX(Plan!$B$9:$B$528,$I$1)),MONTH(INDEX(Plan!$B$9:$B$528,$I$1))+1,MIN(Helpers!$F$43,DAY(EOMONTH(INDEX(Plan!$B$9:$B$528,$I$1),1))))>=INDEX(Plan!$B$9:$B$528,$I$1),DATE(YEAR(INDEX(Plan!$B$9:$B$528,$I$1)),MONTH(INDEX(Plan!$B$9:$B$528,$I$1))+1,MIN(Helpers!$F$43,DAY(EOMONTH(INDEX(Plan!$B$9:$B$528,$I$1),1))))<INDEX(Plan!$C$9:$C$528,$I$1)),DATE(YEAR(INDEX(Plan!$B$9:$B$528,$I$1)),MONTH(INDEX(Plan!$B$9:$B$528,$I$1))+1,MIN(Helpers!$F$43,DAY(EOMONTH(INDEX(Plan!$B$9:$B$528,$I$1),1)))),""))) | AS65: =IF(OR($I$1=0,Helpers!$F$44=""),"",IF(AND(DATE(YEAR(INDEX(Plan!$B$9:$B$528,$I$1)),MONTH(INDEX(Plan!$B$9:$B$528,$I$1)),MIN(Helpers!$F$44,DAY(EOMONTH(INDEX(Plan!$B$9:$B$528,$I$1),0))))>=INDEX(Plan!$B$9:$B$528,$I$1),DATE(YEAR(INDEX(Plan!$B$9:$B$528,$I$1)),MONTH(INDEX(Plan!$B$9:$B$528,$I$1)),MIN(Helpers!$F$44,DAY(EOMONTH(INDEX(Plan!$B$9:$B$528,$I$1),0))))<INDEX(Plan!$C$9:$C$528,$I$1)),DATE(YEAR(INDEX(Plan!$B$9:$B$528,$I$1)),MONTH(INDEX(Plan!$B$9:$B$528,$I$1)),MIN(Helpers!$F$44,DAY(EOMONTH(INDEX(Plan!$B$9:$B$528,$I$1),0)))),IF(AND(DATE(YEAR(INDEX(Plan!$B$9:$B$528,$I$1)),MONTH(INDEX(Plan!$B$9:$B$528,$I$1))+1,MIN(Helpers!$F$44,DAY(EOMONTH(INDEX(Plan!$B$9:$B$528,$I$1),1))))>=INDEX(Plan!$B$9:$B$528,$I$1),DATE(YEAR(INDEX(Plan!$B$9:$B$528,$I$1)),MONTH(INDEX(Plan!$B$9:$B$528,$I$1))+1,MIN(Helpers!$F$44,DAY(EOMONTH(INDEX(Plan!$B$9:$B$528,$I$1),1))))<INDEX(Plan!$C$9:$C$528,$I$1)),DATE(YEAR(INDEX(Plan!$B$9:$B$528,$I$1)),MONTH(INDEX(Plan!$B$9:$B$528,$I$1))+1,MIN(Helpers!$F$44,DAY(EOMONTH(INDEX(Plan!$B$9:$B$528,$I$1),1)))),""))) | AT65: =IF(OR($I$1=0,Helpers!$F$45=""),"",IF(AND(DATE(YEAR(INDEX(Plan!$B$9:$B$528,$I$1)),MONTH(INDEX(Plan!$B$9:$B$528,$I$1)),MIN(Helpers!$F$45,DAY(EOMONTH(INDEX(Plan!$B$9:$B$528,$I$1),0))))>=INDEX(Plan!$B$9:$B$528,$I$1),DATE(YEAR(INDEX(Plan!$B$9:$B$528,$I$1)),MONTH(INDEX(Plan!$B$9:$B$528,$I$1)),MIN(Helpers!$F$45,DAY(EOMONTH(INDEX(Plan!$B$9:$B$528,$I$1),0))))<INDEX(Plan!$C$9:$C$528,$I$1)),DATE(YEAR(INDEX(Plan!$B$9:$B$528,$I$1)),MONTH(INDEX(Plan!$B$9:$B$528,$I$1)),MIN(Helpers!$F$45,DAY(EOMONTH(INDEX(Plan!$B$9:$B$528,$I$1),0)))),IF(AND(DATE(YEAR(INDEX(Plan!$B$9:$B$528,$I$1)),MONTH(INDEX(Plan!$B$9:$B$528,$I$1))+1,MIN(Helpers!$F$45,DAY(EOMONTH(INDEX(Plan!$B$9:$B$528,$I$1),1))))>=INDEX(Plan!$B$9:$B$528,$I$1),DATE(YEAR(INDEX(Plan!$B$9:$B$528,$I$1)),MONTH(INDEX(Plan!$B$9:$B$528,$I$1))+1,MIN(Helpers!$F$45,DAY(EOMONTH(INDEX(Plan!$B$9:$B$528,$I$1),1))))<INDEX(Plan!$C$9:$C$528,$I$1)),DATE(YEAR(INDEX(Plan!$B$9:$B$528,$I$1)),MONTH(INDEX(Plan!$B$9:$B$528,$I$1))+1,MIN(Helpers!$F$45,DAY(EOMONTH(INDEX(Plan!$B$9:$B$528,$I$1),1)))),""))) | AU65: =IF(OR($I$1=0,Helpers!$F$46=""),"",IF(AND(DATE(YEAR(INDEX(Plan!$B$9:$B$528,$I$1)),MONTH(INDEX(Plan!$B$9:$B$528,$I$1)),MIN(Helpers!$F$46,DAY(EOMONTH(INDEX(Plan!$B$9:$B$528,$I$1),0))))>=INDEX(Plan!$B$9:$B$528,$I$1),DATE(YEAR(INDEX(Plan!$B$9:$B$528,$I$1)),MONTH(INDEX(Plan!$B$9:$B$528,$I$1)),MIN(Helpers!$F$46,DAY(EOMONTH(INDEX(Plan!$B$9:$B$528,$I$1),0))))<INDEX(Plan!$C$9:$C$528,$I$1)),DATE(YEAR(INDEX(Plan!$B$9:$B$528,$I$1)),MONTH(INDEX(Plan!$B$9:$B$528,$I$1)),MIN(Helpers!$F$46,DAY(EOMONTH(INDEX(Plan!$B$9:$B$528,$I$1),0)))),IF(AND(DATE(YEAR(INDEX(Plan!$B$9:$B$528,$I$1)),MONTH(INDEX(Plan!$B$9:$B$528,$I$1))+1,MIN(Helpers!$F$46,DAY(EOMONTH(INDEX(Plan!$B$9:$B$528,$I$1),1))))>=INDEX(Plan!$B$9:$B$528,$I$1),DATE(YEAR(INDEX(Plan!$B$9:$B$528,$I$1)),MONTH(INDEX(Plan!$B$9:$B$528,$I$1))+1,MIN(Helpers!$F$46,DAY(EOMONTH(INDEX(Plan!$B$9:$B$528,$I$1),1))))<INDEX(Plan!$C$9:$C$528,$I$1)),DATE(YEAR(INDEX(Plan!$B$9:$B$528,$I$1)),MONTH(INDEX(Plan!$B$9:$B$528,$I$1))+1,MIN(Helpers!$F$46,DAY(EOMONTH(INDEX(Plan!$B$9:$B$528,$I$1),1)))),""))) | AV65: =IF(OR($I$1=0,Helpers!$F$47=""),"",IF(AND(DATE(YEAR(INDEX(Plan!$B$9:$B$528,$I$1)),MONTH(INDEX(Plan!$B$9:$B$528,$I$1)),MIN(Helpers!$F$47,DAY(EOMONTH(INDEX(Plan!$B$9:$B$528,$I$1),0))))>=INDEX(Plan!$B$9:$B$528,$I$1),DATE(YEAR(INDEX(Plan!$B$9:$B$528,$I$1)),MONTH(INDEX(Plan!$B$9:$B$528,$I$1)),MIN(Helpers!$F$47,DAY(EOMONTH(INDEX(Plan!$B$9:$B$528,$I$1),0))))<INDEX(Plan!$C$9:$C$528,$I$1)),DATE(YEAR(INDEX(Plan!$B$9:$B$528,$I$1)),MONTH(INDEX(Plan!$B$9:$B$528,$I$1)),MIN(Helpers!$F$47,DAY(EOMONTH(INDEX(Plan!$B$9:$B$528,$I$1),0)))),IF(AND(DATE(YEAR(INDEX(Plan!$B$9:$B$528,$I$1)),MONTH(INDEX(Plan!$B$9:$B$528,$I$1))+1,MIN(Helpers!$F$47,DAY(EOMONTH(INDEX(Plan!$B$9:$B$528,$I$1),1))))>=INDEX(Plan!$B$9:$B$528,$I$1),DATE(YEAR(INDEX(Plan!$B$9:$B$528,$I$1)),MONTH(INDEX(Plan!$B$9:$B$528,$I$1))+1,MIN(Helpers!$F$47,DAY(EOMONTH(INDEX(Plan!$B$9:$B$528,$I$1),1))))<INDEX(Plan!$C$9:$C$528,$I$1)),DATE(YEAR(INDEX(Plan!$B$9:$B$528,$I$1)),MONTH(INDEX(Plan!$B$9:$B$528,$I$1))+1,MIN(Helpers!$F$47,DAY(EOMONTH(INDEX(Plan!$B$9:$B$528,$I$1),1)))),""))) | AW65: =IF(OR($I$1=0,Helpers!$F$48=""),"",IF(AND(DATE(YEAR(INDEX(Plan!$B$9:$B$528,$I$1)),MONTH(INDEX(Plan!$B$9:$B$528,$I$1)),MIN(Helpers!$F$48,DAY(EOMONTH(INDEX(Plan!$B$9:$B$528,$I$1),0))))>=INDEX(Plan!$B$9:$B$528,$I$1),DATE(YEAR(INDEX(Plan!$B$9:$B$528,$I$1)),MONTH(INDEX(Plan!$B$9:$B$528,$I$1)),MIN(Helpers!$F$48,DAY(EOMONTH(INDEX(Plan!$B$9:$B$528,$I$1),0))))<INDEX(Plan!$C$9:$C$528,$I$1)),DATE(YEAR(INDEX(Plan!$B$9:$B$528,$I$1)),MONTH(INDEX(Plan!$B$9:$B$528,$I$1)),MIN(Helpers!$F$48,DAY(EOMONTH(INDEX(Plan!$B$9:$B$528,$I$1),0)))),IF(AND(DATE(YEAR(INDEX(Plan!$B$9:$B$528,$I$1)),MONTH(INDEX(Plan!$B$9:$B$528,$I$1))+1,MIN(Helpers!$F$48,DAY(EOMONTH(INDEX(Plan!$B$9:$B$528,$I$1),1))))>=INDEX(Plan!$B$9:$B$528,$I$1),DATE(YEAR(INDEX(Plan!$B$9:$B$528,$I$1)),MONTH(INDEX(Plan!$B$9:$B$528,$I$1))+1,MIN(Helpers!$F$48,DAY(EOMONTH(INDEX(Plan!$B$9:$B$528,$I$1),1))))<INDEX(Plan!$C$9:$C$528,$I$1)),DATE(YEAR(INDEX(Plan!$B$9:$B$528,$I$1)),MONTH(INDEX(Plan!$B$9:$B$528,$I$1))+1,MIN(Helpers!$F$48,DAY(EOMONTH(INDEX(Plan!$B$9:$B$528,$I$1),1)))),""))) | AX65: =IF(OR($I$1=0,Helpers!$F$49=""),"",IF(AND(DATE(YEAR(INDEX(Plan!$B$9:$B$528,$I$1)),MONTH(INDEX(Plan!$B$9:$B$528,$I$1)),MIN(Helpers!$F$49,DAY(EOMONTH(INDEX(Plan!$B$9:$B$528,$I$1),0))))>=INDEX(Plan!$B$9:$B$528,$I$1),DATE(YEAR(INDEX(Plan!$B$9:$B$528,$I$1)),MONTH(INDEX(Plan!$B$9:$B$528,$I$1)),MIN(Helpers!$F$49,DAY(EOMONTH(INDEX(Plan!$B$9:$B$528,$I$1),0))))<INDEX(Plan!$C$9:$C$528,$I$1)),DATE(YEAR(INDEX(Plan!$B$9:$B$528,$I$1)),MONTH(INDEX(Plan!$B$9:$B$528,$I$1)),MIN(Helpers!$F$49,DAY(EOMONTH(INDEX(Plan!$B$9:$B$528,$I$1),0)))),IF(AND(DATE(YEAR(INDEX(Plan!$B$9:$B$528,$I$1)),MONTH(INDEX(Plan!$B$9:$B$528,$I$1))+1,MIN(Helpers!$F$49,DAY(EOMONTH(INDEX(Plan!$B$9:$B$528,$I$1),1))))>=INDEX(Plan!$B$9:$B$528,$I$1),DATE(YEAR(INDEX(Plan!$B$9:$B$528,$I$1)),MONTH(INDEX(Plan!$B$9:$B$528,$I$1))+1,MIN(Helpers!$F$49,DAY(EOMONTH(INDEX(Plan!$B$9:$B$528,$I$1),1))))<INDEX(Plan!$C$9:$C$528,$I$1)),DATE(YEAR(INDEX(Plan!$B$9:$B$528,$I$1)),MONTH(INDEX(Plan!$B$9:$B$528,$I$1))+1,MIN(Helpers!$F$49,DAY(EOMONTH(INDEX(Plan!$B$9:$B$528,$I$1),1)))),""))) | AY65: =IF(OR($I$1=0,Helpers!$F$50=""),"",IF(AND(DATE(YEAR(INDEX(Plan!$B$9:$B$528,$I$1)),MONTH(INDEX(Plan!$B$9:$B$528,$I$1)),MIN(Helpers!$F$50,DAY(EOMONTH(INDEX(Plan!$B$9:$B$528,$I$1),0))))>=INDEX(Plan!$B$9:$B$528,$I$1),DATE(YEAR(INDEX(Plan!$B$9:$B$528,$I$1)),MONTH(INDEX(Plan!$B$9:$B$528,$I$1)),MIN(Helpers!$F$50,DAY(EOMONTH(INDEX(Plan!$B$9:$B$528,$I$1),0))))<INDEX(Plan!$C$9:$C$528,$I$1)),DATE(YEAR(INDEX(Plan!$B$9:$B$528,$I$1)),MONTH(INDEX(Plan!$B$9:$B$528,$I$1)),MIN(Helpers!$F$50,DAY(EOMONTH(INDEX(Plan!$B$9:$B$528,$I$1),0)))),IF(AND(DATE(YEAR(INDEX(Plan!$B$9:$B$528,$I$1)),MONTH(INDEX(Plan!$B$9:$B$528,$I$1))+1,MIN(Helpers!$F$50,DAY(EOMONTH(INDEX(Plan!$B$9:$B$528,$I$1),1))))>=INDEX(Plan!$B$9:$B$528,$I$1),DATE(YEAR(INDEX(Plan!$B$9:$B$528,$I$1)),MONTH(INDEX(Plan!$B$9:$B$528,$I$1))+1,MIN(Helpers!$F$50,DAY(EOMONTH(INDEX(Plan!$B$9:$B$528,$I$1),1))))<INDEX(Plan!$C$9:$C$528,$I$1)),DATE(YEAR(INDEX(Plan!$B$9:$B$528,$I$1)),MONTH(INDEX(Plan!$B$9:$B$528,$I$1))+1,MIN(Helpers!$F$50,DAY(EOMONTH(INDEX(Plan!$B$9:$B$528,$I$1),1)))),""))) | AZ65: =IF(OR($I$1=0,Helpers!$F$51=""),"",IF(AND(DATE(YEAR(INDEX(Plan!$B$9:$B$528,$I$1)),MONTH(INDEX(Plan!$B$9:$B$528,$I$1)),MIN(Helpers!$F$51,DAY(EOMONTH(INDEX(Plan!$B$9:$B$528,$I$1),0))))>=INDEX(Plan!$B$9:$B$528,$I$1),DATE(YEAR(INDEX(Plan!$B$9:$B$528,$I$1)),MONTH(INDEX(Plan!$B$9:$B$528,$I$1)),MIN(Helpers!$F$51,DAY(EOMONTH(INDEX(Plan!$B$9:$B$528,$I$1),0))))<INDEX(Plan!$C$9:$C$528,$I$1)),DATE(YEAR(INDEX(Plan!$B$9:$B$528,$I$1)),MONTH(INDEX(Plan!$B$9:$B$528,$I$1)),MIN(Helpers!$F$51,DAY(EOMONTH(INDEX(Plan!$B$9:$B$528,$I$1),0)))),IF(AND(DATE(YEAR(INDEX(Plan!$B$9:$B$528,$I$1)),MONTH(INDEX(Plan!$B$9:$B$528,$I$1))+1,MIN(Helpers!$F$51,DAY(EOMONTH(INDEX(Plan!$B$9:$B$528,$I$1),1))))>=INDEX(Plan!$B$9:$B$528,$I$1),DATE(YEAR(INDEX(Plan!$B$9:$B$528,$I$1)),MONTH(INDEX(Plan!$B$9:$B$528,$I$1))+1,MIN(Helpers!$F$51,DAY(EOMONTH(INDEX(Plan!$B$9:$B$528,$I$1),1))))<INDEX(Plan!$C$9:$C$528,$I$1)),DATE(YEAR(INDEX(Plan!$B$9:$B$528,$I$1)),MONTH(INDEX(Plan!$B$9:$B$528,$I$1))+1,MIN(Helpers!$F$51,DAY(EOMONTH(INDEX(Plan!$B$9:$B$528,$I$1),1)))),"")))
C66: =Helpers!$D$2 -> 0.24 | D66: =Helpers!$D$3 -> 0.18 | E66: =Helpers!$D$4 -> 0 | F66: =Helpers!$D$5 -> 0 | G66: =Helpers!$D$6 -> 0 | H66: =Helpers!$D$7 -> 0 | I66: =Helpers!$D$8 -> 0 | J66: =Helpers!$D$9 -> 0 | K66: =Helpers!$D$10 -> 0 | L66: =Helpers!$D$11 -> 0 | M66: =Helpers!$D$12 -> 0 | N66: =Helpers!$D$13 -> 0 | O66: =Helpers!$D$14 -> 0 | P66: =Helpers!$D$15 -> 0 | Q66: =Helpers!$D$16 -> 0 | R66: =Helpers!$D$17 -> 0 | S66: =Helpers!$D$18 -> 0 | T66: =Helpers!$D$19 -> 0 | U66: =Helpers!$D$20 -> 0 | V66: =Helpers!$D$21 -> 0 | W66: =Helpers!$D$22 -> 0 | X66: =Helpers!$D$23 -> 0 | Y66: =Helpers!$D$24 -> 0 | Z66: =Helpers!$D$25 -> 0 | AA66: =Helpers!$D$26 -> 0 | AB66: =Helpers!$D$27 -> 0 | AC66: =Helpers!$D$28 -> 0 | AD66: =Helpers!$D$29 -> 0 | AE66: =Helpers!$D$30 -> 0 | AF66: =Helpers!$D$31 -> 0 | AG66: =Helpers!$D$32 -> 0 | AH66: =Helpers!$D$33 -> 0 | AI66: =Helpers!$D$34 -> 0 | AJ66: =Helpers!$D$35 -> 0 | AK66: =Helpers!$D$36 -> 0 | AL66: =Helpers!$D$37 -> 0 | AM66: =Helpers!$D$38 -> 0 | AN66: =Helpers!$D$39 -> 0 | AO66: =Helpers!$D$40 -> 0 | AP66: =Helpers!$D$41 -> 0 | AQ66: =Helpers!$D$42 -> 0 | AR66: =Helpers!$D$43 -> 0 | AS66: =Helpers!$D$44 -> 0 | AT66: =Helpers!$D$45 -> 0 | AU66: =Helpers!$D$46 -> 0 | AV66: =Helpers!$D$47 -> 0 | AW66: =Helpers!$D$48 -> 0 | AX66: =Helpers!$D$49 -> 0 | AY66: =Helpers!$D$50 -> 0 | AZ66: =Helpers!$D$51 -> 0

Sheet Plan
A1: Plan · payday by payday
A2: Type Paid on a row when you've done that payday. The row turns yellow. White columns E to H are for real life.
Z3: Minimum due · by debt, in payoff order | BX3: Bill paid · by debt, in payoff order | DV3: Extra paid · by debt, in payoff order | FT3: Balance after · by debt, in payoff order
Z4: =Helpers!$C$2 -> Card A | AA4: =Helpers!$C$3 -> Card B | AB4: =Helpers!$C$4 | AC4: =Helpers!$C$5 | AD4: =Helpers!$C$6 | AE4: =Helpers!$C$7 | AF4: =Helpers!$C$8 | AG4: =Helpers!$C$9 | AH4: =Helpers!$C$10 | AI4: =Helpers!$C$11 | AJ4: =Helpers!$C$12 | AK4: =Helpers!$C$13 | AL4: =Helpers!$C$14 | AM4: =Helpers!$C$15 | AN4: =Helpers!$C$16 | AO4: =Helpers!$C$17 | AP4: =Helpers!$C$18 | AQ4: =Helpers!$C$19 | AR4: =Helpers!$C$20 | AS4: =Helpers!$C$21 | AT4: =Helpers!$C$22 | AU4: =Helpers!$C$23 | AV4: =Helpers!$C$24 | AW4: =Helpers!$C$25 | AX4: =Helpers!$C$26 | AY4: =Helpers!$C$27 | AZ4: =Helpers!$C$28 | BA4: =Helpers!$C$29 | BB4: =Helpers!$C$30 | BC4: =Helpers!$C$31 | BD4: =Helpers!$C$32 | BE4: =Helpers!$C$33 | BF4: =Helpers!$C$34 | BG4: =Helpers!$C$35 | BH4: =Helpers!$C$36 | BI4: =Helpers!$C$37 | BJ4: =Helpers!$C$38 | BK4: =Helpers!$C$39 | BL4: =Helpers!$C$40 | BM4: =Helpers!$C$41 | BN4: =Helpers!$C$42 | BO4: =Helpers!$C$43 | BP4: =Helpers!$C$44 | BQ4: =Helpers!$C$45 | BR4: =Helpers!$C$46 | BS4: =Helpers!$C$47 | BT4: =Helpers!$C$48 | BU4: =Helpers!$C$49 | BV4: =Helpers!$C$50 | BW4: =Helpers!$C$51 | BX4: =Helpers!$C$2 -> Card A | BY4: =Helpers!$C$3 -> Card B | BZ4: =Helpers!$C$4 | CA4: =Helpers!$C$5 | CB4: =Helpers!$C$6 | CC4: =Helpers!$C$7 | CD4: =Helpers!$C$8 | CE4: =Helpers!$C$9 | CF4: =Helpers!$C$10 | CG4: =Helpers!$C$11 | CH4: =Helpers!$C$12 | CI4: =Helpers!$C$13 | CJ4: =Helpers!$C$14 | CK4: =Helpers!$C$15 | CL4: =Helpers!$C$16 | CM4: =Helpers!$C$17 | CN4: =Helpers!$C$18 | CO4: =Helpers!$C$19 | CP4: =Helpers!$C$20 | CQ4: =Helpers!$C$21 | CR4: =Helpers!$C$22 | CS4: =Helpers!$C$23 | CT4: =Helpers!$C$24 | CU4: =Helpers!$C$25 | CV4: =Helpers!$C$26 | CW4: =Helpers!$C$27 | CX4: =Helpers!$C$28 | CY4: =Helpers!$C$29 | CZ4: =Helpers!$C$30 | DA4: =Helpers!$C$31 | DB4: =Helpers!$C$32 | DC4: =Helpers!$C$33 | DD4: =Helpers!$C$34 | DE4: =Helpers!$C$35 | DF4: =Helpers!$C$36 | DG4: =Helpers!$C$37 | DH4: =Helpers!$C$38 | DI4: =Helpers!$C$39 | DJ4: =Helpers!$C$40 | DK4: =Helpers!$C$41 | DL4: =Helpers!$C$42 | DM4: =Helpers!$C$43 | DN4: =Helpers!$C$44 | DO4: =Helpers!$C$45 | DP4: =Helpers!$C$46 | DQ4: =Helpers!$C$47 | DR4: =Helpers!$C$48 | DS4: =Helpers!$C$49 | DT4: =Helpers!$C$50 | DU4: =Helpers!$C$51 | DV4: =Helpers!$C$2 -> Card A | DW4: =Helpers!$C$3 -> Card B | DX4: =Helpers!$C$4 | DY4: =Helpers!$C$5 | DZ4: =Helpers!$C$6 | EA4: =Helpers!$C$7 | EB4: =Helpers!$C$8 | EC4: =Helpers!$C$9 | ED4: =Helpers!$C$10 | EE4: =Helpers!$C$11 | EF4: =Helpers!$C$12 | EG4: =Helpers!$C$13 | EH4: =Helpers!$C$14 | EI4: =Helpers!$C$15 | EJ4: =Helpers!$C$16 | EK4: =Helpers!$C$17 | EL4: =Helpers!$C$18 | EM4: =Helpers!$C$19 | EN4: =Helpers!$C$20 | EO4: =Helpers!$C$21 | EP4: =Helpers!$C$22 | EQ4: =Helpers!$C$23 | ER4: =Helpers!$C$24 | ES4: =Helpers!$C$25 | ET4: =Helpers!$C$26 | EU4: =Helpers!$C$27 | EV4: =Helpers!$C$28 | EW4: =Helpers!$C$29 | EX4: =Helpers!$C$30 | EY4: =Helpers!$C$31 | EZ4: =Helpers!$C$32 | FA4: =Helpers!$C$33 | FB4: =Helpers!$C$34 | FC4: =Helpers!$C$35 | FD4: =Helpers!$C$36 | FE4: =Helpers!$C$37 | FF4: =Helpers!$C$38 | FG4: =Helpers!$C$39 | FH4: =Helpers!$C$40 | FI4: =Helpers!$C$41 | FJ4: =Helpers!$C$42 | FK4: =Helpers!$C$43 | FL4: =Helpers!$C$44 | FM4: =Helpers!$C$45 | FN4: =Helpers!$C$46 | FO4: =Helpers!$C$47 | FP4: =Helpers!$C$48 | FQ4: =Helpers!$C$49 | FR4: =Helpers!$C$50 | FS4: =Helpers!$C$51 | FT4: =Helpers!$C$2 -> Card A | FU4: =Helpers!$C$3 -> Card B | FV4: =Helpers!$C$4 | FW4: =Helpers!$C$5 | FX4: =Helpers!$C$6 | FY4: =Helpers!$C$7 | FZ4: =Helpers!$C$8 | GA4: =Helpers!$C$9 | GB4: =Helpers!$C$10 | GC4: =Helpers!$C$11 | GD4: =Helpers!$C$12 | GE4: =Helpers!$C$13 | GF4: =Helpers!$C$14 | GG4: =Helpers!$C$15 | GH4: =Helpers!$C$16 | GI4: =Helpers!$C$17 | GJ4: =Helpers!$C$18 | GK4: =Helpers!$C$19 | GL4: =Helpers!$C$20 | GM4: =Helpers!$C$21 | GN4: =Helpers!$C$22 | GO4: =Helpers!$C$23 | GP4: =Helpers!$C$24 | GQ4: =Helpers!$C$25 | GR4: =Helpers!$C$26 | GS4: =Helpers!$C$27 | GT4: =Helpers!$C$28 | GU4: =Helpers!$C$29 | GV4: =Helpers!$C$30 | GW4: =Helpers!$C$31 | GX4: =Helpers!$C$32 | GY4: =Helpers!$C$33 | GZ4: =Helpers!$C$34 | HA4: =Helpers!$C$35 | HB4: =Helpers!$C$36 | HC4: =Helpers!$C$37 | HD4: =Helpers!$C$38 | HE4: =Helpers!$C$39 | HF4: =Helpers!$C$40 | HG4: =Helpers!$C$41 | HH4: =Helpers!$C$42 | HI4: =Helpers!$C$43 | HJ4: =Helpers!$C$44 | HK4: =Helpers!$C$45 | HL4: =Helpers!$C$46 | HM4: =Helpers!$C$47 | HN4: =Helpers!$C$48 | HO4: =Helpers!$C$49 | HP4: =Helpers!$C$50 | HQ4: =Helpers!$C$51
Y5: min / due | Z5: =Helpers!$E$2 -> 25 | AA5: =Helpers!$E$3 -> 40 | AB5: =Helpers!$E$4 -> 0 | AC5: =Helpers!$E$5 -> 0 | AD5: =Helpers!$E$6 -> 0 | AE5: =Helpers!$E$7 -> 0 | AF5: =Helpers!$E$8 -> 0 | AG5: =Helpers!$E$9 -> 0 | AH5: =Helpers!$E$10 -> 0 | AI5: =Helpers!$E$11 -> 0 | AJ5: =Helpers!$E$12 -> 0 | AK5: =Helpers!$E$13 -> 0 | AL5: =Helpers!$E$14 -> 0 | AM5: =Helpers!$E$15 -> 0 | AN5: =Helpers!$E$16 -> 0 | AO5: =Helpers!$E$17 -> 0 | AP5: =Helpers!$E$18 -> 0 | AQ5: =Helpers!$E$19 -> 0 | AR5: =Helpers!$E$20 -> 0 | AS5: =Helpers!$E$21 -> 0 | AT5: =Helpers!$E$22 -> 0 | AU5: =Helpers!$E$23 -> 0 | AV5: =Helpers!$E$24 -> 0 | AW5: =Helpers!$E$25 -> 0 | AX5: =Helpers!$E$26 -> 0 | AY5: =Helpers!$E$27 -> 0 | AZ5: =Helpers!$E$28 -> 0 | BA5: =Helpers!$E$29 -> 0 | BB5: =Helpers!$E$30 -> 0 | BC5: =Helpers!$E$31 -> 0 | BD5: =Helpers!$E$32 -> 0 | BE5: =Helpers!$E$33 -> 0 | BF5: =Helpers!$E$34 -> 0 | BG5: =Helpers!$E$35 -> 0 | BH5: =Helpers!$E$36 -> 0 | BI5: =Helpers!$E$37 -> 0 | BJ5: =Helpers!$E$38 -> 0 | BK5: =Helpers!$E$39 -> 0 | BL5: =Helpers!$E$40 -> 0 | BM5: =Helpers!$E$41 -> 0 | BN5: =Helpers!$E$42 -> 0 | BO5: =Helpers!$E$43 -> 0 | BP5: =Helpers!$E$44 -> 0 | BQ5: =Helpers!$E$45 -> 0 | BR5: =Helpers!$E$46 -> 0 | BS5: =Helpers!$E$47 -> 0 | BT5: =Helpers!$E$48 -> 0 | BU5: =Helpers!$E$49 -> 0 | BV5: =Helpers!$E$50 -> 0 | BW5: =Helpers!$E$51 -> 0 | FT5: =Helpers!$D$2 -> 0.24 | FU5: =Helpers!$D$3 -> 0.18 | FV5: =Helpers!$D$4 -> 0 | FW5: =Helpers!$D$5 -> 0 | FX5: =Helpers!$D$6 -> 0 | FY5: =Helpers!$D$7 -> 0 | FZ5: =Helpers!$D$8 -> 0 | GA5: =Helpers!$D$9 -> 0 | GB5: =Helpers!$D$10 -> 0 | GC5: =Helpers!$D$11 -> 0 | GD5: =Helpers!$D$12 -> 0 | GE5: =Helpers!$D$13 -> 0 | GF5: =Helpers!$D$14 -> 0 | GG5: =Helpers!$D$15 -> 0 | GH5: =Helpers!$D$16 -> 0 | GI5: =Helpers!$D$17 -> 0 | GJ5: =Helpers!$D$18 -> 0 | GK5: =Helpers!$D$19 -> 0 | GL5: =Helpers!$D$20 -> 0 | GM5: =Helpers!$D$21 -> 0 | GN5: =Helpers!$D$22 -> 0 | GO5: =Helpers!$D$23 -> 0 | GP5: =Helpers!$D$24 -> 0 | GQ5: =Helpers!$D$25 -> 0 | GR5: =Helpers!$D$26 -> 0 | GS5: =Helpers!$D$27 -> 0 | GT5: =Helpers!$D$28 -> 0 | GU5: =Helpers!$D$29 -> 0 | GV5: =Helpers!$D$30 -> 0 | GW5: =Helpers!$D$31 -> 0 | GX5: =Helpers!$D$32 -> 0 | GY5: =Helpers!$D$33 -> 0 | GZ5: =Helpers!$D$34 -> 0 | HA5: =Helpers!$D$35 -> 0 | HB5: =Helpers!$D$36 -> 0 | HC5: =Helpers!$D$37 -> 0 | HD5: =Helpers!$D$38 -> 0 | HE5: =Helpers!$D$39 -> 0 | HF5: =Helpers!$D$40 -> 0 | HG5: =Helpers!$D$41 -> 0 | HH5: =Helpers!$D$42 -> 0 | HI5: =Helpers!$D$43 -> 0 | HJ5: =Helpers!$D$44 -> 0 | HK5: =Helpers!$D$45 -> 0 | HL5: =Helpers!$D$46 -> 0 | HM5: =Helpers!$D$47 -> 0 | HN5: =Helpers!$D$48 -> 0 | HO5: =Helpers!$D$49 -> 0 | HP5: =Helpers!$D$50 -> 0 | HQ5: =Helpers!$D$51 -> 0
Z6: =Helpers!$F$2 -> 10 | AA6: =Helpers!$F$3 -> 20 | AB6: =Helpers!$F$4 | AC6: =Helpers!$F$5 | AD6: =Helpers!$F$6 | AE6: =Helpers!$F$7 | AF6: =Helpers!$F$8 | AG6: =Helpers!$F$9 | AH6: =Helpers!$F$10 | AI6: =Helpers!$F$11 | AJ6: =Helpers!$F$12 | AK6: =Helpers!$F$13 | AL6: =Helpers!$F$14 | AM6: =Helpers!$F$15 | AN6: =Helpers!$F$16 | AO6: =Helpers!$F$17 | AP6: =Helpers!$F$18 | AQ6: =Helpers!$F$19 | AR6: =Helpers!$F$20 | AS6: =Helpers!$F$21 | AT6: =Helpers!$F$22 | AU6: =Helpers!$F$23 | AV6: =Helpers!$F$24 | AW6: =Helpers!$F$25 | AX6: =Helpers!$F$26 | AY6: =Helpers!$F$27 | AZ6: =Helpers!$F$28 | BA6: =Helpers!$F$29 | BB6: =Helpers!$F$30 | BC6: =Helpers!$F$31 | BD6: =Helpers!$F$32 | BE6: =Helpers!$F$33 | BF6: =Helpers!$F$34 | BG6: =Helpers!$F$35 | BH6: =Helpers!$F$36 | BI6: =Helpers!$F$37 | BJ6: =Helpers!$F$38 | BK6: =Helpers!$F$39 | BL6: =Helpers!$F$40 | BM6: =Helpers!$F$41 | BN6: =Helpers!$F$42 | BO6: =Helpers!$F$43 | BP6: =Helpers!$F$44 | BQ6: =Helpers!$F$45 | BR6: =Helpers!$F$46 | BS6: =Helpers!$F$47 | BT6: =Helpers!$F$48 | BU6: =Helpers!$F$49 | BV6: =Helpers!$F$50 | BW6: =Helpers!$F$51 | DV6: 1 | DW6: 2 | DX6: 3 | DY6: 4 | DZ6: 5 | EA6: 6 | EB6: 7 | EC6: 8 | ED6: 9 | EE6: 10 | EF6: 11 | EG6: 12 | EH6: 13 | EI6: 14 | EJ6: 15 | EK6: 16 | EL6: 17 | EM6: 18 | EN6: 19 | EO6: 20 | EP6: 21 | EQ6: 22 | ER6: 23 | ES6: 24 | ET6: 25 | EU6: 26 | EV6: 27 | EW6: 28 | EX6: 29 | EY6: 30 | EZ6: 31 | FA6: 32 | FB6: 33 | FC6: 34 | FD6: 35 | FE6: 36 | FF6: 37 | FG6: 38 | FH6: 39 | FI6: 40 | FJ6: 41 | FK6: 42 | FL6: 43 | FM6: 44 | FN6: 45 | FO6: 46 | FP6: 47 | FQ6: 48 | FR6: 49 | FS6: 50 | FT6: 1 | FU6: 2 | FV6: 3 | FW6: 4 | FX6: 5 | FY6: 6 | FZ6: 7 | GA6: 8 | GB6: 9 | GC6: 10 | GD6: 11 | GE6: 12 | GF6: 13 | GG6: 14 | GH6: 15 | GI6: 16 | GJ6: 17 | GK6: 18 | GL6: 19 | GM6: 20 | GN6: 21 | GO6: 22 | GP6: 23 | GQ6: 24 | GR6: 25 | GS6: 26 | GT6: 27 | GU6: 28 | GV6: 29 | GW6: 30 | GX6: 31 | GY6: 32 | GZ6: 33 | HA6: 34 | HB6: 35 | HC6: 36 | HD6: 37 | HE6: 38 | HF6: 39 | HG6: 40 | HH6: 41 | HI6: 42 | HJ6: 43 | HK6: 44 | HL6: 45 | HM6: 46 | HN6: 47 | HO6: 48 | HP6: 49 | HQ6: 50
A7: Payday # | B7: Payday | C7: Next payday | D7: Paid? | E7: Amount +/- | F7: New charge | G7: Buffer used | H7: Yearly bill paid | I7: Money for the plan | J7: To yearly bills | K7: To buffer | L7: Buffer after | M7: Yearly bills saved | N7: Bills this payday | O7: Freed-up minimums | P7: Extra for debts | Q7: Extra paid | R7: Move this payday | S7: Interest | T7: Still owed | U7: Focus debt | V7: Charge goes to # | W7: Open | X7: Minimums only: owed | Z7: =IF(Helpers!$C$2="","#1",Helpers!$C$2) -> Card A | AA7: =IF(Helpers!$C$3="","#2",Helpers!$C$3) -> Card B | AB7: =IF(Helpers!$C$4="","#3",Helpers!$C$4) -> #3 | AC7: =IF(Helpers!$C$5="","#4",Helpers!$C$5) -> #4 | AD7: =IF(Helpers!$C$6="","#5",Helpers!$C$6) -> #5 | AE7: =IF(Helpers!$C$7="","#6",Helpers!$C$7) -> #6 | AF7: =IF(Helpers!$C$8="","#7",Helpers!$C$8) -> #7 | AG7: =IF(Helpers!$C$9="","#8",Helpers!$C$9) -> #8 | AH7: =IF(Helpers!$C$10="","#9",Helpers!$C$10) -> #9 | AI7: =IF(Helpers!$C$11="","#10",Helpers!$C$11) -> #10 | AJ7: =IF(Helpers!$C$12="","#11",Helpers!$C$12) -> #11 | AK7: =IF(Helpers!$C$13="","#12",Helpers!$C$13) -> #12 | AL7: =IF(Helpers!$C$14="","#13",Helpers!$C$14) -> #13 | AM7: =IF(Helpers!$C$15="","#14",Helpers!$C$15) -> #14 | AN7: =IF(Helpers!$C$16="","#15",Helpers!$C$16) -> #15 | AO7: =IF(Helpers!$C$17="","#16",Helpers!$C$17) -> #16 | AP7: =IF(Helpers!$C$18="","#17",Helpers!$C$18) -> #17 | AQ7: =IF(Helpers!$C$19="","#18",Helpers!$C$19) -> #18 | AR7: =IF(Helpers!$C$20="","#19",Helpers!$C$20) -> #19 | AS7: =IF(Helpers!$C$21="","#20",Helpers!$C$21) -> #20 | AT7: =IF(Helpers!$C$22="","#21",Helpers!$C$22) -> #21 | AU7: =IF(Helpers!$C$23="","#22",Helpers!$C$23) -> #22 | AV7: =IF(Helpers!$C$24="","#23",Helpers!$C$24) -> #23 | AW7: =IF(Helpers!$C$25="","#24",Helpers!$C$25) -> #24 | AX7: =IF(Helpers!$C$26="","#25",Helpers!$C$26) -> #25 | AY7: =IF(Helpers!$C$27="","#26",Helpers!$C$27) -> #26 | AZ7: =IF(Helpers!$C$28="","#27",Helpers!$C$28) -> #27 | BA7: =IF(Helpers!$C$29="","#28",Helpers!$C$29) -> #28 | BB7: =IF(Helpers!$C$30="","#29",Helpers!$C$30) -> #29 | BC7: =IF(Helpers!$C$31="","#30",Helpers!$C$31) -> #30 | BD7: =IF(Helpers!$C$32="","#31",Helpers!$C$32) -> #31 | BE7: =IF(Helpers!$C$33="","#32",Helpers!$C$33) -> #32 | BF7: =IF(Helpers!$C$34="","#33",Helpers!$C$34) -> #33 | BG7: =IF(Helpers!$C$35="","#34",Helpers!$C$35) -> #34 | BH7: =IF(Helpers!$C$36="","#35",Helpers!$C$36) -> #35 | BI7: =IF(Helpers!$C$37="","#36",Helpers!$C$37) -> #36 | BJ7: =IF(Helpers!$C$38="","#37",Helpers!$C$38) -> #37 | BK7: =IF(Helpers!$C$39="","#38",Helpers!$C$39) -> #38 | BL7: =IF(Helpers!$C$40="","#39",Helpers!$C$40) -> #39 | BM7: =IF(Helpers!$C$41="","#40",Helpers!$C$41) -> #40 | BN7: =IF(Helpers!$C$42="","#41",Helpers!$C$42) -> #41 | BO7: =IF(Helpers!$C$43="","#42",Helpers!$C$43) -> #42 | BP7: =IF(Helpers!$C$44="","#43",Helpers!$C$44) -> #43 | BQ7: =IF(Helpers!$C$45="","#44",Helpers!$C$45) -> #44 | BR7: =IF(Helpers!$C$46="","#45",Helpers!$C$46) -> #45 | BS7: =IF(Helpers!$C$47="","#46",Helpers!$C$47) -> #46 | BT7: =IF(Helpers!$C$48="","#47",Helpers!$C$48) -> #47 | BU7: =IF(Helpers!$C$49="","#48",Helpers!$C$49) -> #48 | BV7: =IF(Helpers!$C$50="","#49",Helpers!$C$50) -> #49 | BW7: =IF(Helpers!$C$51="","#50",Helpers!$C$51) -> #50 | BX7: =IF(Helpers!$C$2="","#1",Helpers!$C$2) -> Card A | BY7: =IF(Helpers!$C$3="","#2",Helpers!$C$3) -> Card B | BZ7: =IF(Helpers!$C$4="","#3",Helpers!$C$4) -> #3 | CA7: =IF(Helpers!$C$5="","#4",Helpers!$C$5) -> #4 | CB7: =IF(Helpers!$C$6="","#5",Helpers!$C$6) -> #5 | CC7: =IF(Helpers!$C$7="","#6",Helpers!$C$7) -> #6 | CD7: =IF(Helpers!$C$8="","#7",Helpers!$C$8) -> #7 | CE7: =IF(Helpers!$C$9="","#8",Helpers!$C$9) -> #8 | CF7: =IF(Helpers!$C$10="","#9",Helpers!$C$10) -> #9 | CG7: =IF(Helpers!$C$11="","#10",Helpers!$C$11) -> #10 | CH7: =IF(Helpers!$C$12="","#11",Helpers!$C$12) -> #11 | CI7: =IF(Helpers!$C$13="","#12",Helpers!$C$13) -> #12 | CJ7: =IF(Helpers!$C$14="","#13",Helpers!$C$14) -> #13 | CK7: =IF(Helpers!$C$15="","#14",Helpers!$C$15) -> #14 | CL7: =IF(Helpers!$C$16="","#15",Helpers!$C$16) -> #15 | CM7: =IF(Helpers!$C$17="","#16",Helpers!$C$17) -> #16 | CN7: =IF(Helpers!$C$18="","#17",Helpers!$C$18) -> #17 | CO7: =IF(Helpers!$C$19="","#18",Helpers!$C$19) -> #18 | CP7: =IF(Helpers!$C$20="","#19",Helpers!$C$20) -> #19 | CQ7: =IF(Helpers!$C$21="","#20",Helpers!$C$21) -> #20 | CR7: =IF(Helpers!$C$22="","#21",Helpers!$C$22) -> #21 | CS7: =IF(Helpers!$C$23="","#22",Helpers!$C$23) -> #22 | CT7: =IF(Helpers!$C$24="","#23",Helpers!$C$24) -> #23 | CU7: =IF(Helpers!$C$25="","#24",Helpers!$C$25) -> #24 | CV7: =IF(Helpers!$C$26="","#25",Helpers!$C$26) -> #25 | CW7: =IF(Helpers!$C$27="","#26",Helpers!$C$27) -> #26 | CX7: =IF(Helpers!$C$28="","#27",Helpers!$C$28) -> #27 | CY7: =IF(Helpers!$C$29="","#28",Helpers!$C$29) -> #28 | CZ7: =IF(Helpers!$C$30="","#29",Helpers!$C$30) -> #29 | DA7: =IF(Helpers!$C$31="","#30",Helpers!$C$31) -> #30 | DB7: =IF(Helpers!$C$32="","#31",Helpers!$C$32) -> #31 | DC7: =IF(Helpers!$C$33="","#32",Helpers!$C$33) -> #32 | DD7: =IF(Helpers!$C$34="","#33",Helpers!$C$34) -> #33 | DE7: =IF(Helpers!$C$35="","#34",Helpers!$C$35) -> #34 | DF7: =IF(Helpers!$C$36="","#35",Helpers!$C$36) -> #35 | DG7: =IF(Helpers!$C$37="","#36",Helpers!$C$37) -> #36 | DH7: =IF(Helpers!$C$38="","#37",Helpers!$C$38) -> #37 | DI7: =IF(Helpers!$C$39="","#38",Helpers!$C$39) -> #38 | DJ7: =IF(Helpers!$C$40="","#39",Helpers!$C$40) -> #39 | DK7: =IF(Helpers!$C$41="","#40",Helpers!$C$41) -> #40 | DL7: =IF(Helpers!$C$42="","#41",Helpers!$C$42) -> #41 | DM7: =IF(Helpers!$C$43="","#42",Helpers!$C$43) -> #42 | DN7: =IF(Helpers!$C$44="","#43",Helpers!$C$44) -> #43 | DO7: =IF(Helpers!$C$45="","#44",Helpers!$C$45) -> #44 | DP7: =IF(Helpers!$C$46="","#45",Helpers!$C$46) -> #45 | DQ7: =IF(Helpers!$C$47="","#46",Helpers!$C$47) -> #46 | DR7: =IF(Helpers!$C$48="","#47",Helpers!$C$48) -> #47 | DS7: =IF(Helpers!$C$49="","#48",Helpers!$C$49) -> #48 | DT7: =IF(Helpers!$C$50="","#49",Helpers!$C$50) -> #49 | DU7: =IF(Helpers!$C$51="","#50",Helpers!$C$51) -> #50 | DV7: =IF(Helpers!$C$2="","#1",Helpers!$C$2) -> Card A | DW7: =IF(Helpers!$C$3="","#2",Helpers!$C$3) -> Card B | DX7: =IF(Helpers!$C$4="","#3",Helpers!$C$4) -> #3 | DY7: =IF(Helpers!$C$5="","#4",Helpers!$C$5) -> #4 | DZ7: =IF(Helpers!$C$6="","#5",Helpers!$C$6) -> #5 | EA7: =IF(Helpers!$C$7="","#6",Helpers!$C$7) -> #6 | EB7: =IF(Helpers!$C$8="","#7",Helpers!$C$8) -> #7 | EC7: =IF(Helpers!$C$9="","#8",Helpers!$C$9) -> #8 | ED7: =IF(Helpers!$C$10="","#9",Helpers!$C$10) -> #9 | EE7: =IF(Helpers!$C$11="","#10",Helpers!$C$11) -> #10 | EF7: =IF(Helpers!$C$12="","#11",Helpers!$C$12) -> #11 | EG7: =IF(Helpers!$C$13="","#12",Helpers!$C$13) -> #12 | EH7: =IF(Helpers!$C$14="","#13",Helpers!$C$14) -> #13 | EI7: =IF(Helpers!$C$15="","#14",Helpers!$C$15) -> #14 | EJ7: =IF(Helpers!$C$16="","#15",Helpers!$C$16) -> #15 | EK7: =IF(Helpers!$C$17="","#16",Helpers!$C$17) -> #16 | EL7: =IF(Helpers!$C$18="","#17",Helpers!$C$18) -> #17 | EM7: =IF(Helpers!$C$19="","#18",Helpers!$C$19) -> #18 | EN7: =IF(Helpers!$C$20="","#19",Helpers!$C$20) -> #19 | EO7: =IF(Helpers!$C$21="","#20",Helpers!$C$21) -> #20 | EP7: =IF(Helpers!$C$22="","#21",Helpers!$C$22) -> #21 | EQ7: =IF(Helpers!$C$23="","#22",Helpers!$C$23) -> #22 | ER7: =IF(Helpers!$C$24="","#23",Helpers!$C$24) -> #23 | ES7: =IF(Helpers!$C$25="","#24",Helpers!$C$25) -> #24 | ET7: =IF(Helpers!$C$26="","#25",Helpers!$C$26) -> #25 | EU7: =IF(Helpers!$C$27="","#26",Helpers!$C$27) -> #26 | EV7: =IF(Helpers!$C$28="","#27",Helpers!$C$28) -> #27 | EW7: =IF(Helpers!$C$29="","#28",Helpers!$C$29) -> #28 | EX7: =IF(Helpers!$C$30="","#29",Helpers!$C$30) -> #29 | EY7: =IF(Helpers!$C$31="","#30",Helpers!$C$31) -> #30 | EZ7: =IF(Helpers!$C$32="","#31",Helpers!$C$32) -> #31 | FA7: =IF(Helpers!$C$33="","#32",Helpers!$C$33) -> #32 | FB7: =IF(Helpers!$C$34="","#33",Helpers!$C$34) -> #33 | FC7: =IF(Helpers!$C$35="","#34",Helpers!$C$35) -> #34 | FD7: =IF(Helpers!$C$36="","#35",Helpers!$C$36) -> #35 | FE7: =IF(Helpers!$C$37="","#36",Helpers!$C$37) -> #36 | FF7: =IF(Helpers!$C$38="","#37",Helpers!$C$38) -> #37 | FG7: =IF(Helpers!$C$39="","#38",Helpers!$C$39) -> #38 | FH7: =IF(Helpers!$C$40="","#39",Helpers!$C$40) -> #39 | FI7: =IF(Helpers!$C$41="","#40",Helpers!$C$41) -> #40 | FJ7: =IF(Helpers!$C$42="","#41",Helpers!$C$42) -> #41 | FK7: =IF(Helpers!$C$43="","#42",Helpers!$C$43) -> #42 | FL7: =IF(Helpers!$C$44="","#43",Helpers!$C$44) -> #43 | FM7: =IF(Helpers!$C$45="","#44",Helpers!$C$45) -> #44 | FN7: =IF(Helpers!$C$46="","#45",Helpers!$C$46) -> #45 | FO7: =IF(Helpers!$C$47="","#46",Helpers!$C$47) -> #46 | FP7: =IF(Helpers!$C$48="","#47",Helpers!$C$48) -> #47 | FQ7: =IF(Helpers!$C$49="","#48",Helpers!$C$49) -> #48 | FR7: =IF(Helpers!$C$50="","#49",Helpers!$C$50) -> #49 | FS7: =IF(Helpers!$C$51="","#50",Helpers!$C$51) -> #50 | FT7: =IF(Helpers!$C$2="","#1",Helpers!$C$2) -> Card A | FU7: =IF(Helpers!$C$3="","#2",Helpers!$C$3) -> Card B | FV7: =IF(Helpers!$C$4="","#3",Helpers!$C$4) -> #3 | FW7: =IF(Helpers!$C$5="","#4",Helpers!$C$5) -> #4 | FX7: =IF(Helpers!$C$6="","#5",Helpers!$C$6) -> #5 | FY7: =IF(Helpers!$C$7="","#6",Helpers!$C$7) -> #6 | FZ7: =IF(Helpers!$C$8="","#7",Helpers!$C$8) -> #7 | GA7: =IF(Helpers!$C$9="","#8",Helpers!$C$9) -> #8 | GB7: =IF(Helpers!$C$10="","#9",Helpers!$C$10) -> #9 | GC7: =IF(Helpers!$C$11="","#10",Helpers!$C$11) -> #10 | GD7: =IF(Helpers!$C$12="","#11",Helpers!$C$12) -> #11 | GE7: =IF(Helpers!$C$13="","#12",Helpers!$C$13) -> #12 | GF7: =IF(Helpers!$C$14="","#13",Helpers!$C$14) -> #13 | GG7: =IF(Helpers!$C$15="","#14",Helpers!$C$15) -> #14 | GH7: =IF(Helpers!$C$16="","#15",Helpers!$C$16) -> #15 | GI7: =IF(Helpers!$C$17="","#16",Helpers!$C$17) -> #16 | GJ7: =IF(Helpers!$C$18="","#17",Helpers!$C$18) -> #17 | GK7: =IF(Helpers!$C$19="","#18",Helpers!$C$19) -> #18 | GL7: =IF(Helpers!$C$20="","#19",Helpers!$C$20) -> #19 | GM7: =IF(Helpers!$C$21="","#20",Helpers!$C$21) -> #20 | GN7: =IF(Helpers!$C$22="","#21",Helpers!$C$22) -> #21 | GO7: =IF(Helpers!$C$23="","#22",Helpers!$C$23) -> #22 | GP7: =IF(Helpers!$C$24="","#23",Helpers!$C$24) -> #23 | GQ7: =IF(Helpers!$C$25="","#24",Helpers!$C$25) -> #24 | GR7: =IF(Helpers!$C$26="","#25",Helpers!$C$26) -> #25 | GS7: =IF(Helpers!$C$27="","#26",Helpers!$C$27) -> #26 | GT7: =IF(Helpers!$C$28="","#27",Helpers!$C$28) -> #27 | GU7: =IF(Helpers!$C$29="","#28",Helpers!$C$29) -> #28 | GV7: =IF(Helpers!$C$30="","#29",Helpers!$C$30) -> #29 | GW7: =IF(Helpers!$C$31="","#30",Helpers!$C$31) -> #30 | GX7: =IF(Helpers!$C$32="","#31",Helpers!$C$32) -> #31 | GY7: =IF(Helpers!$C$33="","#32",Helpers!$C$33) -> #32 | GZ7: =IF(Helpers!$C$34="","#33",Helpers!$C$34) -> #33 | HA7: =IF(Helpers!$C$35="","#34",Helpers!$C$35) -> #34 | HB7: =IF(Helpers!$C$36="","#35",Helpers!$C$36) -> #35 | HC7: =IF(Helpers!$C$37="","#36",Helpers!$C$37) -> #36 | HD7: =IF(Helpers!$C$38="","#37",Helpers!$C$38) -> #37 | HE7: =IF(Helpers!$C$39="","#38",Helpers!$C$39) -> #38 | HF7: =IF(Helpers!$C$40="","#39",Helpers!$C$40) -> #39 | HG7: =IF(Helpers!$C$41="","#40",Helpers!$C$41) -> #40 | HH7: =IF(Helpers!$C$42="","#41",Helpers!$C$42) -> #41 | HI7: =IF(Helpers!$C$43="","#42",Helpers!$C$43) -> #42 | HJ7: =IF(Helpers!$C$44="","#43",Helpers!$C$44) -> #43 | HK7: =IF(Helpers!$C$45="","#44",Helpers!$C$45) -> #44 | HL7: =IF(Helpers!$C$46="","#45",Helpers!$C$46) -> #45 | HM7: =IF(Helpers!$C$47="","#46",Helpers!$C$47) -> #46 | HN7: =IF(Helpers!$C$48="","#47",Helpers!$C$48) -> #47 | HO7: =IF(Helpers!$C$49="","#48",Helpers!$C$49) -> #48 | HP7: =IF(Helpers!$C$50="","#49",Helpers!$C$50) -> #49 | HQ7: =IF(Helpers!$C$51="","#50",Helpers!$C$51) -> #50
A8: Start | B8: =Setup!$C$8 -> 46325 | L8: =N(Setup!$C$13) -> 300 | M8: 0 | T8: =SUM(FT8:HQ8) -> 1700 | X8: =T8 -> 1700 | FT8: =Helpers!$G$2 -> 500 | FU8: =Helpers!$G$3 -> 1200 | FV8: =Helpers!$G$4 -> 0 | FW8: =Helpers!$G$5 -> 0 | FX8: =Helpers!$G$6 -> 0 | FY8: =Helpers!$G$7 -> 0 | FZ8: =Helpers!$G$8 -> 0 | GA8: =Helpers!$G$9 -> 0 | GB8: =Helpers!$G$10 -> 0 | GC8: =Helpers!$G$11 -> 0 | GD8: =Helpers!$G$12 -> 0 | GE8: =Helpers!$G$13 -> 0 | GF8: =Helpers!$G$14 -> 0 | GG8: =Helpers!$G$15 -> 0 | GH8: =Helpers!$G$16 -> 0 | GI8: =Helpers!$G$17 -> 0 | GJ8: =Helpers!$G$18 -> 0 | GK8: =Helpers!$G$19 -> 0 | GL8: =Helpers!$G$20 -> 0 | GM8: =Helpers!$G$21 -> 0 | GN8: =Helpers!$G$22 -> 0 | GO8: =Helpers!$G$23 -> 0 | GP8: =Helpers!$G$24 -> 0 | GQ8: =Helpers!$G$25 -> 0 | GR8: =Helpers!$G$26 -> 0 | GS8: =Helpers!$G$27 -> 0 | GT8: =Helpers!$G$28 -> 0 | GU8: =Helpers!$G$29 -> 0 | GV8: =Helpers!$G$30 -> 0 | GW8: =Helpers!$G$31 -> 0 | GX8: =Helpers!$G$32 -> 0 | GY8: =Helpers!$G$33 -> 0 | GZ8: =Helpers!$G$34 -> 0 | HA8: =Helpers!$G$35 -> 0 | HB8: =Helpers!$G$36 -> 0 | HC8: =Helpers!$G$37 -> 0 | HD8: =Helpers!$G$38 -> 0 | HE8: =Helpers!$G$39 -> 0 | HF8: =Helpers!$G$40 -> 0 | HG8: =Helpers!$G$41 -> 0 | HH8: =Helpers!$G$42 -> 0 | HI8: =Helpers!$G$43 -> 0 | HJ8: =Helpers!$G$44 -> 0 | HK8: =Helpers!$G$45 -> 0 | HL8: =Helpers!$G$46 -> 0 | HM8: =Helpers!$G$47 -> 0 | HN8: =Helpers!$G$48 -> 0 | HO8: =Helpers!$G$49 -> 0 | HP8: =Helpers!$G$50 -> 0 | HQ8: =Helpers!$G$51 -> 0
A9: 1 | B9: =IF(Setup!$C$7="Every month",EDATE(Setup!$C$8,($A9-1)),IF(Setup!$C$7="Twice a month",DATE(YEAR(Setup!$C$8),MONTH(Setup!$C$8)+INT((($A9-1)+Setup!$C$41)/2),MIN(IF(MOD(($A9-1)+Setup!$C$41,2)=0,Setup!$C$39,Setup!$C$40),DAY(EOMONTH(DATE(YEAR(Setup!$C$8),MONTH(Setup!$C$8)+INT((($A9-1)+Setup!$C$41)/2),1),0)))),Setup!$C$8+($A9-1)*IF(Setup!$C$7="Every week",7,14))) -> 46325 | C9: =IF(Setup!$C$7="Every month",EDATE(Setup!$C$8,$A9),IF(Setup!$C$7="Twice a month",DATE(YEAR(Setup!$C$8),MONTH(Setup!$C$8)+INT(($A9+Setup!$C$41)/2),MIN(IF(MOD($A9+Setup!$C$41,2)=0,Setup!$C$39,Setup!$C$40),DAY(EOMONTH(DATE(YEAR(Setup!$C$8),MONTH(Setup!$C$8)+INT(($A9+Setup!$C$41)/2),1),0)))),Setup!$C$8+$A9*IF(Setup!$C$7="Every week",7,14))) -> 46339 | I9: =N(Setup!$C$11)+N(E9) -> 100 | J9: =MIN(Setup!$C$37,MAX(I9,0)) -> 9.2307692 | K9: =MIN(MAX(N(Setup!$C$14)-L8,0),MAX(I9-J9,0)) -> 90.769231 | L9: =L8+K9-N(G9) -> 390.76923 | M9: =M8+J9-N(H9) -> 9.2307692 | N9: =SUM(BX9:DU9) -> 25 | O9: =SUM(Z9:BW9)-N9 -> 0 | P9: =MAX(I9-J9-K9,0)+O9 -> 0 | Q9: =SUM(DV9:FS9) -> 0 | R9: =N9+J9+K9+Q9 -> 125 | S9: =T9-T8-N(F9)+N9+Q9 -> 12.923077 | T9: =SUM(FT9:HQ9) -> 1687.9231 | U9: =IF(T8<0.005,"",INDEX(Helpers!$C$2:$C$51,IF(_xlfn.MINIFS($DV$6:$FS$6,DV9:FS9,">0.005")=0,V9,_xlfn.MINIFS($DV$6:$FS$6,DV9:FS9,">0.005")))) -> Card A | V9: =IF(_xlfn.MINIFS($FT$6:$HQ$6,FT8:HQ8,">0.005")=0,1,_xlfn.MINIFS($FT$6:$HQ$6,FT8:HQ8,">0.005")) -> 1 | W9: =IF(AND(D9<>"Paid",T8>0.005),1,0) -> 1 | X9: =SUMPRODUCT(((Helpers!$G$2:$G$51*(1+(Helpers!$D$2:$D$51+0.000000001)/12)^(($B9-Setup!$C$8)/(365.25/12))-Helpers!$E$2:$E$51*((1+(Helpers!$D$2:$D$51+0.000000001)/12)^(($B9-Setup!$C$8)/(365.25/12))-1)/((Helpers!$D$2:$D$51+0.000000001)/12))>0)*(Helpers!$G$2:$G$51*(1+(Helpers!$D$2:$D$51+0.000000001)/12)^(($B9-Setup!$C$8)/(365.25/12))-Helpers!$E$2:$E$51*((1+(Helpers!$D$2:$D$51+0.000000001)/12)^(($B9-Setup!$C$8)/(365.25/12))-1)/((Helpers!$D$2:$D$51+0.000000001)/12))) -> 1700 | Z9: =IF(OR(N(Z$5)=0,Z$6=""),0,Z$5*((DATE(YEAR($B9),MONTH($B9),MIN(Z$6,DAY(EOMONTH($B9,0))))>=$B9)*(DATE(YEAR($B9),MONTH($B9),MIN(Z$6,DAY(EOMONTH($B9,0))))<$C9)+(DATE(YEAR($B9),MONTH($B9)+1,MIN(Z$6,DAY(EOMONTH($B9,1))))>=$B9)*(DATE(YEAR($B9),MONTH($B9)+1,MIN(Z$6,DAY(EOMONTH($B9,1))))<$C9))) -> 25 | AA9: =IF(OR(N(AA$5)=0,AA$6=""),0,AA$5*((DATE(YEAR($B9),MONTH($B9),MIN(AA$6,DAY(EOMONTH($B9,0))))>=$B9)*(DATE(YEAR($B9),MONTH($B9),MIN(AA$6,DAY(EOMONTH($B9,0))))<$C9)+(DATE(YEAR($B9),MONTH($B9)+1,MIN(AA$6,DAY(EOMONTH($B9,1))))>=$B9)*(DATE(YEAR($B9),MONTH($B9)+1,MIN(AA$6,DAY(EOMONTH($B9,1))))<$C9))) -> 0 | AB9: =IF(OR(N(AB$5)=0,AB$6=""),0,AB$5*((DATE(YEAR($B9),MONTH($B9),MIN(AB$6,DAY(EOMONTH($B9,0))))>=$B9)*(DATE(YEAR($B9),MONTH($B9),MIN(AB$6,DAY(EOMONTH($B9,0))))<$C9)+(DATE(YEAR($B9),MONTH($B9)+1,MIN(AB$6,DAY(EOMONTH($B9,1))))>=$B9)*(DATE(YEAR($B9),MONTH($B9)+1,MIN(AB$6,DAY(EOMONTH($B9,1))))<$C9))) -> 0 | AC9: =IF(OR(N(AC$5)=0,AC$6=""),0,AC$5*((DATE(YEAR($B9),MONTH($B9),MIN(AC$6,DAY(EOMONTH($B9,0))))>=$B9)*(DATE(YEAR($B9),MONTH($B9),MIN(AC$6,DAY(EOMONTH($B9,0))))<$C9)+(DATE(YEAR($B9),MONTH($B9)+1,MIN(AC$6,DAY(EOMONTH($B9,1))))>=$B9)*(DATE(YEAR($B9),MONTH($B9)+1,MIN(AC$6,DAY(EOMONTH($B9,1))))<$C9))) -> 0 | AD9: =IF(OR(N(AD$5)=0,AD$6=""),0,AD$5*((DATE(YEAR($B9),MONTH($B9),MIN(AD$6,DAY(EOMONTH($B9,0))))>=$B9)*(DATE(YEAR($B9),MONTH($B9),MIN(AD$6,DAY(EOMONTH($B9,0))))<$C9)+(DATE(YEAR($B9),MONTH($B9)+1,MIN(AD$6,DAY(EOMONTH($B9,1))))>=$B9)*(DATE(YEAR($B9),MONTH($B9)+1,MIN(AD$6,DAY(EOMONTH($B9,1))))<$C9))) -> 0 | AE9: =IF(OR(N(AE$5)=0,AE$6=""),0,AE$5*((DATE(YEAR($B9),MONTH($B9),MIN(AE$6,DAY(EOMONTH($B9,0))))>=$B9)*(DATE(YEAR($B9),MONTH($B9),MIN(AE$6,DAY(EOMONTH($B9,0))))<$C9)+(DATE(YEAR($B9),MONTH($B9)+1,MIN(AE$6,DAY(EOMONTH($B9,1))))>=$B9)*(DATE(YEAR($B9),MONTH($B9)+1,MIN(AE$6,DAY(EOMONTH($B9,1))))<$C9))) -> 0 | AF9: =IF(OR(N(AF$5)=0,AF$6=""),0,AF$5*((DATE(YEAR($B9),MONTH($B9),MIN(AF$6,DAY(EOMONTH($B9,0))))>=$B9)*(DATE(YEAR($B9),MONTH($B9),MIN(AF$6,DAY(EOMONTH($B9,0))))<$C9)+(DATE(YEAR($B9),MONTH($B9)+1,MIN(AF$6,DAY(EOMONTH($B9,1))))>=$B9)*(DATE(YEAR($B9),MONTH($B9)+1,MIN(AF$6,DAY(EOMONTH($B9,1))))<$C9))) -> 0 | AG9: =IF(OR(N(AG$5)=0,AG$6=""),0,AG$5*((DATE(YEAR($B9),MONTH($B9),MIN(AG$6,DAY(EOMONTH($B9,0))))>=$B9)*(DATE(YEAR($B9),MONTH($B9),MIN(AG$6,DAY(EOMONTH($B9,0))))<$C9)+(DATE(YEAR($B9),MONTH($B9)+1,MIN(AG$6,DAY(EOMONTH($B9,1))))>=$B9)*(DATE(YEAR($B9),MONTH($B9)+1,MIN(AG$6,DAY(EOMONTH($B9,1))))<$C9))) -> 0 | ... BW9: =IF(OR(N(BW$5)=0,BW$6=""),0,BW$5*((DATE(YEAR($B9),MONTH($B9),MIN(BW$6,DAY(EOMONTH($B9,0))))>=$B9)*(DATE(YEAR($B9),MONTH($B9),MIN(BW$6,DAY(EOMONTH($B9,0))))<$C9)+(DATE(YEAR($B9),MONTH($B9)+1,MIN(BW$6,DAY(EOMONTH($B9,1))))>=$B9)*(DATE(YEAR($B9),MONTH($B9)+1,MIN(BW$6,DAY(EOMONTH($B9,1))))<$C9))) -> 0 | BX9: =MIN(Z9,(FT8*(1+FT$5/Setup!$C$36)+IF($V9=1,N($F9),0))) -> 25 | BY9: =MIN(AA9,(FU8*(1+FU$5/Setup!$C$36)+IF($V9=2,N($F9),0))) -> 0 | BZ9: =MIN(AB9,(FV8*(1+FV$5/Setup!$C$36)+IF($V9=3,N($F9),0))) -> 0 | CA9: =MIN(AC9,(FW8*(1+FW$5/Setup!$C$36)+IF($V9=4,N($F9),0))) -> 0 | CB9: =MIN(AD9,(FX8*(1+FX$5/Setup!$C$36)+IF($V9=5,N($F9),0))) -> 0 | CC9: =MIN(AE9,(FY8*(1+FY$5/Setup!$C$36)+IF($V9=6,N($F9),0))) -> 0 | CD9: =MIN(AF9,(FZ8*(1+FZ$5/Setup!$C$36)+IF($V9=7,N($F9),0))) -> 0 | CE9: =MIN(AG9,(GA8*(1+GA$5/Setup!$C$36)+IF($V9=8,N($F9),0))) -> 0 | CF9: =MIN(AH9,(GB8*(1+GB$5/Setup!$C$36)+IF($V9=9,N($F9),0))) -> 0 | CG9: =MIN(AI9,(GC8*(1+GC$5/Setup!$C$36)+IF($V9=10,N($F9),0))) -> 0 | CH9: =MIN(AJ9,(GD8*(1+GD$5/Setup!$C$36)+IF($V9=11,N($F9),0))) -> 0 | CI9: =MIN(AK9,(GE8*(1+GE$5/Setup!$C$36)+IF($V9=12,N($F9),0))) -> 0 | CJ9: =MIN(AL9,(GF8*(1+GF$5/Setup!$C$36)+IF($V9=13,N($F9),0))) -> 0 | CK9: =MIN(AM9,(GG8*(1+GG$5/Setup!$C$36)+IF($V9=14,N($F9),0))) -> 0 | CL9: =MIN(AN9,(GH8*(1+GH$5/Setup!$C$36)+IF($V9=15,N($F9),0))) -> 0 | CM9: =MIN(AO9,(GI8*(1+GI$5/Setup!$C$36)+IF($V9=16,N($F9),0))) -> 0 | CN9: =MIN(AP9,(GJ8*(1+GJ$5/Setup!$C$36)+IF($V9=17,N($F9),0))) -> 0 | CO9: =MIN(AQ9,(GK8*(1+GK$5/Setup!$C$36)+IF($V9=18,N($F9),0))) -> 0 | CP9: =MIN(AR9,(GL8*(1+GL$5/Setup!$C$36)+IF($V9=19,N($F9),0))) -> 0 | CQ9: =MIN(AS9,(GM8*(1+GM$5/Setup!$C$36)+IF($V9=20,N($F9),0))) -> 0 | CR9: =MIN(AT9,(GN8*(1+GN$5/Setup!$C$36)+IF($V9=21,N($F9),0))) -> 0 | CS9: =MIN(AU9,(GO8*(1+GO$5/Setup!$C$36)+IF($V9=22,N($F9),0))) -> 0 | CT9: =MIN(AV9,(GP8*(1+GP$5/Setup!$C$36)+IF($V9=23,N($F9),0))) -> 0 | CU9: =MIN(AW9,(GQ8*(1+GQ$5/Setup!$C$36)+IF($V9=24,N($F9),0))) -> 0 | CV9: =MIN(AX9,(GR8*(1+GR$5/Setup!$C$36)+IF($V9=25,N($F9),0))) -> 0 | CW9: =MIN(AY9,(GS8*(1+GS$5/Setup!$C$36)+IF($V9=26,N($F9),0))) -> 0 | CX9: =MIN(AZ9,(GT8*(1+GT$5/Setup!$C$36)+IF($V9=27,N($F9),0))) -> 0 | CY9: =MIN(BA9,(GU8*(1+GU$5/Setup!$C$36)+IF($V9=28,N($F9),0))) -> 0 | CZ9: =MIN(BB9,(GV8*(1+GV$5/Setup!$C$36)+IF($V9=29,N($F9),0))) -> 0 | DA9: =MIN(BC9,(GW8*(1+GW$5/Setup!$C$36)+IF($V9=30,N($F9),0))) -> 0 | DB9: =MIN(BD9,(GX8*(1+GX$5/Setup!$C$36)+IF($V9=31,N($F9),0))) -> 0 | DC9: =MIN(BE9,(GY8*(1+GY$5/Setup!$C$36)+IF($V9=32,N($F9),0))) -> 0 | DD9: =MIN(BF9,(GZ8*(1+GZ$5/Setup!$C$36)+IF($V9=33,N($F9),0))) -> 0 | DE9: =MIN(BG9,(HA8*(1+HA$5/Setup!$C$36)+IF($V9=34,N($F9),0))) -> 0 | DF9: =MIN(BH9,(HB8*(1+HB$5/Setup!$C$36)+IF($V9=35,N($F9),0))) -> 0 | DG9: =MIN(BI9,(HC8*(1+HC$5/Setup!$C$36)+IF($V9=36,N($F9),0))) -> 0 | DH9: =MIN(BJ9,(HD8*(1+HD$5/Setup!$C$36)+IF($V9=37,N($F9),0))) -> 0 | DI9: =MIN(BK9,(HE8*(1+HE$5/Setup!$C$36)+IF($V9=38,N($F9),0))) -> 0 | DJ9: =MIN(BL9,(HF8*(1+HF$5/Setup!$C$36)+IF($V9=39,N($F9),0))) -> 0 | DK9: =MIN(BM9,(HG8*(1+HG$5/Setup!$C$36)+IF($V9=40,N($F9),0))) -> 0 | DL9: =MIN(BN9,(HH8*(1+HH$5/Setup!$C$36)+IF($V9=41,N($F9),0))) -> 0 | DM9: =MIN(BO9,(HI8*(1+HI$5/Setup!$C$36)+IF($V9=42,N($F9),0))) -> 0 | DN9: =MIN(BP9,(HJ8*(1+HJ$5/Setup!$C$36)+IF($V9=43,N($F9),0))) -> 0 | DO9: =MIN(BQ9,(HK8*(1+HK$5/Setup!$C$36)+IF($V9=44,N($F9),0))) -> 0 | DP9: =MIN(BR9,(HL8*(1+HL$5/Setup!$C$36)+IF($V9=45,N($F9),0))) -> 0 | DQ9: =MIN(BS9,(HM8*(1+HM$5/Setup!$C$36)+IF($V9=46,N($F9),0))) -> 0 | DR9: =MIN(BT9,(HN8*(1+HN$5/Setup!$C$36)+IF($V9=47,N($F9),0))) -> 0 | DS9: =MIN(BU9,(HO8*(1+HO$5/Setup!$C$36)+IF($V9=48,N($F9),0))) -> 0 | DT9: =MIN(BV9,(HP8*(1+HP$5/Setup!$C$36)+IF($V9=49,N($F9),0))) -> 0 | DU9: =MIN(BW9,(HQ8*(1+HQ$5/Setup!$C$36)+IF($V9=50,N($F9),0))) -> 0 | DV9: =MIN(MAX((FT8*(1+FT$5/Setup!$C$36)+IF($V9=1,N($F9),0))-BX9,0),MAX($P9-0,0)) -> 0 | DW9: =MIN(MAX((FU8*(1+FU$5/Setup!$C$36)+IF($V9=2,N($F9),0))-BY9,0),MAX($P9-SUM(DV9:DV9),0)) -> 0 | DX9: =MIN(MAX((FV8*(1+FV$5/Setup!$C$36)+IF($V9=3,N($F9),0))-BZ9,0),MAX($P9-SUM(DV9:DW9),0)) -> 0 | DY9: =MIN(MAX((FW8*(1+FW$5/Setup!$C$36)+IF($V9=4,N($F9),0))-CA9,0),MAX($P9-SUM(DV9:DX9),0)) -> 0 | DZ9: =MIN(MAX((FX8*(1+FX$5/Setup!$C$36)+IF($V9=5,N($F9),0))-CB9,0),MAX($P9-SUM(DV9:DY9),0)) -> 0 | EA9: =MIN(MAX((FY8*(1+FY$5/Setup!$C$36)+IF($V9=6,N($F9),0))-CC9,0),MAX($P9-SUM(DV9:DZ9),0)) -> 0 | EB9: =MIN(MAX((FZ8*(1+FZ$5/Setup!$C$36)+IF($V9=7,N($F9),0))-CD9,0),MAX($P9-SUM(DV9:EA9),0)) -> 0 | EC9: =MIN(MAX((GA8*(1+GA$5/Setup!$C$36)+IF($V9=8,N($F9),0))-CE9,0),MAX($P9-SUM(DV9:EB9),0)) -> 0 | ED9: =MIN(MAX((GB8*(1+GB$5/Setup!$C$36)+IF($V9=9,N($F9),0))-CF9,0),MAX($P9-SUM(DV9:EC9),0)) -> 0 | EE9: =MIN(MAX((GC8*(1+GC$5/Setup!$C$36)+IF($V9=10,N($F9),0))-CG9,0),MAX($P9-SUM(DV9:ED9),0)) -> 0 | EF9: =MIN(MAX((GD8*(1+GD$5/Setup!$C$36)+IF($V9=11,N($F9),0))-CH9,0),MAX($P9-SUM(DV9:EE9),0)) -> 0 | EG9: =MIN(MAX((GE8*(1+GE$5/Setup!$C$36)+IF($V9=12,N($F9),0))-CI9,0),MAX($P9-SUM(DV9:EF9),0)) -> 0 | EH9: =MIN(MAX((GF8*(1+GF$5/Setup!$C$36)+IF($V9=13,N($F9),0))-CJ9,0),MAX($P9-SUM(DV9:EG9),0)) -> 0 | EI9: =MIN(MAX((GG8*(1+GG$5/Setup!$C$36)+IF($V9=14,N($F9),0))-CK9,0),MAX($P9-SUM(DV9:EH9),0)) -> 0 | EJ9: =MIN(MAX((GH8*(1+GH$5/Setup!$C$36)+IF($V9=15,N($F9),0))-CL9,0),MAX($P9-SUM(DV9:EI9),0)) -> 0 | EK9: =MIN(MAX((GI8*(1+GI$5/Setup!$C$36)+IF($V9=16,N($F9),0))-CM9,0),MAX($P9-SUM(DV9:EJ9),0)) -> 0 | EL9: =MIN(MAX((GJ8*(1+GJ$5/Setup!$C$36)+IF($V9=17,N($F9),0))-CN9,0),MAX($P9-SUM(DV9:EK9),0)) -> 0 | EM9: =MIN(MAX((GK8*(1+GK$5/Setup!$C$36)+IF($V9=18,N($F9),0))-CO9,0),MAX($P9-SUM(DV9:EL9),0)) -> 0 | EN9: =MIN(MAX((GL8*(1+GL$5/Setup!$C$36)+IF($V9=19,N($F9),0))-CP9,0),MAX($P9-SUM(DV9:EM9),0)) -> 0 | EO9: =MIN(MAX((GM8*(1+GM$5/Setup!$C$36)+IF($V9=20,N($F9),0))-CQ9,0),MAX($P9-SUM(DV9:EN9),0)) -> 0 | EP9: =MIN(MAX((GN8*(1+GN$5/Setup!$C$36)+IF($V9=21,N($F9),0))-CR9,0),MAX($P9-SUM(DV9:EO9),0)) -> 0 | EQ9: =MIN(MAX((GO8*(1+GO$5/Setup!$C$36)+IF($V9=22,N($F9),0))-CS9,0),MAX($P9-SUM(DV9:EP9),0)) -> 0 | ER9: =MIN(MAX((GP8*(1+GP$5/Setup!$C$36)+IF($V9=23,N($F9),0))-CT9,0),MAX($P9-SUM(DV9:EQ9),0)) -> 0 | ES9: =MIN(MAX((GQ8*(1+GQ$5/Setup!$C$36)+IF($V9=24,N($F9),0))-CU9,0),MAX($P9-SUM(DV9:ER9),0)) -> 0 | ET9: =MIN(MAX((GR8*(1+GR$5/Setup!$C$36)+IF($V9=25,N($F9),0))-CV9,0),MAX($P9-SUM(DV9:ES9),0)) -> 0 | EU9: =MIN(MAX((GS8*(1+GS$5/Setup!$C$36)+IF($V9=26,N($F9),0))-CW9,0),MAX($P9-SUM(DV9:ET9),0)) -> 0 | EV9: =MIN(MAX((GT8*(1+GT$5/Setup!$C$36)+IF($V9=27,N($F9),0))-CX9,0),MAX($P9-SUM(DV9:EU9),0)) -> 0 | EW9: =MIN(MAX((GU8*(1+GU$5/Setup!$C$36)+IF($V9=28,N($F9),0))-CY9,0),MAX($P9-SUM(DV9:EV9),0)) -> 0 | EX9: =MIN(MAX((GV8*(1+GV$5/Setup!$C$36)+IF($V9=29,N($F9),0))-CZ9,0),MAX($P9-SUM(DV9:EW9),0)) -> 0 | EY9: =MIN(MAX((GW8*(1+GW$5/Setup!$C$36)+IF($V9=30,N($F9),0))-DA9,0),MAX($P9-SUM(DV9:EX9),0)) -> 0 | EZ9: =MIN(MAX((GX8*(1+GX$5/Setup!$C$36)+IF($V9=31,N($F9),0))-DB9,0),MAX($P9-SUM(DV9:EY9),0)) -> 0 | FA9: =MIN(MAX((GY8*(1+GY$5/Setup!$C$36)+IF($V9=32,N($F9),0))-DC9,0),MAX($P9-SUM(DV9:EZ9),0)) -> 0 | FB9: =MIN(MAX((GZ8*(1+GZ$5/Setup!$C$36)+IF($V9=33,N($F9),0))-DD9,0),MAX($P9-SUM(DV9:FA9),0)) -> 0 | FC9: =MIN(MAX((HA8*(1+HA$5/Setup!$C$36)+IF($V9=34,N($F9),0))-DE9,0),MAX($P9-SUM(DV9:FB9),0)) -> 0 | FD9: =MIN(MAX((HB8*(1+HB$5/Setup!$C$36)+IF($V9=35,N($F9),0))-DF9,0),MAX($P9-SUM(DV9:FC9),0)) -> 0 | FE9: =MIN(MAX((HC8*(1+HC$5/Setup!$C$36)+IF($V9=36,N($F9),0))-DG9,0),MAX($P9-SUM(DV9:FD9),0)) -> 0 | FF9: =MIN(MAX((HD8*(1+HD$5/Setup!$C$36)+IF($V9=37,N($F9),0))-DH9,0),MAX($P9-SUM(DV9:FE9),0)) -> 0 | FG9: =MIN(MAX((HE8*(1+HE$5/Setup!$C$36)+IF($V9=38,N($F9),0))-DI9,0),MAX($P9-SUM(DV9:FF9),0)) -> 0 | FH9: =MIN(MAX((HF8*(1+HF$5/Setup!$C$36)+IF($V9=39,N($F9),0))-DJ9,0),MAX($P9-SUM(DV9:FG9),0)) -> 0 | FI9: =MIN(MAX((HG8*(1+HG$5/Setup!$C$36)+IF($V9=40,N($F9),0))-DK9,0),MAX($P9-SUM(DV9:FH9),0)) -> 0 | FJ9: =MIN(MAX((HH8*(1+HH$5/Setup!$C$36)+IF($V9=41,N($F9),0))-DL9,0),MAX($P9-SUM(DV9:FI9),0)) -> 0 | FK9: =MIN(MAX((HI8*(1+HI$5/Setup!$C$36)+IF($V9=42,N($F9),0))-DM9,0),MAX($P9-SUM(DV9:FJ9),0)) -> 0 | FL9: =MIN(MAX((HJ8*(1+HJ$5/Setup!$C$36)+IF($V9=43,N($F9),0))-DN9,0),MAX($P9-SUM(DV9:FK9),0)) -> 0 | FM9: =MIN(MAX((HK8*(1+HK$5/Setup!$C$36)+IF($V9=44,N($F9),0))-DO9,0),MAX($P9-SUM(DV9:FL9),0)) -> 0 | FN9: =MIN(MAX((HL8*(1+HL$5/Setup!$C$36)+IF($V9=45,N($F9),0))-DP9,0),MAX($P9-SUM(DV9:FM9),0)) -> 0 | FO9: =MIN(MAX((HM8*(1+HM$5/Setup!$C$36)+IF($V9=46,N($F9),0))-DQ9,0),MAX($P9-SUM(DV9:FN9),0)) -> 0 | FP9: =MIN(MAX((HN8*(1+HN$5/Setup!$C$36)+IF($V9=47,N($F9),0))-DR9,0),MAX($P9-SUM(DV9:FO9),0)) -> 0 | FQ9: =MIN(MAX((HO8*(1+HO$5/Setup!$C$36)+IF($V9=48,N($F9),0))-DS9,0),MAX($P9-SUM(DV9:FP9),0)) -> 0 | FR9: =MIN(MAX((HP8*(1+HP$5/Setup!$C$36)+IF($V9=49,N($F9),0))-DT9,0),MAX($P9-SUM(DV9:FQ9),0)) -> 0 | FS9: =MIN(MAX((HQ8*(1+HQ$5/Setup!$C$36)+IF($V9=50,N($F9),0))-DU9,0),MAX($P9-SUM(DV9:FR9),0)) -> 0 | FT9: =IF((FT8*(1+FT$5/Setup!$C$36)+IF($V9=1,N($F9),0))-BX9-DV9<0.005,0,(FT8*(1+FT$5/Setup!$C$36)+IF($V9=1,N($F9),0))-BX9-DV9) -> 479.61538 | FU9: =IF((FU8*(1+FU$5/Setup!$C$36)+IF($V9=2,N($F9),0))-BY9-DW9<0.005,0,(FU8*(1+FU$5/Setup!$C$36)+IF($V9=2,N($F9),0))-BY9-DW9) -> 1208.3077 | FV9: =IF((FV8*(1+FV$5/Setup!$C$36)+IF($V9=3,N($F9),0))-BZ9-DX9<0.005,0,(FV8*(1+FV$5/Setup!$C$36)+IF($V9=3,N($F9),0))-BZ9-DX9) -> 0 | FW9: =IF((FW8*(1+FW$5/Setup!$C$36)+IF($V9=4,N($F9),0))-CA9-DY9<0.005,0,(FW8*(1+FW$5/Setup!$C$36)+IF($V9=4,N($F9),0))-CA9-DY9) -> 0 | FX9: =IF((FX8*(1+FX$5/Setup!$C$36)+IF($V9=5,N($F9),0))-CB9-DZ9<0.005,0,(FX8*(1+FX$5/Setup!$C$36)+IF($V9=5,N($F9),0))-CB9-DZ9) -> 0 | FY9: =IF((FY8*(1+FY$5/Setup!$C$36)+IF($V9=6,N($F9),0))-CC9-EA9<0.005,0,(FY8*(1+FY$5/Setup!$C$36)+IF($V9=6,N($F9),0))-CC9-EA9) -> 0 | FZ9: =IF((FZ8*(1+FZ$5/Setup!$C$36)+IF($V9=7,N($F9),0))-CD9-EB9<0.005,0,(FZ8*(1+FZ$5/Setup!$C$36)+IF($V9=7,N($F9),0))-CD9-EB9) -> 0 | GA9: =IF((GA8*(1+GA$5/Setup!$C$36)+IF($V9=8,N($F9),0))-CE9-EC9<0.005,0,(GA8*(1+GA$5/Setup!$C$36)+IF($V9=8,N($F9),0))-CE9-EC9) -> 0 | GB9: =IF((GB8*(1+GB$5/Setup!$C$36)+IF($V9=9,N($F9),0))-CF9-ED9<0.005,0,(GB8*(1+GB$5/Setup!$C$36)+IF($V9=9,N($F9),0))-CF9-ED9) -> 0 | GC9: =IF((GC8*(1+GC$5/Setup!$C$36)+IF($V9=10,N($F9),0))-CG9-EE9<0.005,0,(GC8*(1+GC$5/Setup!$C$36)+IF($V9=10,N($F9),0))-CG9-EE9) -> 0 | GD9: =IF((GD8*(1+GD$5/Setup!$C$36)+IF($V9=11,N($F9),0))-CH9-EF9<0.005,0,(GD8*(1+GD$5/Setup!$C$36)+IF($V9=11,N($F9),0))-CH9-EF9) -> 0 | GE9: =IF((GE8*(1+GE$5/Setup!$C$36)+IF($V9=12,N($F9),0))-CI9-EG9<0.005,0,(GE8*(1+GE$5/Setup!$C$36)+IF($V9=12,N($F9),0))-CI9-EG9) -> 0 | GF9: =IF((GF8*(1+GF$5/Setup!$C$36)+IF($V9=13,N($F9),0))-CJ9-EH9<0.005,0,(GF8*(1+GF$5/Setup!$C$36)+IF($V9=13,N($F9),0))-CJ9-EH9) -> 0 | GG9: =IF((GG8*(1+GG$5/Setup!$C$36)+IF($V9=14,N($F9),0))-CK9-EI9<0.005,0,(GG8*(1+GG$5/Setup!$C$36)+IF($V9=14,N($F9),0))-CK9-EI9) -> 0 | GH9: =IF((GH8*(1+GH$5/Setup!$C$36)+IF($V9=15,N($F9),0))-CL9-EJ9<0.005,0,(GH8*(1+GH$5/Setup!$C$36)+IF($V9=15,N($F9),0))-CL9-EJ9) -> 0 | GI9: =IF((GI8*(1+GI$5/Setup!$C$36)+IF($V9=16,N($F9),0))-CM9-EK9<0.005,0,(GI8*(1+GI$5/Setup!$C$36)+IF($V9=16,N($F9),0))-CM9-EK9) -> 0 | GJ9: =IF((GJ8*(1+GJ$5/Setup!$C$36)+IF($V9=17,N($F9),0))-CN9-EL9<0.005,0,(GJ8*(1+GJ$5/Setup!$C$36)+IF($V9=17,N($F9),0))-CN9-EL9) -> 0 | GK9: =IF((GK8*(1+GK$5/Setup!$C$36)+IF($V9=18,N($F9),0))-CO9-EM9<0.005,0,(GK8*(1+GK$5/Setup!$C$36)+IF($V9=18,N($F9),0))-CO9-EM9) -> 0 | GL9: =IF((GL8*(1+GL$5/Setup!$C$36)+IF($V9=19,N($F9),0))-CP9-EN9<0.005,0,(GL8*(1+GL$5/Setup!$C$36)+IF($V9=19,N($F9),0))-CP9-EN9) -> 0 | GM9: =IF((GM8*(1+GM$5/Setup!$C$36)+IF($V9=20,N($F9),0))-CQ9-EO9<0.005,0,(GM8*(1+GM$5/Setup!$C$36)+IF($V9=20,N($F9),0))-CQ9-EO9) -> 0 | GN9: =IF((GN8*(1+GN$5/Setup!$C$36)+IF($V9=21,N($F9),0))-CR9-EP9<0.005,0,(GN8*(1+GN$5/Setup!$C$36)+IF($V9=21,N($F9),0))-CR9-EP9) -> 0 | GO9: =IF((GO8*(1+GO$5/Setup!$C$36)+IF($V9=22,N($F9),0))-CS9-EQ9<0.005,0,(GO8*(1+GO$5/Setup!$C$36)+IF($V9=22,N($F9),0))-CS9-EQ9) -> 0 | GP9: =IF((GP8*(1+GP$5/Setup!$C$36)+IF($V9=23,N($F9),0))-CT9-ER9<0.005,0,(GP8*(1+GP$5/Setup!$C$36)+IF($V9=23,N($F9),0))-CT9-ER9) -> 0 | GQ9: =IF((GQ8*(1+GQ$5/Setup!$C$36)+IF($V9=24,N($F9),0))-CU9-ES9<0.005,0,(GQ8*(1+GQ$5/Setup!$C$36)+IF($V9=24,N($F9),0))-CU9-ES9) -> 0 | GR9: =IF((GR8*(1+GR$5/Setup!$C$36)+IF($V9=25,N($F9),0))-CV9-ET9<0.005,0,(GR8*(1+GR$5/Setup!$C$36)+IF($V9=25,N($F9),0))-CV9-ET9) -> 0 | GS9: =IF((GS8*(1+GS$5/Setup!$C$36)+IF($V9=26,N($F9),0))-CW9-EU9<0.005,0,(GS8*(1+GS$5/Setup!$C$36)+IF($V9=26,N($F9),0))-CW9-EU9) -> 0 | GT9: =IF((GT8*(1+GT$5/Setup!$C$36)+IF($V9=27,N($F9),0))-CX9-EV9<0.005,0,(GT8*(1+GT$5/Setup!$C$36)+IF($V9=27,N($F9),0))-CX9-EV9) -> 0 | GU9: =IF((GU8*(1+GU$5/Setup!$C$36)+IF($V9=28,N($F9),0))-CY9-EW9<0.005,0,(GU8*(1+GU$5/Setup!$C$36)+IF($V9=28,N($F9),0))-CY9-EW9) -> 0 | GV9: =IF((GV8*(1+GV$5/Setup!$C$36)+IF($V9=29,N($F9),0))-CZ9-EX9<0.005,0,(GV8*(1+GV$5/Setup!$C$36)+IF($V9=29,N($F9),0))-CZ9-EX9) -> 0 | GW9: =IF((GW8*(1+GW$5/Setup!$C$36)+IF($V9=30,N($F9),0))-DA9-EY9<0.005,0,(GW8*(1+GW$5/Setup!$C$36)+IF($V9=30,N($F9),0))-DA9-EY9) -> 0 | GX9: =IF((GX8*(1+GX$5/Setup!$C$36)+IF($V9=31,N($F9),0))-DB9-EZ9<0.005,0,(GX8*(1+GX$5/Setup!$C$36)+IF($V9=31,N($F9),0))-DB9-EZ9) -> 0 | GY9: =IF((GY8*(1+GY$5/Setup!$C$36)+IF($V9=32,N($F9),0))-DC9-FA9<0.005,0,(GY8*(1+GY$5/Setup!$C$36)+IF($V9=32,N($F9),0))-DC9-FA9) -> 0 | GZ9: =IF((GZ8*(1+GZ$5/Setup!$C$36)+IF($V9=33,N($F9),0))-DD9-FB9<0.005,0,(GZ8*(1+GZ$5/Setup!$C$36)+IF($V9=33,N($F9),0))-DD9-FB9) -> 0 | HA9: =IF((HA8*(1+HA$5/Setup!$C$36)+IF($V9=34,N($F9),0))-DE9-FC9<0.005,0,(HA8*(1+HA$5/Setup!$C$36)+IF($V9=34,N($F9),0))-DE9-FC9) -> 0 | HB9: =IF((HB8*(1+HB$5/Setup!$C$36)+IF($V9=35,N($F9),0))-DF9-FD9<0.005,0,(HB8*(1+HB$5/Setup!$C$36)+IF($V9=35,N($F9),0))-DF9-FD9) -> 0 | HC9: =IF((HC8*(1+HC$5/Setup!$C$36)+IF($V9=36,N($F9),0))-DG9-FE9<0.005,0,(HC8*(1+HC$5/Setup!$C$36)+IF($V9=36,N($F9),0))-DG9-FE9) -> 0 | HD9: =IF((HD8*(1+HD$5/Setup!$C$36)+IF($V9=37,N($F9),0))-DH9-FF9<0.005,0,(HD8*(1+HD$5/Setup!$C$36)+IF($V9=37,N($F9),0))-DH9-FF9) -> 0 | HE9: =IF((HE8*(1+HE$5/Setup!$C$36)+IF($V9=38,N($F9),0))-DI9-FG9<0.005,0,(HE8*(1+HE$5/Setup!$C$36)+IF($V9=38,N($F9),0))-DI9-FG9) -> 0 | HF9: =IF((HF8*(1+HF$5/Setup!$C$36)+IF($V9=39,N($F9),0))-DJ9-FH9<0.005,0,(HF8*(1+HF$5/Setup!$C$36)+IF($V9=39,N($F9),0))-DJ9-FH9) -> 0 | HG9: =IF((HG8*(1+HG$5/Setup!$C$36)+IF($V9=40,N($F9),0))-DK9-FI9<0.005,0,(HG8*(1+HG$5/Setup!$C$36)+IF($V9=40,N($F9),0))-DK9-FI9) -> 0 | HH9: =IF((HH8*(1+HH$5/Setup!$C$36)+IF($V9=41,N($F9),0))-DL9-FJ9<0.005,0,(HH8*(1+HH$5/Setup!$C$36)+IF($V9=41,N($F9),0))-DL9-FJ9) -> 0 | HI9: =IF((HI8*(1+HI$5/Setup!$C$36)+IF($V9=42,N($F9),0))-DM9-FK9<0.005,0,(HI8*(1+HI$5/Setup!$C$36)+IF($V9=42,N($F9),0))-DM9-FK9) -> 0 | HJ9: =IF((HJ8*(1+HJ$5/Setup!$C$36)+IF($V9=43,N($F9),0))-DN9-FL9<0.005,0,(HJ8*(1+HJ$5/Setup!$C$36)+IF($V9=43,N($F9),0))-DN9-FL9) -> 0 | HK9: =IF((HK8*(1+HK$5/Setup!$C$36)+IF($V9=44,N($F9),0))-DO9-FM9<0.005,0,(HK8*(1+HK$5/Setup!$C$36)+IF($V9=44,N($F9),0))-DO9-FM9) -> 0 | HL9: =IF((HL8*(1+HL$5/Setup!$C$36)+IF($V9=45,N($F9),0))-DP9-FN9<0.005,0,(HL8*(1+HL$5/Setup!$C$36)+IF($V9=45,N($F9),0))-DP9-FN9) -> 0 | HM9: =IF((HM8*(1+HM$5/Setup!$C$36)+IF($V9=46,N($F9),0))-DQ9-FO9<0.005,0,(HM8*(1+HM$5/Setup!$C$36)+IF($V9=46,N($F9),0))-DQ9-FO9) -> 0 | HN9: =IF((HN8*(1+HN$5/Setup!$C$36)+IF($V9=47,N($F9),0))-DR9-FP9<0.005,0,(HN8*(1+HN$5/Setup!$C$36)+IF($V9=47,N($F9),0))-DR9-FP9) -> 0 | HO9: =IF((HO8*(1+HO$5/Setup!$C$36)+IF($V9=48,N($F9),0))-DS9-FQ9<0.005,0,(HO8*(1+HO$5/Setup!$C$36)+IF($V9=48,N($F9),0))-DS9-FQ9) -> 0 | HP9: =IF((HP8*(1+HP$5/Setup!$C$36)+IF($V9=49,N($F9),0))-DT9-FR9<0.005,0,(HP8*(1+HP$5/Setup!$C$36)+IF($V9=49,N($F9),0))-DT9-FR9) -> 0 | HQ9: =IF((HQ8*(1+HQ$5/Setup!$C$36)+IF($V9=50,N($F9),0))-DU9-FS9<0.005,0,(HQ8*(1+HQ$5/Setup!$C$36)+IF($V9=50,N($F9),0))-DU9-FS9) -> 0
A10: 2 | B10: =IF(Setup!$C$7="Every month",EDATE(Setup!$C$8,($A10-1)),IF(Setup!$C$7="Twice a month",DATE(YEAR(Setup!$C$8),MONTH(Setup!$C$8)+INT((($A10-1)+Setup!$C$41)/2),MIN(IF(MOD(($A10-1)+Setup!$C$41,2)=0,Setup!$C$39,Setup!$C$40),DAY(EOMONTH(DATE(YEAR(Setup!$C$8),MONTH(Setup!$C$8)+INT((($A10-1)+Setup!$C$41)/2),1),0)))),Setup!$C$8+($A10-1)*IF(Setup!$C$7="Every week",7,14))) -> 46339 | C10: =IF(Setup!$C$7="Every month",EDATE(Setup!$C$8,$A10),IF(Setup!$C$7="Twice a month",DATE(YEAR(Setup!$C$8),MONTH(Setup!$C$8)+INT(($A10+Setup!$C$41)/2),MIN(IF(MOD($A10+Setup!$C$41,2)=0,Setup!$C$39,Setup!$C$40),DAY(EOMONTH(DATE(YEAR(Setup!$C$8),MONTH(Setup!$C$8)+INT(($A10+Setup!$C$41)/2),1),0)))),Setup!$C$8+$A10*IF(Setup!$C$7="Every week",7,14))) -> 46353 | I10: =N(Setup!$C$11)+N(E10) -> 100 | J10: =MIN(Setup!$C$37,MAX(I10,0)) -> 9.2307692 | K10: =MIN(MAX(N(Setup!$C$14)-L9,0),MAX(I10-J10,0)) -> 90.769231 | L10: =L9+K10-N(G10) -> 481.53846 | M10: =M9+J10-N(H10) -> 18.461538 | N10: =SUM(BX10:DU10) -> 40 | O10: =SUM(Z10:BW10)-N10 -> 0 | P10: =MAX(I10-J10-K10,0)+O10 -> 0 | Q10: =SUM(DV10:FS10) -> 0 | R10: =N10+J10+K10+Q10 -> 140 | S10: =T10-T9-N(F10)+N10+Q10 -> 12.792426 | T10: =SUM(FT10:HQ10) -> 1660.7155 | U10: =IF(T9<0.005,"",INDEX(Helpers!$C$2:$C$51,IF(_xlfn.MINIFS($DV$6:$FS$6,DV10:FS10,">0.005")=0,V10,_xlfn.MINIFS($DV$6:$FS$6,DV10:FS10,">0.005")))) -> Card A | V10: =IF(_xlfn.MINIFS($FT$6:$HQ$6,FT9:HQ9,">0.005")=0,1,_xlfn.MINIFS($FT$6:$HQ$6,FT9:HQ9,">0.005")) -> 1 | W10: =IF(AND(D10<>"Paid",T9>0.005),1,0) -> 1 | X10: =SUMPRODUCT(((Helpers!$G$2:$G$51*(1+(Helpers!$D$2:$D$51+0.000000001)/12)^(($B10-Setup!$C$8)/(365.25/12))-Helpers!$E$2:$E$51*((1+(Helpers!$D$2:$D$51+0.000000001)/12)^(($B10-Setup!$C$8)/(365.25/12))-1)/((Helpers!$D$2:$D$51+0.000000001)/12))>0)*(Helpers!$G$2:$G$51*(1+(Helpers!$D$2:$D$51+0.000000001)/12)^(($B10-Setup!$C$8)/(365.25/12))-Helpers!$E$2:$E$51*((1+(Helpers!$D$2:$D$51+0.000000001)/12)^(($B10-Setup!$C$8)/(365.25/12))-1)/((Helpers!$D$2:$D$51+0.000000001)/12))) -> 1683.0591 | Z10: =IF(OR(N(Z$5)=0,Z$6=""),0,Z$5*((DATE(YEAR($B10),MONTH($B10),MIN(Z$6,DAY(EOMONTH($B10,0))))>=$B10)*(DATE(YEAR($B10),MONTH($B10),MIN(Z$6,DAY(EOMONTH($B10,0))))<$C10)+(DATE(YEAR($B10),MONTH($B10)+1,MIN(Z$6,DAY(EOMONTH($B10,1))))>=$B10)*(DATE(YEAR($B10),MONTH($B10)+1,MIN(Z$6,DAY(EOMONTH($B10,1))))<$C10))) -> 0 | AA10: =IF(OR(N(AA$5)=0,AA$6=""),0,AA$5*((DATE(YEAR($B10),MONTH($B10),MIN(AA$6,DAY(EOMONTH($B10,0))))>=$B10)*(DATE(YEAR($B10),MONTH($B10),MIN(AA$6,DAY(EOMONTH($B10,0))))<$C10)+(DATE(YEAR($B10),MONTH($B10)+1,MIN(AA$6,DAY(EOMONTH($B10,1))))>=$B10)*(DATE(YEAR($B10),MONTH($B10)+1,MIN(AA$6,DAY(EOMONTH($B10,1))))<$C10))) -> 40 | AB10: =IF(OR(N(AB$5)=0,AB$6=""),0,AB$5*((DATE(YEAR($B10),MONTH($B10),MIN(AB$6,DAY(EOMONTH($B10,0))))>=$B10)*(DATE(YEAR($B10),MONTH($B10),MIN(AB$6,DAY(EOMONTH($B10,0))))<$C10)+(DATE(YEAR($B10),MONTH($B10)+1,MIN(AB$6,DAY(EOMONTH($B10,1))))>=$B10)*(DATE(YEAR($B10),MONTH($B10)+1,MIN(AB$6,DAY(EOMONTH($B10,1))))<$C10))) -> 0 | AC10: =IF(OR(N(AC$5)=0,AC$6=""),0,AC$5*((DATE(YEAR($B10),MONTH($B10),MIN(AC$6,DAY(EOMONTH($B10,0))))>=$B10)*(DATE(YEAR($B10),MONTH($B10),MIN(AC$6,DAY(EOMONTH($B10,0))))<$C10)+(DATE(YEAR($B10),MONTH($B10)+1,MIN(AC$6,DAY(EOMONTH($B10,1))))>=$B10)*(DATE(YEAR($B10),MONTH($B10)+1,MIN(AC$6,DAY(EOMONTH($B10,1))))<$C10))) -> 0 | AD10: =IF(OR(N(AD$5)=0,AD$6=""),0,AD$5*((DATE(YEAR($B10),MONTH($B10),MIN(AD$6,DAY(EOMONTH($B10,0))))>=$B10)*(DATE(YEAR($B10),MONTH($B10),MIN(AD$6,DAY(EOMONTH($B10,0))))<$C10)+(DATE(YEAR($B10),MONTH($B10)+1,MIN(AD$6,DAY(EOMONTH($B10,1))))>=$B10)*(DATE(YEAR($B10),MONTH($B10)+1,MIN(AD$6,DAY(EOMONTH($B10,1))))<$C10))) -> 0 | AE10: =IF(OR(N(AE$5)=0,AE$6=""),0,AE$5*((DATE(YEAR($B10),MONTH($B10),MIN(AE$6,DAY(EOMONTH($B10,0))))>=$B10)*(DATE(YEAR($B10),MONTH($B10),MIN(AE$6,DAY(EOMONTH($B10,0))))<$C10)+(DATE(YEAR($B10),MONTH($B10)+1,MIN(AE$6,DAY(EOMONTH($B10,1))))>=$B10)*(DATE(YEAR($B10),MONTH($B10)+1,MIN(AE$6,DAY(EOMONTH($B10,1))))<$C10))) -> 0 | AF10: =IF(OR(N(AF$5)=0,AF$6=""),0,AF$5*((DATE(YEAR($B10),MONTH($B10),MIN(AF$6,DAY(EOMONTH($B10,0))))>=$B10)*(DATE(YEAR($B10),MONTH($B10),MIN(AF$6,DAY(EOMONTH($B10,0))))<$C10)+(DATE(YEAR($B10),MONTH($B10)+1,MIN(AF$6,DAY(EOMONTH($B10,1))))>=$B10)*(DATE(YEAR($B10),MONTH($B10)+1,MIN(AF$6,DAY(EOMONTH($B10,1))))<$C10))) -> 0 | AG10: =IF(OR(N(AG$5)=0,AG$6=""),0,AG$5*((DATE(YEAR($B10),MONTH($B10),MIN(AG$6,DAY(EOMONTH($B10,0))))>=$B10)*(DATE(YEAR($B10),MONTH($B10),MIN(AG$6,DAY(EOMONTH($B10,0))))<$C10)+(DATE(YEAR($B10),MONTH($B10)+1,MIN(AG$6,DAY(EOMONTH($B10,1))))>=$B10)*(DATE(YEAR($B10),MONTH($B10)+1,MIN(AG$6,DAY(EOMONTH($B10,1))))<$C10))) -> 0 | ... BW10: =IF(OR(N(BW$5)=0,BW$6=""),0,BW$5*((DATE(YEAR($B10),MONTH($B10),MIN(BW$6,DAY(EOMONTH($B10,0))))>=$B10)*(DATE(YEAR($B10),MONTH($B10),MIN(BW$6,DAY(EOMONTH($B10,0))))<$C10)+(DATE(YEAR($B10),MONTH($B10)+1,MIN(BW$6,DAY(EOMONTH($B10,1))))>=$B10)*(DATE(YEAR($B10),MONTH($B10)+1,MIN(BW$6,DAY(EOMONTH($B10,1))))<$C10))) -> 0 | BX10: =MIN(Z10,(FT9*(1+FT$5/Setup!$C$36)+IF($V10=1,N($F10),0))) -> 0 | BY10: =MIN(AA10,(FU9*(1+FU$5/Setup!$C$36)+IF($V10=2,N($F10),0))) -> 40 | BZ10: =MIN(AB10,(FV9*(1+FV$5/Setup!$C$36)+IF($V10=3,N($F10),0))) -> 0 | CA10: =MIN(AC10,(FW9*(1+FW$5/Setup!$C$36)+IF($V10=4,N($F10),0))) -> 0 | CB10: =MIN(AD10,(FX9*(1+FX$5/Setup!$C$36)+IF($V10=5,N($F10),0))) -> 0 | CC10: =MIN(AE10,(FY9*(1+FY$5/Setup!$C$36)+IF($V10=6,N($F10),0))) -> 0 | CD10: =MIN(AF10,(FZ9*(1+FZ$5/Setup!$C$36)+IF($V10=7,N($F10),0))) -> 0 | CE10: =MIN(AG10,(GA9*(1+GA$5/Setup!$C$36)+IF($V10=8,N($F10),0))) -> 0 | CF10: =MIN(AH10,(GB9*(1+GB$5/Setup!$C$36)+IF($V10=9,N($F10),0))) -> 0 | CG10: =MIN(AI10,(GC9*(1+GC$5/Setup!$C$36)+IF($V10=10,N($F10),0))) -> 0 | CH10: =MIN(AJ10,(GD9*(1+GD$5/Setup!$C$36)+IF($V10=11,N($F10),0))) -> 0 | CI10: =MIN(AK10,(GE9*(1+GE$5/Setup!$C$36)+IF($V10=12,N($F10),0))) -> 0 | CJ10: =MIN(AL10,(GF9*(1+GF$5/Setup!$C$36)+IF($V10=13,N($F10),0))) -> 0 | CK10: =MIN(AM10,(GG9*(1+GG$5/Setup!$C$36)+IF($V10=14,N($F10),0))) -> 0 | CL10: =MIN(AN10,(GH9*(1+GH$5/Setup!$C$36)+IF($V10=15,N($F10),0))) -> 0 | CM10: =MIN(AO10,(GI9*(1+GI$5/Setup!$C$36)+IF($V10=16,N($F10),0))) -> 0 | CN10: =MIN(AP10,(GJ9*(1+GJ$5/Setup!$C$36)+IF($V10=17,N($F10),0))) -> 0 | CO10: =MIN(AQ10,(GK9*(1+GK$5/Setup!$C$36)+IF($V10=18,N($F10),0))) -> 0 | CP10: =MIN(AR10,(GL9*(1+GL$5/Setup!$C$36)+IF($V10=19,N($F10),0))) -> 0 | CQ10: =MIN(AS10,(GM9*(1+GM$5/Setup!$C$36)+IF($V10=20,N($F10),0))) -> 0 | CR10: =MIN(AT10,(GN9*(1+GN$5/Setup!$C$36)+IF($V10=21,N($F10),0))) -> 0 | CS10: =MIN(AU10,(GO9*(1+GO$5/Setup!$C$36)+IF($V10=22,N($F10),0))) -> 0 | CT10: =MIN(AV10,(GP9*(1+GP$5/Setup!$C$36)+IF($V10=23,N($F10),0))) -> 0 | CU10: =MIN(AW10,(GQ9*(1+GQ$5/Setup!$C$36)+IF($V10=24,N($F10),0))) -> 0 | CV10: =MIN(AX10,(GR9*(1+GR$5/Setup!$C$36)+IF($V10=25,N($F10),0))) -> 0 | CW10: =MIN(AY10,(GS9*(1+GS$5/Setup!$C$36)+IF($V10=26,N($F10),0))) -> 0 | CX10: =MIN(AZ10,(GT9*(1+GT$5/Setup!$C$36)+IF($V10=27,N($F10),0))) -> 0 | CY10: =MIN(BA10,(GU9*(1+GU$5/Setup!$C$36)+IF($V10=28,N($F10),0))) -> 0 | CZ10: =MIN(BB10,(GV9*(1+GV$5/Setup!$C$36)+IF($V10=29,N($F10),0))) -> 0 | DA10: =MIN(BC10,(GW9*(1+GW$5/Setup!$C$36)+IF($V10=30,N($F10),0))) -> 0 | DB10: =MIN(BD10,(GX9*(1+GX$5/Setup!$C$36)+IF($V10=31,N($F10),0))) -> 0 | DC10: =MIN(BE10,(GY9*(1+GY$5/Setup!$C$36)+IF($V10=32,N($F10),0))) -> 0 | DD10: =MIN(BF10,(GZ9*(1+GZ$5/Setup!$C$36)+IF($V10=33,N($F10),0))) -> 0 | DE10: =MIN(BG10,(HA9*(1+HA$5/Setup!$C$36)+IF($V10=34,N($F10),0))) -> 0 | DF10: =MIN(BH10,(HB9*(1+HB$5/Setup!$C$36)+IF($V10=35,N($F10),0))) -> 0 | DG10: =MIN(BI10,(HC9*(1+HC$5/Setup!$C$36)+IF($V10=36,N($F10),0))) -> 0 | DH10: =MIN(BJ10,(HD9*(1+HD$5/Setup!$C$36)+IF($V10=37,N($F10),0))) -> 0 | DI10: =MIN(BK10,(HE9*(1+HE$5/Setup!$C$36)+IF($V10=38,N($F10),0))) -> 0 | DJ10: =MIN(BL10,(HF9*(1+HF$5/Setup!$C$36)+IF($V10=39,N($F10),0))) -> 0 | DK10: =MIN(BM10,(HG9*(1+HG$5/Setup!$C$36)+IF($V10=40,N($F10),0))) -> 0 | DL10: =MIN(BN10,(HH9*(1+HH$5/Setup!$C$36)+IF($V10=41,N($F10),0))) -> 0 | DM10: =MIN(BO10,(HI9*(1+HI$5/Setup!$C$36)+IF($V10=42,N($F10),0))) -> 0 | DN10: =MIN(BP10,(HJ9*(1+HJ$5/Setup!$C$36)+IF($V10=43,N($F10),0))) -> 0 | DO10: =MIN(BQ10,(HK9*(1+HK$5/Setup!$C$36)+IF($V10=44,N($F10),0))) -> 0 | DP10: =MIN(BR10,(HL9*(1+HL$5/Setup!$C$36)+IF($V10=45,N($F10),0))) -> 0 | DQ10: =MIN(BS10,(HM9*(1+HM$5/Setup!$C$36)+IF($V10=46,N($F10),0))) -> 0 | DR10: =MIN(BT10,(HN9*(1+HN$5/Setup!$C$36)+IF($V10=47,N($F10),0))) -> 0 | DS10: =MIN(BU10,(HO9*(1+HO$5/Setup!$C$36)+IF($V10=48,N($F10),0))) -> 0 | DT10: =MIN(BV10,(HP9*(1+HP$5/Setup!$C$36)+IF($V10=49,N($F10),0))) -> 0 | DU10: =MIN(BW10,(HQ9*(1+HQ$5/Setup!$C$36)+IF($V10=50,N($F10),0))) -> 0 | DV10: =MIN(MAX((FT9*(1+FT$5/Setup!$C$36)+IF($V10=1,N($F10),0))-BX10,0),MAX($P10-0,0)) -> 0 | DW10: =MIN(MAX((FU9*(1+FU$5/Setup!$C$36)+IF($V10=2,N($F10),0))-BY10,0),MAX($P10-SUM(DV10:DV10),0)) -> 0 | DX10: =MIN(MAX((FV9*(1+FV$5/Setup!$C$36)+IF($V10=3,N($F10),0))-BZ10,0),MAX($P10-SUM(DV10:DW10),0)) -> 0 | DY10: =MIN(MAX((FW9*(1+FW$5/Setup!$C$36)+IF($V10=4,N($F10),0))-CA10,0),MAX($P10-SUM(DV10:DX10),0)) -> 0 | DZ10: =MIN(MAX((FX9*(1+FX$5/Setup!$C$36)+IF($V10=5,N($F10),0))-CB10,0),MAX($P10-SUM(DV10:DY10),0)) -> 0 | EA10: =MIN(MAX((FY9*(1+FY$5/Setup!$C$36)+IF($V10=6,N($F10),0))-CC10,0),MAX($P10-SUM(DV10:DZ10),0)) -> 0 | EB10: =MIN(MAX((FZ9*(1+FZ$5/Setup!$C$36)+IF($V10=7,N($F10),0))-CD10,0),MAX($P10-SUM(DV10:EA10),0)) -> 0 | EC10: =MIN(MAX((GA9*(1+GA$5/Setup!$C$36)+IF($V10=8,N($F10),0))-CE10,0),MAX($P10-SUM(DV10:EB10),0)) -> 0 | ED10: =MIN(MAX((GB9*(1+GB$5/Setup!$C$36)+IF($V10=9,N($F10),0))-CF10,0),MAX($P10-SUM(DV10:EC10),0)) -> 0 | EE10: =MIN(MAX((GC9*(1+GC$5/Setup!$C$36)+IF($V10=10,N($F10),0))-CG10,0),MAX($P10-SUM(DV10:ED10),0)) -> 0 | EF10: =MIN(MAX((GD9*(1+GD$5/Setup!$C$36)+IF($V10=11,N($F10),0))-CH10,0),MAX($P10-SUM(DV10:EE10),0)) -> 0 | EG10: =MIN(MAX((GE9*(1+GE$5/Setup!$C$36)+IF($V10=12,N($F10),0))-CI10,0),MAX($P10-SUM(DV10:EF10),0)) -> 0 | EH10: =MIN(MAX((GF9*(1+GF$5/Setup!$C$36)+IF($V10=13,N($F10),0))-CJ10,0),MAX($P10-SUM(DV10:EG10),0)) -> 0 | EI10: =MIN(MAX((GG9*(1+GG$5/Setup!$C$36)+IF($V10=14,N($F10),0))-CK10,0),MAX($P10-SUM(DV10:EH10),0)) -> 0 | EJ10: =MIN(MAX((GH9*(1+GH$5/Setup!$C$36)+IF($V10=15,N($F10),0))-CL10,0),MAX($P10-SUM(DV10:EI10),0)) -> 0 | EK10: =MIN(MAX((GI9*(1+GI$5/Setup!$C$36)+IF($V10=16,N($F10),0))-CM10,0),MAX($P10-SUM(DV10:EJ10),0)) -> 0 | EL10: =MIN(MAX((GJ9*(1+GJ$5/Setup!$C$36)+IF($V10=17,N($F10),0))-CN10,0),MAX($P10-SUM(DV10:EK10),0)) -> 0 | EM10: =MIN(MAX((GK9*(1+GK$5/Setup!$C$36)+IF($V10=18,N($F10),0))-CO10,0),MAX($P10-SUM(DV10:EL10),0)) -> 0 | EN10: =MIN(MAX((GL9*(1+GL$5/Setup!$C$36)+IF($V10=19,N($F10),0))-CP10,0),MAX($P10-SUM(DV10:EM10),0)) -> 0 | EO10: =MIN(MAX((GM9*(1+GM$5/Setup!$C$36)+IF($V10=20,N($F10),0))-CQ10,0),MAX($P10-SUM(DV10:EN10),0)) -> 0 | EP10: =MIN(MAX((GN9*(1+GN$5/Setup!$C$36)+IF($V10=21,N($F10),0))-CR10,0),MAX($P10-SUM(DV10:EO10),0)) -> 0 | EQ10: =MIN(MAX((GO9*(1+GO$5/Setup!$C$36)+IF($V10=22,N($F10),0))-CS10,0),MAX($P10-SUM(DV10:EP10),0)) -> 0 | ER10: =MIN(MAX((GP9*(1+GP$5/Setup!$C$36)+IF($V10=23,N($F10),0))-CT10,0),MAX($P10-SUM(DV10:EQ10),0)) -> 0 | ES10: =MIN(MAX((GQ9*(1+GQ$5/Setup!$C$36)+IF($V10=24,N($F10),0))-CU10,0),MAX($P10-SUM(DV10:ER10),0)) -> 0 | ET10: =MIN(MAX((GR9*(1+GR$5/Setup!$C$36)+IF($V10=25,N($F10),0))-CV10,0),MAX($P10-SUM(DV10:ES10),0)) -> 0 | EU10: =MIN(MAX((GS9*(1+GS$5/Setup!$C$36)+IF($V10=26,N($F10),0))-CW10,0),MAX($P10-SUM(DV10:ET10),0)) -> 0 | EV10: =MIN(MAX((GT9*(1+GT$5/Setup!$C$36)+IF($V10=27,N($F10),0))-CX10,0),MAX($P10-SUM(DV10:EU10),0)) -> 0 | EW10: =MIN(MAX((GU9*(1+GU$5/Setup!$C$36)+IF($V10=28,N($F10),0))-CY10,0),MAX($P10-SUM(DV10:EV10),0)) -> 0 | EX10: =MIN(MAX((GV9*(1+GV$5/Setup!$C$36)+IF($V10=29,N($F10),0))-CZ10,0),MAX($P10-SUM(DV10:EW10),0)) -> 0 | EY10: =MIN(MAX((GW9*(1+GW$5/Setup!$C$36)+IF($V10=30,N($F10),0))-DA10,0),MAX($P10-SUM(DV10:EX10),0)) -> 0 | EZ10: =MIN(MAX((GX9*(1+GX$5/Setup!$C$36)+IF($V10=31,N($F10),0))-DB10,0),MAX($P10-SUM(DV10:EY10),0)) -> 0 | FA10: =MIN(MAX((GY9*(1+GY$5/Setup!$C$36)+IF($V10=32,N($F10),0))-DC10,0),MAX($P10-SUM(DV10:EZ10),0)) -> 0 | FB10: =MIN(MAX((GZ9*(1+GZ$5/Setup!$C$36)+IF($V10=33,N($F10),0))-DD10,0),MAX($P10-SUM(DV10:FA10),0)) -> 0 | FC10: =MIN(MAX((HA9*(1+HA$5/Setup!$C$36)+IF($V10=34,N($F10),0))-DE10,0),MAX($P10-SUM(DV10:FB10),0)) -> 0 | FD10: =MIN(MAX((HB9*(1+HB$5/Setup!$C$36)+IF($V10=35,N($F10),0))-DF10,0),MAX($P10-SUM(DV10:FC10),0)) -> 0 | FE10: =MIN(MAX((HC9*(1+HC$5/Setup!$C$36)+IF($V10=36,N($F10),0))-DG10,0),MAX($P10-SUM(DV10:FD10),0)) -> 0 | FF10: =MIN(MAX((HD9*(1+HD$5/Setup!$C$36)+IF($V10=37,N($F10),0))-DH10,0),MAX($P10-SUM(DV10:FE10),0)) -> 0 | FG10: =MIN(MAX((HE9*(1+HE$5/Setup!$C$36)+IF($V10=38,N($F10),0))-DI10,0),MAX($P10-SUM(DV10:FF10),0)) -> 0 | FH10: =MIN(MAX((HF9*(1+HF$5/Setup!$C$36)+IF($V10=39,N($F10),0))-DJ10,0),MAX($P10-SUM(DV10:FG10),0)) -> 0 | FI10: =MIN(MAX((HG9*(1+HG$5/Setup!$C$36)+IF($V10=40,N($F10),0))-DK10,0),MAX($P10-SUM(DV10:FH10),0)) -> 0 | FJ10: =MIN(MAX((HH9*(1+HH$5/Setup!$C$36)+IF($V10=41,N($F10),0))-DL10,0),MAX($P10-SUM(DV10:FI10),0)) -> 0 | FK10: =MIN(MAX((HI9*(1+HI$5/Setup!$C$36)+IF($V10=42,N($F10),0))-DM10,0),MAX($P10-SUM(DV10:FJ10),0)) -> 0 | FL10: =MIN(MAX((HJ9*(1+HJ$5/Setup!$C$36)+IF($V10=43,N($F10),0))-DN10,0),MAX($P10-SUM(DV10:FK10),0)) -> 0 | FM10: =MIN(MAX((HK9*(1+HK$5/Setup!$C$36)+IF($V10=44,N($F10),0))-DO10,0),MAX($P10-SUM(DV10:FL10),0)) -> 0 | FN10: =MIN(MAX((HL9*(1+HL$5/Setup!$C$36)+IF($V10=45,N($F10),0))-DP10,0),MAX($P10-SUM(DV10:FM10),0)) -> 0 | FO10: =MIN(MAX((HM9*(1+HM$5/Setup!$C$36)+IF($V10=46,N($F10),0))-DQ10,0),MAX($P10-SUM(DV10:FN10),0)) -> 0 | FP10: =MIN(MAX((HN9*(1+HN$5/Setup!$C$36)+IF($V10=47,N($F10),0))-DR10,0),MAX($P10-SUM(DV10:FO10),0)) -> 0 | FQ10: =MIN(MAX((HO9*(1+HO$5/Setup!$C$36)+IF($V10=48,N($F10),0))-DS10,0),MAX($P10-SUM(DV10:FP10),0)) -> 0 | FR10: =MIN(MAX((HP9*(1+HP$5/Setup!$C$36)+IF($V10=49,N($F10),0))-DT10,0),MAX($P10-SUM(DV10:FQ10),0)) -> 0 | FS10: =MIN(MAX((HQ9*(1+HQ$5/Setup!$C$36)+IF($V10=50,N($F10),0))-DU10,0),MAX($P10-SUM(DV10:FR10),0)) -> 0 | FT10: =IF((FT9*(1+FT$5/Setup!$C$36)+IF($V10=1,N($F10),0))-BX10-DV10<0.005,0,(FT9*(1+FT$5/Setup!$C$36)+IF($V10=1,N($F10),0))-BX10-DV10) -> 484.0426 | FU10: =IF((FU9*(1+FU$5/Setup!$C$36)+IF($V10=2,N($F10),0))-BY10-DW10<0.005,0,(FU9*(1+FU$5/Setup!$C$36)+IF($V10=2,N($F10),0))-BY10-DW10) -> 1176.6729 | FV10: =IF((FV9*(1+FV$5/Setup!$C$36)+IF($V10=3,N($F10),0))-BZ10-DX10<0.005,0,(FV9*(1+FV$5/Setup!$C$36)+IF($V10=3,N($F10),0))-BZ10-DX10) -> 0 | FW10: =IF((FW9*(1+FW$5/Setup!$C$36)+IF($V10=4,N($F10),0))-CA10-DY10<0.005,0,(FW9*(1+FW$5/Setup!$C$36)+IF($V10=4,N($F10),0))-CA10-DY10) -> 0 | FX10: =IF((FX9*(1+FX$5/Setup!$C$36)+IF($V10=5,N($F10),0))-CB10-DZ10<0.005,0,(FX9*(1+FX$5/Setup!$C$36)+IF($V10=5,N($F10),0))-CB10-DZ10) -> 0 | FY10: =IF((FY9*(1+FY$5/Setup!$C$36)+IF($V10=6,N($F10),0))-CC10-EA10<0.005,0,(FY9*(1+FY$5/Setup!$C$36)+IF($V10=6,N($F10),0))-CC10-EA10) -> 0 | FZ10: =IF((FZ9*(1+FZ$5/Setup!$C$36)+IF($V10=7,N($F10),0))-CD10-EB10<0.005,0,(FZ9*(1+FZ$5/Setup!$C$36)+IF($V10=7,N($F10),0))-CD10-EB10) -> 0 | GA10: =IF((GA9*(1+GA$5/Setup!$C$36)+IF($V10=8,N($F10),0))-CE10-EC10<0.005,0,(GA9*(1+GA$5/Setup!$C$36)+IF($V10=8,N($F10),0))-CE10-EC10) -> 0 | GB10: =IF((GB9*(1+GB$5/Setup!$C$36)+IF($V10=9,N($F10),0))-CF10-ED10<0.005,0,(GB9*(1+GB$5/Setup!$C$36)+IF($V10=9,N($F10),0))-CF10-ED10) -> 0 | GC10: =IF((GC9*(1+GC$5/Setup!$C$36)+IF($V10=10,N($F10),0))-CG10-EE10<0.005,0,(GC9*(1+GC$5/Setup!$C$36)+IF($V10=10,N($F10),0))-CG10-EE10) -> 0 | GD10: =IF((GD9*(1+GD$5/Setup!$C$36)+IF($V10=11,N($F10),0))-CH10-EF10<0.005,0,(GD9*(1+GD$5/Setup!$C$36)+IF($V10=11,N($F10),0))-CH10-EF10) -> 0 | GE10: =IF((GE9*(1+GE$5/Setup!$C$36)+IF($V10=12,N($F10),0))-CI10-EG10<0.005,0,(GE9*(1+GE$5/Setup!$C$36)+IF($V10=12,N($F10),0))-CI10-EG10) -> 0 | GF10: =IF((GF9*(1+GF$5/Setup!$C$36)+IF($V10=13,N($F10),0))-CJ10-EH10<0.005,0,(GF9*(1+GF$5/Setup!$C$36)+IF($V10=13,N($F10),0))-CJ10-EH10) -> 0 | GG10: =IF((GG9*(1+GG$5/Setup!$C$36)+IF($V10=14,N($F10),0))-CK10-EI10<0.005,0,(GG9*(1+GG$5/Setup!$C$36)+IF($V10=14,N($F10),0))-CK10-EI10) -> 0 | GH10: =IF((GH9*(1+GH$5/Setup!$C$36)+IF($V10=15,N($F10),0))-CL10-EJ10<0.005,0,(GH9*(1+GH$5/Setup!$C$36)+IF($V10=15,N($F10),0))-CL10-EJ10) -> 0 | GI10: =IF((GI9*(1+GI$5/Setup!$C$36)+IF($V10=16,N($F10),0))-CM10-EK10<0.005,0,(GI9*(1+GI$5/Setup!$C$36)+IF($V10=16,N($F10),0))-CM10-EK10) -> 0 | GJ10: =IF((GJ9*(1+GJ$5/Setup!$C$36)+IF($V10=17,N($F10),0))-CN10-EL10<0.005,0,(GJ9*(1+GJ$5/Setup!$C$36)+IF($V10=17,N($F10),0))-CN10-EL10) -> 0 | GK10: =IF((GK9*(1+GK$5/Setup!$C$36)+IF($V10=18,N($F10),0))-CO10-EM10<0.005,0,(GK9*(1+GK$5/Setup!$C$36)+IF($V10=18,N($F10),0))-CO10-EM10) -> 0 | GL10: =IF((GL9*(1+GL$5/Setup!$C$36)+IF($V10=19,N($F10),0))-CP10-EN10<0.005,0,(GL9*(1+GL$5/Setup!$C$36)+IF($V10=19,N($F10),0))-CP10-EN10) -> 0 | GM10: =IF((GM9*(1+GM$5/Setup!$C$36)+IF($V10=20,N($F10),0))-CQ10-EO10<0.005,0,(GM9*(1+GM$5/Setup!$C$36)+IF($V10=20,N($F10),0))-CQ10-EO10) -> 0 | GN10: =IF((GN9*(1+GN$5/Setup!$C$36)+IF($V10=21,N($F10),0))-CR10-EP10<0.005,0,(GN9*(1+GN$5/Setup!$C$36)+IF($V10=21,N($F10),0))-CR10-EP10) -> 0 | GO10: =IF((GO9*(1+GO$5/Setup!$C$36)+IF($V10=22,N($F10),0))-CS10-EQ10<0.005,0,(GO9*(1+GO$5/Setup!$C$36)+IF($V10=22,N($F10),0))-CS10-EQ10) -> 0 | GP10: =IF((GP9*(1+GP$5/Setup!$C$36)+IF($V10=23,N($F10),0))-CT10-ER10<0.005,0,(GP9*(1+GP$5/Setup!$C$36)+IF($V10=23,N($F10),0))-CT10-ER10) -> 0 | GQ10: =IF((GQ9*(1+GQ$5/Setup!$C$36)+IF($V10=24,N($F10),0))-CU10-ES10<0.005,0,(GQ9*(1+GQ$5/Setup!$C$36)+IF($V10=24,N($F10),0))-CU10-ES10) -> 0 | GR10: =IF((GR9*(1+GR$5/Setup!$C$36)+IF($V10=25,N($F10),0))-CV10-ET10<0.005,0,(GR9*(1+GR$5/Setup!$C$36)+IF($V10=25,N($F10),0))-CV10-ET10) -> 0 | GS10: =IF((GS9*(1+GS$5/Setup!$C$36)+IF($V10=26,N($F10),0))-CW10-EU10<0.005,0,(GS9*(1+GS$5/Setup!$C$36)+IF($V10=26,N($F10),0))-CW10-EU10) -> 0 | GT10: =IF((GT9*(1+GT$5/Setup!$C$36)+IF($V10=27,N($F10),0))-CX10-EV10<0.005,0,(GT9*(1+GT$5/Setup!$C$36)+IF($V10=27,N($F10),0))-CX10-EV10) -> 0 | GU10: =IF((GU9*(1+GU$5/Setup!$C$36)+IF($V10=28,N($F10),0))-CY10-EW10<0.005,0,(GU9*(1+GU$5/Setup!$C$36)+IF($V10=28,N($F10),0))-CY10-EW10) -> 0 | GV10: =IF((GV9*(1+GV$5/Setup!$C$36)+IF($V10=29,N($F10),0))-CZ10-EX10<0.005,0,(GV9*(1+GV$5/Setup!$C$36)+IF($V10=29,N($F10),0))-CZ10-EX10) -> 0 | GW10: =IF((GW9*(1+GW$5/Setup!$C$36)+IF($V10=30,N($F10),0))-DA10-EY10<0.005,0,(GW9*(1+GW$5/Setup!$C$36)+IF($V10=30,N($F10),0))-DA10-EY10) -> 0 | GX10: =IF((GX9*(1+GX$5/Setup!$C$36)+IF($V10=31,N($F10),0))-DB10-EZ10<0.005,0,(GX9*(1+GX$5/Setup!$C$36)+IF($V10=31,N($F10),0))-DB10-EZ10) -> 0 | GY10: =IF((GY9*(1+GY$5/Setup!$C$36)+IF($V10=32,N($F10),0))-DC10-FA10<0.005,0,(GY9*(1+GY$5/Setup!$C$36)+IF($V10=32,N($F10),0))-DC10-FA10) -> 0 | GZ10: =IF((GZ9*(1+GZ$5/Setup!$C$36)+IF($V10=33,N($F10),0))-DD10-FB10<0.005,0,(GZ9*(1+GZ$5/Setup!$C$36)+IF($V10=33,N($F10),0))-DD10-FB10) -> 0 | HA10: =IF((HA9*(1+HA$5/Setup!$C$36)+IF($V10=34,N($F10),0))-DE10-FC10<0.005,0,(HA9*(1+HA$5/Setup!$C$36)+IF($V10=34,N($F10),0))-DE10-FC10) -> 0 | HB10: =IF((HB9*(1+HB$5/Setup!$C$36)+IF($V10=35,N($F10),0))-DF10-FD10<0.005,0,(HB9*(1+HB$5/Setup!$C$36)+IF($V10=35,N($F10),0))-DF10-FD10) -> 0 | HC10: =IF((HC9*(1+HC$5/Setup!$C$36)+IF($V10=36,N($F10),0))-DG10-FE10<0.005,0,(HC9*(1+HC$5/Setup!$C$36)+IF($V10=36,N($F10),0))-DG10-FE10) -> 0 | HD10: =IF((HD9*(1+HD$5/Setup!$C$36)+IF($V10=37,N($F10),0))-DH10-FF10<0.005,0,(HD9*(1+HD$5/Setup!$C$36)+IF($V10=37,N($F10),0))-DH10-FF10) -> 0 | HE10: =IF((HE9*(1+HE$5/Setup!$C$36)+IF($V10=38,N($F10),0))-DI10-FG10<0.005,0,(HE9*(1+HE$5/Setup!$C$36)+IF($V10=38,N($F10),0))-DI10-FG10) -> 0 | HF10: =IF((HF9*(1+HF$5/Setup!$C$36)+IF($V10=39,N($F10),0))-DJ10-FH10<0.005,0,(HF9*(1+HF$5/Setup!$C$36)+IF($V10=39,N($F10),0))-DJ10-FH10) -> 0 | HG10: =IF((HG9*(1+HG$5/Setup!$C$36)+IF($V10=40,N($F10),0))-DK10-FI10<0.005,0,(HG9*(1+HG$5/Setup!$C$36)+IF($V10=40,N($F10),0))-DK10-FI10) -> 0 | HH10: =IF((HH9*(1+HH$5/Setup!$C$36)+IF($V10=41,N($F10),0))-DL10-FJ10<0.005,0,(HH9*(1+HH$5/Setup!$C$36)+IF($V10=41,N($F10),0))-DL10-FJ10) -> 0 | HI10: =IF((HI9*(1+HI$5/Setup!$C$36)+IF($V10=42,N($F10),0))-DM10-FK10<0.005,0,(HI9*(1+HI$5/Setup!$C$36)+IF($V10=42,N($F10),0))-DM10-FK10) -> 0 | HJ10: =IF((HJ9*(1+HJ$5/Setup!$C$36)+IF($V10=43,N($F10),0))-DN10-FL10<0.005,0,(HJ9*(1+HJ$5/Setup!$C$36)+IF($V10=43,N($F10),0))-DN10-FL10) -> 0 | HK10: =IF((HK9*(1+HK$5/Setup!$C$36)+IF($V10=44,N($F10),0))-DO10-FM10<0.005,0,(HK9*(1+HK$5/Setup!$C$36)+IF($V10=44,N($F10),0))-DO10-FM10) -> 0 | HL10: =IF((HL9*(1+HL$5/Setup!$C$36)+IF($V10=45,N($F10),0))-DP10-FN10<0.005,0,(HL9*(1+HL$5/Setup!$C$36)+IF($V10=45,N($F10),0))-DP10-FN10) -> 0 | HM10: =IF((HM9*(1+HM$5/Setup!$C$36)+IF($V10=46,N($F10),0))-DQ10-FO10<0.005,0,(HM9*(1+HM$5/Setup!$C$36)+IF($V10=46,N($F10),0))-DQ10-FO10) -> 0 | HN10: =IF((HN9*(1+HN$5/Setup!$C$36)+IF($V10=47,N($F10),0))-DR10-FP10<0.005,0,(HN9*(1+HN$5/Setup!$C$36)+IF($V10=47,N($F10),0))-DR10-FP10) -> 0 | HO10: =IF((HO9*(1+HO$5/Setup!$C$36)+IF($V10=48,N($F10),0))-DS10-FQ10<0.005,0,(HO9*(1+HO$5/Setup!$C$36)+IF($V10=48,N($F10),0))-DS10-FQ10) -> 0 | HP10: =IF((HP9*(1+HP$5/Setup!$C$36)+IF($V10=49,N($F10),0))-DT10-FR10<0.005,0,(HP9*(1+HP$5/Setup!$C$36)+IF($V10=49,N($F10),0))-DT10-FR10) -> 0 | HQ10: =IF((HQ9*(1+HQ$5/Setup!$C$36)+IF($V10=50,N($F10),0))-DU10-FS10<0.005,0,(HQ9*(1+HQ$5/Setup!$C$36)+IF($V10=50,N($F10),0))-DU10-FS10) -> 0
A11: 3 | B11: =IF(Setup!$C$7="Every month",EDATE(Setup!$C$8,($A11-1)),IF(Setup!$C$7="Twice a month",DATE(YEAR(Setup!$C$8),MONTH(Setup!$C$8)+INT((($A11-1)+Setup!$C$41)/2),MIN(IF(MOD(($A11-1)+Setup!$C$41,2)=0,Setup!$C$39,Setup!$C$40),DAY(EOMONTH(DATE(YEAR(Setup!$C$8),MONTH(Setup!$C$8)+INT((($A11-1)+Setup!$C$41)/2),1),0)))),Setup!$C$8+($A11-1)*IF(Setup!$C$7="Every week",7,14))) -> 46353 | C11: =IF(Setup!$C$7="Every month",EDATE(Setup!$C$8,$A11),IF(Setup!$C$7="Twice a month",DATE(YEAR(Setup!$C$8),MONTH(Setup!$C$8)+INT(($A11+Setup!$C$41)/2),MIN(IF(MOD($A11+Setup!$C$41,2)=0,Setup!$C$39,Setup!$C$40),DAY(EOMONTH(DATE(YEAR(Setup!$C$8),MONTH(Setup!$C$8)+INT(($A11+Setup!$C$41)/2),1),0)))),Setup!$C$8+$A11*IF(Setup!$C$7="Every week",7,14))) -> 46367 | I11: =N(Setup!$C$11)+N(E11) -> 100 | J11: =MIN(Setup!$C$37,MAX(I11,0)) -> 9.2307692 | K11: =MIN(MAX(N(Setup!$C$14)-L10,0),MAX(I11-J11,0)) -> 18.461538 | L11: =L10+K11-N(G11) -> 500 | M11: =M10+J11-N(H11) -> 27.692308 | N11: =SUM(BX11:DU11) -> 25 | O11: =SUM(Z11:BW11)-N11 -> 0 | P11: =MAX(I11-J11-K11,0)+O11 -> 72.307692 | Q11: =SUM(DV11:FS11) -> 72.307692 | R11: =N11+J11+K11+Q11 -> 125 | S11: =T11-T10-N(F11)+N11+Q11 -> 12.614283 | T11: =SUM(FT11:HQ11) -> 1576.0221 | U11: =IF(T10<0.005,"",INDEX(Helpers!$C$2:$C$51,IF(_xlfn.MINIFS($DV$6:$FS$6,DV11:FS11,">0.005")=0,V11,_xlfn.MINIFS($DV$6:$FS$6,DV11:FS11,">0.005")))) -> Card A | V11: =IF(_xlfn.MINIFS($FT$6:$HQ$6,FT10:HQ10,">0.005")=0,1,_xlfn.MINIFS($FT$6:$HQ$6,FT10:HQ10,">0.005")) -> 1 | W11: =IF(AND(D11<>"Paid",T10>0.005),1,0) -> 1 | X11: =SUMPRODUCT(((Helpers!$G$2:$G$51*(1+(Helpers!$D$2:$D$51+0.000000001)/12)^(($B11-Setup!$C$8)/(365.25/12))-Helpers!$E$2:$E$51*((1+(Helpers!$D$2:$D$51+0.000000001)/12)^(($B11-Setup!$C$8)/(365.25/12))-1)/((Helpers!$D$2:$D$51+0.000000001)/12))>0)*(Helpers!$G$2:$G$51*(1+(Helpers!$D$2:$D$51+0.000000001)/12)^(($B11-Setup!$C$8)/(365.25/12))-Helpers!$E$2:$E$51*((1+(Helpers!$D$2:$D$51+0.000000001)/12)^(($B11-Setup!$C$8)/(365.25/12))-1)/((Helpers!$D$2:$D$51+0.000000001)/12))) -> 1665.9861 | Z11: =IF(OR(N(Z$5)=0,Z$6=""),0,Z$5*((DATE(YEAR($B11),MONTH($B11),MIN(Z$6,DAY(EOMONTH($B11,0))))>=$B11)*(DATE(YEAR($B11),MONTH($B11),MIN(Z$6,DAY(EOMONTH($B11,0))))<$C11)+(DATE(YEAR($B11),MONTH($B11)+1,MIN(Z$6,DAY(EOMONTH($B11,1))))>=$B11)*(DATE(YEAR($B11),MONTH($B11)+1,MIN(Z$6,DAY(EOMONTH($B11,1))))<$C11))) -> 25 | AA11: =IF(OR(N(AA$5)=0,AA$6=""),0,AA$5*((DATE(YEAR($B11),MONTH($B11),MIN(AA$6,DAY(EOMONTH($B11,0))))>=$B11)*(DATE(YEAR($B11),MONTH($B11),MIN(AA$6,DAY(EOMONTH($B11,0))))<$C11)+(DATE(YEAR($B11),MONTH($B11)+1,MIN(AA$6,DAY(EOMONTH($B11,1))))>=$B11)*(DATE(YEAR($B11),MONTH($B11)+1,MIN(AA$6,DAY(EOMONTH($B11,1))))<$C11))) -> 0 | AB11: =IF(OR(N(AB$5)=0,AB$6=""),0,AB$5*((DATE(YEAR($B11),MONTH($B11),MIN(AB$6,DAY(EOMONTH($B11,0))))>=$B11)*(DATE(YEAR($B11),MONTH($B11),MIN(AB$6,DAY(EOMONTH($B11,0))))<$C11)+(DATE(YEAR($B11),MONTH($B11)+1,MIN(AB$6,DAY(EOMONTH($B11,1))))>=$B11)*(DATE(YEAR($B11),MONTH($B11)+1,MIN(AB$6,DAY(EOMONTH($B11,1))))<$C11))) -> 0 | AC11: =IF(OR(N(AC$5)=0,AC$6=""),0,AC$5*((DATE(YEAR($B11),MONTH($B11),MIN(AC$6,DAY(EOMONTH($B11,0))))>=$B11)*(DATE(YEAR($B11),MONTH($B11),MIN(AC$6,DAY(EOMONTH($B11,0))))<$C11)+(DATE(YEAR($B11),MONTH($B11)+1,MIN(AC$6,DAY(EOMONTH($B11,1))))>=$B11)*(DATE(YEAR($B11),MONTH($B11)+1,MIN(AC$6,DAY(EOMONTH($B11,1))))<$C11))) -> 0 | AD11: =IF(OR(N(AD$5)=0,AD$6=""),0,AD$5*((DATE(YEAR($B11),MONTH($B11),MIN(AD$6,DAY(EOMONTH($B11,0))))>=$B11)*(DATE(YEAR($B11),MONTH($B11),MIN(AD$6,DAY(EOMONTH($B11,0))))<$C11)+(DATE(YEAR($B11),MONTH($B11)+1,MIN(AD$6,DAY(EOMONTH($B11,1))))>=$B11)*(DATE(YEAR($B11),MONTH($B11)+1,MIN(AD$6,DAY(EOMONTH($B11,1))))<$C11))) -> 0 | AE11: =IF(OR(N(AE$5)=0,AE$6=""),0,AE$5*((DATE(YEAR($B11),MONTH($B11),MIN(AE$6,DAY(EOMONTH($B11,0))))>=$B11)*(DATE(YEAR($B11),MONTH($B11),MIN(AE$6,DAY(EOMONTH($B11,0))))<$C11)+(DATE(YEAR($B11),MONTH($B11)+1,MIN(AE$6,DAY(EOMONTH($B11,1))))>=$B11)*(DATE(YEAR($B11),MONTH($B11)+1,MIN(AE$6,DAY(EOMONTH($B11,1))))<$C11))) -> 0 | AF11: =IF(OR(N(AF$5)=0,AF$6=""),0,AF$5*((DATE(YEAR($B11),MONTH($B11),MIN(AF$6,DAY(EOMONTH($B11,0))))>=$B11)*(DATE(YEAR($B11),MONTH($B11),MIN(AF$6,DAY(EOMONTH($B11,0))))<$C11)+(DATE(YEAR($B11),MONTH($B11)+1,MIN(AF$6,DAY(EOMONTH($B11,1))))>=$B11)*(DATE(YEAR($B11),MONTH($B11)+1,MIN(AF$6,DAY(EOMONTH($B11,1))))<$C11))) -> 0 | AG11: =IF(OR(N(AG$5)=0,AG$6=""),0,AG$5*((DATE(YEAR($B11),MONTH($B11),MIN(AG$6,DAY(EOMONTH($B11,0))))>=$B11)*(DATE(YEAR($B11),MONTH($B11),MIN(AG$6,DAY(EOMONTH($B11,0))))<$C11)+(DATE(YEAR($B11),MONTH($B11)+1,MIN(AG$6,DAY(EOMONTH($B11,1))))>=$B11)*(DATE(YEAR($B11),MONTH($B11)+1,MIN(AG$6,DAY(EOMONTH($B11,1))))<$C11))) -> 0 | ... BW11: =IF(OR(N(BW$5)=0,BW$6=""),0,BW$5*((DATE(YEAR($B11),MONTH($B11),MIN(BW$6,DAY(EOMONTH($B11,0))))>=$B11)*(DATE(YEAR($B11),MONTH($B11),MIN(BW$6,DAY(EOMONTH($B11,0))))<$C11)+(DATE(YEAR($B11),MONTH($B11)+1,MIN(BW$6,DAY(EOMONTH($B11,1))))>=$B11)*(DATE(YEAR($B11),MONTH($B11)+1,MIN(BW$6,DAY(EOMONTH($B11,1))))<$C11))) -> 0 | BX11: =MIN(Z11,(FT10*(1+FT$5/Setup!$C$36)+IF($V11=1,N($F11),0))) -> 25 | BY11: =MIN(AA11,(FU10*(1+FU$5/Setup!$C$36)+IF($V11=2,N($F11),0))) -> 0 | BZ11: =MIN(AB11,(FV10*(1+FV$5/Setup!$C$36)+IF($V11=3,N($F11),0))) -> 0 | CA11: =MIN(AC11,(FW10*(1+FW$5/Setup!$C$36)+IF($V11=4,N($F11),0))) -> 0 | CB11: =MIN(AD11,(FX10*(1+FX$5/Setup!$C$36)+IF($V11=5,N($F11),0))) -> 0 | CC11: =MIN(AE11,(FY10*(1+FY$5/Setup!$C$36)+IF($V11=6,N($F11),0))) -> 0 | CD11: =MIN(AF11,(FZ10*(1+FZ$5/Setup!$C$36)+IF($V11=7,N($F11),0))) -> 0 | CE11: =MIN(AG11,(GA10*(1+GA$5/Setup!$C$36)+IF($V11=8,N($F11),0))) -> 0 | CF11: =MIN(AH11,(GB10*(1+GB$5/Setup!$C$36)+IF($V11=9,N($F11),0))) -> 0 | CG11: =MIN(AI11,(GC10*(1+GC$5/Setup!$C$36)+IF($V11=10,N($F11),0))) -> 0 | CH11: =MIN(AJ11,(GD10*(1+GD$5/Setup!$C$36)+IF($V11=11,N($F11),0))) -> 0 | CI11: =MIN(AK11,(GE10*(1+GE$5/Setup!$C$36)+IF($V11=12,N($F11),0))) -> 0 | CJ11: =MIN(AL11,(GF10*(1+GF$5/Setup!$C$36)+IF($V11=13,N($F11),0))) -> 0 | CK11: =MIN(AM11,(GG10*(1+GG$5/Setup!$C$36)+IF($V11=14,N($F11),0))) -> 0 | CL11: =MIN(AN11,(GH10*(1+GH$5/Setup!$C$36)+IF($V11=15,N($F11),0))) -> 0 | CM11: =MIN(AO11,(GI10*(1+GI$5/Setup!$C$36)+IF($V11=16,N($F11),0))) -> 0 | CN11: =MIN(AP11,(GJ10*(1+GJ$5/Setup!$C$36)+IF($V11=17,N($F11),0))) -> 0 | CO11: =MIN(AQ11,(GK10*(1+GK$5/Setup!$C$36)+IF($V11=18,N($F11),0))) -> 0 | CP11: =MIN(AR11,(GL10*(1+GL$5/Setup!$C$36)+IF($V11=19,N($F11),0))) -> 0 | CQ11: =MIN(AS11,(GM10*(1+GM$5/Setup!$C$36)+IF($V11=20,N($F11),0))) -> 0 | CR11: =MIN(AT11,(GN10*(1+GN$5/Setup!$C$36)+IF($V11=21,N($F11),0))) -> 0 | CS11: =MIN(AU11,(GO10*(1+GO$5/Setup!$C$36)+IF($V11=22,N($F11),0))) -> 0 | CT11: =MIN(AV11,(GP10*(1+GP$5/Setup!$C$36)+IF($V11=23,N($F11),0))) -> 0 | CU11: =MIN(AW11,(GQ10*(1+GQ$5/Setup!$C$36)+IF($V11=24,N($F11),0))) -> 0 | CV11: =MIN(AX11,(GR10*(1+GR$5/Setup!$C$36)+IF($V11=25,N($F11),0))) -> 0 | CW11: =MIN(AY11,(GS10*(1+GS$5/Setup!$C$36)+IF($V11=26,N($F11),0))) -> 0 | CX11: =MIN(AZ11,(GT10*(1+GT$5/Setup!$C$36)+IF($V11=27,N($F11),0))) -> 0 | CY11: =MIN(BA11,(GU10*(1+GU$5/Setup!$C$36)+IF($V11=28,N($F11),0))) -> 0 | CZ11: =MIN(BB11,(GV10*(1+GV$5/Setup!$C$36)+IF($V11=29,N($F11),0))) -> 0 | DA11: =MIN(BC11,(GW10*(1+GW$5/Setup!$C$36)+IF($V11=30,N($F11),0))) -> 0 | DB11: =MIN(BD11,(GX10*(1+GX$5/Setup!$C$36)+IF($V11=31,N($F11),0))) -> 0 | DC11: =MIN(BE11,(GY10*(1+GY$5/Setup!$C$36)+IF($V11=32,N($F11),0))) -> 0 | DD11: =MIN(BF11,(GZ10*(1+GZ$5/Setup!$C$36)+IF($V11=33,N($F11),0))) -> 0 | DE11: =MIN(BG11,(HA10*(1+HA$5/Setup!$C$36)+IF($V11=34,N($F11),0))) -> 0 | DF11: =MIN(BH11,(HB10*(1+HB$5/Setup!$C$36)+IF($V11=35,N($F11),0))) -> 0 | DG11: =MIN(BI11,(HC10*(1+HC$5/Setup!$C$36)+IF($V11=36,N($F11),0))) -> 0 | DH11: =MIN(BJ11,(HD10*(1+HD$5/Setup!$C$36)+IF($V11=37,N($F11),0))) -> 0 | DI11: =MIN(BK11,(HE10*(1+HE$5/Setup!$C$36)+IF($V11=38,N($F11),0))) -> 0 | DJ11: =MIN(BL11,(HF10*(1+HF$5/Setup!$C$36)+IF($V11=39,N($F11),0))) -> 0 | DK11: =MIN(BM11,(HG10*(1+HG$5/Setup!$C$36)+IF($V11=40,N($F11),0))) -> 0 | DL11: =MIN(BN11,(HH10*(1+HH$5/Setup!$C$36)+IF($V11=41,N($F11),0))) -> 0 | DM11: =MIN(BO11,(HI10*(1+HI$5/Setup!$C$36)+IF($V11=42,N($F11),0))) -> 0 | DN11: =MIN(BP11,(HJ10*(1+HJ$5/Setup!$C$36)+IF($V11=43,N($F11),0))) -> 0 | DO11: =MIN(BQ11,(HK10*(1+HK$5/Setup!$C$36)+IF($V11=44,N($F11),0))) -> 0 | DP11: =MIN(BR11,(HL10*(1+HL$5/Setup!$C$36)+IF($V11=45,N($F11),0))) -> 0 | DQ11: =MIN(BS11,(HM10*(1+HM$5/Setup!$C$36)+IF($V11=46,N($F11),0))) -> 0 | DR11: =MIN(BT11,(HN10*(1+HN$5/Setup!$C$36)+IF($V11=47,N($F11),0))) -> 0 | DS11: =MIN(BU11,(HO10*(1+HO$5/Setup!$C$36)+IF($V11=48,N($F11),0))) -> 0 | DT11: =MIN(BV11,(HP10*(1+HP$5/Setup!$C$36)+IF($V11=49,N($F11),0))) -> 0 | DU11: =MIN(BW11,(HQ10*(1+HQ$5/Setup!$C$36)+IF($V11=50,N($F11),0))) -> 0 | DV11: =MIN(MAX((FT10*(1+FT$5/Setup!$C$36)+IF($V11=1,N($F11),0))-BX11,0),MAX($P11-0,0)) -> 72.307692 | DW11: =MIN(MAX((FU10*(1+FU$5/Setup!$C$36)+IF($V11=2,N($F11),0))-BY11,0),MAX($P11-SUM(DV11:DV11),0)) -> 0 | DX11: =MIN(MAX((FV10*(1+FV$5/Setup!$C$36)+IF($V11=3,N($F11),0))-BZ11,0),MAX($P11-SUM(DV11:DW11),0)) -> 0 | DY11: =MIN(MAX((FW10*(1+FW$5/Setup!$C$36)+IF($V11=4,N($F11),0))-CA11,0),MAX($P11-SUM(DV11:DX11),0)) -> 0 | DZ11: =MIN(MAX((FX10*(1+FX$5/Setup!$C$36)+IF($V11=5,N($F11),0))-CB11,0),MAX($P11-SUM(DV11:DY11),0)) -> 0 | EA11: =MIN(MAX((FY10*(1+FY$5/Setup!$C$36)+IF($V11=6,N($F11),0))-CC11,0),MAX($P11-SUM(DV11:DZ11),0)) -> 0 | EB11: =MIN(MAX((FZ10*(1+FZ$5/Setup!$C$36)+IF($V11=7,N($F11),0))-CD11,0),MAX($P11-SUM(DV11:EA11),0)) -> 0 | EC11: =MIN(MAX((GA10*(1+GA$5/Setup!$C$36)+IF($V11=8,N($F11),0))-CE11,0),MAX($P11-SUM(DV11:EB11),0)) -> 0 | ED11: =MIN(MAX((GB10*(1+GB$5/Setup!$C$36)+IF($V11=9,N($F11),0))-CF11,0),MAX($P11-SUM(DV11:EC11),0)) -> 0 | EE11: =MIN(MAX((GC10*(1+GC$5/Setup!$C$36)+IF($V11=10,N($F11),0))-CG11,0),MAX($P11-SUM(DV11:ED11),0)) -> 0 | EF11: =MIN(MAX((GD10*(1+GD$5/Setup!$C$36)+IF($V11=11,N($F11),0))-CH11,0),MAX($P11-SUM(DV11:EE11),0)) -> 0 | EG11: =MIN(MAX((GE10*(1+GE$5/Setup!$C$36)+IF($V11=12,N($F11),0))-CI11,0),MAX($P11-SUM(DV11:EF11),0)) -> 0 | EH11: =MIN(MAX((GF10*(1+GF$5/Setup!$C$36)+IF($V11=13,N($F11),0))-CJ11,0),MAX($P11-SUM(DV11:EG11),0)) -> 0 | EI11: =MIN(MAX((GG10*(1+GG$5/Setup!$C$36)+IF($V11=14,N($F11),0))-CK11,0),MAX($P11-SUM(DV11:EH11),0)) -> 0 | EJ11: =MIN(MAX((GH10*(1+GH$5/Setup!$C$36)+IF($V11=15,N($F11),0))-CL11,0),MAX($P11-SUM(DV11:EI11),0)) -> 0 | EK11: =MIN(MAX((GI10*(1+GI$5/Setup!$C$36)+IF($V11=16,N($F11),0))-CM11,0),MAX($P11-SUM(DV11:EJ11),0)) -> 0 | EL11: =MIN(MAX((GJ10*(1+GJ$5/Setup!$C$36)+IF($V11=17,N($F11),0))-CN11,0),MAX($P11-SUM(DV11:EK11),0)) -> 0 | EM11: =MIN(MAX((GK10*(1+GK$5/Setup!$C$36)+IF($V11=18,N($F11),0))-CO11,0),MAX($P11-SUM(DV11:EL11),0)) -> 0 | EN11: =MIN(MAX((GL10*(1+GL$5/Setup!$C$36)+IF($V11=19,N($F11),0))-CP11,0),MAX($P11-SUM(DV11:EM11),0)) -> 0 | EO11: =MIN(MAX((GM10*(1+GM$5/Setup!$C$36)+IF($V11=20,N($F11),0))-CQ11,0),MAX($P11-SUM(DV11:EN11),0)) -> 0 | EP11: =MIN(MAX((GN10*(1+GN$5/Setup!$C$36)+IF($V11=21,N($F11),0))-CR11,0),MAX($P11-SUM(DV11:EO11),0)) -> 0 | EQ11: =MIN(MAX((GO10*(1+GO$5/Setup!$C$36)+IF($V11=22,N($F11),0))-CS11,0),MAX($P11-SUM(DV11:EP11),0)) -> 0 | ER11: =MIN(MAX((GP10*(1+GP$5/Setup!$C$36)+IF($V11=23,N($F11),0))-CT11,0),MAX($P11-SUM(DV11:EQ11),0)) -> 0 | ES11: =MIN(MAX((GQ10*(1+GQ$5/Setup!$C$36)+IF($V11=24,N($F11),0))-CU11,0),MAX($P11-SUM(DV11:ER11),0)) -> 0 | ET11: =MIN(MAX((GR10*(1+GR$5/Setup!$C$36)+IF($V11=25,N($F11),0))-CV11,0),MAX($P11-SUM(DV11:ES11),0)) -> 0 | EU11: =MIN(MAX((GS10*(1+GS$5/Setup!$C$36)+IF($V11=26,N($F11),0))-CW11,0),MAX($P11-SUM(DV11:ET11),0)) -> 0 | EV11: =MIN(MAX((GT10*(1+GT$5/Setup!$C$36)+IF($V11=27,N($F11),0))-CX11,0),MAX($P11-SUM(DV11:EU11),0)) -> 0 | EW11: =MIN(MAX((GU10*(1+GU$5/Setup!$C$36)+IF($V11=28,N($F11),0))-CY11,0),MAX($P11-SUM(DV11:EV11),0)) -> 0 | EX11: =MIN(MAX((GV10*(1+GV$5/Setup!$C$36)+IF($V11=29,N($F11),0))-CZ11,0),MAX($P11-SUM(DV11:EW11),0)) -> 0 | EY11: =MIN(MAX((GW10*(1+GW$5/Setup!$C$36)+IF($V11=30,N($F11),0))-DA11,0),MAX($P11-SUM(DV11:EX11),0)) -> 0 | EZ11: =MIN(MAX((GX10*(1+GX$5/Setup!$C$36)+IF($V11=31,N($F11),0))-DB11,0),MAX($P11-SUM(DV11:EY11),0)) -> 0 | FA11: =MIN(MAX((GY10*(1+GY$5/Setup!$C$36)+IF($V11=32,N($F11),0))-DC11,0),MAX($P11-SUM(DV11:EZ11),0)) -> 0 | FB11: =MIN(MAX((GZ10*(1+GZ$5/Setup!$C$36)+IF($V11=33,N($F11),0))-DD11,0),MAX($P11-SUM(DV11:FA11),0)) -> 0 | FC11: =MIN(MAX((HA10*(1+HA$5/Setup!$C$36)+IF($V11=34,N($F11),0))-DE11,0),MAX($P11-SUM(DV11:FB11),0)) -> 0 | FD11: =MIN(MAX((HB10*(1+HB$5/Setup!$C$36)+IF($V11=35,N($F11),0))-DF11,0),MAX($P11-SUM(DV11:FC11),0)) -> 0 | FE11: =MIN(MAX((HC10*(1+HC$5/Setup!$C$36)+IF($V11=36,N($F11),0))-DG11,0),MAX($P11-SUM(DV11:FD11),0)) -> 0 | FF11: =MIN(MAX((HD10*(1+HD$5/Setup!$C$36)+IF($V11=37,N($F11),0))-DH11,0),MAX($P11-SUM(DV11:FE11),0)) -> 0 | FG11: =MIN(MAX((HE10*(1+HE$5/Setup!$C$36)+IF($V11=38,N($F11),0))-DI11,0),MAX($P11-SUM(DV11:FF11),0)) -> 0 | FH11: =MIN(MAX((HF10*(1+HF$5/Setup!$C$36)+IF($V11=39,N($F11),0))-DJ11,0),MAX($P11-SUM(DV11:FG11),0)) -> 0 | FI11: =MIN(MAX((HG10*(1+HG$5/Setup!$C$36)+IF($V11=40,N($F11),0))-DK11,0),MAX($P11-SUM(DV11:FH11),0)) -> 0 | FJ11: =MIN(MAX((HH10*(1+HH$5/Setup!$C$36)+IF($V11=41,N($F11),0))-DL11,0),MAX($P11-SUM(DV11:FI11),0)) -> 0 | FK11: =MIN(MAX((HI10*(1+HI$5/Setup!$C$36)+IF($V11=42,N($F11),0))-DM11,0),MAX($P11-SUM(DV11:FJ11),0)) -> 0 | FL11: =MIN(MAX((HJ10*(1+HJ$5/Setup!$C$36)+IF($V11=43,N($F11),0))-DN11,0),MAX($P11-SUM(DV11:FK11),0)) -> 0 | FM11: =MIN(MAX((HK10*(1+HK$5/Setup!$C$36)+IF($V11=44,N($F11),0))-DO11,0),MAX($P11-SUM(DV11:FL11),0)) -> 0 | FN11: =MIN(MAX((HL10*(1+HL$5/Setup!$C$36)+IF($V11=45,N($F11),0))-DP11,0),MAX($P11-SUM(DV11:FM11),0)) -> 0 | FO11: =MIN(MAX((HM10*(1+HM$5/Setup!$C$36)+IF($V11=46,N($F11),0))-DQ11,0),MAX($P11-SUM(DV11:FN11),0)) -> 0 | FP11: =MIN(MAX((HN10*(1+HN$5/Setup!$C$36)+IF($V11=47,N($F11),0))-DR11,0),MAX($P11-SUM(DV11:FO11),0)) -> 0 | FQ11: =MIN(MAX((HO10*(1+HO$5/Setup!$C$36)+IF($V11=48,N($F11),0))-DS11,0),MAX($P11-SUM(DV11:FP11),0)) -> 0 | FR11: =MIN(MAX((HP10*(1+HP$5/Setup!$C$36)+IF($V11=49,N($F11),0))-DT11,0),MAX($P11-SUM(DV11:FQ11),0)) -> 0 | FS11: =MIN(MAX((HQ10*(1+HQ$5/Setup!$C$36)+IF($V11=50,N($F11),0))-DU11,0),MAX($P11-SUM(DV11:FR11),0)) -> 0 | FT11: =IF((FT10*(1+FT$5/Setup!$C$36)+IF($V11=1,N($F11),0))-BX11-DV11<0.005,0,(FT10*(1+FT$5/Setup!$C$36)+IF($V11=1,N($F11),0))-BX11-DV11) -> 391.203 | FU11: =IF((FU10*(1+FU$5/Setup!$C$36)+IF($V11=2,N($F11),0))-BY11-DW11<0.005,0,(FU10*(1+FU$5/Setup!$C$36)+IF($V11=2,N($F11),0))-BY11-DW11) -> 1184.8191 | FV11: =IF((FV10*(1+FV$5/Setup!$C$36)+IF($V11=3,N($F11),0))-BZ11-DX11<0.005,0,(FV10*(1+FV$5/Setup!$C$36)+IF($V11=3,N($F11),0))-BZ11-DX11) -> 0 | FW11: =IF((FW10*(1+FW$5/Setup!$C$36)+IF($V11=4,N($F11),0))-CA11-DY11<0.005,0,(FW10*(1+FW$5/Setup!$C$36)+IF($V11=4,N($F11),0))-CA11-DY11) -> 0 | FX11: =IF((FX10*(1+FX$5/Setup!$C$36)+IF($V11=5,N($F11),0))-CB11-DZ11<0.005,0,(FX10*(1+FX$5/Setup!$C$36)+IF($V11=5,N($F11),0))-CB11-DZ11) -> 0 | FY11: =IF((FY10*(1+FY$5/Setup!$C$36)+IF($V11=6,N($F11),0))-CC11-EA11<0.005,0,(FY10*(1+FY$5/Setup!$C$36)+IF($V11=6,N($F11),0))-CC11-EA11) -> 0 | FZ11: =IF((FZ10*(1+FZ$5/Setup!$C$36)+IF($V11=7,N($F11),0))-CD11-EB11<0.005,0,(FZ10*(1+FZ$5/Setup!$C$36)+IF($V11=7,N($F11),0))-CD11-EB11) -> 0 | GA11: =IF((GA10*(1+GA$5/Setup!$C$36)+IF($V11=8,N($F11),0))-CE11-EC11<0.005,0,(GA10*(1+GA$5/Setup!$C$36)+IF($V11=8,N($F11),0))-CE11-EC11) -> 0 | GB11: =IF((GB10*(1+GB$5/Setup!$C$36)+IF($V11=9,N($F11),0))-CF11-ED11<0.005,0,(GB10*(1+GB$5/Setup!$C$36)+IF($V11=9,N($F11),0))-CF11-ED11) -> 0 | GC11: =IF((GC10*(1+GC$5/Setup!$C$36)+IF($V11=10,N($F11),0))-CG11-EE11<0.005,0,(GC10*(1+GC$5/Setup!$C$36)+IF($V11=10,N($F11),0))-CG11-EE11) -> 0 | GD11: =IF((GD10*(1+GD$5/Setup!$C$36)+IF($V11=11,N($F11),0))-CH11-EF11<0.005,0,(GD10*(1+GD$5/Setup!$C$36)+IF($V11=11,N($F11),0))-CH11-EF11) -> 0 | GE11: =IF((GE10*(1+GE$5/Setup!$C$36)+IF($V11=12,N($F11),0))-CI11-EG11<0.005,0,(GE10*(1+GE$5/Setup!$C$36)+IF($V11=12,N($F11),0))-CI11-EG11) -> 0 | GF11: =IF((GF10*(1+GF$5/Setup!$C$36)+IF($V11=13,N($F11),0))-CJ11-EH11<0.005,0,(GF10*(1+GF$5/Setup!$C$36)+IF($V11=13,N($F11),0))-CJ11-EH11) -> 0 | GG11: =IF((GG10*(1+GG$5/Setup!$C$36)+IF($V11=14,N($F11),0))-CK11-EI11<0.005,0,(GG10*(1+GG$5/Setup!$C$36)+IF($V11=14,N($F11),0))-CK11-EI11) -> 0 | GH11: =IF((GH10*(1+GH$5/Setup!$C$36)+IF($V11=15,N($F11),0))-CL11-EJ11<0.005,0,(GH10*(1+GH$5/Setup!$C$36)+IF($V11=15,N($F11),0))-CL11-EJ11) -> 0 | GI11: =IF((GI10*(1+GI$5/Setup!$C$36)+IF($V11=16,N($F11),0))-CM11-EK11<0.005,0,(GI10*(1+GI$5/Setup!$C$36)+IF($V11=16,N($F11),0))-CM11-EK11) -> 0 | GJ11: =IF((GJ10*(1+GJ$5/Setup!$C$36)+IF($V11=17,N($F11),0))-CN11-EL11<0.005,0,(GJ10*(1+GJ$5/Setup!$C$36)+IF($V11=17,N($F11),0))-CN11-EL11) -> 0 | GK11: =IF((GK10*(1+GK$5/Setup!$C$36)+IF($V11=18,N($F11),0))-CO11-EM11<0.005,0,(GK10*(1+GK$5/Setup!$C$36)+IF($V11=18,N($F11),0))-CO11-EM11) -> 0 | GL11: =IF((GL10*(1+GL$5/Setup!$C$36)+IF($V11=19,N($F11),0))-CP11-EN11<0.005,0,(GL10*(1+GL$5/Setup!$C$36)+IF($V11=19,N($F11),0))-CP11-EN11) -> 0 | GM11: =IF((GM10*(1+GM$5/Setup!$C$36)+IF($V11=20,N($F11),0))-CQ11-EO11<0.005,0,(GM10*(1+GM$5/Setup!$C$36)+IF($V11=20,N($F11),0))-CQ11-EO11) -> 0 | GN11: =IF((GN10*(1+GN$5/Setup!$C$36)+IF($V11=21,N($F11),0))-CR11-EP11<0.005,0,(GN10*(1+GN$5/Setup!$C$36)+IF($V11=21,N($F11),0))-CR11-EP11) -> 0 | GO11: =IF((GO10*(1+GO$5/Setup!$C$36)+IF($V11=22,N($F11),0))-CS11-EQ11<0.005,0,(GO10*(1+GO$5/Setup!$C$36)+IF($V11=22,N($F11),0))-CS11-EQ11) -> 0 | GP11: =IF((GP10*(1+GP$5/Setup!$C$36)+IF($V11=23,N($F11),0))-CT11-ER11<0.005,0,(GP10*(1+GP$5/Setup!$C$36)+IF($V11=23,N($F11),0))-CT11-ER11) -> 0 | GQ11: =IF((GQ10*(1+GQ$5/Setup!$C$36)+IF($V11=24,N($F11),0))-CU11-ES11<0.005,0,(GQ10*(1+GQ$5/Setup!$C$36)+IF($V11=24,N($F11),0))-CU11-ES11) -> 0 | GR11: =IF((GR10*(1+GR$5/Setup!$C$36)+IF($V11=25,N($F11),0))-CV11-ET11<0.005,0,(GR10*(1+GR$5/Setup!$C$36)+IF($V11=25,N($F11),0))-CV11-ET11) -> 0 | GS11: =IF((GS10*(1+GS$5/Setup!$C$36)+IF($V11=26,N($F11),0))-CW11-EU11<0.005,0,(GS10*(1+GS$5/Setup!$C$36)+IF($V11=26,N($F11),0))-CW11-EU11) -> 0 | GT11: =IF((GT10*(1+GT$5/Setup!$C$36)+IF($V11=27,N($F11),0))-CX11-EV11<0.005,0,(GT10*(1+GT$5/Setup!$C$36)+IF($V11=27,N($F11),0))-CX11-EV11) -> 0 | GU11: =IF((GU10*(1+GU$5/Setup!$C$36)+IF($V11=28,N($F11),0))-CY11-EW11<0.005,0,(GU10*(1+GU$5/Setup!$C$36)+IF($V11=28,N($F11),0))-CY11-EW11) -> 0 | GV11: =IF((GV10*(1+GV$5/Setup!$C$36)+IF($V11=29,N($F11),0))-CZ11-EX11<0.005,0,(GV10*(1+GV$5/Setup!$C$36)+IF($V11=29,N($F11),0))-CZ11-EX11) -> 0 | GW11: =IF((GW10*(1+GW$5/Setup!$C$36)+IF($V11=30,N($F11),0))-DA11-EY11<0.005,0,(GW10*(1+GW$5/Setup!$C$36)+IF($V11=30,N($F11),0))-DA11-EY11) -> 0 | GX11: =IF((GX10*(1+GX$5/Setup!$C$36)+IF($V11=31,N($F11),0))-DB11-EZ11<0.005,0,(GX10*(1+GX$5/Setup!$C$36)+IF($V11=31,N($F11),0))-DB11-EZ11) -> 0 | GY11: =IF((GY10*(1+GY$5/Setup!$C$36)+IF($V11=32,N($F11),0))-DC11-FA11<0.005,0,(GY10*(1+GY$5/Setup!$C$36)+IF($V11=32,N($F11),0))-DC11-FA11) -> 0 | GZ11: =IF((GZ10*(1+GZ$5/Setup!$C$36)+IF($V11=33,N($F11),0))-DD11-FB11<0.005,0,(GZ10*(1+GZ$5/Setup!$C$36)+IF($V11=33,N($F11),0))-DD11-FB11) -> 0 | HA11: =IF((HA10*(1+HA$5/Setup!$C$36)+IF($V11=34,N($F11),0))-DE11-FC11<0.005,0,(HA10*(1+HA$5/Setup!$C$36)+IF($V11=34,N($F11),0))-DE11-FC11) -> 0 | HB11: =IF((HB10*(1+HB$5/Setup!$C$36)+IF($V11=35,N($F11),0))-DF11-FD11<0.005,0,(HB10*(1+HB$5/Setup!$C$36)+IF($V11=35,N($F11),0))-DF11-FD11) -> 0 | HC11: =IF((HC10*(1+HC$5/Setup!$C$36)+IF($V11=36,N($F11),0))-DG11-FE11<0.005,0,(HC10*(1+HC$5/Setup!$C$36)+IF($V11=36,N($F11),0))-DG11-FE11) -> 0 | HD11: =IF((HD10*(1+HD$5/Setup!$C$36)+IF($V11=37,N($F11),0))-DH11-FF11<0.005,0,(HD10*(1+HD$5/Setup!$C$36)+IF($V11=37,N($F11),0))-DH11-FF11) -> 0 | HE11: =IF((HE10*(1+HE$5/Setup!$C$36)+IF($V11=38,N($F11),0))-DI11-FG11<0.005,0,(HE10*(1+HE$5/Setup!$C$36)+IF($V11=38,N($F11),0))-DI11-FG11) -> 0 | HF11: =IF((HF10*(1+HF$5/Setup!$C$36)+IF($V11=39,N($F11),0))-DJ11-FH11<0.005,0,(HF10*(1+HF$5/Setup!$C$36)+IF($V11=39,N($F11),0))-DJ11-FH11) -> 0 | HG11: =IF((HG10*(1+HG$5/Setup!$C$36)+IF($V11=40,N($F11),0))-DK11-FI11<0.005,0,(HG10*(1+HG$5/Setup!$C$36)+IF($V11=40,N($F11),0))-DK11-FI11) -> 0 | HH11: =IF((HH10*(1+HH$5/Setup!$C$36)+IF($V11=41,N($F11),0))-DL11-FJ11<0.005,0,(HH10*(1+HH$5/Setup!$C$36)+IF($V11=41,N($F11),0))-DL11-FJ11) -> 0 | HI11: =IF((HI10*(1+HI$5/Setup!$C$36)+IF($V11=42,N($F11),0))-DM11-FK11<0.005,0,(HI10*(1+HI$5/Setup!$C$36)+IF($V11=42,N($F11),0))-DM11-FK11) -> 0 | HJ11: =IF((HJ10*(1+HJ$5/Setup!$C$36)+IF($V11=43,N($F11),0))-DN11-FL11<0.005,0,(HJ10*(1+HJ$5/Setup!$C$36)+IF($V11=43,N($F11),0))-DN11-FL11) -> 0 | HK11: =IF((HK10*(1+HK$5/Setup!$C$36)+IF($V11=44,N($F11),0))-DO11-FM11<0.005,0,(HK10*(1+HK$5/Setup!$C$36)+IF($V11=44,N($F11),0))-DO11-FM11) -> 0 | HL11: =IF((HL10*(1+HL$5/Setup!$C$36)+IF($V11=45,N($F11),0))-DP11-FN11<0.005,0,(HL10*(1+HL$5/Setup!$C$36)+IF($V11=45,N($F11),0))-DP11-FN11) -> 0 | HM11: =IF((HM10*(1+HM$5/Setup!$C$36)+IF($V11=46,N($F11),0))-DQ11-FO11<0.005,0,(HM10*(1+HM$5/Setup!$C$36)+IF($V11=46,N($F11),0))-DQ11-FO11) -> 0 | HN11: =IF((HN10*(1+HN$5/Setup!$C$36)+IF($V11=47,N($F11),0))-DR11-FP11<0.005,0,(HN10*(1+HN$5/Setup!$C$36)+IF($V11=47,N($F11),0))-DR11-FP11) -> 0 | HO11: =IF((HO10*(1+HO$5/Setup!$C$36)+IF($V11=48,N($F11),0))-DS11-FQ11<0.005,0,(HO10*(1+HO$5/Setup!$C$36)+IF($V11=48,N($F11),0))-DS11-FQ11) -> 0 | HP11: =IF((HP10*(1+HP$5/Setup!$C$36)+IF($V11=49,N($F11),0))-DT11-FR11<0.005,0,(HP10*(1+HP$5/Setup!$C$36)+IF($V11=49,N($F11),0))-DT11-FR11) -> 0 | HQ11: =IF((HQ10*(1+HQ$5/Setup!$C$36)+IF($V11=50,N($F11),0))-DU11-FS11<0.005,0,(HQ10*(1+HQ$5/Setup!$C$36)+IF($V11=50,N($F11),0))-DU11-FS11) -> 0
A12: 4 | B12: =IF(Setup!$C$7="Every month",EDATE(Setup!$C$8,($A12-1)),IF(Setup!$C$7="Twice a month",DATE(YEAR(Setup!$C$8),MONTH(Setup!$C$8)+INT((($A12-1)+Setup!$C$41)/2),MIN(IF(MOD(($A12-1)+Setup!$C$41,2)=0,Setup!$C$39,Setup!$C$40),DAY(EOMONTH(DATE(YEAR(Setup!$C$8),MONTH(Setup!$C$8)+INT((($A12-1)+Setup!$C$41)/2),1),0)))),Setup!$C$8+($A12-1)*IF(Setup!$C$7="Every week",7,14))) -> 46367 | C12: =IF(Setup!$C$7="Every month",EDATE(Setup!$C$8,$A12),IF(Setup!$C$7="Twice a month",DATE(YEAR(Setup!$C$8),MONTH(Setup!$C$8)+INT(($A12+Setup!$C$41)/2),MIN(IF(MOD($A12+Setup!$C$41,2)=0,Setup!$C$39,Setup!$C$40),DAY(EOMONTH(DATE(YEAR(Setup!$C$8),MONTH(Setup!$C$8)+INT(($A12+Setup!$C$41)/2),1),0)))),Setup!$C$8+$A12*IF(Setup!$C$7="Every week",7,14))) -> 46381 | I12: =N(Setup!$C$11)+N(E12) -> 100 | J12: =MIN(Setup!$C$37,MAX(I12,0)) -> 9.2307692 | K12: =MIN(MAX(N(Setup!$C$14)-L11,0),MAX(I12-J12,0)) -> 0 | L12: =L11+K12-N(G12) -> 500 | M12: =M11+J12-N(H12) -> 36.923077 | N12: =SUM(BX12:DU12) -> 40 | O12: =SUM(Z12:BW12)-N12 -> 0 | P12: =MAX(I12-J12-K12,0)+O12 -> 90.769231 | Q12: =SUM(DV12:FS12) -> 90.769231 | R12: =N12+J12+K12+Q12 -> 140 | S12: =T12-T11-N(F12)+N12+Q12 -> 11.813698 | T12: =SUM(FT12:HQ12) -> 1457.0666 | U12: =IF(T11<0.005,"",INDEX(Helpers!$C$2:$C$51,IF(_xlfn.MINIFS($DV$6:$FS$6,DV12:FS12,">0.005")=0,V12,_xlfn.MINIFS($DV$6:$FS$6,DV12:FS12,">0.005")))) -> Card A | V12: =IF(_xlfn.MINIFS($FT$6:$HQ$6,FT11:HQ11,">0.005")=0,1,_xlfn.MINIFS($FT$6:$HQ$6,FT11:HQ11,">0.005")) -> 1 | W12: =IF(AND(D12<>"Paid",T11>0.005),1,0) -> 1 | X12: =SUMPRODUCT(((Helpers!$G$2:$G$51*(1+(Helpers!$D$2:$D$51+0.000000001)/12)^(($B12-Setup!$C$8)/(365.25/12))-Helpers!$E$2:$E$51*((1+(Helpers!$D$2:$D$51+0.000000001)/12)^(($B12-Setup!$C$8)/(365.25/12))-1)/((Helpers!$D$2:$D$51+0.000000001)/12))>0)*(Helpers!$G$2:$G$51*(1+(Helpers!$D$2:$D$51+0.000000001)/12)^(($B12-Setup!$C$8)/(365.25/12))-Helpers!$E$2:$E$51*((1+(Helpers!$D$2:$D$51+0.000000001)/12)^(($B12-Setup!$C$8)/(365.25/12))-1)/((Helpers!$D$2:$D$51+0.000000001)/12))) -> 1648.78 | Z12: =IF(OR(N(Z$5)=0,Z$6=""),0,Z$5*((DATE(YEAR($B12),MONTH($B12),MIN(Z$6,DAY(EOMONTH($B12,0))))>=$B12)*(DATE(YEAR($B12),MONTH($B12),MIN(Z$6,DAY(EOMONTH($B12,0))))<$C12)+(DATE(YEAR($B12),MONTH($B12)+1,MIN(Z$6,DAY(EOMONTH($B12,1))))>=$B12)*(DATE(YEAR($B12),MONTH($B12)+1,MIN(Z$6,DAY(EOMONTH($B12,1))))<$C12))) -> 0 | AA12: =IF(OR(N(AA$5)=0,AA$6=""),0,AA$5*((DATE(YEAR($B12),MONTH($B12),MIN(AA$6,DAY(EOMONTH($B12,0))))>=$B12)*(DATE(YEAR($B12),MONTH($B12),MIN(AA$6,DAY(EOMONTH($B12,0))))<$C12)+(DATE(YEAR($B12),MONTH($B12)+1,MIN(AA$6,DAY(EOMONTH($B12,1))))>=$B12)*(DATE(YEAR($B12),MONTH($B12)+1,MIN(AA$6,DAY(EOMONTH($B12,1))))<$C12))) -> 40 | AB12: =IF(OR(N(AB$5)=0,AB$6=""),0,AB$5*((DATE(YEAR($B12),MONTH($B12),MIN(AB$6,DAY(EOMONTH($B12,0))))>=$B12)*(DATE(YEAR($B12),MONTH($B12),MIN(AB$6,DAY(EOMONTH($B12,0))))<$C12)+(DATE(YEAR($B12),MONTH($B12)+1,MIN(AB$6,DAY(EOMONTH($B12,1))))>=$B12)*(DATE(YEAR($B12),MONTH($B12)+1,MIN(AB$6,DAY(EOMONTH($B12,1))))<$C12))) -> 0 | AC12: =IF(OR(N(AC$5)=0,AC$6=""),0,AC$5*((DATE(YEAR($B12),MONTH($B12),MIN(AC$6,DAY(EOMONTH($B12,0))))>=$B12)*(DATE(YEAR($B12),MONTH($B12),MIN(AC$6,DAY(EOMONTH($B12,0))))<$C12)+(DATE(YEAR($B12),MONTH($B12)+1,MIN(AC$6,DAY(EOMONTH($B12,1))))>=$B12)*(DATE(YEAR($B12),MONTH($B12)+1,MIN(AC$6,DAY(EOMONTH($B12,1))))<$C12))) -> 0 | AD12: =IF(OR(N(AD$5)=0,AD$6=""),0,AD$5*((DATE(YEAR($B12),MONTH($B12),MIN(AD$6,DAY(EOMONTH($B12,0))))>=$B12)*(DATE(YEAR($B12),MONTH($B12),MIN(AD$6,DAY(EOMONTH($B12,0))))<$C12)+(DATE(YEAR($B12),MONTH($B12)+1,MIN(AD$6,DAY(EOMONTH($B12,1))))>=$B12)*(DATE(YEAR($B12),MONTH($B12)+1,MIN(AD$6,DAY(EOMONTH($B12,1))))<$C12))) -> 0 | AE12: =IF(OR(N(AE$5)=0,AE$6=""),0,AE$5*((DATE(YEAR($B12),MONTH($B12),MIN(AE$6,DAY(EOMONTH($B12,0))))>=$B12)*(DATE(YEAR($B12),MONTH($B12),MIN(AE$6,DAY(EOMONTH($B12,0))))<$C12)+(DATE(YEAR($B12),MONTH($B12)+1,MIN(AE$6,DAY(EOMONTH($B12,1))))>=$B12)*(DATE(YEAR($B12),MONTH($B12)+1,MIN(AE$6,DAY(EOMONTH($B12,1))))<$C12))) -> 0 | AF12: =IF(OR(N(AF$5)=0,AF$6=""),0,AF$5*((DATE(YEAR($B12),MONTH($B12),MIN(AF$6,DAY(EOMONTH($B12,0))))>=$B12)*(DATE(YEAR($B12),MONTH($B12),MIN(AF$6,DAY(EOMONTH($B12,0))))<$C12)+(DATE(YEAR($B12),MONTH($B12)+1,MIN(AF$6,DAY(EOMONTH($B12,1))))>=$B12)*(DATE(YEAR($B12),MONTH($B12)+1,MIN(AF$6,DAY(EOMONTH($B12,1))))<$C12))) -> 0 | AG12: =IF(OR(N(AG$5)=0,AG$6=""),0,AG$5*((DATE(YEAR($B12),MONTH($B12),MIN(AG$6,DAY(EOMONTH($B12,0))))>=$B12)*(DATE(YEAR($B12),MONTH($B12),MIN(AG$6,DAY(EOMONTH($B12,0))))<$C12)+(DATE(YEAR($B12),MONTH($B12)+1,MIN(AG$6,DAY(EOMONTH($B12,1))))>=$B12)*(DATE(YEAR($B12),MONTH($B12)+1,MIN(AG$6,DAY(EOMONTH($B12,1))))<$C12))) -> 0 | ... BW12: =IF(OR(N(BW$5)=0,BW$6=""),0,BW$5*((DATE(YEAR($B12),MONTH($B12),MIN(BW$6,DAY(EOMONTH($B12,0))))>=$B12)*(DATE(YEAR($B12),MONTH($B12),MIN(BW$6,DAY(EOMONTH($B12,0))))<$C12)+(DATE(YEAR($B12),MONTH($B12)+1,MIN(BW$6,DAY(EOMONTH($B12,1))))>=$B12)*(DATE(YEAR($B12),MONTH($B12)+1,MIN(BW$6,DAY(EOMONTH($B12,1))))<$C12))) -> 0 | BX12: =MIN(Z12,(FT11*(1+FT$5/Setup!$C$36)+IF($V12=1,N($F12),0))) -> 0 | BY12: =MIN(AA12,(FU11*(1+FU$5/Setup!$C$36)+IF($V12=2,N($F12),0))) -> 40 | BZ12: =MIN(AB12,(FV11*(1+FV$5/Setup!$C$36)+IF($V12=3,N($F12),0))) -> 0 | CA12: =MIN(AC12,(FW11*(1+FW$5/Setup!$C$36)+IF($V12=4,N($F12),0))) -> 0 | CB12: =MIN(AD12,(FX11*(1+FX$5/Setup!$C$36)+IF($V12=5,N($F12),0))) -> 0 | CC12: =MIN(AE12,(FY11*(1+FY$5/Setup!$C$36)+IF($V12=6,N($F12),0))) -> 0 | CD12: =MIN(AF12,(FZ11*(1+FZ$5/Setup!$C$36)+IF($V12=7,N($F12),0))) -> 0 | CE12: =MIN(AG12,(GA11*(1+GA$5/Setup!$C$36)+IF($V12=8,N($F12),0))) -> 0 | CF12: =MIN(AH12,(GB11*(1+GB$5/Setup!$C$36)+IF($V12=9,N($F12),0))) -> 0 | CG12: =MIN(AI12,(GC11*(1+GC$5/Setup!$C$36)+IF($V12=10,N($F12),0))) -> 0 | CH12: =MIN(AJ12,(GD11*(1+GD$5/Setup!$C$36)+IF($V12=11,N($F12),0))) -> 0 | CI12: =MIN(AK12,(GE11*(1+GE$5/Setup!$C$36)+IF($V12=12,N($F12),0))) -> 0 | CJ12: =MIN(AL12,(GF11*(1+GF$5/Setup!$C$36)+IF($V12=13,N($F12),0))) -> 0 | CK12: =MIN(AM12,(GG11*(1+GG$5/Setup!$C$36)+IF($V12=14,N($F12),0))) -> 0 | CL12: =MIN(AN12,(GH11*(1+GH$5/Setup!$C$36)+IF($V12=15,N($F12),0))) -> 0 | CM12: =MIN(AO12,(GI11*(1+GI$5/Setup!$C$36)+IF($V12=16,N($F12),0))) -> 0 | CN12: =MIN(AP12,(GJ11*(1+GJ$5/Setup!$C$36)+IF($V12=17,N($F12),0))) -> 0 | CO12: =MIN(AQ12,(GK11*(1+GK$5/Setup!$C$36)+IF($V12=18,N($F12),0))) -> 0 | CP12: =MIN(AR12,(GL11*(1+GL$5/Setup!$C$36)+IF($V12=19,N($F12),0))) -> 0 | CQ12: =MIN(AS12,(GM11*(1+GM$5/Setup!$C$36)+IF($V12=20,N($F12),0))) -> 0 | CR12: =MIN(AT12,(GN11*(1+GN$5/Setup!$C$36)+IF($V12=21,N($F12),0))) -> 0 | CS12: =MIN(AU12,(GO11*(1+GO$5/Setup!$C$36)+IF($V12=22,N($F12),0))) -> 0 | CT12: =MIN(AV12,(GP11*(1+GP$5/Setup!$C$36)+IF($V12=23,N($F12),0))) -> 0 | CU12: =MIN(AW12,(GQ11*(1+GQ$5/Setup!$C$36)+IF($V12=24,N($F12),0))) -> 0 | CV12: =MIN(AX12,(GR11*(1+GR$5/Setup!$C$36)+IF($V12=25,N($F12),0))) -> 0 | CW12: =MIN(AY12,(GS11*(1+GS$5/Setup!$C$36)+IF($V12=26,N($F12),0))) -> 0 | CX12: =MIN(AZ12,(GT11*(1+GT$5/Setup!$C$36)+IF($V12=27,N($F12),0))) -> 0 | CY12: =MIN(BA12,(GU11*(1+GU$5/Setup!$C$36)+IF($V12=28,N($F12),0))) -> 0 | CZ12: =MIN(BB12,(GV11*(1+GV$5/Setup!$C$36)+IF($V12=29,N($F12),0))) -> 0 | DA12: =MIN(BC12,(GW11*(1+GW$5/Setup!$C$36)+IF($V12=30,N($F12),0))) -> 0 | DB12: =MIN(BD12,(GX11*(1+GX$5/Setup!$C$36)+IF($V12=31,N($F12),0))) -> 0 | DC12: =MIN(BE12,(GY11*(1+GY$5/Setup!$C$36)+IF($V12=32,N($F12),0))) -> 0 | DD12: =MIN(BF12,(GZ11*(1+GZ$5/Setup!$C$36)+IF($V12=33,N($F12),0))) -> 0 | DE12: =MIN(BG12,(HA11*(1+HA$5/Setup!$C$36)+IF($V12=34,N($F12),0))) -> 0 | DF12: =MIN(BH12,(HB11*(1+HB$5/Setup!$C$36)+IF($V12=35,N($F12),0))) -> 0 | DG12: =MIN(BI12,(HC11*(1+HC$5/Setup!$C$36)+IF($V12=36,N($F12),0))) -> 0 | DH12: =MIN(BJ12,(HD11*(1+HD$5/Setup!$C$36)+IF($V12=37,N($F12),0))) -> 0 | DI12: =MIN(BK12,(HE11*(1+HE$5/Setup!$C$36)+IF($V12=38,N($F12),0))) -> 0 | DJ12: =MIN(BL12,(HF11*(1+HF$5/Setup!$C$36)+IF($V12=39,N($F12),0))) -> 0 | DK12: =MIN(BM12,(HG11*(1+HG$5/Setup!$C$36)+IF($V12=40,N($F12),0))) -> 0 | DL12: =MIN(BN12,(HH11*(1+HH$5/Setup!$C$36)+IF($V12=41,N($F12),0))) -> 0 | DM12: =MIN(BO12,(HI11*(1+HI$5/Setup!$C$36)+IF($V12=42,N($F12),0))) -> 0 | DN12: =MIN(BP12,(HJ11*(1+HJ$5/Setup!$C$36)+IF($V12=43,N($F12),0))) -> 0 | DO12: =MIN(BQ12,(HK11*(1+HK$5/Setup!$C$36)+IF($V12=44,N($F12),0))) -> 0 | DP12: =MIN(BR12,(HL11*(1+HL$5/Setup!$C$36)+IF($V12=45,N($F12),0))) -> 0 | DQ12: =MIN(BS12,(HM11*(1+HM$5/Setup!$C$36)+IF($V12=46,N($F12),0))) -> 0 | DR12: =MIN(BT12,(HN11*(1+HN$5/Setup!$C$36)+IF($V12=47,N($F12),0))) -> 0 | DS12: =MIN(BU12,(HO11*(1+HO$5/Setup!$C$36)+IF($V12=48,N($F12),0))) -> 0 | DT12: =MIN(BV12,(HP11*(1+HP$5/Setup!$C$36)+IF($V12=49,N($F12),0))) -> 0 | DU12: =MIN(BW12,(HQ11*(1+HQ$5/Setup!$C$36)+IF($V12=50,N($F12),0))) -> 0 | DV12: =MIN(MAX((FT11*(1+FT$5/Setup!$C$36)+IF($V12=1,N($F12),0))-BX12,0),MAX($P12-0,0)) -> 90.769231 | DW12: =MIN(MAX((FU11*(1+FU$5/Setup!$C$36)+IF($V12=2,N($F12),0))-BY12,0),MAX($P12-SUM(DV12:DV12),0)) -> 0 | DX12: =MIN(MAX((FV11*(1+FV$5/Setup!$C$36)+IF($V12=3,N($F12),0))-BZ12,0),MAX($P12-SUM(DV12:DW12),0)) -> 0 | DY12: =MIN(MAX((FW11*(1+FW$5/Setup!$C$36)+IF($V12=4,N($F12),0))-CA12,0),MAX($P12-SUM(DV12:DX12),0)) -> 0 | DZ12: =MIN(MAX((FX11*(1+FX$5/Setup!$C$36)+IF($V12=5,N($F12),0))-CB12,0),MAX($P12-SUM(DV12:DY12),0)) -> 0 | EA12: =MIN(MAX((FY11*(1+FY$5/Setup!$C$36)+IF($V12=6,N($F12),0))-CC12,0),MAX($P12-SUM(DV12:DZ12),0)) -> 0 | EB12: =MIN(MAX((FZ11*(1+FZ$5/Setup!$C$36)+IF($V12=7,N($F12),0))-CD12,0),MAX($P12-SUM(DV12:EA12),0)) -> 0 | EC12: =MIN(MAX((GA11*(1+GA$5/Setup!$C$36)+IF($V12=8,N($F12),0))-CE12,0),MAX($P12-SUM(DV12:EB12),0)) -> 0 | ED12: =MIN(MAX((GB11*(1+GB$5/Setup!$C$36)+IF($V12=9,N($F12),0))-CF12,0),MAX($P12-SUM(DV12:EC12),0)) -> 0 | EE12: =MIN(MAX((GC11*(1+GC$5/Setup!$C$36)+IF($V12=10,N($F12),0))-CG12,0),MAX($P12-SUM(DV12:ED12),0)) -> 0 | EF12: =MIN(MAX((GD11*(1+GD$5/Setup!$C$36)+IF($V12=11,N($F12),0))-CH12,0),MAX($P12-SUM(DV12:EE12),0)) -> 0 | EG12: =MIN(MAX((GE11*(1+GE$5/Setup!$C$36)+IF($V12=12,N($F12),0))-CI12,0),MAX($P12-SUM(DV12:EF12),0)) -> 0 | EH12: =MIN(MAX((GF11*(1+GF$5/Setup!$C$36)+IF($V12=13,N($F12),0))-CJ12,0),MAX($P12-SUM(DV12:EG12),0)) -> 0 | EI12: =MIN(MAX((GG11*(1+GG$5/Setup!$C$36)+IF($V12=14,N($F12),0))-CK12,0),MAX($P12-SUM(DV12:EH12),0)) -> 0 | EJ12: =MIN(MAX((GH11*(1+GH$5/Setup!$C$36)+IF($V12=15,N($F12),0))-CL12,0),MAX($P12-SUM(DV12:EI12),0)) -> 0 | EK12: =MIN(MAX((GI11*(1+GI$5/Setup!$C$36)+IF($V12=16,N($F12),0))-CM12,0),MAX($P12-SUM(DV12:EJ12),0)) -> 0 | EL12: =MIN(MAX((GJ11*(1+GJ$5/Setup!$C$36)+IF($V12=17,N($F12),0))-CN12,0),MAX($P12-SUM(DV12:EK12),0)) -> 0 | EM12: =MIN(MAX((GK11*(1+GK$5/Setup!$C$36)+IF($V12=18,N($F12),0))-CO12,0),MAX($P12-SUM(DV12:EL12),0)) -> 0 | EN12: =MIN(MAX((GL11*(1+GL$5/Setup!$C$36)+IF($V12=19,N($F12),0))-CP12,0),MAX($P12-SUM(DV12:EM12),0)) -> 0 | EO12: =MIN(MAX((GM11*(1+GM$5/Setup!$C$36)+IF($V12=20,N($F12),0))-CQ12,0),MAX($P12-SUM(DV12:EN12),0)) -> 0 | EP12: =MIN(MAX((GN11*(1+GN$5/Setup!$C$36)+IF($V12=21,N($F12),0))-CR12,0),MAX($P12-SUM(DV12:EO12),0)) -> 0 | EQ12: =MIN(MAX((GO11*(1+GO$5/Setup!$C$36)+IF($V12=22,N($F12),0))-CS12,0),MAX($P12-SUM(DV12:EP12),0)) -> 0 | ER12: =MIN(MAX((GP11*(1+GP$5/Setup!$C$36)+IF($V12=23,N($F12),0))-CT12,0),MAX($P12-SUM(DV12:EQ12),0)) -> 0 | ES12: =MIN(MAX((GQ11*(1+GQ$5/Setup!$C$36)+IF($V12=24,N($F12),0))-CU12,0),MAX($P12-SUM(DV12:ER12),0)) -> 0 | ET12: =MIN(MAX((GR11*(1+GR$5/Setup!$C$36)+IF($V12=25,N($F12),0))-CV12,0),MAX($P12-SUM(DV12:ES12),0)) -> 0 | EU12: =MIN(MAX((GS11*(1+GS$5/Setup!$C$36)+IF($V12=26,N($F12),0))-CW12,0),MAX($P12-SUM(DV12:ET12),0)) -> 0 | EV12: =MIN(MAX((GT11*(1+GT$5/Setup!$C$36)+IF($V12=27,N($F12),0))-CX12,0),MAX($P12-SUM(DV12:EU12),0)) -> 0 | EW12: =MIN(MAX((GU11*(1+GU$5/Setup!$C$36)+IF($V12=28,N($F12),0))-CY12,0),MAX($P12-SUM(DV12:EV12),0)) -> 0 | EX12: =MIN(MAX((GV11*(1+GV$5/Setup!$C$36)+IF($V12=29,N($F12),0))-CZ12,0),MAX($P12-SUM(DV12:EW12),0)) -> 0 | EY12: =MIN(MAX((GW11*(1+GW$5/Setup!$C$36)+IF($V12=30,N($F12),0))-DA12,0),MAX($P12-SUM(DV12:EX12),0)) -> 0 | EZ12: =MIN(MAX((GX11*(1+GX$5/Setup!$C$36)+IF($V12=31,N($F12),0))-DB12,0),MAX($P12-SUM(DV12:EY12),0)) -> 0 | FA12: =MIN(MAX((GY11*(1+GY$5/Setup!$C$36)+IF($V12=32,N($F12),0))-DC12,0),MAX($P12-SUM(DV12:EZ12),0)) -> 0 | FB12: =MIN(MAX((GZ11*(1+GZ$5/Setup!$C$36)+IF($V12=33,N($F12),0))-DD12,0),MAX($P12-SUM(DV12:FA12),0)) -> 0 | FC12: =MIN(MAX((HA11*(1+HA$5/Setup!$C$36)+IF($V12=34,N($F12),0))-DE12,0),MAX($P12-SUM(DV12:FB12),0)) -> 0 | FD12: =MIN(MAX((HB11*(1+HB$5/Setup!$C$36)+IF($V12=35,N($F12),0))-DF12,0),MAX($P12-SUM(DV12:FC12),0)) -> 0 | FE12: =MIN(MAX((HC11*(1+HC$5/Setup!$C$36)+IF($V12=36,N($F12),0))-DG12,0),MAX($P12-SUM(DV12:FD12),0)) -> 0 | FF12: =MIN(MAX((HD11*(1+HD$5/Setup!$C$36)+IF($V12=37,N($F12),0))-DH12,0),MAX($P12-SUM(DV12:FE12),0)) -> 0 | FG12: =MIN(MAX((HE11*(1+HE$5/Setup!$C$36)+IF($V12=38,N($F12),0))-DI12,0),MAX($P12-SUM(DV12:FF12),0)) -> 0 | FH12: =MIN(MAX((HF11*(1+HF$5/Setup!$C$36)+IF($V12=39,N($F12),0))-DJ12,0),MAX($P12-SUM(DV12:FG12),0)) -> 0 | FI12: =MIN(MAX((HG11*(1+HG$5/Setup!$C$36)+IF($V12=40,N($F12),0))-DK12,0),MAX($P12-SUM(DV12:FH12),0)) -> 0 | FJ12: =MIN(MAX((HH11*(1+HH$5/Setup!$C$36)+IF($V12=41,N($F12),0))-DL12,0),MAX($P12-SUM(DV12:FI12),0)) -> 0 | FK12: =MIN(MAX((HI11*(1+HI$5/Setup!$C$36)+IF($V12=42,N($F12),0))-DM12,0),MAX($P12-SUM(DV12:FJ12),0)) -> 0 | FL12: =MIN(MAX((HJ11*(1+HJ$5/Setup!$C$36)+IF($V12=43,N($F12),0))-DN12,0),MAX($P12-SUM(DV12:FK12),0)) -> 0 | FM12: =MIN(MAX((HK11*(1+HK$5/Setup!$C$36)+IF($V12=44,N($F12),0))-DO12,0),MAX($P12-SUM(DV12:FL12),0)) -> 0 | FN12: =MIN(MAX((HL11*(1+HL$5/Setup!$C$36)+IF($V12=45,N($F12),0))-DP12,0),MAX($P12-SUM(DV12:FM12),0)) -> 0 | FO12: =MIN(MAX((HM11*(1+HM$5/Setup!$C$36)+IF($V12=46,N($F12),0))-DQ12,0),MAX($P12-SUM(DV12:FN12),0)) -> 0 | FP12: =MIN(MAX((HN11*(1+HN$5/Setup!$C$36)+IF($V12=47,N($F12),0))-DR12,0),MAX($P12-SUM(DV12:FO12),0)) -> 0 | FQ12: =MIN(MAX((HO11*(1+HO$5/Setup!$C$36)+IF($V12=48,N($F12),0))-DS12,0),MAX($P12-SUM(DV12:FP12),0)) -> 0 | FR12: =MIN(MAX((HP11*(1+HP$5/Setup!$C$36)+IF($V12=49,N($F12),0))-DT12,0),MAX($P12-SUM(DV12:FQ12),0)) -> 0 | FS12: =MIN(MAX((HQ11*(1+HQ$5/Setup!$C$36)+IF($V12=50,N($F12),0))-DU12,0),MAX($P12-SUM(DV12:FR12),0)) -> 0 | FT12: =IF((FT11*(1+FT$5/Setup!$C$36)+IF($V12=1,N($F12),0))-BX12-DV12<0.005,0,(FT11*(1+FT$5/Setup!$C$36)+IF($V12=1,N($F12),0))-BX12-DV12) -> 304.04487 | FU12: =IF((FU11*(1+FU$5/Setup!$C$36)+IF($V12=2,N($F12),0))-BY12-DW12<0.005,0,(FU11*(1+FU$5/Setup!$C$36)+IF($V12=2,N($F12),0))-BY12-DW12) -> 1153.0217 | FV12: =IF((FV11*(1+FV$5/Setup!$C$36)+IF($V12=3,N($F12),0))-BZ12-DX12<0.005,0,(FV11*(1+FV$5/Setup!$C$36)+IF($V12=3,N($F12),0))-BZ12-DX12) -> 0 | FW12: =IF((FW11*(1+FW$5/Setup!$C$36)+IF($V12=4,N($F12),0))-CA12-DY12<0.005,0,(FW11*(1+FW$5/Setup!$C$36)+IF($V12=4,N($F12),0))-CA12-DY12) -> 0 | FX12: =IF((FX11*(1+FX$5/Setup!$C$36)+IF($V12=5,N($F12),0))-CB12-DZ12<0.005,0,(FX11*(1+FX$5/Setup!$C$36)+IF($V12=5,N($F12),0))-CB12-DZ12) -> 0 | FY12: =IF((FY11*(1+FY$5/Setup!$C$36)+IF($V12=6,N($F12),0))-CC12-EA12<0.005,0,(FY11*(1+FY$5/Setup!$C$36)+IF($V12=6,N($F12),0))-CC12-EA12) -> 0 | FZ12: =IF((FZ11*(1+FZ$5/Setup!$C$36)+IF($V12=7,N($F12),0))-CD12-EB12<0.005,0,(FZ11*(1+FZ$5/Setup!$C$36)+IF($V12=7,N($F12),0))-CD12-EB12) -> 0 | GA12: =IF((GA11*(1+GA$5/Setup!$C$36)+IF($V12=8,N($F12),0))-CE12-EC12<0.005,0,(GA11*(1+GA$5/Setup!$C$36)+IF($V12=8,N($F12),0))-CE12-EC12) -> 0 | GB12: =IF((GB11*(1+GB$5/Setup!$C$36)+IF($V12=9,N($F12),0))-CF12-ED12<0.005,0,(GB11*(1+GB$5/Setup!$C$36)+IF($V12=9,N($F12),0))-CF12-ED12) -> 0 | GC12: =IF((GC11*(1+GC$5/Setup!$C$36)+IF($V12=10,N($F12),0))-CG12-EE12<0.005,0,(GC11*(1+GC$5/Setup!$C$36)+IF($V12=10,N($F12),0))-CG12-EE12) -> 0 | GD12: =IF((GD11*(1+GD$5/Setup!$C$36)+IF($V12=11,N($F12),0))-CH12-EF12<0.005,0,(GD11*(1+GD$5/Setup!$C$36)+IF($V12=11,N($F12),0))-CH12-EF12) -> 0 | GE12: =IF((GE11*(1+GE$5/Setup!$C$36)+IF($V12=12,N($F12),0))-CI12-EG12<0.005,0,(GE11*(1+GE$5/Setup!$C$36)+IF($V12=12,N($F12),0))-CI12-EG12) -> 0 | GF12: =IF((GF11*(1+GF$5/Setup!$C$36)+IF($V12=13,N($F12),0))-CJ12-EH12<0.005,0,(GF11*(1+GF$5/Setup!$C$36)+IF($V12=13,N($F12),0))-CJ12-EH12) -> 0 | GG12: =IF((GG11*(1+GG$5/Setup!$C$36)+IF($V12=14,N($F12),0))-CK12-EI12<0.005,0,(GG11*(1+GG$5/Setup!$C$36)+IF($V12=14,N($F12),0))-CK12-EI12) -> 0 | GH12: =IF((GH11*(1+GH$5/Setup!$C$36)+IF($V12=15,N($F12),0))-CL12-EJ12<0.005,0,(GH11*(1+GH$5/Setup!$C$36)+IF($V12=15,N($F12),0))-CL12-EJ12) -> 0 | GI12: =IF((GI11*(1+GI$5/Setup!$C$36)+IF($V12=16,N($F12),0))-CM12-EK12<0.005,0,(GI11*(1+GI$5/Setup!$C$36)+IF($V12=16,N($F12),0))-CM12-EK12) -> 0 | GJ12: =IF((GJ11*(1+GJ$5/Setup!$C$36)+IF($V12=17,N($F12),0))-CN12-EL12<0.005,0,(GJ11*(1+GJ$5/Setup!$C$36)+IF($V12=17,N($F12),0))-CN12-EL12) -> 0 | GK12: =IF((GK11*(1+GK$5/Setup!$C$36)+IF($V12=18,N($F12),0))-CO12-EM12<0.005,0,(GK11*(1+GK$5/Setup!$C$36)+IF($V12=18,N($F12),0))-CO12-EM12) -> 0 | GL12: =IF((GL11*(1+GL$5/Setup!$C$36)+IF($V12=19,N($F12),0))-CP12-EN12<0.005,0,(GL11*(1+GL$5/Setup!$C$36)+IF($V12=19,N($F12),0))-CP12-EN12) -> 0 | GM12: =IF((GM11*(1+GM$5/Setup!$C$36)+IF($V12=20,N($F12),0))-CQ12-EO12<0.005,0,(GM11*(1+GM$5/Setup!$C$36)+IF($V12=20,N($F12),0))-CQ12-EO12) -> 0 | GN12: =IF((GN11*(1+GN$5/Setup!$C$36)+IF($V12=21,N($F12),0))-CR12-EP12<0.005,0,(GN11*(1+GN$5/Setup!$C$36)+IF($V12=21,N($F12),0))-CR12-EP12) -> 0 | GO12: =IF((GO11*(1+GO$5/Setup!$C$36)+IF($V12=22,N($F12),0))-CS12-EQ12<0.005,0,(GO11*(1+GO$5/Setup!$C$36)+IF($V12=22,N($F12),0))-CS12-EQ12) -> 0 | GP12: =IF((GP11*(1+GP$5/Setup!$C$36)+IF($V12=23,N($F12),0))-CT12-ER12<0.005,0,(GP11*(1+GP$5/Setup!$C$36)+IF($V12=23,N($F12),0))-CT12-ER12) -> 0 | GQ12: =IF((GQ11*(1+GQ$5/Setup!$C$36)+IF($V12=24,N($F12),0))-CU12-ES12<0.005,0,(GQ11*(1+GQ$5/Setup!$C$36)+IF($V12=24,N($F12),0))-CU12-ES12) -> 0 | GR12: =IF((GR11*(1+GR$5/Setup!$C$36)+IF($V12=25,N($F12),0))-CV12-ET12<0.005,0,(GR11*(1+GR$5/Setup!$C$36)+IF($V12=25,N($F12),0))-CV12-ET12) -> 0 | GS12: =IF((GS11*(1+GS$5/Setup!$C$36)+IF($V12=26,N($F12),0))-CW12-EU12<0.005,0,(GS11*(1+GS$5/Setup!$C$36)+IF($V12=26,N($F12),0))-CW12-EU12) -> 0 | GT12: =IF((GT11*(1+GT$5/Setup!$C$36)+IF($V12=27,N($F12),0))-CX12-EV12<0.005,0,(GT11*(1+GT$5/Setup!$C$36)+IF($V12=27,N($F12),0))-CX12-EV12) -> 0 | GU12: =IF((GU11*(1+GU$5/Setup!$C$36)+IF($V12=28,N($F12),0))-CY12-EW12<0.005,0,(GU11*(1+GU$5/Setup!$C$36)+IF($V12=28,N($F12),0))-CY12-EW12) -> 0 | GV12: =IF((GV11*(1+GV$5/Setup!$C$36)+IF($V12=29,N($F12),0))-CZ12-EX12<0.005,0,(GV11*(1+GV$5/Setup!$C$36)+IF($V12=29,N($F12),0))-CZ12-EX12) -> 0 | GW12: =IF((GW11*(1+GW$5/Setup!$C$36)+IF($V12=30,N($F12),0))-DA12-EY12<0.005,0,(GW11*(1+GW$5/Setup!$C$36)+IF($V12=30,N($F12),0))-DA12-EY12) -> 0 | GX12: =IF((GX11*(1+GX$5/Setup!$C$36)+IF($V12=31,N($F12),0))-DB12-EZ12<0.005,0,(GX11*(1+GX$5/Setup!$C$36)+IF($V12=31,N($F12),0))-DB12-EZ12) -> 0 | GY12: =IF((GY11*(1+GY$5/Setup!$C$36)+IF($V12=32,N($F12),0))-DC12-FA12<0.005,0,(GY11*(1+GY$5/Setup!$C$36)+IF($V12=32,N($F12),0))-DC12-FA12) -> 0 | GZ12: =IF((GZ11*(1+GZ$5/Setup!$C$36)+IF($V12=33,N($F12),0))-DD12-FB12<0.005,0,(GZ11*(1+GZ$5/Setup!$C$36)+IF($V12=33,N($F12),0))-DD12-FB12) -> 0 | HA12: =IF((HA11*(1+HA$5/Setup!$C$36)+IF($V12=34,N($F12),0))-DE12-FC12<0.005,0,(HA11*(1+HA$5/Setup!$C$36)+IF($V12=34,N($F12),0))-DE12-FC12) -> 0 | HB12: =IF((HB11*(1+HB$5/Setup!$C$36)+IF($V12=35,N($F12),0))-DF12-FD12<0.005,0,(HB11*(1+HB$5/Setup!$C$36)+IF($V12=35,N($F12),0))-DF12-FD12) -> 0 | HC12: =IF((HC11*(1+HC$5/Setup!$C$36)+IF($V12=36,N($F12),0))-DG12-FE12<0.005,0,(HC11*(1+HC$5/Setup!$C$36)+IF($V12=36,N($F12),0))-DG12-FE12) -> 0 | HD12: =IF((HD11*(1+HD$5/Setup!$C$36)+IF($V12=37,N($F12),0))-DH12-FF12<0.005,0,(HD11*(1+HD$5/Setup!$C$36)+IF($V12=37,N($F12),0))-DH12-FF12) -> 0 | HE12: =IF((HE11*(1+HE$5/Setup!$C$36)+IF($V12=38,N($F12),0))-DI12-FG12<0.005,0,(HE11*(1+HE$5/Setup!$C$36)+IF($V12=38,N($F12),0))-DI12-FG12) -> 0 | HF12: =IF((HF11*(1+HF$5/Setup!$C$36)+IF($V12=39,N($F12),0))-DJ12-FH12<0.005,0,(HF11*(1+HF$5/Setup!$C$36)+IF($V12=39,N($F12),0))-DJ12-FH12) -> 0 | HG12: =IF((HG11*(1+HG$5/Setup!$C$36)+IF($V12=40,N($F12),0))-DK12-FI12<0.005,0,(HG11*(1+HG$5/Setup!$C$36)+IF($V12=40,N($F12),0))-DK12-FI12) -> 0 | HH12: =IF((HH11*(1+HH$5/Setup!$C$36)+IF($V12=41,N($F12),0))-DL12-FJ12<0.005,0,(HH11*(1+HH$5/Setup!$C$36)+IF($V12=41,N($F12),0))-DL12-FJ12) -> 0 | HI12: =IF((HI11*(1+HI$5/Setup!$C$36)+IF($V12=42,N($F12),0))-DM12-FK12<0.005,0,(HI11*(1+HI$5/Setup!$C$36)+IF($V12=42,N($F12),0))-DM12-FK12) -> 0 | HJ12: =IF((HJ11*(1+HJ$5/Setup!$C$36)+IF($V12=43,N($F12),0))-DN12-FL12<0.005,0,(HJ11*(1+HJ$5/Setup!$C$36)+IF($V12=43,N($F12),0))-DN12-FL12) -> 0 | HK12: =IF((HK11*(1+HK$5/Setup!$C$36)+IF($V12=44,N($F12),0))-DO12-FM12<0.005,0,(HK11*(1+HK$5/Setup!$C$36)+IF($V12=44,N($F12),0))-DO12-FM12) -> 0 | HL12: =IF((HL11*(1+HL$5/Setup!$C$36)+IF($V12=45,N($F12),0))-DP12-FN12<0.005,0,(HL11*(1+HL$5/Setup!$C$36)+IF($V12=45,N($F12),0))-DP12-FN12) -> 0 | HM12: =IF((HM11*(1+HM$5/Setup!$C$36)+IF($V12=46,N($F12),0))-DQ12-FO12<0.005,0,(HM11*(1+HM$5/Setup!$C$36)+IF($V12=46,N($F12),0))-DQ12-FO12) -> 0 | HN12: =IF((HN11*(1+HN$5/Setup!$C$36)+IF($V12=47,N($F12),0))-DR12-FP12<0.005,0,(HN11*(1+HN$5/Setup!$C$36)+IF($V12=47,N($F12),0))-DR12-FP12) -> 0 | HO12: =IF((HO11*(1+HO$5/Setup!$C$36)+IF($V12=48,N($F12),0))-DS12-FQ12<0.005,0,(HO11*(1+HO$5/Setup!$C$36)+IF($V12=48,N($F12),0))-DS12-FQ12) -> 0 | HP12: =IF((HP11*(1+HP$5/Setup!$C$36)+IF($V12=49,N($F12),0))-DT12-FR12<0.005,0,(HP11*(1+HP$5/Setup!$C$36)+IF($V12=49,N($F12),0))-DT12-FR12) -> 0 | HQ12: =IF((HQ11*(1+HQ$5/Setup!$C$36)+IF($V12=50,N($F12),0))-DU12-FS12<0.005,0,(HQ11*(1+HQ$5/Setup!$C$36)+IF($V12=50,N($F12),0))-DU12-FS12) -> 0
