Workbook

Sheet Start Here
B1: Paycheck Payoff Planner
B2: PaidInYellow · One paycheck at a time.
C4: Works best on a computer. On your phone, open the Today tab: it shows your next payday on one screen.
B5: First time (about 15 minutes)
B6: 1 | C6: If you opened this from our link, go to File > Make a copy, and work in your copy.
B7: 2 | C7: Setup: how often you get paid, your next payday, and how much you can put toward the plan each payday on top of your minimums.
B8: 3 | C8: Debts: add every debt with its balance, interest rate, monthly minimum and due day. There is room for 50. Include the ones you would rather forget.
B9: 4 | C9: Yearly Bills: add the bills that come once or twice a year, like car repairs or holiday gifts. The sheet splits each one into a small amount per payday.
B10: 5 | C10: Dashboard: your debt-free date is at the top. The sample numbers are there to show how it works, so replace them with yours.
B12: Every payday (about 10 minutes)
B13: 1 | C13: On your phone, open the Today tab. It shows this payday on one screen. On a computer, Paycheck Plan shows every payday.
B14: 2 | C14: Make the payments in that row: minimums, buffer, yearly bills, and the extra payment to the debt it names.
B15: 3 | C15: Paid more or less than usual this time? Type the difference in "+/- this payday", for example 80 or -50.
B16: 4 | C16: Anything new go on a card? Type the amount in "New charges" and pick a type. Nobody sees this but you.
B17: 5 | C17: Choose "Paid" in the Paid? column, right next to the date. The row turns yellow.
B19: Once a month
C20: Check your real balances against the sheet. If they have drifted, type today's balances on Debts, set your next payday on Setup, and clear the Paid, +/- and New charges columns. The plan then starts fresh from today.
B22: Colors
C23: White cells: type here.
C24: Cream cells: the sheet fills these in. Leave them alone.
C25: Yellow: paid.
B27: Good to know
C28: Your buffer comes first. Until it reaches your goal, the extra money goes there, so one surprise bill doesn't land back on a card.
C29: The math is an estimate. Lenders work out interest a little differently and the sheet plans per payday, so real balances will be close but not exact. The monthly check keeps it honest.
C30: Payoff order: "PaidInYellow order" clears the smallest balance first, except a debt whose minimum doesn't cover its interest, which goes first because it grows. "Biggest interest first" usually costs less in total. "My own order" follows the numbers you type on Debts.
C31: If the minimums are more than you can pay, read "When the plan isn't enough" in the Never Back in Debt Guide, or call a nonprofit credit counselor (NFCC.org in the US). This sheet helps you plan and isn't financial advice.
C33: For your personal use. Please don't share or resell this file.
C34: PaidInYellow · paidinyellow.com · help@paidinyellow.com

Sheet Today
B1: Today
B2: Your next payday on one screen.
B4: Debt-free by | C4: =Dashboard!B5
B5: Next payday | C5: =IF(INDEX('Paycheck Plan'!$A$7:$A$526,Engine!$D$1)="","All paid",INDEX('Paycheck Plan'!$B$7:$B$526,Engine!$D$1))
B6: Payday number | C6: =IF(INDEX('Paycheck Plan'!$A$7:$A$526,Engine!$D$1)="","",INDEX('Paycheck Plan'!$A$7:$A$526,Engine!$D$1))
B8: Pay or move this payday
B9: 1. Minimum payments | C9: =IF(INDEX('Paycheck Plan'!$A$7:$A$526,Engine!$D$1)="","",Setup!$C$5&TEXT(INDEX('Paycheck Plan'!$G$7:$G$526,Engine!$D$1),"#,##0.00"))
B10: The smallest payment each debt asks for. Autopay usually takes care of these.
B11: 2. Move to your buffer | C11: =IF(INDEX('Paycheck Plan'!$A$7:$A$526,Engine!$D$1)="","",Setup!$C$5&TEXT(INDEX('Paycheck Plan'!$H$7:$H$526,Engine!$D$1),"#,##0.00"))
B12: Savings for surprise bills, in a separate account.
B13: 3. Move to yearly bills | C13: =IF(INDEX('Paycheck Plan'!$A$7:$A$526,Engine!$D$1)="","",Setup!$C$5&TEXT(INDEX('Paycheck Plan'!$I$7:$I$526,Engine!$D$1),"#,##0.00"))
B14: A little each payday for bills like car repairs and gifts.
B15: 4. Extra payment | C15: =IF(INDEX('Paycheck Plan'!$A$7:$A$526,Engine!$D$1)="","",Setup!$C$5&TEXT(INDEX('Paycheck Plan'!$E$7:$E$526,Engine!$D$1),"#,##0.00"))
B16: =IF(INDEX('Paycheck Plan'!$A$7:$A$526,Engine!$D$1)="","",IF(INDEX('Paycheck Plan'!$E$7:$E$526,Engine!$D$1)>0.005,"Send it to "&INDEX('Paycheck Plan'!$F$7:$F$526,Engine!$D$1)&". All the extra goes to this one debt.","No extra this time. Your buffer fills first."))
B17: Total | C17: =IF(INDEX('Paycheck Plan'!$A$7:$A$526,Engine!$D$1)="","",Setup!$C$5&TEXT(INDEX('Paycheck Plan'!$D$7:$D$526,Engine!$D$1),"#,##0.00"))
B19: =IF(INDEX('Paycheck Plan'!$A$7:$A$526,Engine!$D$1)="","Every debt is paid.","Done? Open Paycheck Plan, find payday "&INDEX('Paycheck Plan'!$A$7:$A$526,Engine!$D$1)&" and choose Paid.")
B21: Where you are
B22: Debt left | C22: =Setup!$C$5&TEXT(INDEX(Engine!$J$10:$J$530,Engine!$D$1),"#,##0")
B23: Debt gone | C23: =IFERROR(1-INDEX(Engine!$J$10:$J$530,Engine!$D$1)/Engine!$J$10,1)
B24: Buffer | C24: =Setup!$C$5&TEXT(INDEX(Engine!$F$10:$F$530,Engine!$D$1),"#,##0")&" of "&Setup!$C$5&TEXT(Setup!$C$10,"#,##0")
B25: Interest per day | C25: =Setup!$C$5&TEXT(SUMPRODUCT(INDEX(Engine!$T$10:$BQ$530,Engine!$D$1,0),Engine!$T$6:$BQ$6)/365,"#,##0.00")
B26: What your debts cost you each day right now. It drops as balances go down.

Sheet Dashboard
B1: Your debt-free dashboard
B2: Updates every time you mark a payday Paid.
B4: You'll be debt-free by
B5: =IFERROR(INDEX(Engine!$B$10:$B$530,Engine!$B$2+1),"More than 20 years. See Compare.")
B6: =IF(Engine!$B$2-Engine!$B$1<=0,"Every debt is paid.","That's "&(Engine!$B$2-Engine!$B$1)&" paydays from now, one paycheck at a time.")
B8: This payday
B9: =IF(INDEX('Paycheck Plan'!$A$7:$A$526,Engine!$D$1)="","Nothing left to pay. Keep your buffer and yearly bills going.",TEXT(INDEX('Paycheck Plan'!$B$7:$B$526,Engine!$D$1),"mmm d")&": set aside "&Setup!$C$5&TEXT(INDEX('Paycheck Plan'!$D$7:$D$526,Engine!$D$1),"#,##0")&" in total. "&IF(INDEX('Paycheck Plan'!$E$7:$E$526,Engine!$D$1)>0.005,"Your extra payment is "&Setup!$C$5&TEXT(INDEX('Paycheck Plan'!$E$7:$E$526,Engine!$D$1),"#,##0")&" to "&INDEX('Paycheck Plan'!$F$7:$F$526,Engine!$D$1)&".","This one fills your buffer, so there's no extra payment yet."))
B12: Debt left | G12: Paid off so far | L12: Interest per day right now | Q12: Paydays left
B13: =Setup!$C$5&TEXT(INDEX(Engine!$J$10:$J$530,Engine!$D$1),"#,##0") | G13: =Setup!$C$5&TEXT(MAX(0,Engine!$J$10-INDEX(Engine!$J$10:$J$530,Engine!$D$1)),"#,##0") | L13: =Setup!$C$5&TEXT(SUMPRODUCT(INDEX(Engine!$T$10:$BQ$530,Engine!$D$1,0),Engine!$T$6:$BQ$6)/365,"#,##0.00") | Q13: =MAX(0,Engine!$B$2-Engine!$B$1)
B15: ="Debt gone: "&TEXT(IFERROR(1-INDEX(Engine!$J$10:$J$530,Engine!$D$1)/Engine!$J$10,1),"0%")
W16: =IFERROR(1-INDEX(Engine!$J$10:$J$530,Engine!$D$1)/Engine!$J$10,1)
B18: =IF(INDEX('Paycheck Plan'!$A$7:$A$526,Engine!$D$1)="","Focus debt: all done","Focus debt: "&INDEX(Engine!$T$4:$BQ$4,INDEX(Engine!$K$11:$K$530,Engine!$D$1))&", "&TEXT(IFERROR(MAX(0,1-INDEX(Engine!$T$10:$BQ$530,Engine!$D$1,INDEX(Engine!$K$11:$K$530,Engine!$D$1))/INDEX(Engine!$T$5:$BQ$5,INDEX(Engine!$K$11:$K$530,Engine!$D$1))),1),"0%")&" paid")
W19: =IFERROR(MAX(0,1-INDEX(Engine!$T$10:$BQ$530,Engine!$D$1,INDEX(Engine!$K$11:$K$530,Engine!$D$1))/INDEX(Engine!$T$5:$BQ$5,INDEX(Engine!$K$11:$K$530,Engine!$D$1))),1)
B21: ="Buffer: "&Setup!$C$5&TEXT(INDEX(Engine!$F$10:$F$530,Engine!$D$1),"#,##0")&" of "&Setup!$C$5&TEXT(Setup!$C$10,"#,##0")
W22: =IFERROR(MIN(1,INDEX(Engine!$F$10:$F$530,Engine!$D$1)/Setup!$C$10),1)
B24: Interest on your plan | G24: Interest paying minimums only | L24: Interest you avoid | Q24: Yearly bills per payday
B25: =Setup!$C$5&TEXT(SUM(Engine!$I$11:$I$530),"#,##0") | G25: =IF(COUNTIF(Debts!$L$6:$L$55,"Never")>0,"Never ends",Setup!$C$5&TEXT(SUM(Debts!$L$6:$L$55),"#,##0")) | L25: =IF(COUNTIF(Debts!$L$6:$L$55,"Never")>0,"Your plan ends it",Setup!$C$5&TEXT(MAX(0,SUM(Debts!$L$6:$L$55)-SUM(Engine!$I$11:$I$530)),"#,##0")) | Q25: =Setup!$C$5&TEXT(Setup!$C$14,"#,##0")
B27: Where new charges came from
B28: Everyday | G28: Emergency | L28: One-off | Q28: Log charges on Paycheck Plan. The pattern shows where new debt comes from.
B29: =Setup!$C$5&TEXT(SUMIF('Paycheck Plan'!$L$7:$L$526,"Everyday",'Paycheck Plan'!$K$7:$K$526),"#,##0") | G29: =Setup!$C$5&TEXT(SUMIF('Paycheck Plan'!$L$7:$L$526,"Emergency",'Paycheck Plan'!$K$7:$K$526),"#,##0") | L29: =Setup!$C$5&TEXT(SUMIF('Paycheck Plan'!$L$7:$L$526,"One-off",'Paycheck Plan'!$K$7:$K$526),"#,##0")
B31: Debt left, payday by payday

Sheet Paycheck Plan
B1: Paycheck plan
B2: One row per payday. Make the payments, then choose Paid. The cream columns are worked out for you.
B4: Start at the first row that isn't yellow. If you skip a payday, do the next one. The date still moves.
A6: Payday | B6: Date | C6: Paid? | D6: Total to set aside | E6: Extra payment | F6: Extra goes to | G6: For minimums | H6: To buffer | I6: To yearly bills | J6: +/- this payday | K6: New charges | L6: Charge type | M6: Debt left after
A7: =IF(Engine!$J$10>0.005,Engine!A11,"") | B7: =IF($A7="","",Engine!B11) | D7: =IF($A7="","",G7+H7+I7+E7) | E7: =IF($A7="","",SUM(Engine!DP11:FM11)) | F7: =IF($A7="","",IF(E7>0.005,INDEX(Engine!$T$4:$BQ$4,Engine!K11),IF(H7>0,"Buffer first",""))) | G7: =IF($A7="","",SUM(Engine!BR11:DO11)) | H7: =IF($A7="","",Engine!E11) | I7: =IF($A7="","",Engine!G11) | M7: =IF($A7="","",Engine!J11)
A8: =IF(Engine!$J$11>0.005,Engine!A12,"") | B8: =IF($A8="","",Engine!B12) | D8: =IF($A8="","",G8+H8+I8+E8) | E8: =IF($A8="","",SUM(Engine!DP12:FM12)) | F8: =IF($A8="","",IF(E8>0.005,INDEX(Engine!$T$4:$BQ$4,Engine!K12),IF(H8>0,"Buffer first",""))) | G8: =IF($A8="","",SUM(Engine!BR12:DO12)) | H8: =IF($A8="","",Engine!E12) | I8: =IF($A8="","",Engine!G12) | M8: =IF($A8="","",Engine!J12)
A9: =IF(Engine!$J$12>0.005,Engine!A13,"") | B9: =IF($A9="","",Engine!B13) | D9: =IF($A9="","",G9+H9+I9+E9) | E9: =IF($A9="","",SUM(Engine!DP13:FM13)) | F9: =IF($A9="","",IF(E9>0.005,INDEX(Engine!$T$4:$BQ$4,Engine!K13),IF(H9>0,"Buffer first",""))) | G9: =IF($A9="","",SUM(Engine!BR13:DO13)) | H9: =IF($A9="","",Engine!E13) | I9: =IF($A9="","",Engine!G13) | M9: =IF($A9="","",Engine!J13)
A10: =IF(Engine!$J$13>0.005,Engine!A14,"") | B10: =IF($A10="","",Engine!B14) | D10: =IF($A10="","",G10+H10+I10+E10) | E10: =IF($A10="","",SUM(Engine!DP14:FM14)) | F10: =IF($A10="","",IF(E10>0.005,INDEX(Engine!$T$4:$BQ$4,Engine!K14),IF(H10>0,"Buffer first",""))) | G10: =IF($A10="","",SUM(Engine!BR14:DO14)) | H10: =IF($A10="","",Engine!E14) | I10: =IF($A10="","",Engine!G14) | M10: =IF($A10="","",Engine!J14)
A11: =IF(Engine!$J$14>0.005,Engine!A15,"") | B11: =IF($A11="","",Engine!B15) | D11: =IF($A11="","",G11+H11+I11+E11) | E11: =IF($A11="","",SUM(Engine!DP15:FM15)) | F11: =IF($A11="","",IF(E11>0.005,INDEX(Engine!$T$4:$BQ$4,Engine!K15),IF(H11>0,"Buffer first",""))) | G11: =IF($A11="","",SUM(Engine!BR15:DO15)) | H11: =IF($A11="","",Engine!E15) | I11: =IF($A11="","",Engine!G15) | M11: =IF($A11="","",Engine!J15)
A12: =IF(Engine!$J$15>0.005,Engine!A16,"") | B12: =IF($A12="","",Engine!B16) | D12: =IF($A12="","",G12+H12+I12+E12) | E12: =IF($A12="","",SUM(Engine!DP16:FM16)) | F12: =IF($A12="","",IF(E12>0.005,INDEX(Engine!$T$4:$BQ$4,Engine!K16),IF(H12>0,"Buffer first",""))) | G12: =IF($A12="","",SUM(Engine!BR16:DO16)) | H12: =IF($A12="","",Engine!E16) | I12: =IF($A12="","",Engine!G16) | M12: =IF($A12="","",Engine!J16)
A13: =IF(Engine!$J$16>0.005,Engine!A17,"") | B13: =IF($A13="","",Engine!B17) | D13: =IF($A13="","",G13+H13+I13+E13) | E13: =IF($A13="","",SUM(Engine!DP17:FM17)) | F13: =IF($A13="","",IF(E13>0.005,INDEX(Engine!$T$4:$BQ$4,Engine!K17),IF(H13>0,"Buffer first",""))) | G13: =IF($A13="","",SUM(Engine!BR17:DO17)) | H13: =IF($A13="","",Engine!E17) | I13: =IF($A13="","",Engine!G17) | M13: =IF($A13="","",Engine!J17)
A14: =IF(Engine!$J$17>0.005,Engine!A18,"") | B14: =IF($A14="","",Engine!B18) | D14: =IF($A14="","",G14+H14+I14+E14) | E14: =IF($A14="","",SUM(Engine!DP18:FM18)) | F14: =IF($A14="","",IF(E14>0.005,INDEX(Engine!$T$4:$BQ$4,Engine!K18),IF(H14>0,"Buffer first",""))) | G14: =IF($A14="","",SUM(Engine!BR18:DO18)) | H14: =IF($A14="","",Engine!E18) | I14: =IF($A14="","",Engine!G18) | M14: =IF($A14="","",Engine!J18)
A15: =IF(Engine!$J$18>0.005,Engine!A19,"") | B15: =IF($A15="","",Engine!B19) | D15: =IF($A15="","",G15+H15+I15+E15) | E15: =IF($A15="","",SUM(Engine!DP19:FM19)) | F15: =IF($A15="","",IF(E15>0.005,INDEX(Engine!$T$4:$BQ$4,Engine!K19),IF(H15>0,"Buffer first",""))) | G15: =IF($A15="","",SUM(Engine!BR19:DO19)) | H15: =IF($A15="","",Engine!E19) | I15: =IF($A15="","",Engine!G19) | M15: =IF($A15="","",Engine!J19)
A16: =IF(Engine!$J$19>0.005,Engine!A20,"") | B16: =IF($A16="","",Engine!B20) | D16: =IF($A16="","",G16+H16+I16+E16) | E16: =IF($A16="","",SUM(Engine!DP20:FM20)) | F16: =IF($A16="","",IF(E16>0.005,INDEX(Engine!$T$4:$BQ$4,Engine!K20),IF(H16>0,"Buffer first",""))) | G16: =IF($A16="","",SUM(Engine!BR20:DO20)) | H16: =IF($A16="","",Engine!E20) | I16: =IF($A16="","",Engine!G20) | M16: =IF($A16="","",Engine!J20)
A17: =IF(Engine!$J$20>0.005,Engine!A21,"") | B17: =IF($A17="","",Engine!B21) | D17: =IF($A17="","",G17+H17+I17+E17) | E17: =IF($A17="","",SUM(Engine!DP21:FM21)) | F17: =IF($A17="","",IF(E17>0.005,INDEX(Engine!$T$4:$BQ$4,Engine!K21),IF(H17>0,"Buffer first",""))) | G17: =IF($A17="","",SUM(Engine!BR21:DO21)) | H17: =IF($A17="","",Engine!E21) | I17: =IF($A17="","",Engine!G21) | M17: =IF($A17="","",Engine!J21)
A18: =IF(Engine!$J$21>0.005,Engine!A22,"") | B18: =IF($A18="","",Engine!B22) | D18: =IF($A18="","",G18+H18+I18+E18) | E18: =IF($A18="","",SUM(Engine!DP22:FM22)) | F18: =IF($A18="","",IF(E18>0.005,INDEX(Engine!$T$4:$BQ$4,Engine!K22),IF(H18>0,"Buffer first",""))) | G18: =IF($A18="","",SUM(Engine!BR22:DO22)) | H18: =IF($A18="","",Engine!E22) | I18: =IF($A18="","",Engine!G22) | M18: =IF($A18="","",Engine!J22)
A19: =IF(Engine!$J$22>0.005,Engine!A23,"") | B19: =IF($A19="","",Engine!B23) | D19: =IF($A19="","",G19+H19+I19+E19) | E19: =IF($A19="","",SUM(Engine!DP23:FM23)) | F19: =IF($A19="","",IF(E19>0.005,INDEX(Engine!$T$4:$BQ$4,Engine!K23),IF(H19>0,"Buffer first",""))) | G19: =IF($A19="","",SUM(Engine!BR23:DO23)) | H19: =IF($A19="","",Engine!E23) | I19: =IF($A19="","",Engine!G23) | M19: =IF($A19="","",Engine!J23)
A20: =IF(Engine!$J$23>0.005,Engine!A24,"") | B20: =IF($A20="","",Engine!B24) | D20: =IF($A20="","",G20+H20+I20+E20) | E20: =IF($A20="","",SUM(Engine!DP24:FM24)) | F20: =IF($A20="","",IF(E20>0.005,INDEX(Engine!$T$4:$BQ$4,Engine!K24),IF(H20>0,"Buffer first",""))) | G20: =IF($A20="","",SUM(Engine!BR24:DO24)) | H20: =IF($A20="","",Engine!E24) | I20: =IF($A20="","",Engine!G24) | M20: =IF($A20="","",Engine!J24)
A21: =IF(Engine!$J$24>0.005,Engine!A25,"") | B21: =IF($A21="","",Engine!B25) | D21: =IF($A21="","",G21+H21+I21+E21) | E21: =IF($A21="","",SUM(Engine!DP25:FM25)) | F21: =IF($A21="","",IF(E21>0.005,INDEX(Engine!$T$4:$BQ$4,Engine!K25),IF(H21>0,"Buffer first",""))) | G21: =IF($A21="","",SUM(Engine!BR25:DO25)) | H21: =IF($A21="","",Engine!E25) | I21: =IF($A21="","",Engine!G25) | M21: =IF($A21="","",Engine!J25)
A22: =IF(Engine!$J$25>0.005,Engine!A26,"") | B22: =IF($A22="","",Engine!B26) | D22: =IF($A22="","",G22+H22+I22+E22) | E22: =IF($A22="","",SUM(Engine!DP26:FM26)) | F22: =IF($A22="","",IF(E22>0.005,INDEX(Engine!$T$4:$BQ$4,Engine!K26),IF(H22>0,"Buffer first",""))) | G22: =IF($A22="","",SUM(Engine!BR26:DO26)) | H22: =IF($A22="","",Engine!E26) | I22: =IF($A22="","",Engine!G26) | M22: =IF($A22="","",Engine!J26)
A23: =IF(Engine!$J$26>0.005,Engine!A27,"") | B23: =IF($A23="","",Engine!B27) | D23: =IF($A23="","",G23+H23+I23+E23) | E23: =IF($A23="","",SUM(Engine!DP27:FM27)) | F23: =IF($A23="","",IF(E23>0.005,INDEX(Engine!$T$4:$BQ$4,Engine!K27),IF(H23>0,"Buffer first",""))) | G23: =IF($A23="","",SUM(Engine!BR27:DO27)) | H23: =IF($A23="","",Engine!E27) | I23: =IF($A23="","",Engine!G27) | M23: =IF($A23="","",Engine!J27)
A24: =IF(Engine!$J$27>0.005,Engine!A28,"") | B24: =IF($A24="","",Engine!B28) | D24: =IF($A24="","",G24+H24+I24+E24) | E24: =IF($A24="","",SUM(Engine!DP28:FM28)) | F24: =IF($A24="","",IF(E24>0.005,INDEX(Engine!$T$4:$BQ$4,Engine!K28),IF(H24>0,"Buffer first",""))) | G24: =IF($A24="","",SUM(Engine!BR28:DO28)) | H24: =IF($A24="","",Engine!E28) | I24: =IF($A24="","",Engine!G28) | M24: =IF($A24="","",Engine!J28)
A25: =IF(Engine!$J$28>0.005,Engine!A29,"") | B25: =IF($A25="","",Engine!B29) | D25: =IF($A25="","",G25+H25+I25+E25) | E25: =IF($A25="","",SUM(Engine!DP29:FM29)) | F25: =IF($A25="","",IF(E25>0.005,INDEX(Engine!$T$4:$BQ$4,Engine!K29),IF(H25>0,"Buffer first",""))) | G25: =IF($A25="","",SUM(Engine!BR29:DO29)) | H25: =IF($A25="","",Engine!E29) | I25: =IF($A25="","",Engine!G29) | M25: =IF($A25="","",Engine!J29)
A26: =IF(Engine!$J$29>0.005,Engine!A30,"") | B26: =IF($A26="","",Engine!B30) | D26: =IF($A26="","",G26+H26+I26+E26) | E26: =IF($A26="","",SUM(Engine!DP30:FM30)) | F26: =IF($A26="","",IF(E26>0.005,INDEX(Engine!$T$4:$BQ$4,Engine!K30),IF(H26>0,"Buffer first",""))) | G26: =IF($A26="","",SUM(Engine!BR30:DO30)) | H26: =IF($A26="","",Engine!E30) | I26: =IF($A26="","",Engine!G30) | M26: =IF($A26="","",Engine!J30)
A27: =IF(Engine!$J$30>0.005,Engine!A31,"") | B27: =IF($A27="","",Engine!B31) | D27: =IF($A27="","",G27+H27+I27+E27) | E27: =IF($A27="","",SUM(Engine!DP31:FM31)) | F27: =IF($A27="","",IF(E27>0.005,INDEX(Engine!$T$4:$BQ$4,Engine!K31),IF(H27>0,"Buffer first",""))) | G27: =IF($A27="","",SUM(Engine!BR31:DO31)) | H27: =IF($A27="","",Engine!E31) | I27: =IF($A27="","",Engine!G31) | M27: =IF($A27="","",Engine!J31)
A28: =IF(Engine!$J$31>0.005,Engine!A32,"") | B28: =IF($A28="","",Engine!B32) | D28: =IF($A28="","",G28+H28+I28+E28) | E28: =IF($A28="","",SUM(Engine!DP32:FM32)) | F28: =IF($A28="","",IF(E28>0.005,INDEX(Engine!$T$4:$BQ$4,Engine!K32),IF(H28>0,"Buffer first",""))) | G28: =IF($A28="","",SUM(Engine!BR32:DO32)) | H28: =IF($A28="","",Engine!E32) | I28: =IF($A28="","",Engine!G32) | M28: =IF($A28="","",Engine!J32)
A29: =IF(Engine!$J$32>0.005,Engine!A33,"") | B29: =IF($A29="","",Engine!B33) | D29: =IF($A29="","",G29+H29+I29+E29) | E29: =IF($A29="","",SUM(Engine!DP33:FM33)) | F29: =IF($A29="","",IF(E29>0.005,INDEX(Engine!$T$4:$BQ$4,Engine!K33),IF(H29>0,"Buffer first",""))) | G29: =IF($A29="","",SUM(Engine!BR33:DO33)) | H29: =IF($A29="","",Engine!E33) | I29: =IF($A29="","",Engine!G33) | M29: =IF($A29="","",Engine!J33)
A30: =IF(Engine!$J$33>0.005,Engine!A34,"") | B30: =IF($A30="","",Engine!B34) | D30: =IF($A30="","",G30+H30+I30+E30) | E30: =IF($A30="","",SUM(Engine!DP34:FM34)) | F30: =IF($A30="","",IF(E30>0.005,INDEX(Engine!$T$4:$BQ$4,Engine!K34),IF(H30>0,"Buffer first",""))) | G30: =IF($A30="","",SUM(Engine!BR34:DO34)) | H30: =IF($A30="","",Engine!E34) | I30: =IF($A30="","",Engine!G34) | M30: =IF($A30="","",Engine!J34)
A31: =IF(Engine!$J$34>0.005,Engine!A35,"") | B31: =IF($A31="","",Engine!B35) | D31: =IF($A31="","",G31+H31+I31+E31) | E31: =IF($A31="","",SUM(Engine!DP35:FM35)) | F31: =IF($A31="","",IF(E31>0.005,INDEX(Engine!$T$4:$BQ$4,Engine!K35),IF(H31>0,"Buffer first",""))) | G31: =IF($A31="","",SUM(Engine!BR35:DO35)) | H31: =IF($A31="","",Engine!E35) | I31: =IF($A31="","",Engine!G35) | M31: =IF($A31="","",Engine!J35)
A32: =IF(Engine!$J$35>0.005,Engine!A36,"") | B32: =IF($A32="","",Engine!B36) | D32: =IF($A32="","",G32+H32+I32+E32) | E32: =IF($A32="","",SUM(Engine!DP36:FM36)) | F32: =IF($A32="","",IF(E32>0.005,INDEX(Engine!$T$4:$BQ$4,Engine!K36),IF(H32>0,"Buffer first",""))) | G32: =IF($A32="","",SUM(Engine!BR36:DO36)) | H32: =IF($A32="","",Engine!E36) | I32: =IF($A32="","",Engine!G36) | M32: =IF($A32="","",Engine!J36)
A33: =IF(Engine!$J$36>0.005,Engine!A37,"") | B33: =IF($A33="","",Engine!B37) | D33: =IF($A33="","",G33+H33+I33+E33) | E33: =IF($A33="","",SUM(Engine!DP37:FM37)) | F33: =IF($A33="","",IF(E33>0.005,INDEX(Engine!$T$4:$BQ$4,Engine!K37),IF(H33>0,"Buffer first",""))) | G33: =IF($A33="","",SUM(Engine!BR37:DO37)) | H33: =IF($A33="","",Engine!E37) | I33: =IF($A33="","",Engine!G37) | M33: =IF($A33="","",Engine!J37)
A34: =IF(Engine!$J$37>0.005,Engine!A38,"") | B34: =IF($A34="","",Engine!B38) | D34: =IF($A34="","",G34+H34+I34+E34) | E34: =IF($A34="","",SUM(Engine!DP38:FM38)) | F34: =IF($A34="","",IF(E34>0.005,INDEX(Engine!$T$4:$BQ$4,Engine!K38),IF(H34>0,"Buffer first",""))) | G34: =IF($A34="","",SUM(Engine!BR38:DO38)) | H34: =IF($A34="","",Engine!E38) | I34: =IF($A34="","",Engine!G38) | M34: =IF($A34="","",Engine!J38)
A35: =IF(Engine!$J$38>0.005,Engine!A39,"") | B35: =IF($A35="","",Engine!B39) | D35: =IF($A35="","",G35+H35+I35+E35) | E35: =IF($A35="","",SUM(Engine!DP39:FM39)) | F35: =IF($A35="","",IF(E35>0.005,INDEX(Engine!$T$4:$BQ$4,Engine!K39),IF(H35>0,"Buffer first",""))) | G35: =IF($A35="","",SUM(Engine!BR39:DO39)) | H35: =IF($A35="","",Engine!E39) | I35: =IF($A35="","",Engine!G39) | M35: =IF($A35="","",Engine!J39)
A36: =IF(Engine!$J$39>0.005,Engine!A40,"") | B36: =IF($A36="","",Engine!B40) | D36: =IF($A36="","",G36+H36+I36+E36) | E36: =IF($A36="","",SUM(Engine!DP40:FM40)) | F36: =IF($A36="","",IF(E36>0.005,INDEX(Engine!$T$4:$BQ$4,Engine!K40),IF(H36>0,"Buffer first",""))) | G36: =IF($A36="","",SUM(Engine!BR40:DO40)) | H36: =IF($A36="","",Engine!E40) | I36: =IF($A36="","",Engine!G40) | M36: =IF($A36="","",Engine!J40)
A37: =IF(Engine!$J$40>0.005,Engine!A41,"") | B37: =IF($A37="","",Engine!B41) | D37: =IF($A37="","",G37+H37+I37+E37) | E37: =IF($A37="","",SUM(Engine!DP41:FM41)) | F37: =IF($A37="","",IF(E37>0.005,INDEX(Engine!$T$4:$BQ$4,Engine!K41),IF(H37>0,"Buffer first",""))) | G37: =IF($A37="","",SUM(Engine!BR41:DO41)) | H37: =IF($A37="","",Engine!E41) | I37: =IF($A37="","",Engine!G41) | M37: =IF($A37="","",Engine!J41)
A38: =IF(Engine!$J$41>0.005,Engine!A42,"") | B38: =IF($A38="","",Engine!B42) | D38: =IF($A38="","",G38+H38+I38+E38) | E38: =IF($A38="","",SUM(Engine!DP42:FM42)) | F38: =IF($A38="","",IF(E38>0.005,INDEX(Engine!$T$4:$BQ$4,Engine!K42),IF(H38>0,"Buffer first",""))) | G38: =IF($A38="","",SUM(Engine!BR42:DO42)) | H38: =IF($A38="","",Engine!E42) | I38: =IF($A38="","",Engine!G42) | M38: =IF($A38="","",Engine!J42)
A39: =IF(Engine!$J$42>0.005,Engine!A43,"") | B39: =IF($A39="","",Engine!B43) | D39: =IF($A39="","",G39+H39+I39+E39) | E39: =IF($A39="","",SUM(Engine!DP43:FM43)) | F39: =IF($A39="","",IF(E39>0.005,INDEX(Engine!$T$4:$BQ$4,Engine!K43),IF(H39>0,"Buffer first",""))) | G39: =IF($A39="","",SUM(Engine!BR43:DO43)) | H39: =IF($A39="","",Engine!E43) | I39: =IF($A39="","",Engine!G43) | M39: =IF($A39="","",Engine!J43)
A40: =IF(Engine!$J$43>0.005,Engine!A44,"") | B40: =IF($A40="","",Engine!B44) | D40: =IF($A40="","",G40+H40+I40+E40) | E40: =IF($A40="","",SUM(Engine!DP44:FM44)) | F40: =IF($A40="","",IF(E40>0.005,INDEX(Engine!$T$4:$BQ$4,Engine!K44),IF(H40>0,"Buffer first",""))) | G40: =IF($A40="","",SUM(Engine!BR44:DO44)) | H40: =IF($A40="","",Engine!E44) | I40: =IF($A40="","",Engine!G44) | M40: =IF($A40="","",Engine!J44)
A41: =IF(Engine!$J$44>0.005,Engine!A45,"") | B41: =IF($A41="","",Engine!B45) | D41: =IF($A41="","",G41+H41+I41+E41) | E41: =IF($A41="","",SUM(Engine!DP45:FM45)) | F41: =IF($A41="","",IF(E41>0.005,INDEX(Engine!$T$4:$BQ$4,Engine!K45),IF(H41>0,"Buffer first",""))) | G41: =IF($A41="","",SUM(Engine!BR45:DO45)) | H41: =IF($A41="","",Engine!E45) | I41: =IF($A41="","",Engine!G45) | M41: =IF($A41="","",Engine!J45)
A42: =IF(Engine!$J$45>0.005,Engine!A46,"") | B42: =IF($A42="","",Engine!B46) | D42: =IF($A42="","",G42+H42+I42+E42) | E42: =IF($A42="","",SUM(Engine!DP46:FM46)) | F42: =IF($A42="","",IF(E42>0.005,INDEX(Engine!$T$4:$BQ$4,Engine!K46),IF(H42>0,"Buffer first",""))) | G42: =IF($A42="","",SUM(Engine!BR46:DO46)) | H42: =IF($A42="","",Engine!E46) | I42: =IF($A42="","",Engine!G46) | M42: =IF($A42="","",Engine!J46)
A43: =IF(Engine!$J$46>0.005,Engine!A47,"") | B43: =IF($A43="","",Engine!B47) | D43: =IF($A43="","",G43+H43+I43+E43) | E43: =IF($A43="","",SUM(Engine!DP47:FM47)) | F43: =IF($A43="","",IF(E43>0.005,INDEX(Engine!$T$4:$BQ$4,Engine!K47),IF(H43>0,"Buffer first",""))) | G43: =IF($A43="","",SUM(Engine!BR47:DO47)) | H43: =IF($A43="","",Engine!E47) | I43: =IF($A43="","",Engine!G47) | M43: =IF($A43="","",Engine!J47)
A44: =IF(Engine!$J$47>0.005,Engine!A48,"") | B44: =IF($A44="","",Engine!B48) | D44: =IF($A44="","",G44+H44+I44+E44) | E44: =IF($A44="","",SUM(Engine!DP48:FM48)) | F44: =IF($A44="","",IF(E44>0.005,INDEX(Engine!$T$4:$BQ$4,Engine!K48),IF(H44>0,"Buffer first",""))) | G44: =IF($A44="","",SUM(Engine!BR48:DO48)) | H44: =IF($A44="","",Engine!E48) | I44: =IF($A44="","",Engine!G48) | M44: =IF($A44="","",Engine!J48)
A45: =IF(Engine!$J$48>0.005,Engine!A49,"") | B45: =IF($A45="","",Engine!B49) | D45: =IF($A45="","",G45+H45+I45+E45) | E45: =IF($A45="","",SUM(Engine!DP49:FM49)) | F45: =IF($A45="","",IF(E45>0.005,INDEX(Engine!$T$4:$BQ$4,Engine!K49),IF(H45>0,"Buffer first",""))) | G45: =IF($A45="","",SUM(Engine!BR49:DO49)) | H45: =IF($A45="","",Engine!E49) | I45: =IF($A45="","",Engine!G49) | M45: =IF($A45="","",Engine!J49)
A46: =IF(Engine!$J$49>0.005,Engine!A50,"") | B46: =IF($A46="","",Engine!B50) | D46: =IF($A46="","",G46+H46+I46+E46) | E46: =IF($A46="","",SUM(Engine!DP50:FM50)) | F46: =IF($A46="","",IF(E46>0.005,INDEX(Engine!$T$4:$BQ$4,Engine!K50),IF(H46>0,"Buffer first",""))) | G46: =IF($A46="","",SUM(Engine!BR50:DO50)) | H46: =IF($A46="","",Engine!E50) | I46: =IF($A46="","",Engine!G50) | M46: =IF($A46="","",Engine!J50)
A47: =IF(Engine!$J$50>0.005,Engine!A51,"") | B47: =IF($A47="","",Engine!B51) | D47: =IF($A47="","",G47+H47+I47+E47) | E47: =IF($A47="","",SUM(Engine!DP51:FM51)) | F47: =IF($A47="","",IF(E47>0.005,INDEX(Engine!$T$4:$BQ$4,Engine!K51),IF(H47>0,"Buffer first",""))) | G47: =IF($A47="","",SUM(Engine!BR51:DO51)) | H47: =IF($A47="","",Engine!E51) | I47: =IF($A47="","",Engine!G51) | M47: =IF($A47="","",Engine!J51)
A48: =IF(Engine!$J$51>0.005,Engine!A52,"") | B48: =IF($A48="","",Engine!B52) | D48: =IF($A48="","",G48+H48+I48+E48) | E48: =IF($A48="","",SUM(Engine!DP52:FM52)) | F48: =IF($A48="","",IF(E48>0.005,INDEX(Engine!$T$4:$BQ$4,Engine!K52),IF(H48>0,"Buffer first",""))) | G48: =IF($A48="","",SUM(Engine!BR52:DO52)) | H48: =IF($A48="","",Engine!E52) | I48: =IF($A48="","",Engine!G52) | M48: =IF($A48="","",Engine!J52)
A49: =IF(Engine!$J$52>0.005,Engine!A53,"") | B49: =IF($A49="","",Engine!B53) | D49: =IF($A49="","",G49+H49+I49+E49) | E49: =IF($A49="","",SUM(Engine!DP53:FM53)) | F49: =IF($A49="","",IF(E49>0.005,INDEX(Engine!$T$4:$BQ$4,Engine!K53),IF(H49>0,"Buffer first",""))) | G49: =IF($A49="","",SUM(Engine!BR53:DO53)) | H49: =IF($A49="","",Engine!E53) | I49: =IF($A49="","",Engine!G53) | M49: =IF($A49="","",Engine!J53)
A50: =IF(Engine!$J$53>0.005,Engine!A54,"") | B50: =IF($A50="","",Engine!B54) | D50: =IF($A50="","",G50+H50+I50+E50) | E50: =IF($A50="","",SUM(Engine!DP54:FM54)) | F50: =IF($A50="","",IF(E50>0.005,INDEX(Engine!$T$4:$BQ$4,Engine!K54),IF(H50>0,"Buffer first",""))) | G50: =IF($A50="","",SUM(Engine!BR54:DO54)) | H50: =IF($A50="","",Engine!E54) | I50: =IF($A50="","",Engine!G54) | M50: =IF($A50="","",Engine!J54)
A51: =IF(Engine!$J$54>0.005,Engine!A55,"") | B51: =IF($A51="","",Engine!B55) | D51: =IF($A51="","",G51+H51+I51+E51) | E51: =IF($A51="","",SUM(Engine!DP55:FM55)) | F51: =IF($A51="","",IF(E51>0.005,INDEX(Engine!$T$4:$BQ$4,Engine!K55),IF(H51>0,"Buffer first",""))) | G51: =IF($A51="","",SUM(Engine!BR55:DO55)) | H51: =IF($A51="","",Engine!E55) | I51: =IF($A51="","",Engine!G55) | M51: =IF($A51="","",Engine!J55)
A52: =IF(Engine!$J$55>0.005,Engine!A56,"") | B52: =IF($A52="","",Engine!B56) | D52: =IF($A52="","",G52+H52+I52+E52) | E52: =IF($A52="","",SUM(Engine!DP56:FM56)) | F52: =IF($A52="","",IF(E52>0.005,INDEX(Engine!$T$4:$BQ$4,Engine!K56),IF(H52>0,"Buffer first",""))) | G52: =IF($A52="","",SUM(Engine!BR56:DO56)) | H52: =IF($A52="","",Engine!E56) | I52: =IF($A52="","",Engine!G56) | M52: =IF($A52="","",Engine!J56)
A53: =IF(Engine!$J$56>0.005,Engine!A57,"") | B53: =IF($A53="","",Engine!B57) | D53: =IF($A53="","",G53+H53+I53+E53) | E53: =IF($A53="","",SUM(Engine!DP57:FM57)) | F53: =IF($A53="","",IF(E53>0.005,INDEX(Engine!$T$4:$BQ$4,Engine!K57),IF(H53>0,"Buffer first",""))) | G53: =IF($A53="","",SUM(Engine!BR57:DO57)) | H53: =IF($A53="","",Engine!E57) | I53: =IF($A53="","",Engine!G57) | M53: =IF($A53="","",Engine!J57)
A54: =IF(Engine!$J$57>0.005,Engine!A58,"") | B54: =IF($A54="","",Engine!B58) | D54: =IF($A54="","",G54+H54+I54+E54) | E54: =IF($A54="","",SUM(Engine!DP58:FM58)) | F54: =IF($A54="","",IF(E54>0.005,INDEX(Engine!$T$4:$BQ$4,Engine!K58),IF(H54>0,"Buffer first",""))) | G54: =IF($A54="","",SUM(Engine!BR58:DO58)) | H54: =IF($A54="","",Engine!E58) | I54: =IF($A54="","",Engine!G58) | M54: =IF($A54="","",Engine!J58)
A55: =IF(Engine!$J$58>0.005,Engine!A59,"") | B55: =IF($A55="","",Engine!B59) | D55: =IF($A55="","",G55+H55+I55+E55) | E55: =IF($A55="","",SUM(Engine!DP59:FM59)) | F55: =IF($A55="","",IF(E55>0.005,INDEX(Engine!$T$4:$BQ$4,Engine!K59),IF(H55>0,"Buffer first",""))) | G55: =IF($A55="","",SUM(Engine!BR59:DO59)) | H55: =IF($A55="","",Engine!E59) | I55: =IF($A55="","",Engine!G59) | M55: =IF($A55="","",Engine!J59)
A56: =IF(Engine!$J$59>0.005,Engine!A60,"") | B56: =IF($A56="","",Engine!B60) | D56: =IF($A56="","",G56+H56+I56+E56) | E56: =IF($A56="","",SUM(Engine!DP60:FM60)) | F56: =IF($A56="","",IF(E56>0.005,INDEX(Engine!$T$4:$BQ$4,Engine!K60),IF(H56>0,"Buffer first",""))) | G56: =IF($A56="","",SUM(Engine!BR60:DO60)) | H56: =IF($A56="","",Engine!E60) | I56: =IF($A56="","",Engine!G60) | M56: =IF($A56="","",Engine!J60)
A57: =IF(Engine!$J$60>0.005,Engine!A61,"") | B57: =IF($A57="","",Engine!B61) | D57: =IF($A57="","",G57+H57+I57+E57) | E57: =IF($A57="","",SUM(Engine!DP61:FM61)) | F57: =IF($A57="","",IF(E57>0.005,INDEX(Engine!$T$4:$BQ$4,Engine!K61),IF(H57>0,"Buffer first",""))) | G57: =IF($A57="","",SUM(Engine!BR61:DO61)) | H57: =IF($A57="","",Engine!E61) | I57: =IF($A57="","",Engine!G61) | M57: =IF($A57="","",Engine!J61)
A58: =IF(Engine!$J$61>0.005,Engine!A62,"") | B58: =IF($A58="","",Engine!B62) | D58: =IF($A58="","",G58+H58+I58+E58) | E58: =IF($A58="","",SUM(Engine!DP62:FM62)) | F58: =IF($A58="","",IF(E58>0.005,INDEX(Engine!$T$4:$BQ$4,Engine!K62),IF(H58>0,"Buffer first",""))) | G58: =IF($A58="","",SUM(Engine!BR62:DO62)) | H58: =IF($A58="","",Engine!E62) | I58: =IF($A58="","",Engine!G62) | M58: =IF($A58="","",Engine!J62)
A59: =IF(Engine!$J$62>0.005,Engine!A63,"") | B59: =IF($A59="","",Engine!B63) | D59: =IF($A59="","",G59+H59+I59+E59) | E59: =IF($A59="","",SUM(Engine!DP63:FM63)) | F59: =IF($A59="","",IF(E59>0.005,INDEX(Engine!$T$4:$BQ$4,Engine!K63),IF(H59>0,"Buffer first",""))) | G59: =IF($A59="","",SUM(Engine!BR63:DO63)) | H59: =IF($A59="","",Engine!E63) | I59: =IF($A59="","",Engine!G63) | M59: =IF($A59="","",Engine!J63)
A60: =IF(Engine!$J$63>0.005,Engine!A64,"") | B60: =IF($A60="","",Engine!B64) | D60: =IF($A60="","",G60+H60+I60+E60) | E60: =IF($A60="","",SUM(Engine!DP64:FM64)) | F60: =IF($A60="","",IF(E60>0.005,INDEX(Engine!$T$4:$BQ$4,Engine!K64),IF(H60>0,"Buffer first",""))) | G60: =IF($A60="","",SUM(Engine!BR64:DO64)) | H60: =IF($A60="","",Engine!E64) | I60: =IF($A60="","",Engine!G64) | M60: =IF($A60="","",Engine!J64)
A61: =IF(Engine!$J$64>0.005,Engine!A65,"") | B61: =IF($A61="","",Engine!B65) | D61: =IF($A61="","",G61+H61+I61+E61) | E61: =IF($A61="","",SUM(Engine!DP65:FM65)) | F61: =IF($A61="","",IF(E61>0.005,INDEX(Engine!$T$4:$BQ$4,Engine!K65),IF(H61>0,"Buffer first",""))) | G61: =IF($A61="","",SUM(Engine!BR65:DO65)) | H61: =IF($A61="","",Engine!E65) | I61: =IF($A61="","",Engine!G65) | M61: =IF($A61="","",Engine!J65)
A62: =IF(Engine!$J$65>0.005,Engine!A66,"") | B62: =IF($A62="","",Engine!B66) | D62: =IF($A62="","",G62+H62+I62+E62) | E62: =IF($A62="","",SUM(Engine!DP66:FM66)) | F62: =IF($A62="","",IF(E62>0.005,INDEX(Engine!$T$4:$BQ$4,Engine!K66),IF(H62>0,"Buffer first",""))) | G62: =IF($A62="","",SUM(Engine!BR66:DO66)) | H62: =IF($A62="","",Engine!E66) | I62: =IF($A62="","",Engine!G66) | M62: =IF($A62="","",Engine!J66)
A63: =IF(Engine!$J$66>0.005,Engine!A67,"") | B63: =IF($A63="","",Engine!B67) | D63: =IF($A63="","",G63+H63+I63+E63) | E63: =IF($A63="","",SUM(Engine!DP67:FM67)) | F63: =IF($A63="","",IF(E63>0.005,INDEX(Engine!$T$4:$BQ$4,Engine!K67),IF(H63>0,"Buffer first",""))) | G63: =IF($A63="","",SUM(Engine!BR67:DO67)) | H63: =IF($A63="","",Engine!E67) | I63: =IF($A63="","",Engine!G67) | M63: =IF($A63="","",Engine!J67)
A64: =IF(Engine!$J$67>0.005,Engine!A68,"") | B64: =IF($A64="","",Engine!B68) | D64: =IF($A64="","",G64+H64+I64+E64) | E64: =IF($A64="","",SUM(Engine!DP68:FM68)) | F64: =IF($A64="","",IF(E64>0.005,INDEX(Engine!$T$4:$BQ$4,Engine!K68),IF(H64>0,"Buffer first",""))) | G64: =IF($A64="","",SUM(Engine!BR68:DO68)) | H64: =IF($A64="","",Engine!E68) | I64: =IF($A64="","",Engine!G68) | M64: =IF($A64="","",Engine!J68)
A65: =IF(Engine!$J$68>0.005,Engine!A69,"") | B65: =IF($A65="","",Engine!B69) | D65: =IF($A65="","",G65+H65+I65+E65) | E65: =IF($A65="","",SUM(Engine!DP69:FM69)) | F65: =IF($A65="","",IF(E65>0.005,INDEX(Engine!$T$4:$BQ$4,Engine!K69),IF(H65>0,"Buffer first",""))) | G65: =IF($A65="","",SUM(Engine!BR69:DO69)) | H65: =IF($A65="","",Engine!E69) | I65: =IF($A65="","",Engine!G69) | M65: =IF($A65="","",Engine!J69)
A66: =IF(Engine!$J$69>0.005,Engine!A70,"") | B66: =IF($A66="","",Engine!B70) | D66: =IF($A66="","",G66+H66+I66+E66) | E66: =IF($A66="","",SUM(Engine!DP70:FM70)) | F66: =IF($A66="","",IF(E66>0.005,INDEX(Engine!$T$4:$BQ$4,Engine!K70),IF(H66>0,"Buffer first",""))) | G66: =IF($A66="","",SUM(Engine!BR70:DO70)) | H66: =IF($A66="","",Engine!E70) | I66: =IF($A66="","",Engine!G70) | M66: =IF($A66="","",Engine!J70)
A67: =IF(Engine!$J$70>0.005,Engine!A71,"") | B67: =IF($A67="","",Engine!B71) | D67: =IF($A67="","",G67+H67+I67+E67) | E67: =IF($A67="","",SUM(Engine!DP71:FM71)) | F67: =IF($A67="","",IF(E67>0.005,INDEX(Engine!$T$4:$BQ$4,Engine!K71),IF(H67>0,"Buffer first",""))) | G67: =IF($A67="","",SUM(Engine!BR71:DO71)) | H67: =IF($A67="","",Engine!E71) | I67: =IF($A67="","",Engine!G71) | M67: =IF($A67="","",Engine!J71)
A68: =IF(Engine!$J$71>0.005,Engine!A72,"") | B68: =IF($A68="","",Engine!B72) | D68: =IF($A68="","",G68+H68+I68+E68) | E68: =IF($A68="","",SUM(Engine!DP72:FM72)) | F68: =IF($A68="","",IF(E68>0.005,INDEX(Engine!$T$4:$BQ$4,Engine!K72),IF(H68>0,"Buffer first",""))) | G68: =IF($A68="","",SUM(Engine!BR72:DO72)) | H68: =IF($A68="","",Engine!E72) | I68: =IF($A68="","",Engine!G72) | M68: =IF($A68="","",Engine!J72)
A69: =IF(Engine!$J$72>0.005,Engine!A73,"") | B69: =IF($A69="","",Engine!B73) | D69: =IF($A69="","",G69+H69+I69+E69) | E69: =IF($A69="","",SUM(Engine!DP73:FM73)) | F69: =IF($A69="","",IF(E69>0.005,INDEX(Engine!$T$4:$BQ$4,Engine!K73),IF(H69>0,"Buffer first",""))) | G69: =IF($A69="","",SUM(Engine!BR73:DO73)) | H69: =IF($A69="","",Engine!E73) | I69: =IF($A69="","",Engine!G73) | M69: =IF($A69="","",Engine!J73)
A70: =IF(Engine!$J$73>0.005,Engine!A74,"") | B70: =IF($A70="","",Engine!B74) | D70: =IF($A70="","",G70+H70+I70+E70) | E70: =IF($A70="","",SUM(Engine!DP74:FM74)) | F70: =IF($A70="","",IF(E70>0.005,INDEX(Engine!$T$4:$BQ$4,Engine!K74),IF(H70>0,"Buffer first",""))) | G70: =IF($A70="","",SUM(Engine!BR74:DO74)) | H70: =IF($A70="","",Engine!E74) | I70: =IF($A70="","",Engine!G74) | M70: =IF($A70="","",Engine!J74)
A71: =IF(Engine!$J$74>0.005,Engine!A75,"") | B71: =IF($A71="","",Engine!B75) | D71: =IF($A71="","",G71+H71+I71+E71) | E71: =IF($A71="","",SUM(Engine!DP75:FM75)) | F71: =IF($A71="","",IF(E71>0.005,INDEX(Engine!$T$4:$BQ$4,Engine!K75),IF(H71>0,"Buffer first",""))) | G71: =IF($A71="","",SUM(Engine!BR75:DO75)) | H71: =IF($A71="","",Engine!E75) | I71: =IF($A71="","",Engine!G75) | M71: =IF($A71="","",Engine!J75)
A72: =IF(Engine!$J$75>0.005,Engine!A76,"") | B72: =IF($A72="","",Engine!B76) | D72: =IF($A72="","",G72+H72+I72+E72) | E72: =IF($A72="","",SUM(Engine!DP76:FM76)) | F72: =IF($A72="","",IF(E72>0.005,INDEX(Engine!$T$4:$BQ$4,Engine!K76),IF(H72>0,"Buffer first",""))) | G72: =IF($A72="","",SUM(Engine!BR76:DO76)) | H72: =IF($A72="","",Engine!E76) | I72: =IF($A72="","",Engine!G76) | M72: =IF($A72="","",Engine!J76)
A73: =IF(Engine!$J$76>0.005,Engine!A77,"") | B73: =IF($A73="","",Engine!B77) | D73: =IF($A73="","",G73+H73+I73+E73) | E73: =IF($A73="","",SUM(Engine!DP77:FM77)) | F73: =IF($A73="","",IF(E73>0.005,INDEX(Engine!$T$4:$BQ$4,Engine!K77),IF(H73>0,"Buffer first",""))) | G73: =IF($A73="","",SUM(Engine!BR77:DO77)) | H73: =IF($A73="","",Engine!E77) | I73: =IF($A73="","",Engine!G77) | M73: =IF($A73="","",Engine!J77)
A74: =IF(Engine!$J$77>0.005,Engine!A78,"") | B74: =IF($A74="","",Engine!B78) | D74: =IF($A74="","",G74+H74+I74+E74) | E74: =IF($A74="","",SUM(Engine!DP78:FM78)) | F74: =IF($A74="","",IF(E74>0.005,INDEX(Engine!$T$4:$BQ$4,Engine!K78),IF(H74>0,"Buffer first",""))) | G74: =IF($A74="","",SUM(Engine!BR78:DO78)) | H74: =IF($A74="","",Engine!E78) | I74: =IF($A74="","",Engine!G78) | M74: =IF($A74="","",Engine!J78)
A75: =IF(Engine!$J$78>0.005,Engine!A79,"") | B75: =IF($A75="","",Engine!B79) | D75: =IF($A75="","",G75+H75+I75+E75) | E75: =IF($A75="","",SUM(Engine!DP79:FM79)) | F75: =IF($A75="","",IF(E75>0.005,INDEX(Engine!$T$4:$BQ$4,Engine!K79),IF(H75>0,"Buffer first",""))) | G75: =IF($A75="","",SUM(Engine!BR79:DO79)) | H75: =IF($A75="","",Engine!E79) | I75: =IF($A75="","",Engine!G79) | M75: =IF($A75="","",Engine!J79)
A76: =IF(Engine!$J$79>0.005,Engine!A80,"") | B76: =IF($A76="","",Engine!B80) | D76: =IF($A76="","",G76+H76+I76+E76) | E76: =IF($A76="","",SUM(Engine!DP80:FM80)) | F76: =IF($A76="","",IF(E76>0.005,INDEX(Engine!$T$4:$BQ$4,Engine!K80),IF(H76>0,"Buffer first",""))) | G76: =IF($A76="","",SUM(Engine!BR80:DO80)) | H76: =IF($A76="","",Engine!E80) | I76: =IF($A76="","",Engine!G80) | M76: =IF($A76="","",Engine!J80)
A77: =IF(Engine!$J$80>0.005,Engine!A81,"") | B77: =IF($A77="","",Engine!B81) | D77: =IF($A77="","",G77+H77+I77+E77) | E77: =IF($A77="","",SUM(Engine!DP81:FM81)) | F77: =IF($A77="","",IF(E77>0.005,INDEX(Engine!$T$4:$BQ$4,Engine!K81),IF(H77>0,"Buffer first",""))) | G77: =IF($A77="","",SUM(Engine!BR81:DO81)) | H77: =IF($A77="","",Engine!E81) | I77: =IF($A77="","",Engine!G81) | M77: =IF($A77="","",Engine!J81)
A78: =IF(Engine!$J$81>0.005,Engine!A82,"") | B78: =IF($A78="","",Engine!B82) | D78: =IF($A78="","",G78+H78+I78+E78) | E78: =IF($A78="","",SUM(Engine!DP82:FM82)) | F78: =IF($A78="","",IF(E78>0.005,INDEX(Engine!$T$4:$BQ$4,Engine!K82),IF(H78>0,"Buffer first",""))) | G78: =IF($A78="","",SUM(Engine!BR82:DO82)) | H78: =IF($A78="","",Engine!E82) | I78: =IF($A78="","",Engine!G82) | M78: =IF($A78="","",Engine!J82)
A79: =IF(Engine!$J$82>0.005,Engine!A83,"") | B79: =IF($A79="","",Engine!B83) | D79: =IF($A79="","",G79+H79+I79+E79) | E79: =IF($A79="","",SUM(Engine!DP83:FM83)) | F79: =IF($A79="","",IF(E79>0.005,INDEX(Engine!$T$4:$BQ$4,Engine!K83),IF(H79>0,"Buffer first",""))) | G79: =IF($A79="","",SUM(Engine!BR83:DO83)) | H79: =IF($A79="","",Engine!E83) | I79: =IF($A79="","",Engine!G83) | M79: =IF($A79="","",Engine!J83)
A80: =IF(Engine!$J$83>0.005,Engine!A84,"") | B80: =IF($A80="","",Engine!B84) | D80: =IF($A80="","",G80+H80+I80+E80) | E80: =IF($A80="","",SUM(Engine!DP84:FM84)) | F80: =IF($A80="","",IF(E80>0.005,INDEX(Engine!$T$4:$BQ$4,Engine!K84),IF(H80>0,"Buffer first",""))) | G80: =IF($A80="","",SUM(Engine!BR84:DO84)) | H80: =IF($A80="","",Engine!E84) | I80: =IF($A80="","",Engine!G84) | M80: =IF($A80="","",Engine!J84)
A81: =IF(Engine!$J$84>0.005,Engine!A85,"") | B81: =IF($A81="","",Engine!B85) | D81: =IF($A81="","",G81+H81+I81+E81) | E81: =IF($A81="","",SUM(Engine!DP85:FM85)) | F81: =IF($A81="","",IF(E81>0.005,INDEX(Engine!$T$4:$BQ$4,Engine!K85),IF(H81>0,"Buffer first",""))) | G81: =IF($A81="","",SUM(Engine!BR85:DO85)) | H81: =IF($A81="","",Engine!E85) | I81: =IF($A81="","",Engine!G85) | M81: =IF($A81="","",Engine!J85)
A82: =IF(Engine!$J$85>0.005,Engine!A86,"") | B82: =IF($A82="","",Engine!B86) | D82: =IF($A82="","",G82+H82+I82+E82) | E82: =IF($A82="","",SUM(Engine!DP86:FM86)) | F82: =IF($A82="","",IF(E82>0.005,INDEX(Engine!$T$4:$BQ$4,Engine!K86),IF(H82>0,"Buffer first",""))) | G82: =IF($A82="","",SUM(Engine!BR86:DO86)) | H82: =IF($A82="","",Engine!E86) | I82: =IF($A82="","",Engine!G86) | M82: =IF($A82="","",Engine!J86)
A83: =IF(Engine!$J$86>0.005,Engine!A87,"") | B83: =IF($A83="","",Engine!B87) | D83: =IF($A83="","",G83+H83+I83+E83) | E83: =IF($A83="","",SUM(Engine!DP87:FM87)) | F83: =IF($A83="","",IF(E83>0.005,INDEX(Engine!$T$4:$BQ$4,Engine!K87),IF(H83>0,"Buffer first",""))) | G83: =IF($A83="","",SUM(Engine!BR87:DO87)) | H83: =IF($A83="","",Engine!E87) | I83: =IF($A83="","",Engine!G87) | M83: =IF($A83="","",Engine!J87)
A84: =IF(Engine!$J$87>0.005,Engine!A88,"") | B84: =IF($A84="","",Engine!B88) | D84: =IF($A84="","",G84+H84+I84+E84) | E84: =IF($A84="","",SUM(Engine!DP88:FM88)) | F84: =IF($A84="","",IF(E84>0.005,INDEX(Engine!$T$4:$BQ$4,Engine!K88),IF(H84>0,"Buffer first",""))) | G84: =IF($A84="","",SUM(Engine!BR88:DO88)) | H84: =IF($A84="","",Engine!E88) | I84: =IF($A84="","",Engine!G88) | M84: =IF($A84="","",Engine!J88)
A85: =IF(Engine!$J$88>0.005,Engine!A89,"") | B85: =IF($A85="","",Engine!B89) | D85: =IF($A85="","",G85+H85+I85+E85) | E85: =IF($A85="","",SUM(Engine!DP89:FM89)) | F85: =IF($A85="","",IF(E85>0.005,INDEX(Engine!$T$4:$BQ$4,Engine!K89),IF(H85>0,"Buffer first",""))) | G85: =IF($A85="","",SUM(Engine!BR89:DO89)) | H85: =IF($A85="","",Engine!E89) | I85: =IF($A85="","",Engine!G89) | M85: =IF($A85="","",Engine!J89)
A86: =IF(Engine!$J$89>0.005,Engine!A90,"") | B86: =IF($A86="","",Engine!B90) | D86: =IF($A86="","",G86+H86+I86+E86) | E86: =IF($A86="","",SUM(Engine!DP90:FM90)) | F86: =IF($A86="","",IF(E86>0.005,INDEX(Engine!$T$4:$BQ$4,Engine!K90),IF(H86>0,"Buffer first",""))) | G86: =IF($A86="","",SUM(Engine!BR90:DO90)) | H86: =IF($A86="","",Engine!E90) | I86: =IF($A86="","",Engine!G90) | M86: =IF($A86="","",Engine!J90)
A87: =IF(Engine!$J$90>0.005,Engine!A91,"") | B87: =IF($A87="","",Engine!B91) | D87: =IF($A87="","",G87+H87+I87+E87) | E87: =IF($A87="","",SUM(Engine!DP91:FM91)) | F87: =IF($A87="","",IF(E87>0.005,INDEX(Engine!$T$4:$BQ$4,Engine!K91),IF(H87>0,"Buffer first",""))) | G87: =IF($A87="","",SUM(Engine!BR91:DO91)) | H87: =IF($A87="","",Engine!E91) | I87: =IF($A87="","",Engine!G91) | M87: =IF($A87="","",Engine!J91)
A88: =IF(Engine!$J$91>0.005,Engine!A92,"") | B88: =IF($A88="","",Engine!B92) | D88: =IF($A88="","",G88+H88+I88+E88) | E88: =IF($A88="","",SUM(Engine!DP92:FM92)) | F88: =IF($A88="","",IF(E88>0.005,INDEX(Engine!$T$4:$BQ$4,Engine!K92),IF(H88>0,"Buffer first",""))) | G88: =IF($A88="","",SUM(Engine!BR92:DO92)) | H88: =IF($A88="","",Engine!E92) | I88: =IF($A88="","",Engine!G92) | M88: =IF($A88="","",Engine!J92)
A89: =IF(Engine!$J$92>0.005,Engine!A93,"") | B89: =IF($A89="","",Engine!B93) | D89: =IF($A89="","",G89+H89+I89+E89) | E89: =IF($A89="","",SUM(Engine!DP93:FM93)) | F89: =IF($A89="","",IF(E89>0.005,INDEX(Engine!$T$4:$BQ$4,Engine!K93),IF(H89>0,"Buffer first",""))) | G89: =IF($A89="","",SUM(Engine!BR93:DO93)) | H89: =IF($A89="","",Engine!E93) | I89: =IF($A89="","",Engine!G93) | M89: =IF($A89="","",Engine!J93)
A90: =IF(Engine!$J$93>0.005,Engine!A94,"") | B90: =IF($A90="","",Engine!B94) | D90: =IF($A90="","",G90+H90+I90+E90) | E90: =IF($A90="","",SUM(Engine!DP94:FM94)) | F90: =IF($A90="","",IF(E90>0.005,INDEX(Engine!$T$4:$BQ$4,Engine!K94),IF(H90>0,"Buffer first",""))) | G90: =IF($A90="","",SUM(Engine!BR94:DO94)) | H90: =IF($A90="","",Engine!E94) | I90: =IF($A90="","",Engine!G94) | M90: =IF($A90="","",Engine!J94)
A91: =IF(Engine!$J$94>0.005,Engine!A95,"") | B91: =IF($A91="","",Engine!B95) | D91: =IF($A91="","",G91+H91+I91+E91) | E91: =IF($A91="","",SUM(Engine!DP95:FM95)) | F91: =IF($A91="","",IF(E91>0.005,INDEX(Engine!$T$4:$BQ$4,Engine!K95),IF(H91>0,"Buffer first",""))) | G91: =IF($A91="","",SUM(Engine!BR95:DO95)) | H91: =IF($A91="","",Engine!E95) | I91: =IF($A91="","",Engine!G95) | M91: =IF($A91="","",Engine!J95)
A92: =IF(Engine!$J$95>0.005,Engine!A96,"") | B92: =IF($A92="","",Engine!B96) | D92: =IF($A92="","",G92+H92+I92+E92) | E92: =IF($A92="","",SUM(Engine!DP96:FM96)) | F92: =IF($A92="","",IF(E92>0.005,INDEX(Engine!$T$4:$BQ$4,Engine!K96),IF(H92>0,"Buffer first",""))) | G92: =IF($A92="","",SUM(Engine!BR96:DO96)) | H92: =IF($A92="","",Engine!E96) | I92: =IF($A92="","",Engine!G96) | M92: =IF($A92="","",Engine!J96)
A93: =IF(Engine!$J$96>0.005,Engine!A97,"") | B93: =IF($A93="","",Engine!B97) | D93: =IF($A93="","",G93+H93+I93+E93) | E93: =IF($A93="","",SUM(Engine!DP97:FM97)) | F93: =IF($A93="","",IF(E93>0.005,INDEX(Engine!$T$4:$BQ$4,Engine!K97),IF(H93>0,"Buffer first",""))) | G93: =IF($A93="","",SUM(Engine!BR97:DO97)) | H93: =IF($A93="","",Engine!E97) | I93: =IF($A93="","",Engine!G97) | M93: =IF($A93="","",Engine!J97)
A94: =IF(Engine!$J$97>0.005,Engine!A98,"") | B94: =IF($A94="","",Engine!B98) | D94: =IF($A94="","",G94+H94+I94+E94) | E94: =IF($A94="","",SUM(Engine!DP98:FM98)) | F94: =IF($A94="","",IF(E94>0.005,INDEX(Engine!$T$4:$BQ$4,Engine!K98),IF(H94>0,"Buffer first",""))) | G94: =IF($A94="","",SUM(Engine!BR98:DO98)) | H94: =IF($A94="","",Engine!E98) | I94: =IF($A94="","",Engine!G98) | M94: =IF($A94="","",Engine!J98)
A95: =IF(Engine!$J$98>0.005,Engine!A99,"") | B95: =IF($A95="","",Engine!B99) | D95: =IF($A95="","",G95+H95+I95+E95) | E95: =IF($A95="","",SUM(Engine!DP99:FM99)) | F95: =IF($A95="","",IF(E95>0.005,INDEX(Engine!$T$4:$BQ$4,Engine!K99),IF(H95>0,"Buffer first",""))) | G95: =IF($A95="","",SUM(Engine!BR99:DO99)) | H95: =IF($A95="","",Engine!E99) | I95: =IF($A95="","",Engine!G99) | M95: =IF($A95="","",Engine!J99)
A96: =IF(Engine!$J$99>0.005,Engine!A100,"") | B96: =IF($A96="","",Engine!B100) | D96: =IF($A96="","",G96+H96+I96+E96) | E96: =IF($A96="","",SUM(Engine!DP100:FM100)) | F96: =IF($A96="","",IF(E96>0.005,INDEX(Engine!$T$4:$BQ$4,Engine!K100),IF(H96>0,"Buffer first",""))) | G96: =IF($A96="","",SUM(Engine!BR100:DO100)) | H96: =IF($A96="","",Engine!E100) | I96: =IF($A96="","",Engine!G100) | M96: =IF($A96="","",Engine!J100)
A97: =IF(Engine!$J$100>0.005,Engine!A101,"") | B97: =IF($A97="","",Engine!B101) | D97: =IF($A97="","",G97+H97+I97+E97) | E97: =IF($A97="","",SUM(Engine!DP101:FM101)) | F97: =IF($A97="","",IF(E97>0.005,INDEX(Engine!$T$4:$BQ$4,Engine!K101),IF(H97>0,"Buffer first",""))) | G97: =IF($A97="","",SUM(Engine!BR101:DO101)) | H97: =IF($A97="","",Engine!E101) | I97: =IF($A97="","",Engine!G101) | M97: =IF($A97="","",Engine!J101)
A98: =IF(Engine!$J$101>0.005,Engine!A102,"") | B98: =IF($A98="","",Engine!B102) | D98: =IF($A98="","",G98+H98+I98+E98) | E98: =IF($A98="","",SUM(Engine!DP102:FM102)) | F98: =IF($A98="","",IF(E98>0.005,INDEX(Engine!$T$4:$BQ$4,Engine!K102),IF(H98>0,"Buffer first",""))) | G98: =IF($A98="","",SUM(Engine!BR102:DO102)) | H98: =IF($A98="","",Engine!E102) | I98: =IF($A98="","",Engine!G102) | M98: =IF($A98="","",Engine!J102)
A99: =IF(Engine!$J$102>0.005,Engine!A103,"") | B99: =IF($A99="","",Engine!B103) | D99: =IF($A99="","",G99+H99+I99+E99) | E99: =IF($A99="","",SUM(Engine!DP103:FM103)) | F99: =IF($A99="","",IF(E99>0.005,INDEX(Engine!$T$4:$BQ$4,Engine!K103),IF(H99>0,"Buffer first",""))) | G99: =IF($A99="","",SUM(Engine!BR103:DO103)) | H99: =IF($A99="","",Engine!E103) | I99: =IF($A99="","",Engine!G103) | M99: =IF($A99="","",Engine!J103)
A100: =IF(Engine!$J$103>0.005,Engine!A104,"") | B100: =IF($A100="","",Engine!B104) | D100: =IF($A100="","",G100+H100+I100+E100) | E100: =IF($A100="","",SUM(Engine!DP104:FM104)) | F100: =IF($A100="","",IF(E100>0.005,INDEX(Engine!$T$4:$BQ$4,Engine!K104),IF(H100>0,"Buffer first",""))) | G100: =IF($A100="","",SUM(Engine!BR104:DO104)) | H100: =IF($A100="","",Engine!E104) | I100: =IF($A100="","",Engine!G104) | M100: =IF($A100="","",Engine!J104)
A101: =IF(Engine!$J$104>0.005,Engine!A105,"") | B101: =IF($A101="","",Engine!B105) | D101: =IF($A101="","",G101+H101+I101+E101) | E101: =IF($A101="","",SUM(Engine!DP105:FM105)) | F101: =IF($A101="","",IF(E101>0.005,INDEX(Engine!$T$4:$BQ$4,Engine!K105),IF(H101>0,"Buffer first",""))) | G101: =IF($A101="","",SUM(Engine!BR105:DO105)) | H101: =IF($A101="","",Engine!E105) | I101: =IF($A101="","",Engine!G105) | M101: =IF($A101="","",Engine!J105)
A102: =IF(Engine!$J$105>0.005,Engine!A106,"") | B102: =IF($A102="","",Engine!B106) | D102: =IF($A102="","",G102+H102+I102+E102) | E102: =IF($A102="","",SUM(Engine!DP106:FM106)) | F102: =IF($A102="","",IF(E102>0.005,INDEX(Engine!$T$4:$BQ$4,Engine!K106),IF(H102>0,"Buffer first",""))) | G102: =IF($A102="","",SUM(Engine!BR106:DO106)) | H102: =IF($A102="","",Engine!E106) | I102: =IF($A102="","",Engine!G106) | M102: =IF($A102="","",Engine!J106)
...

Sheet Setup
B1: Setup
B2: Fill in the white cells. Everything else updates on its own.
B5: Currency symbol | C5: $ | D5: Any symbol works: $, £, €, MAD.
B6: How often you get paid | C6: Every 2 weeks | D6: Paid twice a month? Fill in your other payday below.
B7: Your next payday | C7: 46318 | D7: The plan starts here. Change it when you restart the plan.
B8: Money for the plan each payday | C8: 150 | D8: On top of your minimums. It pays yearly bills, then your buffer, then extra to debt.
B9: Buffer saved right now | C9: 200 | D9: Money set aside for surprises, in a plain separate account.
B10: Buffer goal | C10: 500 | D10: $500 is a good first goal. You can raise it later.
B11: Payoff order | C11: PaidInYellow order | D11: See Start Here for what each one does.
B12: Twice a month only: your other payday | D12: Day of the month, 1 to 31 (31 = last day). Example: paid on the 15th and the last day, next payday Oct 31: type 15.
B13: Paydays per year | C13: =IF(C6="Every week",52,IF(C6="Every 2 weeks",26,IF(C6="Twice a month",24,12)))
B14: Yearly bills, set aside per payday | C14: ='Yearly Bills'!E27
B15: Order number (used by the sheet) | C15: =IF(C11="Biggest interest first",2,IF(C11="My own order",3,1))
B16: Next payday as a day (31 = last day) | C16: =IF(C7=EOMONTH(C7,0),31,DAY(C7))
B17: Other payday used | C17: =IF(OR(N(C12)<1,N(C12)>31,N(C12)=C16),IF(C16<=15,C16+15,IF(C16=31,15,C16-15)),INT(C12))
B18: Earlier pay day | C18: =MIN(C16,C17)
B19: Later pay day | C19: =MAX(C16,C17)
B20: Next payday is the later one (1 = yes) | C20: =IF(C16=C18,0,1)

Sheet Debts
B1: Your debts
B2: Every debt, one per row. Balances as of today. The cream columns fill in by themselves.
B5: Name | C5: Type | D5: Balance | E5: Interest rate % | F5: Monthly minimum | G5: Due day | H5: My order | I5: Payoff order | J5: Paid off by | K5: Months at minimums only | L5: Interest at minimums only | M5: Interest per day | N5: key
B6: Visa | C6: Credit card | D6: 3200 | E6: 22.9 | F6: 96 | G6: 12 | I6: =IF(B6="","",RANK(N6,$N$6:$N$55,1)) | J6: =IF(B6="","",IF(N(D6)<=0,"Paid",IFERROR(INDEX(Engine!$B$10:$B$530,COUNTIF(INDEX(Engine!$T$10:$BQ$530,0,I6),">0.005")+1),"20+ years"))) | K6: =IF(B6="","",IF(N(D6)<=0,0,IF(F6<=D6*E6/1200,"Never",IF(N(E6)=0,ROUNDUP(D6/F6,0),ROUNDUP(NPER(E6/1200,-F6,D6),0))))) | L6: =IF(B6="","",IF(K6="Never","Never",IF(OR(N(E6)=0,N(D6)<=0),0,F6*NPER(E6/1200,-F6,D6)-D6))) | M6: =IF(B6="","",N(D6)*N(E6)/100/365) | N6: =IF(B6="",1E12+ROW(),CHOOSE(Setup!$C$15,IF(AND(N(E6)>0,F6<=D6*E6/1200),-1E9-E6,D6),-E6*1E6+D6/1E6,IF(H6="",1E6,H6)))+ROW()/1E7
B7: Store card | C7: Store card | D7: 640 | E7: 26.99 | F7: 35 | G7: 5 | I7: =IF(B7="","",RANK(N7,$N$6:$N$55,1)) | J7: =IF(B7="","",IF(N(D7)<=0,"Paid",IFERROR(INDEX(Engine!$B$10:$B$530,COUNTIF(INDEX(Engine!$T$10:$BQ$530,0,I7),">0.005")+1),"20+ years"))) | K7: =IF(B7="","",IF(N(D7)<=0,0,IF(F7<=D7*E7/1200,"Never",IF(N(E7)=0,ROUNDUP(D7/F7,0),ROUNDUP(NPER(E7/1200,-F7,D7),0))))) | L7: =IF(B7="","",IF(K7="Never","Never",IF(OR(N(E7)=0,N(D7)<=0),0,F7*NPER(E7/1200,-F7,D7)-D7))) | M7: =IF(B7="","",N(D7)*N(E7)/100/365) | N7: =IF(B7="",1E12+ROW(),CHOOSE(Setup!$C$15,IF(AND(N(E7)>0,F7<=D7*E7/1200),-1E9-E7,D7),-E7*1E6+D7/1E6,IF(H7="",1E6,H7)))+ROW()/1E7
B8: Car loan | C8: Car loan | D8: 9800 | E8: 7.5 | F8: 285 | G8: 20 | I8: =IF(B8="","",RANK(N8,$N$6:$N$55,1)) | J8: =IF(B8="","",IF(N(D8)<=0,"Paid",IFERROR(INDEX(Engine!$B$10:$B$530,COUNTIF(INDEX(Engine!$T$10:$BQ$530,0,I8),">0.005")+1),"20+ years"))) | K8: =IF(B8="","",IF(N(D8)<=0,0,IF(F8<=D8*E8/1200,"Never",IF(N(E8)=0,ROUNDUP(D8/F8,0),ROUNDUP(NPER(E8/1200,-F8,D8),0))))) | L8: =IF(B8="","",IF(K8="Never","Never",IF(OR(N(E8)=0,N(D8)<=0),0,F8*NPER(E8/1200,-F8,D8)-D8))) | M8: =IF(B8="","",N(D8)*N(E8)/100/365) | N8: =IF(B8="",1E12+ROW(),CHOOSE(Setup!$C$15,IF(AND(N(E8)>0,F8<=D8*E8/1200),-1E9-E8,D8),-E8*1E6+D8/1E6,IF(H8="",1E6,H8)))+ROW()/1E7
B9: Medical bill | C9: Medical | D9: 1150 | E9: 0 | F9: 50 | G9: 1 | I9: =IF(B9="","",RANK(N9,$N$6:$N$55,1)) | J9: =IF(B9="","",IF(N(D9)<=0,"Paid",IFERROR(INDEX(Engine!$B$10:$B$530,COUNTIF(INDEX(Engine!$T$10:$BQ$530,0,I9),">0.005")+1),"20+ years"))) | K9: =IF(B9="","",IF(N(D9)<=0,0,IF(F9<=D9*E9/1200,"Never",IF(N(E9)=0,ROUNDUP(D9/F9,0),ROUNDUP(NPER(E9/1200,-F9,D9),0))))) | L9: =IF(B9="","",IF(K9="Never","Never",IF(OR(N(E9)=0,N(D9)<=0),0,F9*NPER(E9/1200,-F9,D9)-D9))) | M9: =IF(B9="","",N(D9)*N(E9)/100/365) | N9: =IF(B9="",1E12+ROW(),CHOOSE(Setup!$C$15,IF(AND(N(E9)>0,F9<=D9*E9/1200),-1E9-E9,D9),-E9*1E6+D9/1E6,IF(H9="",1E6,H9)))+ROW()/1E7
I10: =IF(B10="","",RANK(N10,$N$6:$N$55,1)) | J10: =IF(B10="","",IF(N(D10)<=0,"Paid",IFERROR(INDEX(Engine!$B$10:$B$530,COUNTIF(INDEX(Engine!$T$10:$BQ$530,0,I10),">0.005")+1),"20+ years"))) | K10: =IF(B10="","",IF(N(D10)<=0,0,IF(F10<=D10*E10/1200,"Never",IF(N(E10)=0,ROUNDUP(D10/F10,0),ROUNDUP(NPER(E10/1200,-F10,D10),0))))) | L10: =IF(B10="","",IF(K10="Never","Never",IF(OR(N(E10)=0,N(D10)<=0),0,F10*NPER(E10/1200,-F10,D10)-D10))) | M10: =IF(B10="","",N(D10)*N(E10)/100/365) | N10: =IF(B10="",1E12+ROW(),CHOOSE(Setup!$C$15,IF(AND(N(E10)>0,F10<=D10*E10/1200),-1E9-E10,D10),-E10*1E6+D10/1E6,IF(H10="",1E6,H10)))+ROW()/1E7
I11: =IF(B11="","",RANK(N11,$N$6:$N$55,1)) | J11: =IF(B11="","",IF(N(D11)<=0,"Paid",IFERROR(INDEX(Engine!$B$10:$B$530,COUNTIF(INDEX(Engine!$T$10:$BQ$530,0,I11),">0.005")+1),"20+ years"))) | K11: =IF(B11="","",IF(N(D11)<=0,0,IF(F11<=D11*E11/1200,"Never",IF(N(E11)=0,ROUNDUP(D11/F11,0),ROUNDUP(NPER(E11/1200,-F11,D11),0))))) | L11: =IF(B11="","",IF(K11="Never","Never",IF(OR(N(E11)=0,N(D11)<=0),0,F11*NPER(E11/1200,-F11,D11)-D11))) | M11: =IF(B11="","",N(D11)*N(E11)/100/365) | N11: =IF(B11="",1E12+ROW(),CHOOSE(Setup!$C$15,IF(AND(N(E11)>0,F11<=D11*E11/1200),-1E9-E11,D11),-E11*1E6+D11/1E6,IF(H11="",1E6,H11)))+ROW()/1E7
I12: =IF(B12="","",RANK(N12,$N$6:$N$55,1)) | J12: =IF(B12="","",IF(N(D12)<=0,"Paid",IFERROR(INDEX(Engine!$B$10:$B$530,COUNTIF(INDEX(Engine!$T$10:$BQ$530,0,I12),">0.005")+1),"20+ years"))) | K12: =IF(B12="","",IF(N(D12)<=0,0,IF(F12<=D12*E12/1200,"Never",IF(N(E12)=0,ROUNDUP(D12/F12,0),ROUNDUP(NPER(E12/1200,-F12,D12),0))))) | L12: =IF(B12="","",IF(K12="Never","Never",IF(OR(N(E12)=0,N(D12)<=0),0,F12*NPER(E12/1200,-F12,D12)-D12))) | M12: =IF(B12="","",N(D12)*N(E12)/100/365) | N12: =IF(B12="",1E12+ROW(),CHOOSE(Setup!$C$15,IF(AND(N(E12)>0,F12<=D12*E12/1200),-1E9-E12,D12),-E12*1E6+D12/1E6,IF(H12="",1E6,H12)))+ROW()/1E7
I13: =IF(B13="","",RANK(N13,$N$6:$N$55,1)) | J13: =IF(B13="","",IF(N(D13)<=0,"Paid",IFERROR(INDEX(Engine!$B$10:$B$530,COUNTIF(INDEX(Engine!$T$10:$BQ$530,0,I13),">0.005")+1),"20+ years"))) | K13: =IF(B13="","",IF(N(D13)<=0,0,IF(F13<=D13*E13/1200,"Never",IF(N(E13)=0,ROUNDUP(D13/F13,0),ROUNDUP(NPER(E13/1200,-F13,D13),0))))) | L13: =IF(B13="","",IF(K13="Never","Never",IF(OR(N(E13)=0,N(D13)<=0),0,F13*NPER(E13/1200,-F13,D13)-D13))) | M13: =IF(B13="","",N(D13)*N(E13)/100/365) | N13: =IF(B13="",1E12+ROW(),CHOOSE(Setup!$C$15,IF(AND(N(E13)>0,F13<=D13*E13/1200),-1E9-E13,D13),-E13*1E6+D13/1E6,IF(H13="",1E6,H13)))+ROW()/1E7
I14: =IF(B14="","",RANK(N14,$N$6:$N$55,1)) | J14: =IF(B14="","",IF(N(D14)<=0,"Paid",IFERROR(INDEX(Engine!$B$10:$B$530,COUNTIF(INDEX(Engine!$T$10:$BQ$530,0,I14),">0.005")+1),"20+ years"))) | K14: =IF(B14="","",IF(N(D14)<=0,0,IF(F14<=D14*E14/1200,"Never",IF(N(E14)=0,ROUNDUP(D14/F14,0),ROUNDUP(NPER(E14/1200,-F14,D14),0))))) | L14: =IF(B14="","",IF(K14="Never","Never",IF(OR(N(E14)=0,N(D14)<=0),0,F14*NPER(E14/1200,-F14,D14)-D14))) | M14: =IF(B14="","",N(D14)*N(E14)/100/365) | N14: =IF(B14="",1E12+ROW(),CHOOSE(Setup!$C$15,IF(AND(N(E14)>0,F14<=D14*E14/1200),-1E9-E14,D14),-E14*1E6+D14/1E6,IF(H14="",1E6,H14)))+ROW()/1E7
I15: =IF(B15="","",RANK(N15,$N$6:$N$55,1)) | J15: =IF(B15="","",IF(N(D15)<=0,"Paid",IFERROR(INDEX(Engine!$B$10:$B$530,COUNTIF(INDEX(Engine!$T$10:$BQ$530,0,I15),">0.005")+1),"20+ years"))) | K15: =IF(B15="","",IF(N(D15)<=0,0,IF(F15<=D15*E15/1200,"Never",IF(N(E15)=0,ROUNDUP(D15/F15,0),ROUNDUP(NPER(E15/1200,-F15,D15),0))))) | L15: =IF(B15="","",IF(K15="Never","Never",IF(OR(N(E15)=0,N(D15)<=0),0,F15*NPER(E15/1200,-F15,D15)-D15))) | M15: =IF(B15="","",N(D15)*N(E15)/100/365) | N15: =IF(B15="",1E12+ROW(),CHOOSE(Setup!$C$15,IF(AND(N(E15)>0,F15<=D15*E15/1200),-1E9-E15,D15),-E15*1E6+D15/1E6,IF(H15="",1E6,H15)))+ROW()/1E7
I16: =IF(B16="","",RANK(N16,$N$6:$N$55,1)) | J16: =IF(B16="","",IF(N(D16)<=0,"Paid",IFERROR(INDEX(Engine!$B$10:$B$530,COUNTIF(INDEX(Engine!$T$10:$BQ$530,0,I16),">0.005")+1),"20+ years"))) | K16: =IF(B16="","",IF(N(D16)<=0,0,IF(F16<=D16*E16/1200,"Never",IF(N(E16)=0,ROUNDUP(D16/F16,0),ROUNDUP(NPER(E16/1200,-F16,D16),0))))) | L16: =IF(B16="","",IF(K16="Never","Never",IF(OR(N(E16)=0,N(D16)<=0),0,F16*NPER(E16/1200,-F16,D16)-D16))) | M16: =IF(B16="","",N(D16)*N(E16)/100/365) | N16: =IF(B16="",1E12+ROW(),CHOOSE(Setup!$C$15,IF(AND(N(E16)>0,F16<=D16*E16/1200),-1E9-E16,D16),-E16*1E6+D16/1E6,IF(H16="",1E6,H16)))+ROW()/1E7
I17: =IF(B17="","",RANK(N17,$N$6:$N$55,1)) | J17: =IF(B17="","",IF(N(D17)<=0,"Paid",IFERROR(INDEX(Engine!$B$10:$B$530,COUNTIF(INDEX(Engine!$T$10:$BQ$530,0,I17),">0.005")+1),"20+ years"))) | K17: =IF(B17="","",IF(N(D17)<=0,0,IF(F17<=D17*E17/1200,"Never",IF(N(E17)=0,ROUNDUP(D17/F17,0),ROUNDUP(NPER(E17/1200,-F17,D17),0))))) | L17: =IF(B17="","",IF(K17="Never","Never",IF(OR(N(E17)=0,N(D17)<=0),0,F17*NPER(E17/1200,-F17,D17)-D17))) | M17: =IF(B17="","",N(D17)*N(E17)/100/365) | N17: =IF(B17="",1E12+ROW(),CHOOSE(Setup!$C$15,IF(AND(N(E17)>0,F17<=D17*E17/1200),-1E9-E17,D17),-E17*1E6+D17/1E6,IF(H17="",1E6,H17)))+ROW()/1E7
I18: =IF(B18="","",RANK(N18,$N$6:$N$55,1)) | J18: =IF(B18="","",IF(N(D18)<=0,"Paid",IFERROR(INDEX(Engine!$B$10:$B$530,COUNTIF(INDEX(Engine!$T$10:$BQ$530,0,I18),">0.005")+1),"20+ years"))) | K18: =IF(B18="","",IF(N(D18)<=0,0,IF(F18<=D18*E18/1200,"Never",IF(N(E18)=0,ROUNDUP(D18/F18,0),ROUNDUP(NPER(E18/1200,-F18,D18),0))))) | L18: =IF(B18="","",IF(K18="Never","Never",IF(OR(N(E18)=0,N(D18)<=0),0,F18*NPER(E18/1200,-F18,D18)-D18))) | M18: =IF(B18="","",N(D18)*N(E18)/100/365) | N18: =IF(B18="",1E12+ROW(),CHOOSE(Setup!$C$15,IF(AND(N(E18)>0,F18<=D18*E18/1200),-1E9-E18,D18),-E18*1E6+D18/1E6,IF(H18="",1E6,H18)))+ROW()/1E7
I19: =IF(B19="","",RANK(N19,$N$6:$N$55,1)) | J19: =IF(B19="","",IF(N(D19)<=0,"Paid",IFERROR(INDEX(Engine!$B$10:$B$530,COUNTIF(INDEX(Engine!$T$10:$BQ$530,0,I19),">0.005")+1),"20+ years"))) | K19: =IF(B19="","",IF(N(D19)<=0,0,IF(F19<=D19*E19/1200,"Never",IF(N(E19)=0,ROUNDUP(D19/F19,0),ROUNDUP(NPER(E19/1200,-F19,D19),0))))) | L19: =IF(B19="","",IF(K19="Never","Never",IF(OR(N(E19)=0,N(D19)<=0),0,F19*NPER(E19/1200,-F19,D19)-D19))) | M19: =IF(B19="","",N(D19)*N(E19)/100/365) | N19: =IF(B19="",1E12+ROW(),CHOOSE(Setup!$C$15,IF(AND(N(E19)>0,F19<=D19*E19/1200),-1E9-E19,D19),-E19*1E6+D19/1E6,IF(H19="",1E6,H19)))+ROW()/1E7
I20: =IF(B20="","",RANK(N20,$N$6:$N$55,1)) | J20: =IF(B20="","",IF(N(D20)<=0,"Paid",IFERROR(INDEX(Engine!$B$10:$B$530,COUNTIF(INDEX(Engine!$T$10:$BQ$530,0,I20),">0.005")+1),"20+ years"))) | K20: =IF(B20="","",IF(N(D20)<=0,0,IF(F20<=D20*E20/1200,"Never",IF(N(E20)=0,ROUNDUP(D20/F20,0),ROUNDUP(NPER(E20/1200,-F20,D20),0))))) | L20: =IF(B20="","",IF(K20="Never","Never",IF(OR(N(E20)=0,N(D20)<=0),0,F20*NPER(E20/1200,-F20,D20)-D20))) | M20: =IF(B20="","",N(D20)*N(E20)/100/365) | N20: =IF(B20="",1E12+ROW(),CHOOSE(Setup!$C$15,IF(AND(N(E20)>0,F20<=D20*E20/1200),-1E9-E20,D20),-E20*1E6+D20/1E6,IF(H20="",1E6,H20)))+ROW()/1E7
I21: =IF(B21="","",RANK(N21,$N$6:$N$55,1)) | J21: =IF(B21="","",IF(N(D21)<=0,"Paid",IFERROR(INDEX(Engine!$B$10:$B$530,COUNTIF(INDEX(Engine!$T$10:$BQ$530,0,I21),">0.005")+1),"20+ years"))) | K21: =IF(B21="","",IF(N(D21)<=0,0,IF(F21<=D21*E21/1200,"Never",IF(N(E21)=0,ROUNDUP(D21/F21,0),ROUNDUP(NPER(E21/1200,-F21,D21),0))))) | L21: =IF(B21="","",IF(K21="Never","Never",IF(OR(N(E21)=0,N(D21)<=0),0,F21*NPER(E21/1200,-F21,D21)-D21))) | M21: =IF(B21="","",N(D21)*N(E21)/100/365) | N21: =IF(B21="",1E12+ROW(),CHOOSE(Setup!$C$15,IF(AND(N(E21)>0,F21<=D21*E21/1200),-1E9-E21,D21),-E21*1E6+D21/1E6,IF(H21="",1E6,H21)))+ROW()/1E7
... I55: =IF(B55="","",RANK(N55,$N$6:$N$55,1)) | J55: =IF(B55="","",IF(N(D55)<=0,"Paid",IFERROR(INDEX(Engine!$B$10:$B$530,COUNTIF(INDEX(Engine!$T$10:$BQ$530,0,I55),">0.005")+1),"20+ years"))) | K55: =IF(B55="","",IF(N(D55)<=0,0,IF(F55<=D55*E55/1200,"Never",IF(N(E55)=0,ROUNDUP(D55/F55,0),ROUNDUP(NPER(E55/1200,-F55,D55),0))))) | L55: =IF(B55="","",IF(K55="Never","Never",IF(OR(N(E55)=0,N(D55)<=0),0,F55*NPER(E55/1200,-F55,D55)-D55))) | M55: =IF(B55="","",N(D55)*N(E55)/100/365) | N55: =IF(B55="",1E12+ROW(),CHOOSE(Setup!$C$15,IF(AND(N(E55)>0,F55<=D55*E55/1200),-1E9-E55,D55),-E55*1E6+D55/1E6,IF(H55="",1E6,H55)))+ROW()/1E7
B57: Total | D57: =SUM(D6:D55) | F57: =SUM(F6:F55) | M57: =SUM(M6:M55)
B58: "Never" means paying only the minimum never clears that balance. If the debt also charges interest, it grows, and the PaidInYellow order puts it first.

Sheet Yearly Bills
B1: Yearly bills
B2: Bills you know are coming, just not every month. A little per payday means they stop being surprises.
B5: Bill | C5: Cost per year | D5: Month it's due | E5: Set aside per payday | F5: Saved so far
B6: Car repairs | C6: 600 | D6: Any time | E6: =IF(N(C6)=0,"",C6/Setup!$C$13)
B7: Gifts and holidays | C7: 500 | D7: December | E7: =IF(N(C7)=0,"",C7/Setup!$C$13)
E8: =IF(N(C8)=0,"",C8/Setup!$C$13)
E9: =IF(N(C9)=0,"",C9/Setup!$C$13)
E10: =IF(N(C10)=0,"",C10/Setup!$C$13)
E11: =IF(N(C11)=0,"",C11/Setup!$C$13)
E12: =IF(N(C12)=0,"",C12/Setup!$C$13)
E13: =IF(N(C13)=0,"",C13/Setup!$C$13)
E14: =IF(N(C14)=0,"",C14/Setup!$C$13)
E15: =IF(N(C15)=0,"",C15/Setup!$C$13)
E16: =IF(N(C16)=0,"",C16/Setup!$C$13)
E17: =IF(N(C17)=0,"",C17/Setup!$C$13)
E18: =IF(N(C18)=0,"",C18/Setup!$C$13)
E19: =IF(N(C19)=0,"",C19/Setup!$C$13)
... E25: =IF(N(C25)=0,"",C25/Setup!$C$13)
B27: Total | C27: =SUM(C6:C25) | E27: =SUM(E6:E25) | F27: =SUM(F6:F25)
B29: Keep this money in the same plain separate account as your buffer, or a second one if that helps you leave it alone.

Sheet Compare
B1: Compare
B2: Your plan next to paying only the minimums.
C5: ="Your plan ("&Setup!$C$11&")" | D5: Minimums only
B6: Debt-free by | C6: =Dashboard!B5 | D6: =IF(COUNTIF(Debts!$K$6:$K$55,"Never")>0,"Never",EDATE(Setup!$C$7,MAX(Debts!$K$6:$K$55)))
B7: Months to go | C7: =IFERROR(ROUND((Engine!$B$2)*12/Setup!$C$13,0),"") | D7: =IF(COUNTIF(Debts!$K$6:$K$55,"Never")>0,"Never",MAX(Debts!$K$6:$K$55))
B8: Total interest | C8: =SUM(Engine!$I$11:$I$530) | D8: =IF(COUNTIF(Debts!$L$6:$L$55,"Never")>0,"Never ends",SUM(Debts!$L$6:$L$55))
B10: Want to compare payoff orders? Change "Payoff order" on Setup and write down what you see.
B12: Payoff order | C12: Debt-free by | D12: Total interest
B13: PaidInYellow order
B14: Biggest interest first
B15: My own order
B17: If the gap is small, pick the order you'll stick with. Clearing a small debt early keeps many people going.
B19: Your payoff order
B20: Debt | C20: Balance today | D20: Paid off by | E20: Order
B21: =Engine!T$4 | C21: =IF(B21="","",Engine!T$5) | D21: =IF(B21="","",IF(Engine!T$5<=0,"Paid",IFERROR(INDEX(Engine!$B$10:$B$530,COUNTIF(Engine!T$10:T$530,">0.005")+1),"20+ years"))) | E21: =IF(B21="","",1)
B22: =Engine!U$4 | C22: =IF(B22="","",Engine!U$5) | D22: =IF(B22="","",IF(Engine!U$5<=0,"Paid",IFERROR(INDEX(Engine!$B$10:$B$530,COUNTIF(Engine!U$10:U$530,">0.005")+1),"20+ years"))) | E22: =IF(B22="","",2)
B23: =Engine!V$4 | C23: =IF(B23="","",Engine!V$5) | D23: =IF(B23="","",IF(Engine!V$5<=0,"Paid",IFERROR(INDEX(Engine!$B$10:$B$530,COUNTIF(Engine!V$10:V$530,">0.005")+1),"20+ years"))) | E23: =IF(B23="","",3)
B24: =Engine!W$4 | C24: =IF(B24="","",Engine!W$5) | D24: =IF(B24="","",IF(Engine!W$5<=0,"Paid",IFERROR(INDEX(Engine!$B$10:$B$530,COUNTIF(Engine!W$10:W$530,">0.005")+1),"20+ years"))) | E24: =IF(B24="","",4)
B25: =Engine!X$4 | C25: =IF(B25="","",Engine!X$5) | D25: =IF(B25="","",IF(Engine!X$5<=0,"Paid",IFERROR(INDEX(Engine!$B$10:$B$530,COUNTIF(Engine!X$10:X$530,">0.005")+1),"20+ years"))) | E25: =IF(B25="","",5)
B26: =Engine!Y$4 | C26: =IF(B26="","",Engine!Y$5) | D26: =IF(B26="","",IF(Engine!Y$5<=0,"Paid",IFERROR(INDEX(Engine!$B$10:$B$530,COUNTIF(Engine!Y$10:Y$530,">0.005")+1),"20+ years"))) | E26: =IF(B26="","",6)
B27: =Engine!Z$4 | C27: =IF(B27="","",Engine!Z$5) | D27: =IF(B27="","",IF(Engine!Z$5<=0,"Paid",IFERROR(INDEX(Engine!$B$10:$B$530,COUNTIF(Engine!Z$10:Z$530,">0.005")+1),"20+ years"))) | E27: =IF(B27="","",7)
B28: =Engine!AA$4 | C28: =IF(B28="","",Engine!AA$5) | D28: =IF(B28="","",IF(Engine!AA$5<=0,"Paid",IFERROR(INDEX(Engine!$B$10:$B$530,COUNTIF(Engine!AA$10:AA$530,">0.005")+1),"20+ years"))) | E28: =IF(B28="","",8)
B29: =Engine!AB$4 | C29: =IF(B29="","",Engine!AB$5) | D29: =IF(B29="","",IF(Engine!AB$5<=0,"Paid",IFERROR(INDEX(Engine!$B$10:$B$530,COUNTIF(Engine!AB$10:AB$530,">0.005")+1),"20+ years"))) | E29: =IF(B29="","",9)
B30: =Engine!AC$4 | C30: =IF(B30="","",Engine!AC$5) | D30: =IF(B30="","",IF(Engine!AC$5<=0,"Paid",IFERROR(INDEX(Engine!$B$10:$B$530,COUNTIF(Engine!AC$10:AC$530,">0.005")+1),"20+ years"))) | E30: =IF(B30="","",10)
B31: =Engine!AD$4 | C31: =IF(B31="","",Engine!AD$5) | D31: =IF(B31="","",IF(Engine!AD$5<=0,"Paid",IFERROR(INDEX(Engine!$B$10:$B$530,COUNTIF(Engine!AD$10:AD$530,">0.005")+1),"20+ years"))) | E31: =IF(B31="","",11)
B32: =Engine!AE$4 | C32: =IF(B32="","",Engine!AE$5) | D32: =IF(B32="","",IF(Engine!AE$5<=0,"Paid",IFERROR(INDEX(Engine!$B$10:$B$530,COUNTIF(Engine!AE$10:AE$530,">0.005")+1),"20+ years"))) | E32: =IF(B32="","",12)
B33: =Engine!AF$4 | C33: =IF(B33="","",Engine!AF$5) | D33: =IF(B33="","",IF(Engine!AF$5<=0,"Paid",IFERROR(INDEX(Engine!$B$10:$B$530,COUNTIF(Engine!AF$10:AF$530,">0.005")+1),"20+ years"))) | E33: =IF(B33="","",13)
B34: =Engine!AG$4 | C34: =IF(B34="","",Engine!AG$5) | D34: =IF(B34="","",IF(Engine!AG$5<=0,"Paid",IFERROR(INDEX(Engine!$B$10:$B$530,COUNTIF(Engine!AG$10:AG$530,">0.005")+1),"20+ years"))) | E34: =IF(B34="","",14)
B35: =Engine!AH$4 | C35: =IF(B35="","",Engine!AH$5) | D35: =IF(B35="","",IF(Engine!AH$5<=0,"Paid",IFERROR(INDEX(Engine!$B$10:$B$530,COUNTIF(Engine!AH$10:AH$530,">0.005")+1),"20+ years"))) | E35: =IF(B35="","",15)
B36: =Engine!AI$4 | C36: =IF(B36="","",Engine!AI$5) | D36: =IF(B36="","",IF(Engine!AI$5<=0,"Paid",IFERROR(INDEX(Engine!$B$10:$B$530,COUNTIF(Engine!AI$10:AI$530,">0.005")+1),"20+ years"))) | E36: =IF(B36="","",16)
B37: =Engine!AJ$4 | C37: =IF(B37="","",Engine!AJ$5) | D37: =IF(B37="","",IF(Engine!AJ$5<=0,"Paid",IFERROR(INDEX(Engine!$B$10:$B$530,COUNTIF(Engine!AJ$10:AJ$530,">0.005")+1),"20+ years"))) | E37: =IF(B37="","",17)
B38: =Engine!AK$4 | C38: =IF(B38="","",Engine!AK$5) | D38: =IF(B38="","",IF(Engine!AK$5<=0,"Paid",IFERROR(INDEX(Engine!$B$10:$B$530,COUNTIF(Engine!AK$10:AK$530,">0.005")+1),"20+ years"))) | E38: =IF(B38="","",18)
B39: =Engine!AL$4 | C39: =IF(B39="","",Engine!AL$5) | D39: =IF(B39="","",IF(Engine!AL$5<=0,"Paid",IFERROR(INDEX(Engine!$B$10:$B$530,COUNTIF(Engine!AL$10:AL$530,">0.005")+1),"20+ years"))) | E39: =IF(B39="","",19)
B40: =Engine!AM$4 | C40: =IF(B40="","",Engine!AM$5) | D40: =IF(B40="","",IF(Engine!AM$5<=0,"Paid",IFERROR(INDEX(Engine!$B$10:$B$530,COUNTIF(Engine!AM$10:AM$530,">0.005")+1),"20+ years"))) | E40: =IF(B40="","",20)
B41: =Engine!AN$4 | C41: =IF(B41="","",Engine!AN$5) | D41: =IF(B41="","",IF(Engine!AN$5<=0,"Paid",IFERROR(INDEX(Engine!$B$10:$B$530,COUNTIF(Engine!AN$10:AN$530,">0.005")+1),"20+ years"))) | E41: =IF(B41="","",21)
B42: =Engine!AO$4 | C42: =IF(B42="","",Engine!AO$5) | D42: =IF(B42="","",IF(Engine!AO$5<=0,"Paid",IFERROR(INDEX(Engine!$B$10:$B$530,COUNTIF(Engine!AO$10:AO$530,">0.005")+1),"20+ years"))) | E42: =IF(B42="","",22)
B43: =Engine!AP$4 | C43: =IF(B43="","",Engine!AP$5) | D43: =IF(B43="","",IF(Engine!AP$5<=0,"Paid",IFERROR(INDEX(Engine!$B$10:$B$530,COUNTIF(Engine!AP$10:AP$530,">0.005")+1),"20+ years"))) | E43: =IF(B43="","",23)
B44: =Engine!AQ$4 | C44: =IF(B44="","",Engine!AQ$5) | D44: =IF(B44="","",IF(Engine!AQ$5<=0,"Paid",IFERROR(INDEX(Engine!$B$10:$B$530,COUNTIF(Engine!AQ$10:AQ$530,">0.005")+1),"20+ years"))) | E44: =IF(B44="","",24)
B45: =Engine!AR$4 | C45: =IF(B45="","",Engine!AR$5) | D45: =IF(B45="","",IF(Engine!AR$5<=0,"Paid",IFERROR(INDEX(Engine!$B$10:$B$530,COUNTIF(Engine!AR$10:AR$530,">0.005")+1),"20+ years"))) | E45: =IF(B45="","",25)
B46: =Engine!AS$4 | C46: =IF(B46="","",Engine!AS$5) | D46: =IF(B46="","",IF(Engine!AS$5<=0,"Paid",IFERROR(INDEX(Engine!$B$10:$B$530,COUNTIF(Engine!AS$10:AS$530,">0.005")+1),"20+ years"))) | E46: =IF(B46="","",26)
B47: =Engine!AT$4 | C47: =IF(B47="","",Engine!AT$5) | D47: =IF(B47="","",IF(Engine!AT$5<=0,"Paid",IFERROR(INDEX(Engine!$B$10:$B$530,COUNTIF(Engine!AT$10:AT$530,">0.005")+1),"20+ years"))) | E47: =IF(B47="","",27)
B48: =Engine!AU$4 | C48: =IF(B48="","",Engine!AU$5) | D48: =IF(B48="","",IF(Engine!AU$5<=0,"Paid",IFERROR(INDEX(Engine!$B$10:$B$530,COUNTIF(Engine!AU$10:AU$530,">0.005")+1),"20+ years"))) | E48: =IF(B48="","",28)
B49: =Engine!AV$4 | C49: =IF(B49="","",Engine!AV$5) | D49: =IF(B49="","",IF(Engine!AV$5<=0,"Paid",IFERROR(INDEX(Engine!$B$10:$B$530,COUNTIF(Engine!AV$10:AV$530,">0.005")+1),"20+ years"))) | E49: =IF(B49="","",29)
B50: =Engine!AW$4 | C50: =IF(B50="","",Engine!AW$5) | D50: =IF(B50="","",IF(Engine!AW$5<=0,"Paid",IFERROR(INDEX(Engine!$B$10:$B$530,COUNTIF(Engine!AW$10:AW$530,">0.005")+1),"20+ years"))) | E50: =IF(B50="","",30)
B51: =Engine!AX$4 | C51: =IF(B51="","",Engine!AX$5) | D51: =IF(B51="","",IF(Engine!AX$5<=0,"Paid",IFERROR(INDEX(Engine!$B$10:$B$530,COUNTIF(Engine!AX$10:AX$530,">0.005")+1),"20+ years"))) | E51: =IF(B51="","",31)
B52: =Engine!AY$4 | C52: =IF(B52="","",Engine!AY$5) | D52: =IF(B52="","",IF(Engine!AY$5<=0,"Paid",IFERROR(INDEX(Engine!$B$10:$B$530,COUNTIF(Engine!AY$10:AY$530,">0.005")+1),"20+ years"))) | E52: =IF(B52="","",32)
B53: =Engine!AZ$4 | C53: =IF(B53="","",Engine!AZ$5) | D53: =IF(B53="","",IF(Engine!AZ$5<=0,"Paid",IFERROR(INDEX(Engine!$B$10:$B$530,COUNTIF(Engine!AZ$10:AZ$530,">0.005")+1),"20+ years"))) | E53: =IF(B53="","",33)
B54: =Engine!BA$4 | C54: =IF(B54="","",Engine!BA$5) | D54: =IF(B54="","",IF(Engine!BA$5<=0,"Paid",IFERROR(INDEX(Engine!$B$10:$B$530,COUNTIF(Engine!BA$10:BA$530,">0.005")+1),"20+ years"))) | E54: =IF(B54="","",34)
B55: =Engine!BB$4 | C55: =IF(B55="","",Engine!BB$5) | D55: =IF(B55="","",IF(Engine!BB$5<=0,"Paid",IFERROR(INDEX(Engine!$B$10:$B$530,COUNTIF(Engine!BB$10:BB$530,">0.005")+1),"20+ years"))) | E55: =IF(B55="","",35)
B56: =Engine!BC$4 | C56: =IF(B56="","",Engine!BC$5) | D56: =IF(B56="","",IF(Engine!BC$5<=0,"Paid",IFERROR(INDEX(Engine!$B$10:$B$530,COUNTIF(Engine!BC$10:BC$530,">0.005")+1),"20+ years"))) | E56: =IF(B56="","",36)
B57: =Engine!BD$4 | C57: =IF(B57="","",Engine!BD$5) | D57: =IF(B57="","",IF(Engine!BD$5<=0,"Paid",IFERROR(INDEX(Engine!$B$10:$B$530,COUNTIF(Engine!BD$10:BD$530,">0.005")+1),"20+ years"))) | E57: =IF(B57="","",37)
B58: =Engine!BE$4 | C58: =IF(B58="","",Engine!BE$5) | D58: =IF(B58="","",IF(Engine!BE$5<=0,"Paid",IFERROR(INDEX(Engine!$B$10:$B$530,COUNTIF(Engine!BE$10:BE$530,">0.005")+1),"20+ years"))) | E58: =IF(B58="","",38)
B59: =Engine!BF$4 | C59: =IF(B59="","",Engine!BF$5) | D59: =IF(B59="","",IF(Engine!BF$5<=0,"Paid",IFERROR(INDEX(Engine!$B$10:$B$530,COUNTIF(Engine!BF$10:BF$530,">0.005")+1),"20+ years"))) | E59: =IF(B59="","",39)
B60: =Engine!BG$4 | C60: =IF(B60="","",Engine!BG$5) | D60: =IF(B60="","",IF(Engine!BG$5<=0,"Paid",IFERROR(INDEX(Engine!$B$10:$B$530,COUNTIF(Engine!BG$10:BG$530,">0.005")+1),"20+ years"))) | E60: =IF(B60="","",40)
B61: =Engine!BH$4 | C61: =IF(B61="","",Engine!BH$5) | D61: =IF(B61="","",IF(Engine!BH$5<=0,"Paid",IFERROR(INDEX(Engine!$B$10:$B$530,COUNTIF(Engine!BH$10:BH$530,">0.005")+1),"20+ years"))) | E61: =IF(B61="","",41)
B62: =Engine!BI$4 | C62: =IF(B62="","",Engine!BI$5) | D62: =IF(B62="","",IF(Engine!BI$5<=0,"Paid",IFERROR(INDEX(Engine!$B$10:$B$530,COUNTIF(Engine!BI$10:BI$530,">0.005")+1),"20+ years"))) | E62: =IF(B62="","",42)
B63: =Engine!BJ$4 | C63: =IF(B63="","",Engine!BJ$5) | D63: =IF(B63="","",IF(Engine!BJ$5<=0,"Paid",IFERROR(INDEX(Engine!$B$10:$B$530,COUNTIF(Engine!BJ$10:BJ$530,">0.005")+1),"20+ years"))) | E63: =IF(B63="","",43)
B64: =Engine!BK$4 | C64: =IF(B64="","",Engine!BK$5) | D64: =IF(B64="","",IF(Engine!BK$5<=0,"Paid",IFERROR(INDEX(Engine!$B$10:$B$530,COUNTIF(Engine!BK$10:BK$530,">0.005")+1),"20+ years"))) | E64: =IF(B64="","",44)
B65: =Engine!BL$4 | C65: =IF(B65="","",Engine!BL$5) | D65: =IF(B65="","",IF(Engine!BL$5<=0,"Paid",IFERROR(INDEX(Engine!$B$10:$B$530,COUNTIF(Engine!BL$10:BL$530,">0.005")+1),"20+ years"))) | E65: =IF(B65="","",45)
B66: =Engine!BM$4 | C66: =IF(B66="","",Engine!BM$5) | D66: =IF(B66="","",IF(Engine!BM$5<=0,"Paid",IFERROR(INDEX(Engine!$B$10:$B$530,COUNTIF(Engine!BM$10:BM$530,">0.005")+1),"20+ years"))) | E66: =IF(B66="","",46)
B67: =Engine!BN$4 | C67: =IF(B67="","",Engine!BN$5) | D67: =IF(B67="","",IF(Engine!BN$5<=0,"Paid",IFERROR(INDEX(Engine!$B$10:$B$530,COUNTIF(Engine!BN$10:BN$530,">0.005")+1),"20+ years"))) | E67: =IF(B67="","",47)
B68: =Engine!BO$4 | C68: =IF(B68="","",Engine!BO$5) | D68: =IF(B68="","",IF(Engine!BO$5<=0,"Paid",IFERROR(INDEX(Engine!$B$10:$B$530,COUNTIF(Engine!BO$10:BO$530,">0.005")+1),"20+ years"))) | E68: =IF(B68="","",48)
B69: =Engine!BP$4 | C69: =IF(B69="","",Engine!BP$5) | D69: =IF(B69="","",IF(Engine!BP$5<=0,"Paid",IFERROR(INDEX(Engine!$B$10:$B$530,COUNTIF(Engine!BP$10:BP$530,">0.005")+1),"20+ years"))) | E69: =IF(B69="","",49)
B70: =Engine!BQ$4 | C70: =IF(B70="","",Engine!BQ$5) | D70: =IF(B70="","",IF(Engine!BQ$5<=0,"Paid",IFERROR(INDEX(Engine!$B$10:$B$530,COUNTIF(Engine!BQ$10:BQ$530,">0.005")+1),"20+ years"))) | E70: =IF(B70="","",50)

Sheet Engine
A1: Paid paydays | B1: =COUNTIF('Paycheck Plan'!$C$7:$C$526,"Paid") | C1: Next index | D1: =B1+1
A2: Debt-free row | B2: =COUNTIF($J$10:$J$530,">0.005")
S3: debts row | T3: =MATCH(SMALL(Debts!$N$6:$N$55,1),Debts!$N$6:$N$55,0) | U3: =MATCH(SMALL(Debts!$N$6:$N$55,2),Debts!$N$6:$N$55,0) | V3: =MATCH(SMALL(Debts!$N$6:$N$55,3),Debts!$N$6:$N$55,0) | W3: =MATCH(SMALL(Debts!$N$6:$N$55,4),Debts!$N$6:$N$55,0) | X3: =MATCH(SMALL(Debts!$N$6:$N$55,5),Debts!$N$6:$N$55,0) | Y3: =MATCH(SMALL(Debts!$N$6:$N$55,6),Debts!$N$6:$N$55,0) | Z3: =MATCH(SMALL(Debts!$N$6:$N$55,7),Debts!$N$6:$N$55,0) | AA3: =MATCH(SMALL(Debts!$N$6:$N$55,8),Debts!$N$6:$N$55,0) | AB3: =MATCH(SMALL(Debts!$N$6:$N$55,9),Debts!$N$6:$N$55,0) | AC3: =MATCH(SMALL(Debts!$N$6:$N$55,10),Debts!$N$6:$N$55,0) | AD3: =MATCH(SMALL(Debts!$N$6:$N$55,11),Debts!$N$6:$N$55,0) | AE3: =MATCH(SMALL(Debts!$N$6:$N$55,12),Debts!$N$6:$N$55,0) | AF3: =MATCH(SMALL(Debts!$N$6:$N$55,13),Debts!$N$6:$N$55,0) | AG3: =MATCH(SMALL(Debts!$N$6:$N$55,14),Debts!$N$6:$N$55,0) | AH3: =MATCH(SMALL(Debts!$N$6:$N$55,15),Debts!$N$6:$N$55,0) | AI3: =MATCH(SMALL(Debts!$N$6:$N$55,16),Debts!$N$6:$N$55,0) | AJ3: =MATCH(SMALL(Debts!$N$6:$N$55,17),Debts!$N$6:$N$55,0) | AK3: =MATCH(SMALL(Debts!$N$6:$N$55,18),Debts!$N$6:$N$55,0) | AL3: =MATCH(SMALL(Debts!$N$6:$N$55,19),Debts!$N$6:$N$55,0) | AM3: =MATCH(SMALL(Debts!$N$6:$N$55,20),Debts!$N$6:$N$55,0) | AN3: =MATCH(SMALL(Debts!$N$6:$N$55,21),Debts!$N$6:$N$55,0) | AO3: =MATCH(SMALL(Debts!$N$6:$N$55,22),Debts!$N$6:$N$55,0) | AP3: =MATCH(SMALL(Debts!$N$6:$N$55,23),Debts!$N$6:$N$55,0) | AQ3: =MATCH(SMALL(Debts!$N$6:$N$55,24),Debts!$N$6:$N$55,0) | AR3: =MATCH(SMALL(Debts!$N$6:$N$55,25),Debts!$N$6:$N$55,0) | AS3: =MATCH(SMALL(Debts!$N$6:$N$55,26),Debts!$N$6:$N$55,0) | AT3: =MATCH(SMALL(Debts!$N$6:$N$55,27),Debts!$N$6:$N$55,0) | AU3: =MATCH(SMALL(Debts!$N$6:$N$55,28),Debts!$N$6:$N$55,0) | AV3: =MATCH(SMALL(Debts!$N$6:$N$55,29),Debts!$N$6:$N$55,0) | AW3: =MATCH(SMALL(Debts!$N$6:$N$55,30),Debts!$N$6:$N$55,0) | AX3: =MATCH(SMALL(Debts!$N$6:$N$55,31),Debts!$N$6:$N$55,0) | AY3: =MATCH(SMALL(Debts!$N$6:$N$55,32),Debts!$N$6:$N$55,0) | AZ3: =MATCH(SMALL(Debts!$N$6:$N$55,33),Debts!$N$6:$N$55,0) | BA3: =MATCH(SMALL(Debts!$N$6:$N$55,34),Debts!$N$6:$N$55,0) | BB3: =MATCH(SMALL(Debts!$N$6:$N$55,35),Debts!$N$6:$N$55,0) | BC3: =MATCH(SMALL(Debts!$N$6:$N$55,36),Debts!$N$6:$N$55,0) | BD3: =MATCH(SMALL(Debts!$N$6:$N$55,37),Debts!$N$6:$N$55,0) | BE3: =MATCH(SMALL(Debts!$N$6:$N$55,38),Debts!$N$6:$N$55,0) | BF3: =MATCH(SMALL(Debts!$N$6:$N$55,39),Debts!$N$6:$N$55,0) | BG3: =MATCH(SMALL(Debts!$N$6:$N$55,40),Debts!$N$6:$N$55,0) | BH3: =MATCH(SMALL(Debts!$N$6:$N$55,41),Debts!$N$6:$N$55,0) | BI3: =MATCH(SMALL(Debts!$N$6:$N$55,42),Debts!$N$6:$N$55,0) | BJ3: =MATCH(SMALL(Debts!$N$6:$N$55,43),Debts!$N$6:$N$55,0) | BK3: =MATCH(SMALL(Debts!$N$6:$N$55,44),Debts!$N$6:$N$55,0) | BL3: =MATCH(SMALL(Debts!$N$6:$N$55,45),Debts!$N$6:$N$55,0) | BM3: =MATCH(SMALL(Debts!$N$6:$N$55,46),Debts!$N$6:$N$55,0) | BN3: =MATCH(SMALL(Debts!$N$6:$N$55,47),Debts!$N$6:$N$55,0) | BO3: =MATCH(SMALL(Debts!$N$6:$N$55,48),Debts!$N$6:$N$55,0) | BP3: =MATCH(SMALL(Debts!$N$6:$N$55,49),Debts!$N$6:$N$55,0) | BQ3: =MATCH(SMALL(Debts!$N$6:$N$55,50),Debts!$N$6:$N$55,0)
S4: name | T4: =IF(INDEX(Debts!$B$6:$B$55,T3)="","",INDEX(Debts!$B$6:$B$55,T3)&"") | U4: =IF(INDEX(Debts!$B$6:$B$55,U3)="","",INDEX(Debts!$B$6:$B$55,U3)&"") | V4: =IF(INDEX(Debts!$B$6:$B$55,V3)="","",INDEX(Debts!$B$6:$B$55,V3)&"") | W4: =IF(INDEX(Debts!$B$6:$B$55,W3)="","",INDEX(Debts!$B$6:$B$55,W3)&"") | X4: =IF(INDEX(Debts!$B$6:$B$55,X3)="","",INDEX(Debts!$B$6:$B$55,X3)&"") | Y4: =IF(INDEX(Debts!$B$6:$B$55,Y3)="","",INDEX(Debts!$B$6:$B$55,Y3)&"") | Z4: =IF(INDEX(Debts!$B$6:$B$55,Z3)="","",INDEX(Debts!$B$6:$B$55,Z3)&"") | AA4: =IF(INDEX(Debts!$B$6:$B$55,AA3)="","",INDEX(Debts!$B$6:$B$55,AA3)&"") | ... BQ4: =IF(INDEX(Debts!$B$6:$B$55,BQ3)="","",INDEX(Debts!$B$6:$B$55,BQ3)&"")
S5: start balance | T5: =N(INDEX(Debts!$D$6:$D$55,T3)) | U5: =N(INDEX(Debts!$D$6:$D$55,U3)) | V5: =N(INDEX(Debts!$D$6:$D$55,V3)) | W5: =N(INDEX(Debts!$D$6:$D$55,W3)) | X5: =N(INDEX(Debts!$D$6:$D$55,X3)) | Y5: =N(INDEX(Debts!$D$6:$D$55,Y3)) | Z5: =N(INDEX(Debts!$D$6:$D$55,Z3)) | AA5: =N(INDEX(Debts!$D$6:$D$55,AA3)) | ... BQ5: =N(INDEX(Debts!$D$6:$D$55,BQ3))
S6: rate (decimal) | T6: =N(INDEX(Debts!$E$6:$E$55,T3))/100 | U6: =N(INDEX(Debts!$E$6:$E$55,U3))/100 | V6: =N(INDEX(Debts!$E$6:$E$55,V3))/100 | W6: =N(INDEX(Debts!$E$6:$E$55,W3))/100 | X6: =N(INDEX(Debts!$E$6:$E$55,X3))/100 | Y6: =N(INDEX(Debts!$E$6:$E$55,Y3))/100 | Z6: =N(INDEX(Debts!$E$6:$E$55,Z3))/100 | AA6: =N(INDEX(Debts!$E$6:$E$55,AA3))/100 | ... BQ6: =N(INDEX(Debts!$E$6:$E$55,BQ3))/100
S7: minimum per payday | T7: =N(INDEX(Debts!$F$6:$F$55,T3))*12/Setup!$C$13 | U7: =N(INDEX(Debts!$F$6:$F$55,U3))*12/Setup!$C$13 | V7: =N(INDEX(Debts!$F$6:$F$55,V3))*12/Setup!$C$13 | W7: =N(INDEX(Debts!$F$6:$F$55,W3))*12/Setup!$C$13 | X7: =N(INDEX(Debts!$F$6:$F$55,X3))*12/Setup!$C$13 | Y7: =N(INDEX(Debts!$F$6:$F$55,Y3))*12/Setup!$C$13 | Z7: =N(INDEX(Debts!$F$6:$F$55,Z3))*12/Setup!$C$13 | AA7: =N(INDEX(Debts!$F$6:$F$55,AA3))*12/Setup!$C$13 | ... BQ7: =N(INDEX(Debts!$F$6:$F$55,BQ3))*12/Setup!$C$13
A9: n | B9: date | C9: adj | D9: charges | E9: to buffer | F9: buffer | G9: yearly | H9: pot | I9: interest | J9: total | K9: focus rank | M9: chart idx | N9: chart date | O9: chart debt left | T9: balances by rank | BR9: minimum paid | DP9: extra paid
A10: 0 | B10: =Setup!$C$7-ROUND(365/Setup!$C$13,0) | F10: =Setup!$C$9 | J10: =SUM(T10:BQ10) | T10: =T5 | U10: =U5 | V10: =V5 | W10: =W5 | X10: =X5 | Y10: =Y5 | Z10: =Z5 | AA10: =AA5 | ... BQ10: =BQ5
A11: =A10+1 | B11: =IF(Setup!$C$6="Every week",Setup!$C$7+7*(A11-1),IF(Setup!$C$6="Every 2 weeks",Setup!$C$7+14*(A11-1),IF(Setup!$C$6="Every month",EDATE(Setup!$C$7,A11-1),EOMONTH(Setup!$C$7,INT((A11-1+Setup!$C$20)/2)-1)+MIN(IF(MOD(A11-1+Setup!$C$20,2)=0,Setup!$C$18,Setup!$C$19),DAY(EOMONTH(Setup!$C$7,INT((A11-1+Setup!$C$20)/2))))))) | C11: =N('Paycheck Plan'!J7) | D11: =N('Paycheck Plan'!K7) | E11: =MIN(MAX(0,Setup!$C$10-F10),MAX(0,Setup!$C$8+C11-G11)) | F11: =F10+E11 | G11: =MIN(Setup!$C$14,MAX(0,Setup!$C$8+C11)) | H11: =MAX(0,Setup!$C$8+C11-G11-E11)+SUM($T$7:$BQ$7)-SUM(BR11:DO11) | I11: =SUMPRODUCT(T10:BQ10,$T$6:$BQ$6)/Setup!$C$13 | J11: =SUM(T11:BQ11) | K11: =IF(MAX(DP11:FM11)>0,MATCH(MAX(DP11:FM11),DP11:FM11,0),1) | M11: =ROUND(0*$B$2/39,0)+1 | N11: =INDEX($B$10:$B$530,MIN(M11,521)) | O11: =INDEX($J$10:$J$530,MIN(M11,521)) | T11: =MAX(0,T10*(1+T$6/Setup!$C$13)-BR11-DP11)+IF($K11=1,$D11,0) | U11: =MAX(0,U10*(1+U$6/Setup!$C$13)-BS11-DQ11)+IF($K11=2,$D11,0) | V11: =MAX(0,V10*(1+V$6/Setup!$C$13)-BT11-DR11)+IF($K11=3,$D11,0) | W11: =MAX(0,W10*(1+W$6/Setup!$C$13)-BU11-DS11)+IF($K11=4,$D11,0) | X11: =MAX(0,X10*(1+X$6/Setup!$C$13)-BV11-DT11)+IF($K11=5,$D11,0) | Y11: =MAX(0,Y10*(1+Y$6/Setup!$C$13)-BW11-DU11)+IF($K11=6,$D11,0) | Z11: =MAX(0,Z10*(1+Z$6/Setup!$C$13)-BX11-DV11)+IF($K11=7,$D11,0) | AA11: =MAX(0,AA10*(1+AA$6/Setup!$C$13)-BY11-DW11)+IF($K11=8,$D11,0) | AB11: =MAX(0,AB10*(1+AB$6/Setup!$C$13)-BZ11-DX11)+IF($K11=9,$D11,0) | AC11: =MAX(0,AC10*(1+AC$6/Setup!$C$13)-CA11-DY11)+IF($K11=10,$D11,0) | AD11: =MAX(0,AD10*(1+AD$6/Setup!$C$13)-CB11-DZ11)+IF($K11=11,$D11,0) | AE11: =MAX(0,AE10*(1+AE$6/Setup!$C$13)-CC11-EA11)+IF($K11=12,$D11,0) | AF11: =MAX(0,AF10*(1+AF$6/Setup!$C$13)-CD11-EB11)+IF($K11=13,$D11,0) | AG11: =MAX(0,AG10*(1+AG$6/Setup!$C$13)-CE11-EC11)+IF($K11=14,$D11,0) | AH11: =MAX(0,AH10*(1+AH$6/Setup!$C$13)-CF11-ED11)+IF($K11=15,$D11,0) | AI11: =MAX(0,AI10*(1+AI$6/Setup!$C$13)-CG11-EE11)+IF($K11=16,$D11,0) | AJ11: =MAX(0,AJ10*(1+AJ$6/Setup!$C$13)-CH11-EF11)+IF($K11=17,$D11,0) | AK11: =MAX(0,AK10*(1+AK$6/Setup!$C$13)-CI11-EG11)+IF($K11=18,$D11,0) | AL11: =MAX(0,AL10*(1+AL$6/Setup!$C$13)-CJ11-EH11)+IF($K11=19,$D11,0) | AM11: =MAX(0,AM10*(1+AM$6/Setup!$C$13)-CK11-EI11)+IF($K11=20,$D11,0) | AN11: =MAX(0,AN10*(1+AN$6/Setup!$C$13)-CL11-EJ11)+IF($K11=21,$D11,0) | AO11: =MAX(0,AO10*(1+AO$6/Setup!$C$13)-CM11-EK11)+IF($K11=22,$D11,0) | AP11: =MAX(0,AP10*(1+AP$6/Setup!$C$13)-CN11-EL11)+IF($K11=23,$D11,0) | AQ11: =MAX(0,AQ10*(1+AQ$6/Setup!$C$13)-CO11-EM11)+IF($K11=24,$D11,0) | AR11: =MAX(0,AR10*(1+AR$6/Setup!$C$13)-CP11-EN11)+IF($K11=25,$D11,0) | AS11: =MAX(0,AS10*(1+AS$6/Setup!$C$13)-CQ11-EO11)+IF($K11=26,$D11,0) | AT11: =MAX(0,AT10*(1+AT$6/Setup!$C$13)-CR11-EP11)+IF($K11=27,$D11,0) | AU11: =MAX(0,AU10*(1+AU$6/Setup!$C$13)-CS11-EQ11)+IF($K11=28,$D11,0) | AV11: =MAX(0,AV10*(1+AV$6/Setup!$C$13)-CT11-ER11)+IF($K11=29,$D11,0) | AW11: =MAX(0,AW10*(1+AW$6/Setup!$C$13)-CU11-ES11)+IF($K11=30,$D11,0) | AX11: =MAX(0,AX10*(1+AX$6/Setup!$C$13)-CV11-ET11)+IF($K11=31,$D11,0) | AY11: =MAX(0,AY10*(1+AY$6/Setup!$C$13)-CW11-EU11)+IF($K11=32,$D11,0) | AZ11: =MAX(0,AZ10*(1+AZ$6/Setup!$C$13)-CX11-EV11)+IF($K11=33,$D11,0) | BA11: =MAX(0,BA10*(1+BA$6/Setup!$C$13)-CY11-EW11)+IF($K11=34,$D11,0) | BB11: =MAX(0,BB10*(1+BB$6/Setup!$C$13)-CZ11-EX11)+IF($K11=35,$D11,0) | BC11: =MAX(0,BC10*(1+BC$6/Setup!$C$13)-DA11-EY11)+IF($K11=36,$D11,0) | BD11: =MAX(0,BD10*(1+BD$6/Setup!$C$13)-DB11-EZ11)+IF($K11=37,$D11,0) | BE11: =MAX(0,BE10*(1+BE$6/Setup!$C$13)-DC11-FA11)+IF($K11=38,$D11,0) | BF11: =MAX(0,BF10*(1+BF$6/Setup!$C$13)-DD11-FB11)+IF($K11=39,$D11,0) | BG11: =MAX(0,BG10*(1+BG$6/Setup!$C$13)-DE11-FC11)+IF($K11=40,$D11,0) | BH11: =MAX(0,BH10*(1+BH$6/Setup!$C$13)-DF11-FD11)+IF($K11=41,$D11,0) | BI11: =MAX(0,BI10*(1+BI$6/Setup!$C$13)-DG11-FE11)+IF($K11=42,$D11,0) | BJ11: =MAX(0,BJ10*(1+BJ$6/Setup!$C$13)-DH11-FF11)+IF($K11=43,$D11,0) | BK11: =MAX(0,BK10*(1+BK$6/Setup!$C$13)-DI11-FG11)+IF($K11=44,$D11,0) | BL11: =MAX(0,BL10*(1+BL$6/Setup!$C$13)-DJ11-FH11)+IF($K11=45,$D11,0) | BM11: =MAX(0,BM10*(1+BM$6/Setup!$C$13)-DK11-FI11)+IF($K11=46,$D11,0) | BN11: =MAX(0,BN10*(1+BN$6/Setup!$C$13)-DL11-FJ11)+IF($K11=47,$D11,0) | BO11: =MAX(0,BO10*(1+BO$6/Setup!$C$13)-DM11-FK11)+IF($K11=48,$D11,0) | BP11: =MAX(0,BP10*(1+BP$6/Setup!$C$13)-DN11-FL11)+IF($K11=49,$D11,0) | BQ11: =MAX(0,BQ10*(1+BQ$6/Setup!$C$13)-DO11-FM11)+IF($K11=50,$D11,0) | BR11: =MIN(T10*(1+T$6/Setup!$C$13),T$7) | BS11: =MIN(U10*(1+U$6/Setup!$C$13),U$7) | BT11: =MIN(V10*(1+V$6/Setup!$C$13),V$7) | BU11: =MIN(W10*(1+W$6/Setup!$C$13),W$7) | BV11: =MIN(X10*(1+X$6/Setup!$C$13),X$7) | BW11: =MIN(Y10*(1+Y$6/Setup!$C$13),Y$7) | BX11: =MIN(Z10*(1+Z$6/Setup!$C$13),Z$7) | BY11: =MIN(AA10*(1+AA$6/Setup!$C$13),AA$7) | ... DO11: =MIN(BQ10*(1+BQ$6/Setup!$C$13),BQ$7) | DP11: =MIN(T10*(1+T$6/Setup!$C$13)-BR11,$H11) | DQ11: =MIN(U10*(1+U$6/Setup!$C$13)-BS11,MAX(0,$H11-SUM($DP11:DP11))) | DR11: =MIN(V10*(1+V$6/Setup!$C$13)-BT11,MAX(0,$H11-SUM($DP11:DQ11))) | DS11: =MIN(W10*(1+W$6/Setup!$C$13)-BU11,MAX(0,$H11-SUM($DP11:DR11))) | DT11: =MIN(X10*(1+X$6/Setup!$C$13)-BV11,MAX(0,$H11-SUM($DP11:DS11))) | DU11: =MIN(Y10*(1+Y$6/Setup!$C$13)-BW11,MAX(0,$H11-SUM($DP11:DT11))) | DV11: =MIN(Z10*(1+Z$6/Setup!$C$13)-BX11,MAX(0,$H11-SUM($DP11:DU11))) | DW11: =MIN(AA10*(1+AA$6/Setup!$C$13)-BY11,MAX(0,$H11-SUM($DP11:DV11))) | DX11: =MIN(AB10*(1+AB$6/Setup!$C$13)-BZ11,MAX(0,$H11-SUM($DP11:DW11))) | ... FM11: =MIN(BQ10*(1+BQ$6/Setup!$C$13)-DO11,MAX(0,$H11-SUM($DP11:FL11)))
A12: =A11+1 | B12: =IF(Setup!$C$6="Every week",Setup!$C$7+7*(A12-1),IF(Setup!$C$6="Every 2 weeks",Setup!$C$7+14*(A12-1),IF(Setup!$C$6="Every month",EDATE(Setup!$C$7,A12-1),EOMONTH(Setup!$C$7,INT((A12-1+Setup!$C$20)/2)-1)+MIN(IF(MOD(A12-1+Setup!$C$20,2)=0,Setup!$C$18,Setup!$C$19),DAY(EOMONTH(Setup!$C$7,INT((A12-1+Setup!$C$20)/2))))))) | C12: =N('Paycheck Plan'!J8) | D12: =N('Paycheck Plan'!K8) | E12: =MIN(MAX(0,Setup!$C$10-F11),MAX(0,Setup!$C$8+C12-G12)) | F12: =F11+E12 | G12: =MIN(Setup!$C$14,MAX(0,Setup!$C$8+C12)) | H12: =MAX(0,Setup!$C$8+C12-G12-E12)+SUM($T$7:$BQ$7)-SUM(BR12:DO12) | I12: =SUMPRODUCT(T11:BQ11,$T$6:$BQ$6)/Setup!$C$13 | J12: =SUM(T12:BQ12) | K12: =IF(MAX(DP12:FM12)>0,MATCH(MAX(DP12:FM12),DP12:FM12,0),1) | M12: =ROUND(1*$B$2/39,0)+1 | N12: =INDEX($B$10:$B$530,MIN(M12,521)) | O12: =INDEX($J$10:$J$530,MIN(M12,521)) | T12: =MAX(0,T11*(1+T$6/Setup!$C$13)-BR12-DP12)+IF($K12=1,$D12,0) | U12: =MAX(0,U11*(1+U$6/Setup!$C$13)-BS12-DQ12)+IF($K12=2,$D12,0) | V12: =MAX(0,V11*(1+V$6/Setup!$C$13)-BT12-DR12)+IF($K12=3,$D12,0) | W12: =MAX(0,W11*(1+W$6/Setup!$C$13)-BU12-DS12)+IF($K12=4,$D12,0) | X12: =MAX(0,X11*(1+X$6/Setup!$C$13)-BV12-DT12)+IF($K12=5,$D12,0) | Y12: =MAX(0,Y11*(1+Y$6/Setup!$C$13)-BW12-DU12)+IF($K12=6,$D12,0) | Z12: =MAX(0,Z11*(1+Z$6/Setup!$C$13)-BX12-DV12)+IF($K12=7,$D12,0) | AA12: =MAX(0,AA11*(1+AA$6/Setup!$C$13)-BY12-DW12)+IF($K12=8,$D12,0) | AB12: =MAX(0,AB11*(1+AB$6/Setup!$C$13)-BZ12-DX12)+IF($K12=9,$D12,0) | AC12: =MAX(0,AC11*(1+AC$6/Setup!$C$13)-CA12-DY12)+IF($K12=10,$D12,0) | AD12: =MAX(0,AD11*(1+AD$6/Setup!$C$13)-CB12-DZ12)+IF($K12=11,$D12,0) | AE12: =MAX(0,AE11*(1+AE$6/Setup!$C$13)-CC12-EA12)+IF($K12=12,$D12,0) | AF12: =MAX(0,AF11*(1+AF$6/Setup!$C$13)-CD12-EB12)+IF($K12=13,$D12,0) | AG12: =MAX(0,AG11*(1+AG$6/Setup!$C$13)-CE12-EC12)+IF($K12=14,$D12,0) | AH12: =MAX(0,AH11*(1+AH$6/Setup!$C$13)-CF12-ED12)+IF($K12=15,$D12,0) | AI12: =MAX(0,AI11*(1+AI$6/Setup!$C$13)-CG12-EE12)+IF($K12=16,$D12,0) | AJ12: =MAX(0,AJ11*(1+AJ$6/Setup!$C$13)-CH12-EF12)+IF($K12=17,$D12,0) | AK12: =MAX(0,AK11*(1+AK$6/Setup!$C$13)-CI12-EG12)+IF($K12=18,$D12,0) | AL12: =MAX(0,AL11*(1+AL$6/Setup!$C$13)-CJ12-EH12)+IF($K12=19,$D12,0) | AM12: =MAX(0,AM11*(1+AM$6/Setup!$C$13)-CK12-EI12)+IF($K12=20,$D12,0) | AN12: =MAX(0,AN11*(1+AN$6/Setup!$C$13)-CL12-EJ12)+IF($K12=21,$D12,0) | AO12: =MAX(0,AO11*(1+AO$6/Setup!$C$13)-CM12-EK12)+IF($K12=22,$D12,0) | AP12: =MAX(0,AP11*(1+AP$6/Setup!$C$13)-CN12-EL12)+IF($K12=23,$D12,0) | AQ12: =MAX(0,AQ11*(1+AQ$6/Setup!$C$13)-CO12-EM12)+IF($K12=24,$D12,0) | AR12: =MAX(0,AR11*(1+AR$6/Setup!$C$13)-CP12-EN12)+IF($K12=25,$D12,0) | AS12: =MAX(0,AS11*(1+AS$6/Setup!$C$13)-CQ12-EO12)+IF($K12=26,$D12,0) | AT12: =MAX(0,AT11*(1+AT$6/Setup!$C$13)-CR12-EP12)+IF($K12=27,$D12,0) | AU12: =MAX(0,AU11*(1+AU$6/Setup!$C$13)-CS12-EQ12)+IF($K12=28,$D12,0) | AV12: =MAX(0,AV11*(1+AV$6/Setup!$C$13)-CT12-ER12)+IF($K12=29,$D12,0) | AW12: =MAX(0,AW11*(1+AW$6/Setup!$C$13)-CU12-ES12)+IF($K12=30,$D12,0) | AX12: =MAX(0,AX11*(1+AX$6/Setup!$C$13)-CV12-ET12)+IF($K12=31,$D12,0) | AY12: =MAX(0,AY11*(1+AY$6/Setup!$C$13)-CW12-EU12)+IF($K12=32,$D12,0) | AZ12: =MAX(0,AZ11*(1+AZ$6/Setup!$C$13)-CX12-EV12)+IF($K12=33,$D12,0) | BA12: =MAX(0,BA11*(1+BA$6/Setup!$C$13)-CY12-EW12)+IF($K12=34,$D12,0) | BB12: =MAX(0,BB11*(1+BB$6/Setup!$C$13)-CZ12-EX12)+IF($K12=35,$D12,0) | BC12: =MAX(0,BC11*(1+BC$6/Setup!$C$13)-DA12-EY12)+IF($K12=36,$D12,0) | BD12: =MAX(0,BD11*(1+BD$6/Setup!$C$13)-DB12-EZ12)+IF($K12=37,$D12,0) | BE12: =MAX(0,BE11*(1+BE$6/Setup!$C$13)-DC12-FA12)+IF($K12=38,$D12,0) | BF12: =MAX(0,BF11*(1+BF$6/Setup!$C$13)-DD12-FB12)+IF($K12=39,$D12,0) | BG12: =MAX(0,BG11*(1+BG$6/Setup!$C$13)-DE12-FC12)+IF($K12=40,$D12,0) | BH12: =MAX(0,BH11*(1+BH$6/Setup!$C$13)-DF12-FD12)+IF($K12=41,$D12,0) | BI12: =MAX(0,BI11*(1+BI$6/Setup!$C$13)-DG12-FE12)+IF($K12=42,$D12,0) | BJ12: =MAX(0,BJ11*(1+BJ$6/Setup!$C$13)-DH12-FF12)+IF($K12=43,$D12,0) | BK12: =MAX(0,BK11*(1+BK$6/Setup!$C$13)-DI12-FG12)+IF($K12=44,$D12,0) | BL12: =MAX(0,BL11*(1+BL$6/Setup!$C$13)-DJ12-FH12)+IF($K12=45,$D12,0) | BM12: =MAX(0,BM11*(1+BM$6/Setup!$C$13)-DK12-FI12)+IF($K12=46,$D12,0) | BN12: =MAX(0,BN11*(1+BN$6/Setup!$C$13)-DL12-FJ12)+IF($K12=47,$D12,0) | BO12: =MAX(0,BO11*(1+BO$6/Setup!$C$13)-DM12-FK12)+IF($K12=48,$D12,0) | BP12: =MAX(0,BP11*(1+BP$6/Setup!$C$13)-DN12-FL12)+IF($K12=49,$D12,0) | BQ12: =MAX(0,BQ11*(1+BQ$6/Setup!$C$13)-DO12-FM12)+IF($K12=50,$D12,0) | BR12: =MIN(T11*(1+T$6/Setup!$C$13),T$7) | BS12: =MIN(U11*(1+U$6/Setup!$C$13),U$7) | BT12: =MIN(V11*(1+V$6/Setup!$C$13),V$7) | BU12: =MIN(W11*(1+W$6/Setup!$C$13),W$7) | BV12: =MIN(X11*(1+X$6/Setup!$C$13),X$7) | BW12: =MIN(Y11*(1+Y$6/Setup!$C$13),Y$7) | BX12: =MIN(Z11*(1+Z$6/Setup!$C$13),Z$7) | BY12: =MIN(AA11*(1+AA$6/Setup!$C$13),AA$7) | ... DO12: =MIN(BQ11*(1+BQ$6/Setup!$C$13),BQ$7) | DP12: =MIN(T11*(1+T$6/Setup!$C$13)-BR12,$H12) | DQ12: =MIN(U11*(1+U$6/Setup!$C$13)-BS12,MAX(0,$H12-SUM($DP12:DP12))) | DR12: =MIN(V11*(1+V$6/Setup!$C$13)-BT12,MAX(0,$H12-SUM($DP12:DQ12))) | DS12: =MIN(W11*(1+W$6/Setup!$C$13)-BU12,MAX(0,$H12-SUM($DP12:DR12))) | DT12: =MIN(X11*(1+X$6/Setup!$C$13)-BV12,MAX(0,$H12-SUM($DP12:DS12))) | DU12: =MIN(Y11*(1+Y$6/Setup!$C$13)-BW12,MAX(0,$H12-SUM($DP12:DT12))) | DV12: =MIN(Z11*(1+Z$6/Setup!$C$13)-BX12,MAX(0,$H12-SUM($DP12:DU12))) | DW12: =MIN(AA11*(1+AA$6/Setup!$C$13)-BY12,MAX(0,$H12-SUM($DP12:DV12))) | DX12: =MIN(AB11*(1+AB$6/Setup!$C$13)-BZ12,MAX(0,$H12-SUM($DP12:DW12))) | ... FM12: =MIN(BQ11*(1+BQ$6/Setup!$C$13)-DO12,MAX(0,$H12-SUM($DP12:FL12)))
A13: =A12+1 | B13: =IF(Setup!$C$6="Every week",Setup!$C$7+7*(A13-1),IF(Setup!$C$6="Every 2 weeks",Setup!$C$7+14*(A13-1),IF(Setup!$C$6="Every month",EDATE(Setup!$C$7,A13-1),EOMONTH(Setup!$C$7,INT((A13-1+Setup!$C$20)/2)-1)+MIN(IF(MOD(A13-1+Setup!$C$20,2)=0,Setup!$C$18,Setup!$C$19),DAY(EOMONTH(Setup!$C$7,INT((A13-1+Setup!$C$20)/2))))))) | C13: =N('Paycheck Plan'!J9) | D13: =N('Paycheck Plan'!K9) | E13: =MIN(MAX(0,Setup!$C$10-F12),MAX(0,Setup!$C$8+C13-G13)) | F13: =F12+E13 | G13: =MIN(Setup!$C$14,MAX(0,Setup!$C$8+C13)) | H13: =MAX(0,Setup!$C$8+C13-G13-E13)+SUM($T$7:$BQ$7)-SUM(BR13:DO13) | I13: =SUMPRODUCT(T12:BQ12,$T$6:$BQ$6)/Setup!$C$13 | J13: =SUM(T13:BQ13) | K13: =IF(MAX(DP13:FM13)>0,MATCH(MAX(DP13:FM13),DP13:FM13,0),1) | M13: =ROUND(2*$B$2/39,0)+1 | N13: =INDEX($B$10:$B$530,MIN(M13,521)) | O13: =INDEX($J$10:$J$530,MIN(M13,521)) | T13: =MAX(0,T12*(1+T$6/Setup!$C$13)-BR13-DP13)+IF($K13=1,$D13,0) | U13: =MAX(0,U12*(1+U$6/Setup!$C$13)-BS13-DQ13)+IF($K13=2,$D13,0) | V13: =MAX(0,V12*(1+V$6/Setup!$C$13)-BT13-DR13)+IF($K13=3,$D13,0) | W13: =MAX(0,W12*(1+W$6/Setup!$C$13)-BU13-DS13)+IF($K13=4,$D13,0) | X13: =MAX(0,X12*(1+X$6/Setup!$C$13)-BV13-DT13)+IF($K13=5,$D13,0) | Y13: =MAX(0,Y12*(1+Y$6/Setup!$C$13)-BW13-DU13)+IF($K13=6,$D13,0) | Z13: =MAX(0,Z12*(1+Z$6/Setup!$C$13)-BX13-DV13)+IF($K13=7,$D13,0) | AA13: =MAX(0,AA12*(1+AA$6/Setup!$C$13)-BY13-DW13)+IF($K13=8,$D13,0) | AB13: =MAX(0,AB12*(1+AB$6/Setup!$C$13)-BZ13-DX13)+IF($K13=9,$D13,0) | AC13: =MAX(0,AC12*(1+AC$6/Setup!$C$13)-CA13-DY13)+IF($K13=10,$D13,0) | AD13: =MAX(0,AD12*(1+AD$6/Setup!$C$13)-CB13-DZ13)+IF($K13=11,$D13,0) | AE13: =MAX(0,AE12*(1+AE$6/Setup!$C$13)-CC13-EA13)+IF($K13=12,$D13,0) | AF13: =MAX(0,AF12*(1+AF$6/Setup!$C$13)-CD13-EB13)+IF($K13=13,$D13,0) | AG13: =MAX(0,AG12*(1+AG$6/Setup!$C$13)-CE13-EC13)+IF($K13=14,$D13,0) | AH13: =MAX(0,AH12*(1+AH$6/Setup!$C$13)-CF13-ED13)+IF($K13=15,$D13,0) | AI13: =MAX(0,AI12*(1+AI$6/Setup!$C$13)-CG13-EE13)+IF($K13=16,$D13,0) | AJ13: =MAX(0,AJ12*(1+AJ$6/Setup!$C$13)-CH13-EF13)+IF($K13=17,$D13,0) | AK13: =MAX(0,AK12*(1+AK$6/Setup!$C$13)-CI13-EG13)+IF($K13=18,$D13,0) | AL13: =MAX(0,AL12*(1+AL$6/Setup!$C$13)-CJ13-EH13)+IF($K13=19,$D13,0) | AM13: =MAX(0,AM12*(1+AM$6/Setup!$C$13)-CK13-EI13)+IF($K13=20,$D13,0) | AN13: =MAX(0,AN12*(1+AN$6/Setup!$C$13)-CL13-EJ13)+IF($K13=21,$D13,0) | AO13: =MAX(0,AO12*(1+AO$6/Setup!$C$13)-CM13-EK13)+IF($K13=22,$D13,0) | AP13: =MAX(0,AP12*(1+AP$6/Setup!$C$13)-CN13-EL13)+IF($K13=23,$D13,0) | AQ13: =MAX(0,AQ12*(1+AQ$6/Setup!$C$13)-CO13-EM13)+IF($K13=24,$D13,0) | AR13: =MAX(0,AR12*(1+AR$6/Setup!$C$13)-CP13-EN13)+IF($K13=25,$D13,0) | AS13: =MAX(0,AS12*(1+AS$6/Setup!$C$13)-CQ13-EO13)+IF($K13=26,$D13,0) | AT13: =MAX(0,AT12*(1+AT$6/Setup!$C$13)-CR13-EP13)+IF($K13=27,$D13,0) | AU13: =MAX(0,AU12*(1+AU$6/Setup!$C$13)-CS13-EQ13)+IF($K13=28,$D13,0) | AV13: =MAX(0,AV12*(1+AV$6/Setup!$C$13)-CT13-ER13)+IF($K13=29,$D13,0) | AW13: =MAX(0,AW12*(1+AW$6/Setup!$C$13)-CU13-ES13)+IF($K13=30,$D13,0) | AX13: =MAX(0,AX12*(1+AX$6/Setup!$C$13)-CV13-ET13)+IF($K13=31,$D13,0) | AY13: =MAX(0,AY12*(1+AY$6/Setup!$C$13)-CW13-EU13)+IF($K13=32,$D13,0) | AZ13: =MAX(0,AZ12*(1+AZ$6/Setup!$C$13)-CX13-EV13)+IF($K13=33,$D13,0) | BA13: =MAX(0,BA12*(1+BA$6/Setup!$C$13)-CY13-EW13)+IF($K13=34,$D13,0) | BB13: =MAX(0,BB12*(1+BB$6/Setup!$C$13)-CZ13-EX13)+IF($K13=35,$D13,0) | BC13: =MAX(0,BC12*(1+BC$6/Setup!$C$13)-DA13-EY13)+IF($K13=36,$D13,0) | BD13: =MAX(0,BD12*(1+BD$6/Setup!$C$13)-DB13-EZ13)+IF($K13=37,$D13,0) | BE13: =MAX(0,BE12*(1+BE$6/Setup!$C$13)-DC13-FA13)+IF($K13=38,$D13,0) | BF13: =MAX(0,BF12*(1+BF$6/Setup!$C$13)-DD13-FB13)+IF($K13=39,$D13,0) | BG13: =MAX(0,BG12*(1+BG$6/Setup!$C$13)-DE13-FC13)+IF($K13=40,$D13,0) | BH13: =MAX(0,BH12*(1+BH$6/Setup!$C$13)-DF13-FD13)+IF($K13=41,$D13,0) | BI13: =MAX(0,BI12*(1+BI$6/Setup!$C$13)-DG13-FE13)+IF($K13=42,$D13,0) | BJ13: =MAX(0,BJ12*(1+BJ$6/Setup!$C$13)-DH13-FF13)+IF($K13=43,$D13,0) | BK13: =MAX(0,BK12*(1+BK$6/Setup!$C$13)-DI13-FG13)+IF($K13=44,$D13,0) | BL13: =MAX(0,BL12*(1+BL$6/Setup!$C$13)-DJ13-FH13)+IF($K13=45,$D13,0) | BM13: =MAX(0,BM12*(1+BM$6/Setup!$C$13)-DK13-FI13)+IF($K13=46,$D13,0) | BN13: =MAX(0,BN12*(1+BN$6/Setup!$C$13)-DL13-FJ13)+IF($K13=47,$D13,0) | BO13: =MAX(0,BO12*(1+BO$6/Setup!$C$13)-DM13-FK13)+IF($K13=48,$D13,0) | BP13: =MAX(0,BP12*(1+BP$6/Setup!$C$13)-DN13-FL13)+IF($K13=49,$D13,0) | BQ13: =MAX(0,BQ12*(1+BQ$6/Setup!$C$13)-DO13-FM13)+IF($K13=50,$D13,0) | BR13: =MIN(T12*(1+T$6/Setup!$C$13),T$7) | BS13: =MIN(U12*(1+U$6/Setup!$C$13),U$7) | BT13: =MIN(V12*(1+V$6/Setup!$C$13),V$7) | BU13: =MIN(W12*(1+W$6/Setup!$C$13),W$7) | BV13: =MIN(X12*(1+X$6/Setup!$C$13),X$7) | BW13: =MIN(Y12*(1+Y$6/Setup!$C$13),Y$7) | BX13: =MIN(Z12*(1+Z$6/Setup!$C$13),Z$7) | BY13: =MIN(AA12*(1+AA$6/Setup!$C$13),AA$7) | ... DO13: =MIN(BQ12*(1+BQ$6/Setup!$C$13),BQ$7) | DP13: =MIN(T12*(1+T$6/Setup!$C$13)-BR13,$H13) | DQ13: =MIN(U12*(1+U$6/Setup!$C$13)-BS13,MAX(0,$H13-SUM($DP13:DP13))) | DR13: =MIN(V12*(1+V$6/Setup!$C$13)-BT13,MAX(0,$H13-SUM($DP13:DQ13))) | DS13: =MIN(W12*(1+W$6/Setup!$C$13)-BU13,MAX(0,$H13-SUM($DP13:DR13))) | DT13: =MIN(X12*(1+X$6/Setup!$C$13)-BV13,MAX(0,$H13-SUM($DP13:DS13))) | DU13: =MIN(Y12*(1+Y$6/Setup!$C$13)-BW13,MAX(0,$H13-SUM($DP13:DT13))) | DV13: =MIN(Z12*(1+Z$6/Setup!$C$13)-BX13,MAX(0,$H13-SUM($DP13:DU13))) | DW13: =MIN(AA12*(1+AA$6/Setup!$C$13)-BY13,MAX(0,$H13-SUM($DP13:DV13))) | DX13: =MIN(AB12*(1+AB$6/Setup!$C$13)-BZ13,MAX(0,$H13-SUM($DP13:DW13))) | ... FM13: =MIN(BQ12*(1+BQ$6/Setup!$C$13)-DO13,MAX(0,$H13-SUM($DP13:FL13)))
A14: =A13+1 | B14: =IF(Setup!$C$6="Every week",Setup!$C$7+7*(A14-1),IF(Setup!$C$6="Every 2 weeks",Setup!$C$7+14*(A14-1),IF(Setup!$C$6="Every month",EDATE(Setup!$C$7,A14-1),EOMONTH(Setup!$C$7,INT((A14-1+Setup!$C$20)/2)-1)+MIN(IF(MOD(A14-1+Setup!$C$20,2)=0,Setup!$C$18,Setup!$C$19),DAY(EOMONTH(Setup!$C$7,INT((A14-1+Setup!$C$20)/2))))))) | C14: =N('Paycheck Plan'!J10) | D14: =N('Paycheck Plan'!K10) | E14: =MIN(MAX(0,Setup!$C$10-F13),MAX(0,Setup!$C$8+C14-G14)) | F14: =F13+E14 | G14: =MIN(Setup!$C$14,MAX(0,Setup!$C$8+C14)) | H14: =MAX(0,Setup!$C$8+C14-G14-E14)+SUM($T$7:$BQ$7)-SUM(BR14:DO14) | I14: =SUMPRODUCT(T13:BQ13,$T$6:$BQ$6)/Setup!$C$13 | J14: =SUM(T14:BQ14) | K14: =IF(MAX(DP14:FM14)>0,MATCH(MAX(DP14:FM14),DP14:FM14,0),1) | M14: =ROUND(3*$B$2/39,0)+1 | N14: =INDEX($B$10:$B$530,MIN(M14,521)) | O14: =INDEX($J$10:$J$530,MIN(M14,521)) | T14: =MAX(0,T13*(1+T$6/Setup!$C$13)-BR14-DP14)+IF($K14=1,$D14,0) | U14: =MAX(0,U13*(1+U$6/Setup!$C$13)-BS14-DQ14)+IF($K14=2,$D14,0) | V14: =MAX(0,V13*(1+V$6/Setup!$C$13)-BT14-DR14)+IF($K14=3,$D14,0) | W14: =MAX(0,W13*(1+W$6/Setup!$C$13)-BU14-DS14)+IF($K14=4,$D14,0) | X14: =MAX(0,X13*(1+X$6/Setup!$C$13)-BV14-DT14)+IF($K14=5,$D14,0) | Y14: =MAX(0,Y13*(1+Y$6/Setup!$C$13)-BW14-DU14)+IF($K14=6,$D14,0) | Z14: =MAX(0,Z13*(1+Z$6/Setup!$C$13)-BX14-DV14)+IF($K14=7,$D14,0) | AA14: =MAX(0,AA13*(1+AA$6/Setup!$C$13)-BY14-DW14)+IF($K14=8,$D14,0) | AB14: =MAX(0,AB13*(1+AB$6/Setup!$C$13)-BZ14-DX14)+IF($K14=9,$D14,0) | AC14: =MAX(0,AC13*(1+AC$6/Setup!$C$13)-CA14-DY14)+IF($K14=10,$D14,0) | AD14: =MAX(0,AD13*(1+AD$6/Setup!$C$13)-CB14-DZ14)+IF($K14=11,$D14,0) | AE14: =MAX(0,AE13*(1+AE$6/Setup!$C$13)-CC14-EA14)+IF($K14=12,$D14,0) | AF14: =MAX(0,AF13*(1+AF$6/Setup!$C$13)-CD14-EB14)+IF($K14=13,$D14,0) | AG14: =MAX(0,AG13*(1+AG$6/Setup!$C$13)-CE14-EC14)+IF($K14=14,$D14,0) | AH14: =MAX(0,AH13*(1+AH$6/Setup!$C$13)-CF14-ED14)+IF($K14=15,$D14,0) | AI14: =MAX(0,AI13*(1+AI$6/Setup!$C$13)-CG14-EE14)+IF($K14=16,$D14,0) | AJ14: =MAX(0,AJ13*(1+AJ$6/Setup!$C$13)-CH14-EF14)+IF($K14=17,$D14,0) | AK14: =MAX(0,AK13*(1+AK$6/Setup!$C$13)-CI14-EG14)+IF($K14=18,$D14,0) | AL14: =MAX(0,AL13*(1+AL$6/Setup!$C$13)-CJ14-EH14)+IF($K14=19,$D14,0) | AM14: =MAX(0,AM13*(1+AM$6/Setup!$C$13)-CK14-EI14)+IF($K14=20,$D14,0) | AN14: =MAX(0,AN13*(1+AN$6/Setup!$C$13)-CL14-EJ14)+IF($K14=21,$D14,0) | AO14: =MAX(0,AO13*(1+AO$6/Setup!$C$13)-CM14-EK14)+IF($K14=22,$D14,0) | AP14: =MAX(0,AP13*(1+AP$6/Setup!$C$13)-CN14-EL14)+IF($K14=23,$D14,0) | AQ14: =MAX(0,AQ13*(1+AQ$6/Setup!$C$13)-CO14-EM14)+IF($K14=24,$D14,0) | AR14: =MAX(0,AR13*(1+AR$6/Setup!$C$13)-CP14-EN14)+IF($K14=25,$D14,0) | AS14: =MAX(0,AS13*(1+AS$6/Setup!$C$13)-CQ14-EO14)+IF($K14=26,$D14,0) | AT14: =MAX(0,AT13*(1+AT$6/Setup!$C$13)-CR14-EP14)+IF($K14=27,$D14,0) | AU14: =MAX(0,AU13*(1+AU$6/Setup!$C$13)-CS14-EQ14)+IF($K14=28,$D14,0) | AV14: =MAX(0,AV13*(1+AV$6/Setup!$C$13)-CT14-ER14)+IF($K14=29,$D14,0) | AW14: =MAX(0,AW13*(1+AW$6/Setup!$C$13)-CU14-ES14)+IF($K14=30,$D14,0) | AX14: =MAX(0,AX13*(1+AX$6/Setup!$C$13)-CV14-ET14)+IF($K14=31,$D14,0) | AY14: =MAX(0,AY13*(1+AY$6/Setup!$C$13)-CW14-EU14)+IF($K14=32,$D14,0) | AZ14: =MAX(0,AZ13*(1+AZ$6/Setup!$C$13)-CX14-EV14)+IF($K14=33,$D14,0) | BA14: =MAX(0,BA13*(1+BA$6/Setup!$C$13)-CY14-EW14)+IF($K14=34,$D14,0) | BB14: =MAX(0,BB13*(1+BB$6/Setup!$C$13)-CZ14-EX14)+IF($K14=35,$D14,0) | BC14: =MAX(0,BC13*(1+BC$6/Setup!$C$13)-DA14-EY14)+IF($K14=36,$D14,0) | BD14: =MAX(0,BD13*(1+BD$6/Setup!$C$13)-DB14-EZ14)+IF($K14=37,$D14,0) | BE14: =MAX(0,BE13*(1+BE$6/Setup!$C$13)-DC14-FA14)+IF($K14=38,$D14,0) | BF14: =MAX(0,BF13*(1+BF$6/Setup!$C$13)-DD14-FB14)+IF($K14=39,$D14,0) | BG14: =MAX(0,BG13*(1+BG$6/Setup!$C$13)-DE14-FC14)+IF($K14=40,$D14,0) | BH14: =MAX(0,BH13*(1+BH$6/Setup!$C$13)-DF14-FD14)+IF($K14=41,$D14,0) | BI14: =MAX(0,BI13*(1+BI$6/Setup!$C$13)-DG14-FE14)+IF($K14=42,$D14,0) | BJ14: =MAX(0,BJ13*(1+BJ$6/Setup!$C$13)-DH14-FF14)+IF($K14=43,$D14,0) | BK14: =MAX(0,BK13*(1+BK$6/Setup!$C$13)-DI14-FG14)+IF($K14=44,$D14,0) | BL14: =MAX(0,BL13*(1+BL$6/Setup!$C$13)-DJ14-FH14)+IF($K14=45,$D14,0) | BM14: =MAX(0,BM13*(1+BM$6/Setup!$C$13)-DK14-FI14)+IF($K14=46,$D14,0) | BN14: =MAX(0,BN13*(1+BN$6/Setup!$C$13)-DL14-FJ14)+IF($K14=47,$D14,0) | BO14: =MAX(0,BO13*(1+BO$6/Setup!$C$13)-DM14-FK14)+IF($K14=48,$D14,0) | BP14: =MAX(0,BP13*(1+BP$6/Setup!$C$13)-DN14-FL14)+IF($K14=49,$D14,0) | BQ14: =MAX(0,BQ13*(1+BQ$6/Setup!$C$13)-DO14-FM14)+IF($K14=50,$D14,0) | BR14: =MIN(T13*(1+T$6/Setup!$C$13),T$7) | BS14: =MIN(U13*(1+U$6/Setup!$C$13),U$7) | BT14: =MIN(V13*(1+V$6/Setup!$C$13),V$7) | BU14: =MIN(W13*(1+W$6/Setup!$C$13),W$7) | BV14: =MIN(X13*(1+X$6/Setup!$C$13),X$7) | BW14: =MIN(Y13*(1+Y$6/Setup!$C$13),Y$7) | BX14: =MIN(Z13*(1+Z$6/Setup!$C$13),Z$7) | BY14: =MIN(AA13*(1+AA$6/Setup!$C$13),AA$7) | ... DO14: =MIN(BQ13*(1+BQ$6/Setup!$C$13),BQ$7) | DP14: =MIN(T13*(1+T$6/Setup!$C$13)-BR14,$H14) | DQ14: =MIN(U13*(1+U$6/Setup!$C$13)-BS14,MAX(0,$H14-SUM($DP14:DP14))) | DR14: =MIN(V13*(1+V$6/Setup!$C$13)-BT14,MAX(0,$H14-SUM($DP14:DQ14))) | DS14: =MIN(W13*(1+W$6/Setup!$C$13)-BU14,MAX(0,$H14-SUM($DP14:DR14))) | DT14: =MIN(X13*(1+X$6/Setup!$C$13)-BV14,MAX(0,$H14-SUM($DP14:DS14))) | DU14: =MIN(Y13*(1+Y$6/Setup!$C$13)-BW14,MAX(0,$H14-SUM($DP14:DT14))) | DV14: =MIN(Z13*(1+Z$6/Setup!$C$13)-BX14,MAX(0,$H14-SUM($DP14:DU14))) | DW14: =MIN(AA13*(1+AA$6/Setup!$C$13)-BY14,MAX(0,$H14-SUM($DP14:DV14))) | DX14: =MIN(AB13*(1+AB$6/Setup!$C$13)-BZ14,MAX(0,$H14-SUM($DP14:DW14))) | ... FM14: =MIN(BQ13*(1+BQ$6/Setup!$C$13)-DO14,MAX(0,$H14-SUM($DP14:FL14)))
A15: =A14+1 | B15: =IF(Setup!$C$6="Every week",Setup!$C$7+7*(A15-1),IF(Setup!$C$6="Every 2 weeks",Setup!$C$7+14*(A15-1),IF(Setup!$C$6="Every month",EDATE(Setup!$C$7,A15-1),EOMONTH(Setup!$C$7,INT((A15-1+Setup!$C$20)/2)-1)+MIN(IF(MOD(A15-1+Setup!$C$20,2)=0,Setup!$C$18,Setup!$C$19),DAY(EOMONTH(Setup!$C$7,INT((A15-1+Setup!$C$20)/2))))))) | C15: =N('Paycheck Plan'!J11) | D15: =N('Paycheck Plan'!K11) | E15: =MIN(MAX(0,Setup!$C$10-F14),MAX(0,Setup!$C$8+C15-G15)) | F15: =F14+E15 | G15: =MIN(Setup!$C$14,MAX(0,Setup!$C$8+C15)) | H15: =MAX(0,Setup!$C$8+C15-G15-E15)+SUM($T$7:$BQ$7)-SUM(BR15:DO15) | I15: =SUMPRODUCT(T14:BQ14,$T$6:$BQ$6)/Setup!$C$13 | J15: =SUM(T15:BQ15) | K15: =IF(MAX(DP15:FM15)>0,MATCH(MAX(DP15:FM15),DP15:FM15,0),1) | M15: =ROUND(4*$B$2/39,0)+1 | N15: =INDEX($B$10:$B$530,MIN(M15,521)) | O15: =INDEX($J$10:$J$530,MIN(M15,521)) | T15: =MAX(0,T14*(1+T$6/Setup!$C$13)-BR15-DP15)+IF($K15=1,$D15,0) | U15: =MAX(0,U14*(1+U$6/Setup!$C$13)-BS15-DQ15)+IF($K15=2,$D15,0) | V15: =MAX(0,V14*(1+V$6/Setup!$C$13)-BT15-DR15)+IF($K15=3,$D15,0) | W15: =MAX(0,W14*(1+W$6/Setup!$C$13)-BU15-DS15)+IF($K15=4,$D15,0) | X15: =MAX(0,X14*(1+X$6/Setup!$C$13)-BV15-DT15)+IF($K15=5,$D15,0) | Y15: =MAX(0,Y14*(1+Y$6/Setup!$C$13)-BW15-DU15)+IF($K15=6,$D15,0) | Z15: =MAX(0,Z14*(1+Z$6/Setup!$C$13)-BX15-DV15)+IF($K15=7,$D15,0) | AA15: =MAX(0,AA14*(1+AA$6/Setup!$C$13)-BY15-DW15)+IF($K15=8,$D15,0) | AB15: =MAX(0,AB14*(1+AB$6/Setup!$C$13)-BZ15-DX15)+IF($K15=9,$D15,0) | AC15: =MAX(0,AC14*(1+AC$6/Setup!$C$13)-CA15-DY15)+IF($K15=10,$D15,0) | AD15: =MAX(0,AD14*(1+AD$6/Setup!$C$13)-CB15-DZ15)+IF($K15=11,$D15,0) | AE15: =MAX(0,AE14*(1+AE$6/Setup!$C$13)-CC15-EA15)+IF($K15=12,$D15,0) | AF15: =MAX(0,AF14*(1+AF$6/Setup!$C$13)-CD15-EB15)+IF($K15=13,$D15,0) | AG15: =MAX(0,AG14*(1+AG$6/Setup!$C$13)-CE15-EC15)+IF($K15=14,$D15,0) | AH15: =MAX(0,AH14*(1+AH$6/Setup!$C$13)-CF15-ED15)+IF($K15=15,$D15,0) | AI15: =MAX(0,AI14*(1+AI$6/Setup!$C$13)-CG15-EE15)+IF($K15=16,$D15,0) | AJ15: =MAX(0,AJ14*(1+AJ$6/Setup!$C$13)-CH15-EF15)+IF($K15=17,$D15,0) | AK15: =MAX(0,AK14*(1+AK$6/Setup!$C$13)-CI15-EG15)+IF($K15=18,$D15,0) | AL15: =MAX(0,AL14*(1+AL$6/Setup!$C$13)-CJ15-EH15)+IF($K15=19,$D15,0) | AM15: =MAX(0,AM14*(1+AM$6/Setup!$C$13)-CK15-EI15)+IF($K15=20,$D15,0) | AN15: =MAX(0,AN14*(1+AN$6/Setup!$C$13)-CL15-EJ15)+IF($K15=21,$D15,0) | AO15: =MAX(0,AO14*(1+AO$6/Setup!$C$13)-CM15-EK15)+IF($K15=22,$D15,0) | AP15: =MAX(0,AP14*(1+AP$6/Setup!$C$13)-CN15-EL15)+IF($K15=23,$D15,0) | AQ15: =MAX(0,AQ14*(1+AQ$6/Setup!$C$13)-CO15-EM15)+IF($K15=24,$D15,0) | AR15: =MAX(0,AR14*(1+AR$6/Setup!$C$13)-CP15-EN15)+IF($K15=25,$D15,0) | AS15: =MAX(0,AS14*(1+AS$6/Setup!$C$13)-CQ15-EO15)+IF($K15=26,$D15,0) | AT15: =MAX(0,AT14*(1+AT$6/Setup!$C$13)-CR15-EP15)+IF($K15=27,$D15,0) | AU15: =MAX(0,AU14*(1+AU$6/Setup!$C$13)-CS15-EQ15)+IF($K15=28,$D15,0) | AV15: =MAX(0,AV14*(1+AV$6/Setup!$C$13)-CT15-ER15)+IF($K15=29,$D15,0) | AW15: =MAX(0,AW14*(1+AW$6/Setup!$C$13)-CU15-ES15)+IF($K15=30,$D15,0) | AX15: =MAX(0,AX14*(1+AX$6/Setup!$C$13)-CV15-ET15)+IF($K15=31,$D15,0) | AY15: =MAX(0,AY14*(1+AY$6/Setup!$C$13)-CW15-EU15)+IF($K15=32,$D15,0) | AZ15: =MAX(0,AZ14*(1+AZ$6/Setup!$C$13)-CX15-EV15)+IF($K15=33,$D15,0) | BA15: =MAX(0,BA14*(1+BA$6/Setup!$C$13)-CY15-EW15)+IF($K15=34,$D15,0) | BB15: =MAX(0,BB14*(1+BB$6/Setup!$C$13)-CZ15-EX15)+IF($K15=35,$D15,0) | BC15: =MAX(0,BC14*(1+BC$6/Setup!$C$13)-DA15-EY15)+IF($K15=36,$D15,0) | BD15: =MAX(0,BD14*(1+BD$6/Setup!$C$13)-DB15-EZ15)+IF($K15=37,$D15,0) | BE15: =MAX(0,BE14*(1+BE$6/Setup!$C$13)-DC15-FA15)+IF($K15=38,$D15,0) | BF15: =MAX(0,BF14*(1+BF$6/Setup!$C$13)-DD15-FB15)+IF($K15=39,$D15,0) | BG15: =MAX(0,BG14*(1+BG$6/Setup!$C$13)-DE15-FC15)+IF($K15=40,$D15,0) | BH15: =MAX(0,BH14*(1+BH$6/Setup!$C$13)-DF15-FD15)+IF($K15=41,$D15,0) | BI15: =MAX(0,BI14*(1+BI$6/Setup!$C$13)-DG15-FE15)+IF($K15=42,$D15,0) | BJ15: =MAX(0,BJ14*(1+BJ$6/Setup!$C$13)-DH15-FF15)+IF($K15=43,$D15,0) | BK15: =MAX(0,BK14*(1+BK$6/Setup!$C$13)-DI15-FG15)+IF($K15=44,$D15,0) | BL15: =MAX(0,BL14*(1+BL$6/Setup!$C$13)-DJ15-FH15)+IF($K15=45,$D15,0) | BM15: =MAX(0,BM14*(1+BM$6/Setup!$C$13)-DK15-FI15)+IF($K15=46,$D15,0) | BN15: =MAX(0,BN14*(1+BN$6/Setup!$C$13)-DL15-FJ15)+IF($K15=47,$D15,0) | BO15: =MAX(0,BO14*(1+BO$6/Setup!$C$13)-DM15-FK15)+IF($K15=48,$D15,0) | BP15: =MAX(0,BP14*(1+BP$6/Setup!$C$13)-DN15-FL15)+IF($K15=49,$D15,0) | BQ15: =MAX(0,BQ14*(1+BQ$6/Setup!$C$13)-DO15-FM15)+IF($K15=50,$D15,0) | BR15: =MIN(T14*(1+T$6/Setup!$C$13),T$7) | BS15: =MIN(U14*(1+U$6/Setup!$C$13),U$7) | BT15: =MIN(V14*(1+V$6/Setup!$C$13),V$7) | BU15: =MIN(W14*(1+W$6/Setup!$C$13),W$7) | BV15: =MIN(X14*(1+X$6/Setup!$C$13),X$7) | BW15: =MIN(Y14*(1+Y$6/Setup!$C$13),Y$7) | BX15: =MIN(Z14*(1+Z$6/Setup!$C$13),Z$7) | BY15: =MIN(AA14*(1+AA$6/Setup!$C$13),AA$7) | ... DO15: =MIN(BQ14*(1+BQ$6/Setup!$C$13),BQ$7) | DP15: =MIN(T14*(1+T$6/Setup!$C$13)-BR15,$H15) | DQ15: =MIN(U14*(1+U$6/Setup!$C$13)-BS15,MAX(0,$H15-SUM($DP15:DP15))) | DR15: =MIN(V14*(1+V$6/Setup!$C$13)-BT15,MAX(0,$H15-SUM($DP15:DQ15))) | DS15: =MIN(W14*(1+W$6/Setup!$C$13)-BU15,MAX(0,$H15-SUM($DP15:DR15))) | DT15: =MIN(X14*(1+X$6/Setup!$C$13)-BV15,MAX(0,$H15-SUM($DP15:DS15))) | DU15: =MIN(Y14*(1+Y$6/Setup!$C$13)-BW15,MAX(0,$H15-SUM($DP15:DT15))) | DV15: =MIN(Z14*(1+Z$6/Setup!$C$13)-BX15,MAX(0,$H15-SUM($DP15:DU15))) | DW15: =MIN(AA14*(1+AA$6/Setup!$C$13)-BY15,MAX(0,$H15-SUM($DP15:DV15))) | DX15: =MIN(AB14*(1+AB$6/Setup!$C$13)-BZ15,MAX(0,$H15-SUM($DP15:DW15))) | ... FM15: =MIN(BQ14*(1+BQ$6/Setup!$C$13)-DO15,MAX(0,$H15-SUM($DP15:FL15)))
A16: =A15+1 | B16: =IF(Setup!$C$6="Every week",Setup!$C$7+7*(A16-1),IF(Setup!$C$6="Every 2 weeks",Setup!$C$7+14*(A16-1),IF(Setup!$C$6="Every month",EDATE(Setup!$C$7,A16-1),EOMONTH(Setup!$C$7,INT((A16-1+Setup!$C$20)/2)-1)+MIN(IF(MOD(A16-1+Setup!$C$20,2)=0,Setup!$C$18,Setup!$C$19),DAY(EOMONTH(Setup!$C$7,INT((A16-1+Setup!$C$20)/2))))))) | C16: =N('Paycheck Plan'!J12) | D16: =N('Paycheck Plan'!K12) | E16: =MIN(MAX(0,Setup!$C$10-F15),MAX(0,Setup!$C$8+C16-G16)) | F16: =F15+E16 | G16: =MIN(Setup!$C$14,MAX(0,Setup!$C$8+C16)) | H16: =MAX(0,Setup!$C$8+C16-G16-E16)+SUM($T$7:$BQ$7)-SUM(BR16:DO16) | I16: =SUMPRODUCT(T15:BQ15,$T$6:$BQ$6)/Setup!$C$13 | J16: =SUM(T16:BQ16) | K16: =IF(MAX(DP16:FM16)>0,MATCH(MAX(DP16:FM16),DP16:FM16,0),1) | M16: =ROUND(5*$B$2/39,0)+1 | N16: =INDEX($B$10:$B$530,MIN(M16,521)) | O16: =INDEX($J$10:$J$530,MIN(M16,521)) | T16: =MAX(0,T15*(1+T$6/Setup!$C$13)-BR16-DP16)+IF($K16=1,$D16,0) | U16: =MAX(0,U15*(1+U$6/Setup!$C$13)-BS16-DQ16)+IF($K16=2,$D16,0) | V16: =MAX(0,V15*(1+V$6/Setup!$C$13)-BT16-DR16)+IF($K16=3,$D16,0) | W16: =MAX(0,W15*(1+W$6/Setup!$C$13)-BU16-DS16)+IF($K16=4,$D16,0) | X16: =MAX(0,X15*(1+X$6/Setup!$C$13)-BV16-DT16)+IF($K16=5,$D16,0) | Y16: =MAX(0,Y15*(1+Y$6/Setup!$C$13)-BW16-DU16)+IF($K16=6,$D16,0) | Z16: =MAX(0,Z15*(1+Z$6/Setup!$C$13)-BX16-DV16)+IF($K16=7,$D16,0) | AA16: =MAX(0,AA15*(1+AA$6/Setup!$C$13)-BY16-DW16)+IF($K16=8,$D16,0) | AB16: =MAX(0,AB15*(1+AB$6/Setup!$C$13)-BZ16-DX16)+IF($K16=9,$D16,0) | AC16: =MAX(0,AC15*(1+AC$6/Setup!$C$13)-CA16-DY16)+IF($K16=10,$D16,0) | AD16: =MAX(0,AD15*(1+AD$6/Setup!$C$13)-CB16-DZ16)+IF($K16=11,$D16,0) | AE16: =MAX(0,AE15*(1+AE$6/Setup!$C$13)-CC16-EA16)+IF($K16=12,$D16,0) | AF16: =MAX(0,AF15*(1+AF$6/Setup!$C$13)-CD16-EB16)+IF($K16=13,$D16,0) | AG16: =MAX(0,AG15*(1+AG$6/Setup!$C$13)-CE16-EC16)+IF($K16=14,$D16,0) | AH16: =MAX(0,AH15*(1+AH$6/Setup!$C$13)-CF16-ED16)+IF($K16=15,$D16,0) | AI16: =MAX(0,AI15*(1+AI$6/Setup!$C$13)-CG16-EE16)+IF($K16=16,$D16,0) | AJ16: =MAX(0,AJ15*(1+AJ$6/Setup!$C$13)-CH16-EF16)+IF($K16=17,$D16,0) | AK16: =MAX(0,AK15*(1+AK$6/Setup!$C$13)-CI16-EG16)+IF($K16=18,$D16,0) | AL16: =MAX(0,AL15*(1+AL$6/Setup!$C$13)-CJ16-EH16)+IF($K16=19,$D16,0) | AM16: =MAX(0,AM15*(1+AM$6/Setup!$C$13)-CK16-EI16)+IF($K16=20,$D16,0) | AN16: =MAX(0,AN15*(1+AN$6/Setup!$C$13)-CL16-EJ16)+IF($K16=21,$D16,0) | AO16: =MAX(0,AO15*(1+AO$6/Setup!$C$13)-CM16-EK16)+IF($K16=22,$D16,0) | AP16: =MAX(0,AP15*(1+AP$6/Setup!$C$13)-CN16-EL16)+IF($K16=23,$D16,0) | AQ16: =MAX(0,AQ15*(1+AQ$6/Setup!$C$13)-CO16-EM16)+IF($K16=24,$D16,0) | AR16: =MAX(0,AR15*(1+AR$6/Setup!$C$13)-CP16-EN16)+IF($K16=25,$D16,0) | AS16: =MAX(0,AS15*(1+AS$6/Setup!$C$13)-CQ16-EO16)+IF($K16=26,$D16,0) | AT16: =MAX(0,AT15*(1+AT$6/Setup!$C$13)-CR16-EP16)+IF($K16=27,$D16,0) | AU16: =MAX(0,AU15*(1+AU$6/Setup!$C$13)-CS16-EQ16)+IF($K16=28,$D16,0) | AV16: =MAX(0,AV15*(1+AV$6/Setup!$C$13)-CT16-ER16)+IF($K16=29,$D16,0) | AW16: =MAX(0,AW15*(1+AW$6/Setup!$C$13)-CU16-ES16)+IF($K16=30,$D16,0) | AX16: =MAX(0,AX15*(1+AX$6/Setup!$C$13)-CV16-ET16)+IF($K16=31,$D16,0) | AY16: =MAX(0,AY15*(1+AY$6/Setup!$C$13)-CW16-EU16)+IF($K16=32,$D16,0) | AZ16: =MAX(0,AZ15*(1+AZ$6/Setup!$C$13)-CX16-EV16)+IF($K16=33,$D16,0) | BA16: =MAX(0,BA15*(1+BA$6/Setup!$C$13)-CY16-EW16)+IF($K16=34,$D16,0) | BB16: =MAX(0,BB15*(1+BB$6/Setup!$C$13)-CZ16-EX16)+IF($K16=35,$D16,0) | BC16: =MAX(0,BC15*(1+BC$6/Setup!$C$13)-DA16-EY16)+IF($K16=36,$D16,0) | BD16: =MAX(0,BD15*(1+BD$6/Setup!$C$13)-DB16-EZ16)+IF($K16=37,$D16,0) | BE16: =MAX(0,BE15*(1+BE$6/Setup!$C$13)-DC16-FA16)+IF($K16=38,$D16,0) | BF16: =MAX(0,BF15*(1+BF$6/Setup!$C$13)-DD16-FB16)+IF($K16=39,$D16,0) | BG16: =MAX(0,BG15*(1+BG$6/Setup!$C$13)-DE16-FC16)+IF($K16=40,$D16,0) | BH16: =MAX(0,BH15*(1+BH$6/Setup!$C$13)-DF16-FD16)+IF($K16=41,$D16,0) | BI16: =MAX(0,BI15*(1+BI$6/Setup!$C$13)-DG16-FE16)+IF($K16=42,$D16,0) | BJ16: =MAX(0,BJ15*(1+BJ$6/Setup!$C$13)-DH16-FF16)+IF($K16=43,$D16,0) | BK16: =MAX(0,BK15*(1+BK$6/Setup!$C$13)-DI16-FG16)+IF($K16=44,$D16,0) | BL16: =MAX(0,BL15*(1+BL$6/Setup!$C$13)-DJ16-FH16)+IF($K16=45,$D16,0) | BM16: =MAX(0,BM15*(1+BM$6/Setup!$C$13)-DK16-FI16)+IF($K16=46,$D16,0) | BN16: =MAX(0,BN15*(1+BN$6/Setup!$C$13)-DL16-FJ16)+IF($K16=47,$D16,0) | BO16: =MAX(0,BO15*(1+BO$6/Setup!$C$13)-DM16-FK16)+IF($K16=48,$D16,0) | BP16: =MAX(0,BP15*(1+BP$6/Setup!$C$13)-DN16-FL16)+IF($K16=49,$D16,0) | BQ16: =MAX(0,BQ15*(1+BQ$6/Setup!$C$13)-DO16-FM16)+IF($K16=50,$D16,0) | BR16: =MIN(T15*(1+T$6/Setup!$C$13),T$7) | BS16: =MIN(U15*(1+U$6/Setup!$C$13),U$7) | BT16: =MIN(V15*(1+V$6/Setup!$C$13),V$7) | BU16: =MIN(W15*(1+W$6/Setup!$C$13),W$7) | BV16: =MIN(X15*(1+X$6/Setup!$C$13),X$7) | BW16: =MIN(Y15*(1+Y$6/Setup!$C$13),Y$7) | BX16: =MIN(Z15*(1+Z$6/Setup!$C$13),Z$7) | BY16: =MIN(AA15*(1+AA$6/Setup!$C$13),AA$7) | ... DO16: =MIN(BQ15*(1+BQ$6/Setup!$C$13),BQ$7) | DP16: =MIN(T15*(1+T$6/Setup!$C$13)-BR16,$H16) | DQ16: =MIN(U15*(1+U$6/Setup!$C$13)-BS16,MAX(0,$H16-SUM($DP16:DP16))) | DR16: =MIN(V15*(1+V$6/Setup!$C$13)-BT16,MAX(0,$H16-SUM($DP16:DQ16))) | DS16: =MIN(W15*(1+W$6/Setup!$C$13)-BU16,MAX(0,$H16-SUM($DP16:DR16))) | DT16: =MIN(X15*(1+X$6/Setup!$C$13)-BV16,MAX(0,$H16-SUM($DP16:DS16))) | DU16: =MIN(Y15*(1+Y$6/Setup!$C$13)-BW16,MAX(0,$H16-SUM($DP16:DT16))) | DV16: =MIN(Z15*(1+Z$6/Setup!$C$13)-BX16,MAX(0,$H16-SUM($DP16:DU16))) | DW16: =MIN(AA15*(1+AA$6/Setup!$C$13)-BY16,MAX(0,$H16-SUM($DP16:DV16))) | DX16: =MIN(AB15*(1+AB$6/Setup!$C$13)-BZ16,MAX(0,$H16-SUM($DP16:DW16))) | ... FM16: =MIN(BQ15*(1+BQ$6/Setup!$C$13)-DO16,MAX(0,$H16-SUM($DP16:FL16)))
A17: =A16+1 | B17: =IF(Setup!$C$6="Every week",Setup!$C$7+7*(A17-1),IF(Setup!$C$6="Every 2 weeks",Setup!$C$7+14*(A17-1),IF(Setup!$C$6="Every month",EDATE(Setup!$C$7,A17-1),EOMONTH(Setup!$C$7,INT((A17-1+Setup!$C$20)/2)-1)+MIN(IF(MOD(A17-1+Setup!$C$20,2)=0,Setup!$C$18,Setup!$C$19),DAY(EOMONTH(Setup!$C$7,INT((A17-1+Setup!$C$20)/2))))))) | C17: =N('Paycheck Plan'!J13) | D17: =N('Paycheck Plan'!K13) | E17: =MIN(MAX(0,Setup!$C$10-F16),MAX(0,Setup!$C$8+C17-G17)) | F17: =F16+E17 | G17: =MIN(Setup!$C$14,MAX(0,Setup!$C$8+C17)) | H17: =MAX(0,Setup!$C$8+C17-G17-E17)+SUM($T$7:$BQ$7)-SUM(BR17:DO17) | I17: =SUMPRODUCT(T16:BQ16,$T$6:$BQ$6)/Setup!$C$13 | J17: =SUM(T17:BQ17) | K17: =IF(MAX(DP17:FM17)>0,MATCH(MAX(DP17:FM17),DP17:FM17,0),1) | M17: =ROUND(6*$B$2/39,0)+1 | N17: =INDEX($B$10:$B$530,MIN(M17,521)) | O17: =INDEX($J$10:$J$530,MIN(M17,521)) | T17: =MAX(0,T16*(1+T$6/Setup!$C$13)-BR17-DP17)+IF($K17=1,$D17,0) | U17: =MAX(0,U16*(1+U$6/Setup!$C$13)-BS17-DQ17)+IF($K17=2,$D17,0) | V17: =MAX(0,V16*(1+V$6/Setup!$C$13)-BT17-DR17)+IF($K17=3,$D17,0) | W17: =MAX(0,W16*(1+W$6/Setup!$C$13)-BU17-DS17)+IF($K17=4,$D17,0) | X17: =MAX(0,X16*(1+X$6/Setup!$C$13)-BV17-DT17)+IF($K17=5,$D17,0) | Y17: =MAX(0,Y16*(1+Y$6/Setup!$C$13)-BW17-DU17)+IF($K17=6,$D17,0) | Z17: =MAX(0,Z16*(1+Z$6/Setup!$C$13)-BX17-DV17)+IF($K17=7,$D17,0) | AA17: =MAX(0,AA16*(1+AA$6/Setup!$C$13)-BY17-DW17)+IF($K17=8,$D17,0) | AB17: =MAX(0,AB16*(1+AB$6/Setup!$C$13)-BZ17-DX17)+IF($K17=9,$D17,0) | AC17: =MAX(0,AC16*(1+AC$6/Setup!$C$13)-CA17-DY17)+IF($K17=10,$D17,0) | AD17: =MAX(0,AD16*(1+AD$6/Setup!$C$13)-CB17-DZ17)+IF($K17=11,$D17,0) | AE17: =MAX(0,AE16*(1+AE$6/Setup!$C$13)-CC17-EA17)+IF($K17=12,$D17,0) | AF17: =MAX(0,AF16*(1+AF$6/Setup!$C$13)-CD17-EB17)+IF($K17=13,$D17,0) | AG17: =MAX(0,AG16*(1+AG$6/Setup!$C$13)-CE17-EC17)+IF($K17=14,$D17,0) | AH17: =MAX(0,AH16*(1+AH$6/Setup!$C$13)-CF17-ED17)+IF($K17=15,$D17,0) | AI17: =MAX(0,AI16*(1+AI$6/Setup!$C$13)-CG17-EE17)+IF($K17=16,$D17,0) | AJ17: =MAX(0,AJ16*(1+AJ$6/Setup!$C$13)-CH17-EF17)+IF($K17=17,$D17,0) | AK17: =MAX(0,AK16*(1+AK$6/Setup!$C$13)-CI17-EG17)+IF($K17=18,$D17,0) | AL17: =MAX(0,AL16*(1+AL$6/Setup!$C$13)-CJ17-EH17)+IF($K17=19,$D17,0) | AM17: =MAX(0,AM16*(1+AM$6/Setup!$C$13)-CK17-EI17)+IF($K17=20,$D17,0) | AN17: =MAX(0,AN16*(1+AN$6/Setup!$C$13)-CL17-EJ17)+IF($K17=21,$D17,0) | AO17: =MAX(0,AO16*(1+AO$6/Setup!$C$13)-CM17-EK17)+IF($K17=22,$D17,0) | AP17: =MAX(0,AP16*(1+AP$6/Setup!$C$13)-CN17-EL17)+IF($K17=23,$D17,0) | AQ17: =MAX(0,AQ16*(1+AQ$6/Setup!$C$13)-CO17-EM17)+IF($K17=24,$D17,0) | AR17: =MAX(0,AR16*(1+AR$6/Setup!$C$13)-CP17-EN17)+IF($K17=25,$D17,0) | AS17: =MAX(0,AS16*(1+AS$6/Setup!$C$13)-CQ17-EO17)+IF($K17=26,$D17,0) | AT17: =MAX(0,AT16*(1+AT$6/Setup!$C$13)-CR17-EP17)+IF($K17=27,$D17,0) | AU17: =MAX(0,AU16*(1+AU$6/Setup!$C$13)-CS17-EQ17)+IF($K17=28,$D17,0) | AV17: =MAX(0,AV16*(1+AV$6/Setup!$C$13)-CT17-ER17)+IF($K17=29,$D17,0) | AW17: =MAX(0,AW16*(1+AW$6/Setup!$C$13)-CU17-ES17)+IF($K17=30,$D17,0) | AX17: =MAX(0,AX16*(1+AX$6/Setup!$C$13)-CV17-ET17)+IF($K17=31,$D17,0) | AY17: =MAX(0,AY16*(1+AY$6/Setup!$C$13)-CW17-EU17)+IF($K17=32,$D17,0) | AZ17: =MAX(0,AZ16*(1+AZ$6/Setup!$C$13)-CX17-EV17)+IF($K17=33,$D17,0) | BA17: =MAX(0,BA16*(1+BA$6/Setup!$C$13)-CY17-EW17)+IF($K17=34,$D17,0) | BB17: =MAX(0,BB16*(1+BB$6/Setup!$C$13)-CZ17-EX17)+IF($K17=35,$D17,0) | BC17: =MAX(0,BC16*(1+BC$6/Setup!$C$13)-DA17-EY17)+IF($K17=36,$D17,0) | BD17: =MAX(0,BD16*(1+BD$6/Setup!$C$13)-DB17-EZ17)+IF($K17=37,$D17,0) | BE17: =MAX(0,BE16*(1+BE$6/Setup!$C$13)-DC17-FA17)+IF($K17=38,$D17,0) | BF17: =MAX(0,BF16*(1+BF$6/Setup!$C$13)-DD17-FB17)+IF($K17=39,$D17,0) | BG17: =MAX(0,BG16*(1+BG$6/Setup!$C$13)-DE17-FC17)+IF($K17=40,$D17,0) | BH17: =MAX(0,BH16*(1+BH$6/Setup!$C$13)-DF17-FD17)+IF($K17=41,$D17,0) | BI17: =MAX(0,BI16*(1+BI$6/Setup!$C$13)-DG17-FE17)+IF($K17=42,$D17,0) | BJ17: =MAX(0,BJ16*(1+BJ$6/Setup!$C$13)-DH17-FF17)+IF($K17=43,$D17,0) | BK17: =MAX(0,BK16*(1+BK$6/Setup!$C$13)-DI17-FG17)+IF($K17=44,$D17,0) | BL17: =MAX(0,BL16*(1+BL$6/Setup!$C$13)-DJ17-FH17)+IF($K17=45,$D17,0) | BM17: =MAX(0,BM16*(1+BM$6/Setup!$C$13)-DK17-FI17)+IF($K17=46,$D17,0) | BN17: =MAX(0,BN16*(1+BN$6/Setup!$C$13)-DL17-FJ17)+IF($K17=47,$D17,0) | BO17: =MAX(0,BO16*(1+BO$6/Setup!$C$13)-DM17-FK17)+IF($K17=48,$D17,0) | BP17: =MAX(0,BP16*(1+BP$6/Setup!$C$13)-DN17-FL17)+IF($K17=49,$D17,0) | BQ17: =MAX(0,BQ16*(1+BQ$6/Setup!$C$13)-DO17-FM17)+IF($K17=50,$D17,0) | BR17: =MIN(T16*(1+T$6/Setup!$C$13),T$7) | BS17: =MIN(U16*(1+U$6/Setup!$C$13),U$7) | BT17: =MIN(V16*(1+V$6/Setup!$C$13),V$7) | BU17: =MIN(W16*(1+W$6/Setup!$C$13),W$7) | BV17: =MIN(X16*(1+X$6/Setup!$C$13),X$7) | BW17: =MIN(Y16*(1+Y$6/Setup!$C$13),Y$7) | BX17: =MIN(Z16*(1+Z$6/Setup!$C$13),Z$7) | BY17: =MIN(AA16*(1+AA$6/Setup!$C$13),AA$7) | ... DO17: =MIN(BQ16*(1+BQ$6/Setup!$C$13),BQ$7) | DP17: =MIN(T16*(1+T$6/Setup!$C$13)-BR17,$H17) | DQ17: =MIN(U16*(1+U$6/Setup!$C$13)-BS17,MAX(0,$H17-SUM($DP17:DP17))) | DR17: =MIN(V16*(1+V$6/Setup!$C$13)-BT17,MAX(0,$H17-SUM($DP17:DQ17))) | DS17: =MIN(W16*(1+W$6/Setup!$C$13)-BU17,MAX(0,$H17-SUM($DP17:DR17))) | DT17: =MIN(X16*(1+X$6/Setup!$C$13)-BV17,MAX(0,$H17-SUM($DP17:DS17))) | DU17: =MIN(Y16*(1+Y$6/Setup!$C$13)-BW17,MAX(0,$H17-SUM($DP17:DT17))) | DV17: =MIN(Z16*(1+Z$6/Setup!$C$13)-BX17,MAX(0,$H17-SUM($DP17:DU17))) | DW17: =MIN(AA16*(1+AA$6/Setup!$C$13)-BY17,MAX(0,$H17-SUM($DP17:DV17))) | DX17: =MIN(AB16*(1+AB$6/Setup!$C$13)-BZ17,MAX(0,$H17-SUM($DP17:DW17))) | ... FM17: =MIN(BQ16*(1+BQ$6/Setup!$C$13)-DO17,MAX(0,$H17-SUM($DP17:FL17)))
A18: =A17+1 | B18: =IF(Setup!$C$6="Every week",Setup!$C$7+7*(A18-1),IF(Setup!$C$6="Every 2 weeks",Setup!$C$7+14*(A18-1),IF(Setup!$C$6="Every month",EDATE(Setup!$C$7,A18-1),EOMONTH(Setup!$C$7,INT((A18-1+Setup!$C$20)/2)-1)+MIN(IF(MOD(A18-1+Setup!$C$20,2)=0,Setup!$C$18,Setup!$C$19),DAY(EOMONTH(Setup!$C$7,INT((A18-1+Setup!$C$20)/2))))))) | C18: =N('Paycheck Plan'!J14) | D18: =N('Paycheck Plan'!K14) | E18: =MIN(MAX(0,Setup!$C$10-F17),MAX(0,Setup!$C$8+C18-G18)) | F18: =F17+E18 | G18: =MIN(Setup!$C$14,MAX(0,Setup!$C$8+C18)) | H18: =MAX(0,Setup!$C$8+C18-G18-E18)+SUM($T$7:$BQ$7)-SUM(BR18:DO18) | I18: =SUMPRODUCT(T17:BQ17,$T$6:$BQ$6)/Setup!$C$13 | J18: =SUM(T18:BQ18) | K18: =IF(MAX(DP18:FM18)>0,MATCH(MAX(DP18:FM18),DP18:FM18,0),1) | M18: =ROUND(7*$B$2/39,0)+1 | N18: =INDEX($B$10:$B$530,MIN(M18,521)) | O18: =INDEX($J$10:$J$530,MIN(M18,521)) | T18: =MAX(0,T17*(1+T$6/Setup!$C$13)-BR18-DP18)+IF($K18=1,$D18,0) | U18: =MAX(0,U17*(1+U$6/Setup!$C$13)-BS18-DQ18)+IF($K18=2,$D18,0) | V18: =MAX(0,V17*(1+V$6/Setup!$C$13)-BT18-DR18)+IF($K18=3,$D18,0) | W18: =MAX(0,W17*(1+W$6/Setup!$C$13)-BU18-DS18)+IF($K18=4,$D18,0) | X18: =MAX(0,X17*(1+X$6/Setup!$C$13)-BV18-DT18)+IF($K18=5,$D18,0) | Y18: =MAX(0,Y17*(1+Y$6/Setup!$C$13)-BW18-DU18)+IF($K18=6,$D18,0) | Z18: =MAX(0,Z17*(1+Z$6/Setup!$C$13)-BX18-DV18)+IF($K18=7,$D18,0) | AA18: =MAX(0,AA17*(1+AA$6/Setup!$C$13)-BY18-DW18)+IF($K18=8,$D18,0) | AB18: =MAX(0,AB17*(1+AB$6/Setup!$C$13)-BZ18-DX18)+IF($K18=9,$D18,0) | AC18: =MAX(0,AC17*(1+AC$6/Setup!$C$13)-CA18-DY18)+IF($K18=10,$D18,0) | AD18: =MAX(0,AD17*(1+AD$6/Setup!$C$13)-CB18-DZ18)+IF($K18=11,$D18,0) | AE18: =MAX(0,AE17*(1+AE$6/Setup!$C$13)-CC18-EA18)+IF($K18=12,$D18,0) | AF18: =MAX(0,AF17*(1+AF$6/Setup!$C$13)-CD18-EB18)+IF($K18=13,$D18,0) | AG18: =MAX(0,AG17*(1+AG$6/Setup!$C$13)-CE18-EC18)+IF($K18=14,$D18,0) | AH18: =MAX(0,AH17*(1+AH$6/Setup!$C$13)-CF18-ED18)+IF($K18=15,$D18,0) | AI18: =MAX(0,AI17*(1+AI$6/Setup!$C$13)-CG18-EE18)+IF($K18=16,$D18,0) | AJ18: =MAX(0,AJ17*(1+AJ$6/Setup!$C$13)-CH18-EF18)+IF($K18=17,$D18,0) | AK18: =MAX(0,AK17*(1+AK$6/Setup!$C$13)-CI18-EG18)+IF($K18=18,$D18,0) | AL18: =MAX(0,AL17*(1+AL$6/Setup!$C$13)-CJ18-EH18)+IF($K18=19,$D18,0) | AM18: =MAX(0,AM17*(1+AM$6/Setup!$C$13)-CK18-EI18)+IF($K18=20,$D18,0) | AN18: =MAX(0,AN17*(1+AN$6/Setup!$C$13)-CL18-EJ18)+IF($K18=21,$D18,0) | AO18: =MAX(0,AO17*(1+AO$6/Setup!$C$13)-CM18-EK18)+IF($K18=22,$D18,0) | AP18: =MAX(0,AP17*(1+AP$6/Setup!$C$13)-CN18-EL18)+IF($K18=23,$D18,0) | AQ18: =MAX(0,AQ17*(1+AQ$6/Setup!$C$13)-CO18-EM18)+IF($K18=24,$D18,0) | AR18: =MAX(0,AR17*(1+AR$6/Setup!$C$13)-CP18-EN18)+IF($K18=25,$D18,0) | AS18: =MAX(0,AS17*(1+AS$6/Setup!$C$13)-CQ18-EO18)+IF($K18=26,$D18,0) | AT18: =MAX(0,AT17*(1+AT$6/Setup!$C$13)-CR18-EP18)+IF($K18=27,$D18,0) | AU18: =MAX(0,AU17*(1+AU$6/Setup!$C$13)-CS18-EQ18)+IF($K18=28,$D18,0) | AV18: =MAX(0,AV17*(1+AV$6/Setup!$C$13)-CT18-ER18)+IF($K18=29,$D18,0) | AW18: =MAX(0,AW17*(1+AW$6/Setup!$C$13)-CU18-ES18)+IF($K18=30,$D18,0) | AX18: =MAX(0,AX17*(1+AX$6/Setup!$C$13)-CV18-ET18)+IF($K18=31,$D18,0) | AY18: =MAX(0,AY17*(1+AY$6/Setup!$C$13)-CW18-EU18)+IF($K18=32,$D18,0) | AZ18: =MAX(0,AZ17*(1+AZ$6/Setup!$C$13)-CX18-EV18)+IF($K18=33,$D18,0) | BA18: =MAX(0,BA17*(1+BA$6/Setup!$C$13)-CY18-EW18)+IF($K18=34,$D18,0) | BB18: =MAX(0,BB17*(1+BB$6/Setup!$C$13)-CZ18-EX18)+IF($K18=35,$D18,0) | BC18: =MAX(0,BC17*(1+BC$6/Setup!$C$13)-DA18-EY18)+IF($K18=36,$D18,0) | BD18: =MAX(0,BD17*(1+BD$6/Setup!$C$13)-DB18-EZ18)+IF($K18=37,$D18,0) | BE18: =MAX(0,BE17*(1+BE$6/Setup!$C$13)-DC18-FA18)+IF($K18=38,$D18,0) | BF18: =MAX(0,BF17*(1+BF$6/Setup!$C$13)-DD18-FB18)+IF($K18=39,$D18,0) | BG18: =MAX(0,BG17*(1+BG$6/Setup!$C$13)-DE18-FC18)+IF($K18=40,$D18,0) | BH18: =MAX(0,BH17*(1+BH$6/Setup!$C$13)-DF18-FD18)+IF($K18=41,$D18,0) | BI18: =MAX(0,BI17*(1+BI$6/Setup!$C$13)-DG18-FE18)+IF($K18=42,$D18,0) | BJ18: =MAX(0,BJ17*(1+BJ$6/Setup!$C$13)-DH18-FF18)+IF($K18=43,$D18,0) | BK18: =MAX(0,BK17*(1+BK$6/Setup!$C$13)-DI18-FG18)+IF($K18=44,$D18,0) | BL18: =MAX(0,BL17*(1+BL$6/Setup!$C$13)-DJ18-FH18)+IF($K18=45,$D18,0) | BM18: =MAX(0,BM17*(1+BM$6/Setup!$C$13)-DK18-FI18)+IF($K18=46,$D18,0) | BN18: =MAX(0,BN17*(1+BN$6/Setup!$C$13)-DL18-FJ18)+IF($K18=47,$D18,0) | BO18: =MAX(0,BO17*(1+BO$6/Setup!$C$13)-DM18-FK18)+IF($K18=48,$D18,0) | BP18: =MAX(0,BP17*(1+BP$6/Setup!$C$13)-DN18-FL18)+IF($K18=49,$D18,0) | BQ18: =MAX(0,BQ17*(1+BQ$6/Setup!$C$13)-DO18-FM18)+IF($K18=50,$D18,0) | BR18: =MIN(T17*(1+T$6/Setup!$C$13),T$7) | BS18: =MIN(U17*(1+U$6/Setup!$C$13),U$7) | BT18: =MIN(V17*(1+V$6/Setup!$C$13),V$7) | BU18: =MIN(W17*(1+W$6/Setup!$C$13),W$7) | BV18: =MIN(X17*(1+X$6/Setup!$C$13),X$7) | BW18: =MIN(Y17*(1+Y$6/Setup!$C$13),Y$7) | BX18: =MIN(Z17*(1+Z$6/Setup!$C$13),Z$7) | BY18: =MIN(AA17*(1+AA$6/Setup!$C$13),AA$7) | ... DO18: =MIN(BQ17*(1+BQ$6/Setup!$C$13),BQ$7) | DP18: =MIN(T17*(1+T$6/Setup!$C$13)-BR18,$H18) | DQ18: =MIN(U17*(1+U$6/Setup!$C$13)-BS18,MAX(0,$H18-SUM($DP18:DP18))) | DR18: =MIN(V17*(1+V$6/Setup!$C$13)-BT18,MAX(0,$H18-SUM($DP18:DQ18))) | DS18: =MIN(W17*(1+W$6/Setup!$C$13)-BU18,MAX(0,$H18-SUM($DP18:DR18))) | DT18: =MIN(X17*(1+X$6/Setup!$C$13)-BV18,MAX(0,$H18-SUM($DP18:DS18))) | DU18: =MIN(Y17*(1+Y$6/Setup!$C$13)-BW18,MAX(0,$H18-SUM($DP18:DT18))) | DV18: =MIN(Z17*(1+Z$6/Setup!$C$13)-BX18,MAX(0,$H18-SUM($DP18:DU18))) | DW18: =MIN(AA17*(1+AA$6/Setup!$C$13)-BY18,MAX(0,$H18-SUM($DP18:DV18))) | DX18: =MIN(AB17*(1+AB$6/Setup!$C$13)-BZ18,MAX(0,$H18-SUM($DP18:DW18))) | ... FM18: =MIN(BQ17*(1+BQ$6/Setup!$C$13)-DO18,MAX(0,$H18-SUM($DP18:FL18)))
A19: =A18+1 | B19: =IF(Setup!$C$6="Every week",Setup!$C$7+7*(A19-1),IF(Setup!$C$6="Every 2 weeks",Setup!$C$7+14*(A19-1),IF(Setup!$C$6="Every month",EDATE(Setup!$C$7,A19-1),EOMONTH(Setup!$C$7,INT((A19-1+Setup!$C$20)/2)-1)+MIN(IF(MOD(A19-1+Setup!$C$20,2)=0,Setup!$C$18,Setup!$C$19),DAY(EOMONTH(Setup!$C$7,INT((A19-1+Setup!$C$20)/2))))))) | C19: =N('Paycheck Plan'!J15) | D19: =N('Paycheck Plan'!K15) | E19: =MIN(MAX(0,Setup!$C$10-F18),MAX(0,Setup!$C$8+C19-G19)) | F19: =F18+E19 | G19: =MIN(Setup!$C$14,MAX(0,Setup!$C$8+C19)) | H19: =MAX(0,Setup!$C$8+C19-G19-E19)+SUM($T$7:$BQ$7)-SUM(BR19:DO19) | I19: =SUMPRODUCT(T18:BQ18,$T$6:$BQ$6)/Setup!$C$13 | J19: =SUM(T19:BQ19) | K19: =IF(MAX(DP19:FM19)>0,MATCH(MAX(DP19:FM19),DP19:FM19,0),1) | M19: =ROUND(8*$B$2/39,0)+1 | N19: =INDEX($B$10:$B$530,MIN(M19,521)) | O19: =INDEX($J$10:$J$530,MIN(M19,521)) | T19: =MAX(0,T18*(1+T$6/Setup!$C$13)-BR19-DP19)+IF($K19=1,$D19,0) | U19: =MAX(0,U18*(1+U$6/Setup!$C$13)-BS19-DQ19)+IF($K19=2,$D19,0) | V19: =MAX(0,V18*(1+V$6/Setup!$C$13)-BT19-DR19)+IF($K19=3,$D19,0) | W19: =MAX(0,W18*(1+W$6/Setup!$C$13)-BU19-DS19)+IF($K19=4,$D19,0) | X19: =MAX(0,X18*(1+X$6/Setup!$C$13)-BV19-DT19)+IF($K19=5,$D19,0) | Y19: =MAX(0,Y18*(1+Y$6/Setup!$C$13)-BW19-DU19)+IF($K19=6,$D19,0) | Z19: =MAX(0,Z18*(1+Z$6/Setup!$C$13)-BX19-DV19)+IF($K19=7,$D19,0) | AA19: =MAX(0,AA18*(1+AA$6/Setup!$C$13)-BY19-DW19)+IF($K19=8,$D19,0) | AB19: =MAX(0,AB18*(1+AB$6/Setup!$C$13)-BZ19-DX19)+IF($K19=9,$D19,0) | AC19: =MAX(0,AC18*(1+AC$6/Setup!$C$13)-CA19-DY19)+IF($K19=10,$D19,0) | AD19: =MAX(0,AD18*(1+AD$6/Setup!$C$13)-CB19-DZ19)+IF($K19=11,$D19,0) | AE19: =MAX(0,AE18*(1+AE$6/Setup!$C$13)-CC19-EA19)+IF($K19=12,$D19,0) | AF19: =MAX(0,AF18*(1+AF$6/Setup!$C$13)-CD19-EB19)+IF($K19=13,$D19,0) | AG19: =MAX(0,AG18*(1+AG$6/Setup!$C$13)-CE19-EC19)+IF($K19=14,$D19,0) | AH19: =MAX(0,AH18*(1+AH$6/Setup!$C$13)-CF19-ED19)+IF($K19=15,$D19,0) | AI19: =MAX(0,AI18*(1+AI$6/Setup!$C$13)-CG19-EE19)+IF($K19=16,$D19,0) | AJ19: =MAX(0,AJ18*(1+AJ$6/Setup!$C$13)-CH19-EF19)+IF($K19=17,$D19,0) | AK19: =MAX(0,AK18*(1+AK$6/Setup!$C$13)-CI19-EG19)+IF($K19=18,$D19,0) | AL19: =MAX(0,AL18*(1+AL$6/Setup!$C$13)-CJ19-EH19)+IF($K19=19,$D19,0) | AM19: =MAX(0,AM18*(1+AM$6/Setup!$C$13)-CK19-EI19)+IF($K19=20,$D19,0) | AN19: =MAX(0,AN18*(1+AN$6/Setup!$C$13)-CL19-EJ19)+IF($K19=21,$D19,0) | AO19: =MAX(0,AO18*(1+AO$6/Setup!$C$13)-CM19-EK19)+IF($K19=22,$D19,0) | AP19: =MAX(0,AP18*(1+AP$6/Setup!$C$13)-CN19-EL19)+IF($K19=23,$D19,0) | AQ19: =MAX(0,AQ18*(1+AQ$6/Setup!$C$13)-CO19-EM19)+IF($K19=24,$D19,0) | AR19: =MAX(0,AR18*(1+AR$6/Setup!$C$13)-CP19-EN19)+IF($K19=25,$D19,0) | AS19: =MAX(0,AS18*(1+AS$6/Setup!$C$13)-CQ19-EO19)+IF($K19=26,$D19,0) | AT19: =MAX(0,AT18*(1+AT$6/Setup!$C$13)-CR19-EP19)+IF($K19=27,$D19,0) | AU19: =MAX(0,AU18*(1+AU$6/Setup!$C$13)-CS19-EQ19)+IF($K19=28,$D19,0) | AV19: =MAX(0,AV18*(1+AV$6/Setup!$C$13)-CT19-ER19)+IF($K19=29,$D19,0) | AW19: =MAX(0,AW18*(1+AW$6/Setup!$C$13)-CU19-ES19)+IF($K19=30,$D19,0) | AX19: =MAX(0,AX18*(1+AX$6/Setup!$C$13)-CV19-ET19)+IF($K19=31,$D19,0) | AY19: =MAX(0,AY18*(1+AY$6/Setup!$C$13)-CW19-EU19)+IF($K19=32,$D19,0) | AZ19: =MAX(0,AZ18*(1+AZ$6/Setup!$C$13)-CX19-EV19)+IF($K19=33,$D19,0) | BA19: =MAX(0,BA18*(1+BA$6/Setup!$C$13)-CY19-EW19)+IF($K19=34,$D19,0) | BB19: =MAX(0,BB18*(1+BB$6/Setup!$C$13)-CZ19-EX19)+IF($K19=35,$D19,0) | BC19: =MAX(0,BC18*(1+BC$6/Setup!$C$13)-DA19-EY19)+IF($K19=36,$D19,0) | BD19: =MAX(0,BD18*(1+BD$6/Setup!$C$13)-DB19-EZ19)+IF($K19=37,$D19,0) | BE19: =MAX(0,BE18*(1+BE$6/Setup!$C$13)-DC19-FA19)+IF($K19=38,$D19,0) | BF19: =MAX(0,BF18*(1+BF$6/Setup!$C$13)-DD19-FB19)+IF($K19=39,$D19,0) | BG19: =MAX(0,BG18*(1+BG$6/Setup!$C$13)-DE19-FC19)+IF($K19=40,$D19,0) | BH19: =MAX(0,BH18*(1+BH$6/Setup!$C$13)-DF19-FD19)+IF($K19=41,$D19,0) | BI19: =MAX(0,BI18*(1+BI$6/Setup!$C$13)-DG19-FE19)+IF($K19=42,$D19,0) | BJ19: =MAX(0,BJ18*(1+BJ$6/Setup!$C$13)-DH19-FF19)+IF($K19=43,$D19,0) | BK19: =MAX(0,BK18*(1+BK$6/Setup!$C$13)-DI19-FG19)+IF($K19=44,$D19,0) | BL19: =MAX(0,BL18*(1+BL$6/Setup!$C$13)-DJ19-FH19)+IF($K19=45,$D19,0) | BM19: =MAX(0,BM18*(1+BM$6/Setup!$C$13)-DK19-FI19)+IF($K19=46,$D19,0) | BN19: =MAX(0,BN18*(1+BN$6/Setup!$C$13)-DL19-FJ19)+IF($K19=47,$D19,0) | BO19: =MAX(0,BO18*(1+BO$6/Setup!$C$13)-DM19-FK19)+IF($K19=48,$D19,0) | BP19: =MAX(0,BP18*(1+BP$6/Setup!$C$13)-DN19-FL19)+IF($K19=49,$D19,0) | BQ19: =MAX(0,BQ18*(1+BQ$6/Setup!$C$13)-DO19-FM19)+IF($K19=50,$D19,0) | BR19: =MIN(T18*(1+T$6/Setup!$C$13),T$7) | BS19: =MIN(U18*(1+U$6/Setup!$C$13),U$7) | BT19: =MIN(V18*(1+V$6/Setup!$C$13),V$7) | BU19: =MIN(W18*(1+W$6/Setup!$C$13),W$7) | BV19: =MIN(X18*(1+X$6/Setup!$C$13),X$7) | BW19: =MIN(Y18*(1+Y$6/Setup!$C$13),Y$7) | BX19: =MIN(Z18*(1+Z$6/Setup!$C$13),Z$7) | BY19: =MIN(AA18*(1+AA$6/Setup!$C$13),AA$7) | ... DO19: =MIN(BQ18*(1+BQ$6/Setup!$C$13),BQ$7) | DP19: =MIN(T18*(1+T$6/Setup!$C$13)-BR19,$H19) | DQ19: =MIN(U18*(1+U$6/Setup!$C$13)-BS19,MAX(0,$H19-SUM($DP19:DP19))) | DR19: =MIN(V18*(1+V$6/Setup!$C$13)-BT19,MAX(0,$H19-SUM($DP19:DQ19))) | DS19: =MIN(W18*(1+W$6/Setup!$C$13)-BU19,MAX(0,$H19-SUM($DP19:DR19))) | DT19: =MIN(X18*(1+X$6/Setup!$C$13)-BV19,MAX(0,$H19-SUM($DP19:DS19))) | DU19: =MIN(Y18*(1+Y$6/Setup!$C$13)-BW19,MAX(0,$H19-SUM($DP19:DT19))) | DV19: =MIN(Z18*(1+Z$6/Setup!$C$13)-BX19,MAX(0,$H19-SUM($DP19:DU19))) | DW19: =MIN(AA18*(1+AA$6/Setup!$C$13)-BY19,MAX(0,$H19-SUM($DP19:DV19))) | DX19: =MIN(AB18*(1+AB$6/Setup!$C$13)-BZ19,MAX(0,$H19-SUM($DP19:DW19))) | ... FM19: =MIN(BQ18*(1+BQ$6/Setup!$C$13)-DO19,MAX(0,$H19-SUM($DP19:FL19)))
A20: =A19+1 | B20: =IF(Setup!$C$6="Every week",Setup!$C$7+7*(A20-1),IF(Setup!$C$6="Every 2 weeks",Setup!$C$7+14*(A20-1),IF(Setup!$C$6="Every month",EDATE(Setup!$C$7,A20-1),EOMONTH(Setup!$C$7,INT((A20-1+Setup!$C$20)/2)-1)+MIN(IF(MOD(A20-1+Setup!$C$20,2)=0,Setup!$C$18,Setup!$C$19),DAY(EOMONTH(Setup!$C$7,INT((A20-1+Setup!$C$20)/2))))))) | C20: =N('Paycheck Plan'!J16) | D20: =N('Paycheck Plan'!K16) | E20: =MIN(MAX(0,Setup!$C$10-F19),MAX(0,Setup!$C$8+C20-G20)) | F20: =F19+E20 | G20: =MIN(Setup!$C$14,MAX(0,Setup!$C$8+C20)) | H20: =MAX(0,Setup!$C$8+C20-G20-E20)+SUM($T$7:$BQ$7)-SUM(BR20:DO20) | I20: =SUMPRODUCT(T19:BQ19,$T$6:$BQ$6)/Setup!$C$13 | J20: =SUM(T20:BQ20) | K20: =IF(MAX(DP20:FM20)>0,MATCH(MAX(DP20:FM20),DP20:FM20,0),1) | M20: =ROUND(9*$B$2/39,0)+1 | N20: =INDEX($B$10:$B$530,MIN(M20,521)) | O20: =INDEX($J$10:$J$530,MIN(M20,521)) | T20: =MAX(0,T19*(1+T$6/Setup!$C$13)-BR20-DP20)+IF($K20=1,$D20,0) | U20: =MAX(0,U19*(1+U$6/Setup!$C$13)-BS20-DQ20)+IF($K20=2,$D20,0) | V20: =MAX(0,V19*(1+V$6/Setup!$C$13)-BT20-DR20)+IF($K20=3,$D20,0) | W20: =MAX(0,W19*(1+W$6/Setup!$C$13)-BU20-DS20)+IF($K20=4,$D20,0) | X20: =MAX(0,X19*(1+X$6/Setup!$C$13)-BV20-DT20)+IF($K20=5,$D20,0) | Y20: =MAX(0,Y19*(1+Y$6/Setup!$C$13)-BW20-DU20)+IF($K20=6,$D20,0) | Z20: =MAX(0,Z19*(1+Z$6/Setup!$C$13)-BX20-DV20)+IF($K20=7,$D20,0) | AA20: =MAX(0,AA19*(1+AA$6/Setup!$C$13)-BY20-DW20)+IF($K20=8,$D20,0) | AB20: =MAX(0,AB19*(1+AB$6/Setup!$C$13)-BZ20-DX20)+IF($K20=9,$D20,0) | AC20: =MAX(0,AC19*(1+AC$6/Setup!$C$13)-CA20-DY20)+IF($K20=10,$D20,0) | AD20: =MAX(0,AD19*(1+AD$6/Setup!$C$13)-CB20-DZ20)+IF($K20=11,$D20,0) | AE20: =MAX(0,AE19*(1+AE$6/Setup!$C$13)-CC20-EA20)+IF($K20=12,$D20,0) | AF20: =MAX(0,AF19*(1+AF$6/Setup!$C$13)-CD20-EB20)+IF($K20=13,$D20,0) | AG20: =MAX(0,AG19*(1+AG$6/Setup!$C$13)-CE20-EC20)+IF($K20=14,$D20,0) | AH20: =MAX(0,AH19*(1+AH$6/Setup!$C$13)-CF20-ED20)+IF($K20=15,$D20,0) | AI20: =MAX(0,AI19*(1+AI$6/Setup!$C$13)-CG20-EE20)+IF($K20=16,$D20,0) | AJ20: =MAX(0,AJ19*(1+AJ$6/Setup!$C$13)-CH20-EF20)+IF($K20=17,$D20,0) | AK20: =MAX(0,AK19*(1+AK$6/Setup!$C$13)-CI20-EG20)+IF($K20=18,$D20,0) | AL20: =MAX(0,AL19*(1+AL$6/Setup!$C$13)-CJ20-EH20)+IF($K20=19,$D20,0) | AM20: =MAX(0,AM19*(1+AM$6/Setup!$C$13)-CK20-EI20)+IF($K20=20,$D20,0) | AN20: =MAX(0,AN19*(1+AN$6/Setup!$C$13)-CL20-EJ20)+IF($K20=21,$D20,0) | AO20: =MAX(0,AO19*(1+AO$6/Setup!$C$13)-CM20-EK20)+IF($K20=22,$D20,0) | AP20: =MAX(0,AP19*(1+AP$6/Setup!$C$13)-CN20-EL20)+IF($K20=23,$D20,0) | AQ20: =MAX(0,AQ19*(1+AQ$6/Setup!$C$13)-CO20-EM20)+IF($K20=24,$D20,0) | AR20: =MAX(0,AR19*(1+AR$6/Setup!$C$13)-CP20-EN20)+IF($K20=25,$D20,0) | AS20: =MAX(0,AS19*(1+AS$6/Setup!$C$13)-CQ20-EO20)+IF($K20=26,$D20,0) | AT20: =MAX(0,AT19*(1+AT$6/Setup!$C$13)-CR20-EP20)+IF($K20=27,$D20,0) | AU20: =MAX(0,AU19*(1+AU$6/Setup!$C$13)-CS20-EQ20)+IF($K20=28,$D20,0) | AV20: =MAX(0,AV19*(1+AV$6/Setup!$C$13)-CT20-ER20)+IF($K20=29,$D20,0) | AW20: =MAX(0,AW19*(1+AW$6/Setup!$C$13)-CU20-ES20)+IF($K20=30,$D20,0) | AX20: =MAX(0,AX19*(1+AX$6/Setup!$C$13)-CV20-ET20)+IF($K20=31,$D20,0) | AY20: =MAX(0,AY19*(1+AY$6/Setup!$C$13)-CW20-EU20)+IF($K20=32,$D20,0) | AZ20: =MAX(0,AZ19*(1+AZ$6/Setup!$C$13)-CX20-EV20)+IF($K20=33,$D20,0) | BA20: =MAX(0,BA19*(1+BA$6/Setup!$C$13)-CY20-EW20)+IF($K20=34,$D20,0) | BB20: =MAX(0,BB19*(1+BB$6/Setup!$C$13)-CZ20-EX20)+IF($K20=35,$D20,0) | BC20: =MAX(0,BC19*(1+BC$6/Setup!$C$13)-DA20-EY20)+IF($K20=36,$D20,0) | BD20: =MAX(0,BD19*(1+BD$6/Setup!$C$13)-DB20-EZ20)+IF($K20=37,$D20,0) | BE20: =MAX(0,BE19*(1+BE$6/Setup!$C$13)-DC20-FA20)+IF($K20=38,$D20,0) | BF20: =MAX(0,BF19*(1+BF$6/Setup!$C$13)-DD20-FB20)+IF($K20=39,$D20,0) | BG20: =MAX(0,BG19*(1+BG$6/Setup!$C$13)-DE20-FC20)+IF($K20=40,$D20,0) | BH20: =MAX(0,BH19*(1+BH$6/Setup!$C$13)-DF20-FD20)+IF($K20=41,$D20,0) | BI20: =MAX(0,BI19*(1+BI$6/Setup!$C$13)-DG20-FE20)+IF($K20=42,$D20,0) | BJ20: =MAX(0,BJ19*(1+BJ$6/Setup!$C$13)-DH20-FF20)+IF($K20=43,$D20,0) | BK20: =MAX(0,BK19*(1+BK$6/Setup!$C$13)-DI20-FG20)+IF($K20=44,$D20,0) | BL20: =MAX(0,BL19*(1+BL$6/Setup!$C$13)-DJ20-FH20)+IF($K20=45,$D20,0) | BM20: =MAX(0,BM19*(1+BM$6/Setup!$C$13)-DK20-FI20)+IF($K20=46,$D20,0) | BN20: =MAX(0,BN19*(1+BN$6/Setup!$C$13)-DL20-FJ20)+IF($K20=47,$D20,0) | BO20: =MAX(0,BO19*(1+BO$6/Setup!$C$13)-DM20-FK20)+IF($K20=48,$D20,0) | BP20: =MAX(0,BP19*(1+BP$6/Setup!$C$13)-DN20-FL20)+IF($K20=49,$D20,0) | BQ20: =MAX(0,BQ19*(1+BQ$6/Setup!$C$13)-DO20-FM20)+IF($K20=50,$D20,0) | BR20: =MIN(T19*(1+T$6/Setup!$C$13),T$7) | BS20: =MIN(U19*(1+U$6/Setup!$C$13),U$7) | BT20: =MIN(V19*(1+V$6/Setup!$C$13),V$7) | BU20: =MIN(W19*(1+W$6/Setup!$C$13),W$7) | BV20: =MIN(X19*(1+X$6/Setup!$C$13),X$7) | BW20: =MIN(Y19*(1+Y$6/Setup!$C$13),Y$7) | BX20: =MIN(Z19*(1+Z$6/Setup!$C$13),Z$7) | BY20: =MIN(AA19*(1+AA$6/Setup!$C$13),AA$7) | ... DO20: =MIN(BQ19*(1+BQ$6/Setup!$C$13),BQ$7) | DP20: =MIN(T19*(1+T$6/Setup!$C$13)-BR20,$H20) | DQ20: =MIN(U19*(1+U$6/Setup!$C$13)-BS20,MAX(0,$H20-SUM($DP20:DP20))) | DR20: =MIN(V19*(1+V$6/Setup!$C$13)-BT20,MAX(0,$H20-SUM($DP20:DQ20))) | DS20: =MIN(W19*(1+W$6/Setup!$C$13)-BU20,MAX(0,$H20-SUM($DP20:DR20))) | DT20: =MIN(X19*(1+X$6/Setup!$C$13)-BV20,MAX(0,$H20-SUM($DP20:DS20))) | DU20: =MIN(Y19*(1+Y$6/Setup!$C$13)-BW20,MAX(0,$H20-SUM($DP20:DT20))) | DV20: =MIN(Z19*(1+Z$6/Setup!$C$13)-BX20,MAX(0,$H20-SUM($DP20:DU20))) | DW20: =MIN(AA19*(1+AA$6/Setup!$C$13)-BY20,MAX(0,$H20-SUM($DP20:DV20))) | DX20: =MIN(AB19*(1+AB$6/Setup!$C$13)-BZ20,MAX(0,$H20-SUM($DP20:DW20))) | ... FM20: =MIN(BQ19*(1+BQ$6/Setup!$C$13)-DO20,MAX(0,$H20-SUM($DP20:FL20)))
A21: =A20+1 | B21: =IF(Setup!$C$6="Every week",Setup!$C$7+7*(A21-1),IF(Setup!$C$6="Every 2 weeks",Setup!$C$7+14*(A21-1),IF(Setup!$C$6="Every month",EDATE(Setup!$C$7,A21-1),EOMONTH(Setup!$C$7,INT((A21-1+Setup!$C$20)/2)-1)+MIN(IF(MOD(A21-1+Setup!$C$20,2)=0,Setup!$C$18,Setup!$C$19),DAY(EOMONTH(Setup!$C$7,INT((A21-1+Setup!$C$20)/2))))))) | C21: =N('Paycheck Plan'!J17) | D21: =N('Paycheck Plan'!K17) | E21: =MIN(MAX(0,Setup!$C$10-F20),MAX(0,Setup!$C$8+C21-G21)) | F21: =F20+E21 | G21: =MIN(Setup!$C$14,MAX(0,Setup!$C$8+C21)) | H21: =MAX(0,Setup!$C$8+C21-G21-E21)+SUM($T$7:$BQ$7)-SUM(BR21:DO21) | I21: =SUMPRODUCT(T20:BQ20,$T$6:$BQ$6)/Setup!$C$13 | J21: =SUM(T21:BQ21) | K21: =IF(MAX(DP21:FM21)>0,MATCH(MAX(DP21:FM21),DP21:FM21,0),1) | M21: =ROUND(10*$B$2/39,0)+1 | N21: =INDEX($B$10:$B$530,MIN(M21,521)) | O21: =INDEX($J$10:$J$530,MIN(M21,521)) | T21: =MAX(0,T20*(1+T$6/Setup!$C$13)-BR21-DP21)+IF($K21=1,$D21,0) | U21: =MAX(0,U20*(1+U$6/Setup!$C$13)-BS21-DQ21)+IF($K21=2,$D21,0) | V21: =MAX(0,V20*(1+V$6/Setup!$C$13)-BT21-DR21)+IF($K21=3,$D21,0) | W21: =MAX(0,W20*(1+W$6/Setup!$C$13)-BU21-DS21)+IF($K21=4,$D21,0) | X21: =MAX(0,X20*(1+X$6/Setup!$C$13)-BV21-DT21)+IF($K21=5,$D21,0) | Y21: =MAX(0,Y20*(1+Y$6/Setup!$C$13)-BW21-DU21)+IF($K21=6,$D21,0) | Z21: =MAX(0,Z20*(1+Z$6/Setup!$C$13)-BX21-DV21)+IF($K21=7,$D21,0) | AA21: =MAX(0,AA20*(1+AA$6/Setup!$C$13)-BY21-DW21)+IF($K21=8,$D21,0) | AB21: =MAX(0,AB20*(1+AB$6/Setup!$C$13)-BZ21-DX21)+IF($K21=9,$D21,0) | AC21: =MAX(0,AC20*(1+AC$6/Setup!$C$13)-CA21-DY21)+IF($K21=10,$D21,0) | AD21: =MAX(0,AD20*(1+AD$6/Setup!$C$13)-CB21-DZ21)+IF($K21=11,$D21,0) | AE21: =MAX(0,AE20*(1+AE$6/Setup!$C$13)-CC21-EA21)+IF($K21=12,$D21,0) | AF21: =MAX(0,AF20*(1+AF$6/Setup!$C$13)-CD21-EB21)+IF($K21=13,$D21,0) | AG21: =MAX(0,AG20*(1+AG$6/Setup!$C$13)-CE21-EC21)+IF($K21=14,$D21,0) | AH21: =MAX(0,AH20*(1+AH$6/Setup!$C$13)-CF21-ED21)+IF($K21=15,$D21,0) | AI21: =MAX(0,AI20*(1+AI$6/Setup!$C$13)-CG21-EE21)+IF($K21=16,$D21,0) | AJ21: =MAX(0,AJ20*(1+AJ$6/Setup!$C$13)-CH21-EF21)+IF($K21=17,$D21,0) | AK21: =MAX(0,AK20*(1+AK$6/Setup!$C$13)-CI21-EG21)+IF($K21=18,$D21,0) | AL21: =MAX(0,AL20*(1+AL$6/Setup!$C$13)-CJ21-EH21)+IF($K21=19,$D21,0) | AM21: =MAX(0,AM20*(1+AM$6/Setup!$C$13)-CK21-EI21)+IF($K21=20,$D21,0) | AN21: =MAX(0,AN20*(1+AN$6/Setup!$C$13)-CL21-EJ21)+IF($K21=21,$D21,0) | AO21: =MAX(0,AO20*(1+AO$6/Setup!$C$13)-CM21-EK21)+IF($K21=22,$D21,0) | AP21: =MAX(0,AP20*(1+AP$6/Setup!$C$13)-CN21-EL21)+IF($K21=23,$D21,0) | AQ21: =MAX(0,AQ20*(1+AQ$6/Setup!$C$13)-CO21-EM21)+IF($K21=24,$D21,0) | AR21: =MAX(0,AR20*(1+AR$6/Setup!$C$13)-CP21-EN21)+IF($K21=25,$D21,0) | AS21: =MAX(0,AS20*(1+AS$6/Setup!$C$13)-CQ21-EO21)+IF($K21=26,$D21,0) | AT21: =MAX(0,AT20*(1+AT$6/Setup!$C$13)-CR21-EP21)+IF($K21=27,$D21,0) | AU21: =MAX(0,AU20*(1+AU$6/Setup!$C$13)-CS21-EQ21)+IF($K21=28,$D21,0) | AV21: =MAX(0,AV20*(1+AV$6/Setup!$C$13)-CT21-ER21)+IF($K21=29,$D21,0) | AW21: =MAX(0,AW20*(1+AW$6/Setup!$C$13)-CU21-ES21)+IF($K21=30,$D21,0) | AX21: =MAX(0,AX20*(1+AX$6/Setup!$C$13)-CV21-ET21)+IF($K21=31,$D21,0) | AY21: =MAX(0,AY20*(1+AY$6/Setup!$C$13)-CW21-EU21)+IF($K21=32,$D21,0) | AZ21: =MAX(0,AZ20*(1+AZ$6/Setup!$C$13)-CX21-EV21)+IF($K21=33,$D21,0) | BA21: =MAX(0,BA20*(1+BA$6/Setup!$C$13)-CY21-EW21)+IF($K21=34,$D21,0) | BB21: =MAX(0,BB20*(1+BB$6/Setup!$C$13)-CZ21-EX21)+IF($K21=35,$D21,0) | BC21: =MAX(0,BC20*(1+BC$6/Setup!$C$13)-DA21-EY21)+IF($K21=36,$D21,0) | BD21: =MAX(0,BD20*(1+BD$6/Setup!$C$13)-DB21-EZ21)+IF($K21=37,$D21,0) | BE21: =MAX(0,BE20*(1+BE$6/Setup!$C$13)-DC21-FA21)+IF($K21=38,$D21,0) | BF21: =MAX(0,BF20*(1+BF$6/Setup!$C$13)-DD21-FB21)+IF($K21=39,$D21,0) | BG21: =MAX(0,BG20*(1+BG$6/Setup!$C$13)-DE21-FC21)+IF($K21=40,$D21,0) | BH21: =MAX(0,BH20*(1+BH$6/Setup!$C$13)-DF21-FD21)+IF($K21=41,$D21,0) | BI21: =MAX(0,BI20*(1+BI$6/Setup!$C$13)-DG21-FE21)+IF($K21=42,$D21,0) | BJ21: =MAX(0,BJ20*(1+BJ$6/Setup!$C$13)-DH21-FF21)+IF($K21=43,$D21,0) | BK21: =MAX(0,BK20*(1+BK$6/Setup!$C$13)-DI21-FG21)+IF($K21=44,$D21,0) | BL21: =MAX(0,BL20*(1+BL$6/Setup!$C$13)-DJ21-FH21)+IF($K21=45,$D21,0) | BM21: =MAX(0,BM20*(1+BM$6/Setup!$C$13)-DK21-FI21)+IF($K21=46,$D21,0) | BN21: =MAX(0,BN20*(1+BN$6/Setup!$C$13)-DL21-FJ21)+IF($K21=47,$D21,0) | BO21: =MAX(0,BO20*(1+BO$6/Setup!$C$13)-DM21-FK21)+IF($K21=48,$D21,0) | BP21: =MAX(0,BP20*(1+BP$6/Setup!$C$13)-DN21-FL21)+IF($K21=49,$D21,0) | BQ21: =MAX(0,BQ20*(1+BQ$6/Setup!$C$13)-DO21-FM21)+IF($K21=50,$D21,0) | BR21: =MIN(T20*(1+T$6/Setup!$C$13),T$7) | BS21: =MIN(U20*(1+U$6/Setup!$C$13),U$7) | BT21: =MIN(V20*(1+V$6/Setup!$C$13),V$7) | BU21: =MIN(W20*(1+W$6/Setup!$C$13),W$7) | BV21: =MIN(X20*(1+X$6/Setup!$C$13),X$7) | BW21: =MIN(Y20*(1+Y$6/Setup!$C$13),Y$7) | BX21: =MIN(Z20*(1+Z$6/Setup!$C$13),Z$7) | BY21: =MIN(AA20*(1+AA$6/Setup!$C$13),AA$7) | ... DO21: =MIN(BQ20*(1+BQ$6/Setup!$C$13),BQ$7) | DP21: =MIN(T20*(1+T$6/Setup!$C$13)-BR21,$H21) | DQ21: =MIN(U20*(1+U$6/Setup!$C$13)-BS21,MAX(0,$H21-SUM($DP21:DP21))) | DR21: =MIN(V20*(1+V$6/Setup!$C$13)-BT21,MAX(0,$H21-SUM($DP21:DQ21))) | DS21: =MIN(W20*(1+W$6/Setup!$C$13)-BU21,MAX(0,$H21-SUM($DP21:DR21))) | DT21: =MIN(X20*(1+X$6/Setup!$C$13)-BV21,MAX(0,$H21-SUM($DP21:DS21))) | DU21: =MIN(Y20*(1+Y$6/Setup!$C$13)-BW21,MAX(0,$H21-SUM($DP21:DT21))) | DV21: =MIN(Z20*(1+Z$6/Setup!$C$13)-BX21,MAX(0,$H21-SUM($DP21:DU21))) | DW21: =MIN(AA20*(1+AA$6/Setup!$C$13)-BY21,MAX(0,$H21-SUM($DP21:DV21))) | DX21: =MIN(AB20*(1+AB$6/Setup!$C$13)-BZ21,MAX(0,$H21-SUM($DP21:DW21))) | ... FM21: =MIN(BQ20*(1+BQ$6/Setup!$C$13)-DO21,MAX(0,$H21-SUM($DP21:FL21)))
A22: =A21+1 | B22: =IF(Setup!$C$6="Every week",Setup!$C$7+7*(A22-1),IF(Setup!$C$6="Every 2 weeks",Setup!$C$7+14*(A22-1),IF(Setup!$C$6="Every month",EDATE(Setup!$C$7,A22-1),EOMONTH(Setup!$C$7,INT((A22-1+Setup!$C$20)/2)-1)+MIN(IF(MOD(A22-1+Setup!$C$20,2)=0,Setup!$C$18,Setup!$C$19),DAY(EOMONTH(Setup!$C$7,INT((A22-1+Setup!$C$20)/2))))))) | C22: =N('Paycheck Plan'!J18) | D22: =N('Paycheck Plan'!K18) | E22: =MIN(MAX(0,Setup!$C$10-F21),MAX(0,Setup!$C$8+C22-G22)) | F22: =F21+E22 | G22: =MIN(Setup!$C$14,MAX(0,Setup!$C$8+C22)) | H22: =MAX(0,Setup!$C$8+C22-G22-E22)+SUM($T$7:$BQ$7)-SUM(BR22:DO22) | I22: =SUMPRODUCT(T21:BQ21,$T$6:$BQ$6)/Setup!$C$13 | J22: =SUM(T22:BQ22) | K22: =IF(MAX(DP22:FM22)>0,MATCH(MAX(DP22:FM22),DP22:FM22,0),1) | M22: =ROUND(11*$B$2/39,0)+1 | N22: =INDEX($B$10:$B$530,MIN(M22,521)) | O22: =INDEX($J$10:$J$530,MIN(M22,521)) | T22: =MAX(0,T21*(1+T$6/Setup!$C$13)-BR22-DP22)+IF($K22=1,$D22,0) | U22: =MAX(0,U21*(1+U$6/Setup!$C$13)-BS22-DQ22)+IF($K22=2,$D22,0) | V22: =MAX(0,V21*(1+V$6/Setup!$C$13)-BT22-DR22)+IF($K22=3,$D22,0) | W22: =MAX(0,W21*(1+W$6/Setup!$C$13)-BU22-DS22)+IF($K22=4,$D22,0) | X22: =MAX(0,X21*(1+X$6/Setup!$C$13)-BV22-DT22)+IF($K22=5,$D22,0) | Y22: =MAX(0,Y21*(1+Y$6/Setup!$C$13)-BW22-DU22)+IF($K22=6,$D22,0) | Z22: =MAX(0,Z21*(1+Z$6/Setup!$C$13)-BX22-DV22)+IF($K22=7,$D22,0) | AA22: =MAX(0,AA21*(1+AA$6/Setup!$C$13)-BY22-DW22)+IF($K22=8,$D22,0) | AB22: =MAX(0,AB21*(1+AB$6/Setup!$C$13)-BZ22-DX22)+IF($K22=9,$D22,0) | AC22: =MAX(0,AC21*(1+AC$6/Setup!$C$13)-CA22-DY22)+IF($K22=10,$D22,0) | AD22: =MAX(0,AD21*(1+AD$6/Setup!$C$13)-CB22-DZ22)+IF($K22=11,$D22,0) | AE22: =MAX(0,AE21*(1+AE$6/Setup!$C$13)-CC22-EA22)+IF($K22=12,$D22,0) | AF22: =MAX(0,AF21*(1+AF$6/Setup!$C$13)-CD22-EB22)+IF($K22=13,$D22,0) | AG22: =MAX(0,AG21*(1+AG$6/Setup!$C$13)-CE22-EC22)+IF($K22=14,$D22,0) | AH22: =MAX(0,AH21*(1+AH$6/Setup!$C$13)-CF22-ED22)+IF($K22=15,$D22,0) | AI22: =MAX(0,AI21*(1+AI$6/Setup!$C$13)-CG22-EE22)+IF($K22=16,$D22,0) | AJ22: =MAX(0,AJ21*(1+AJ$6/Setup!$C$13)-CH22-EF22)+IF($K22=17,$D22,0) | AK22: =MAX(0,AK21*(1+AK$6/Setup!$C$13)-CI22-EG22)+IF($K22=18,$D22,0) | AL22: =MAX(0,AL21*(1+AL$6/Setup!$C$13)-CJ22-EH22)+IF($K22=19,$D22,0) | AM22: =MAX(0,AM21*(1+AM$6/Setup!$C$13)-CK22-EI22)+IF($K22=20,$D22,0) | AN22: =MAX(0,AN21*(1+AN$6/Setup!$C$13)-CL22-EJ22)+IF($K22=21,$D22,0) | AO22: =MAX(0,AO21*(1+AO$6/Setup!$C$13)-CM22-EK22)+IF($K22=22,$D22,0) | AP22: =MAX(0,AP21*(1+AP$6/Setup!$C$13)-CN22-EL22)+IF($K22=23,$D22,0) | AQ22: =MAX(0,AQ21*(1+AQ$6/Setup!$C$13)-CO22-EM22)+IF($K22=24,$D22,0) | AR22: =MAX(0,AR21*(1+AR$6/Setup!$C$13)-CP22-EN22)+IF($K22=25,$D22,0) | AS22: =MAX(0,AS21*(1+AS$6/Setup!$C$13)-CQ22-EO22)+IF($K22=26,$D22,0) | AT22: =MAX(0,AT21*(1+AT$6/Setup!$C$13)-CR22-EP22)+IF($K22=27,$D22,0) | AU22: =MAX(0,AU21*(1+AU$6/Setup!$C$13)-CS22-EQ22)+IF($K22=28,$D22,0) | AV22: =MAX(0,AV21*(1+AV$6/Setup!$C$13)-CT22-ER22)+IF($K22=29,$D22,0) | AW22: =MAX(0,AW21*(1+AW$6/Setup!$C$13)-CU22-ES22)+IF($K22=30,$D22,0) | AX22: =MAX(0,AX21*(1+AX$6/Setup!$C$13)-CV22-ET22)+IF($K22=31,$D22,0) | AY22: =MAX(0,AY21*(1+AY$6/Setup!$C$13)-CW22-EU22)+IF($K22=32,$D22,0) | AZ22: =MAX(0,AZ21*(1+AZ$6/Setup!$C$13)-CX22-EV22)+IF($K22=33,$D22,0) | BA22: =MAX(0,BA21*(1+BA$6/Setup!$C$13)-CY22-EW22)+IF($K22=34,$D22,0) | BB22: =MAX(0,BB21*(1+BB$6/Setup!$C$13)-CZ22-EX22)+IF($K22=35,$D22,0) | BC22: =MAX(0,BC21*(1+BC$6/Setup!$C$13)-DA22-EY22)+IF($K22=36,$D22,0) | BD22: =MAX(0,BD21*(1+BD$6/Setup!$C$13)-DB22-EZ22)+IF($K22=37,$D22,0) | BE22: =MAX(0,BE21*(1+BE$6/Setup!$C$13)-DC22-FA22)+IF($K22=38,$D22,0) | BF22: =MAX(0,BF21*(1+BF$6/Setup!$C$13)-DD22-FB22)+IF($K22=39,$D22,0) | BG22: =MAX(0,BG21*(1+BG$6/Setup!$C$13)-DE22-FC22)+IF($K22=40,$D22,0) | BH22: =MAX(0,BH21*(1+BH$6/Setup!$C$13)-DF22-FD22)+IF($K22=41,$D22,0) | BI22: =MAX(0,BI21*(1+BI$6/Setup!$C$13)-DG22-FE22)+IF($K22=42,$D22,0) | BJ22: =MAX(0,BJ21*(1+BJ$6/Setup!$C$13)-DH22-FF22)+IF($K22=43,$D22,0) | BK22: =MAX(0,BK21*(1+BK$6/Setup!$C$13)-DI22-FG22)+IF($K22=44,$D22,0) | BL22: =MAX(0,BL21*(1+BL$6/Setup!$C$13)-DJ22-FH22)+IF($K22=45,$D22,0) | BM22: =MAX(0,BM21*(1+BM$6/Setup!$C$13)-DK22-FI22)+IF($K22=46,$D22,0) | BN22: =MAX(0,BN21*(1+BN$6/Setup!$C$13)-DL22-FJ22)+IF($K22=47,$D22,0) | BO22: =MAX(0,BO21*(1+BO$6/Setup!$C$13)-DM22-FK22)+IF($K22=48,$D22,0) | BP22: =MAX(0,BP21*(1+BP$6/Setup!$C$13)-DN22-FL22)+IF($K22=49,$D22,0) | BQ22: =MAX(0,BQ21*(1+BQ$6/Setup!$C$13)-DO22-FM22)+IF($K22=50,$D22,0) | BR22: =MIN(T21*(1+T$6/Setup!$C$13),T$7) | BS22: =MIN(U21*(1+U$6/Setup!$C$13),U$7) | BT22: =MIN(V21*(1+V$6/Setup!$C$13),V$7) | BU22: =MIN(W21*(1+W$6/Setup!$C$13),W$7) | BV22: =MIN(X21*(1+X$6/Setup!$C$13),X$7) | BW22: =MIN(Y21*(1+Y$6/Setup!$C$13),Y$7) | BX22: =MIN(Z21*(1+Z$6/Setup!$C$13),Z$7) | BY22: =MIN(AA21*(1+AA$6/Setup!$C$13),AA$7) | ... DO22: =MIN(BQ21*(1+BQ$6/Setup!$C$13),BQ$7) | DP22: =MIN(T21*(1+T$6/Setup!$C$13)-BR22,$H22) | DQ22: =MIN(U21*(1+U$6/Setup!$C$13)-BS22,MAX(0,$H22-SUM($DP22:DP22))) | DR22: =MIN(V21*(1+V$6/Setup!$C$13)-BT22,MAX(0,$H22-SUM($DP22:DQ22))) | DS22: =MIN(W21*(1+W$6/Setup!$C$13)-BU22,MAX(0,$H22-SUM($DP22:DR22))) | DT22: =MIN(X21*(1+X$6/Setup!$C$13)-BV22,MAX(0,$H22-SUM($DP22:DS22))) | DU22: =MIN(Y21*(1+Y$6/Setup!$C$13)-BW22,MAX(0,$H22-SUM($DP22:DT22))) | DV22: =MIN(Z21*(1+Z$6/Setup!$C$13)-BX22,MAX(0,$H22-SUM($DP22:DU22))) | DW22: =MIN(AA21*(1+AA$6/Setup!$C$13)-BY22,MAX(0,$H22-SUM($DP22:DV22))) | DX22: =MIN(AB21*(1+AB$6/Setup!$C$13)-BZ22,MAX(0,$H22-SUM($DP22:DW22))) | ... FM22: =MIN(BQ21*(1+BQ$6/Setup!$C$13)-DO22,MAX(0,$H22-SUM($DP22:FL22)))
A23: =A22+1 | B23: =IF(Setup!$C$6="Every week",Setup!$C$7+7*(A23-1),IF(Setup!$C$6="Every 2 weeks",Setup!$C$7+14*(A23-1),IF(Setup!$C$6="Every month",EDATE(Setup!$C$7,A23-1),EOMONTH(Setup!$C$7,INT((A23-1+Setup!$C$20)/2)-1)+MIN(IF(MOD(A23-1+Setup!$C$20,2)=0,Setup!$C$18,Setup!$C$19),DAY(EOMONTH(Setup!$C$7,INT((A23-1+Setup!$C$20)/2))))))) | C23: =N('Paycheck Plan'!J19) | D23: =N('Paycheck Plan'!K19) | E23: =MIN(MAX(0,Setup!$C$10-F22),MAX(0,Setup!$C$8+C23-G23)) | F23: =F22+E23 | G23: =MIN(Setup!$C$14,MAX(0,Setup!$C$8+C23)) | H23: =MAX(0,Setup!$C$8+C23-G23-E23)+SUM($T$7:$BQ$7)-SUM(BR23:DO23) | I23: =SUMPRODUCT(T22:BQ22,$T$6:$BQ$6)/Setup!$C$13 | J23: =SUM(T23:BQ23) | K23: =IF(MAX(DP23:FM23)>0,MATCH(MAX(DP23:FM23),DP23:FM23,0),1) | M23: =ROUND(12*$B$2/39,0)+1 | N23: =INDEX($B$10:$B$530,MIN(M23,521)) | O23: =INDEX($J$10:$J$530,MIN(M23,521)) | T23: =MAX(0,T22*(1+T$6/Setup!$C$13)-BR23-DP23)+IF($K23=1,$D23,0) | U23: =MAX(0,U22*(1+U$6/Setup!$C$13)-BS23-DQ23)+IF($K23=2,$D23,0) | V23: =MAX(0,V22*(1+V$6/Setup!$C$13)-BT23-DR23)+IF($K23=3,$D23,0) | W23: =MAX(0,W22*(1+W$6/Setup!$C$13)-BU23-DS23)+IF($K23=4,$D23,0) | X23: =MAX(0,X22*(1+X$6/Setup!$C$13)-BV23-DT23)+IF($K23=5,$D23,0) | Y23: =MAX(0,Y22*(1+Y$6/Setup!$C$13)-BW23-DU23)+IF($K23=6,$D23,0) | Z23: =MAX(0,Z22*(1+Z$6/Setup!$C$13)-BX23-DV23)+IF($K23=7,$D23,0) | AA23: =MAX(0,AA22*(1+AA$6/Setup!$C$13)-BY23-DW23)+IF($K23=8,$D23,0) | AB23: =MAX(0,AB22*(1+AB$6/Setup!$C$13)-BZ23-DX23)+IF($K23=9,$D23,0) | AC23: =MAX(0,AC22*(1+AC$6/Setup!$C$13)-CA23-DY23)+IF($K23=10,$D23,0) | AD23: =MAX(0,AD22*(1+AD$6/Setup!$C$13)-CB23-DZ23)+IF($K23=11,$D23,0) | AE23: =MAX(0,AE22*(1+AE$6/Setup!$C$13)-CC23-EA23)+IF($K23=12,$D23,0) | AF23: =MAX(0,AF22*(1+AF$6/Setup!$C$13)-CD23-EB23)+IF($K23=13,$D23,0) | AG23: =MAX(0,AG22*(1+AG$6/Setup!$C$13)-CE23-EC23)+IF($K23=14,$D23,0) | AH23: =MAX(0,AH22*(1+AH$6/Setup!$C$13)-CF23-ED23)+IF($K23=15,$D23,0) | AI23: =MAX(0,AI22*(1+AI$6/Setup!$C$13)-CG23-EE23)+IF($K23=16,$D23,0) | AJ23: =MAX(0,AJ22*(1+AJ$6/Setup!$C$13)-CH23-EF23)+IF($K23=17,$D23,0) | AK23: =MAX(0,AK22*(1+AK$6/Setup!$C$13)-CI23-EG23)+IF($K23=18,$D23,0) | AL23: =MAX(0,AL22*(1+AL$6/Setup!$C$13)-CJ23-EH23)+IF($K23=19,$D23,0) | AM23: =MAX(0,AM22*(1+AM$6/Setup!$C$13)-CK23-EI23)+IF($K23=20,$D23,0) | AN23: =MAX(0,AN22*(1+AN$6/Setup!$C$13)-CL23-EJ23)+IF($K23=21,$D23,0) | AO23: =MAX(0,AO22*(1+AO$6/Setup!$C$13)-CM23-EK23)+IF($K23=22,$D23,0) | AP23: =MAX(0,AP22*(1+AP$6/Setup!$C$13)-CN23-EL23)+IF($K23=23,$D23,0) | AQ23: =MAX(0,AQ22*(1+AQ$6/Setup!$C$13)-CO23-EM23)+IF($K23=24,$D23,0) | AR23: =MAX(0,AR22*(1+AR$6/Setup!$C$13)-CP23-EN23)+IF($K23=25,$D23,0) | AS23: =MAX(0,AS22*(1+AS$6/Setup!$C$13)-CQ23-EO23)+IF($K23=26,$D23,0) | AT23: =MAX(0,AT22*(1+AT$6/Setup!$C$13)-CR23-EP23)+IF($K23=27,$D23,0) | AU23: =MAX(0,AU22*(1+AU$6/Setup!$C$13)-CS23-EQ23)+IF($K23=28,$D23,0) | AV23: =MAX(0,AV22*(1+AV$6/Setup!$C$13)-CT23-ER23)+IF($K23=29,$D23,0) | AW23: =MAX(0,AW22*(1+AW$6/Setup!$C$13)-CU23-ES23)+IF($K23=30,$D23,0) | AX23: =MAX(0,AX22*(1+AX$6/Setup!$C$13)-CV23-ET23)+IF($K23=31,$D23,0) | AY23: =MAX(0,AY22*(1+AY$6/Setup!$C$13)-CW23-EU23)+IF($K23=32,$D23,0) | AZ23: =MAX(0,AZ22*(1+AZ$6/Setup!$C$13)-CX23-EV23)+IF($K23=33,$D23,0) | BA23: =MAX(0,BA22*(1+BA$6/Setup!$C$13)-CY23-EW23)+IF($K23=34,$D23,0) | BB23: =MAX(0,BB22*(1+BB$6/Setup!$C$13)-CZ23-EX23)+IF($K23=35,$D23,0) | BC23: =MAX(0,BC22*(1+BC$6/Setup!$C$13)-DA23-EY23)+IF($K23=36,$D23,0) | BD23: =MAX(0,BD22*(1+BD$6/Setup!$C$13)-DB23-EZ23)+IF($K23=37,$D23,0) | BE23: =MAX(0,BE22*(1+BE$6/Setup!$C$13)-DC23-FA23)+IF($K23=38,$D23,0) | BF23: =MAX(0,BF22*(1+BF$6/Setup!$C$13)-DD23-FB23)+IF($K23=39,$D23,0) | BG23: =MAX(0,BG22*(1+BG$6/Setup!$C$13)-DE23-FC23)+IF($K23=40,$D23,0) | BH23: =MAX(0,BH22*(1+BH$6/Setup!$C$13)-DF23-FD23)+IF($K23=41,$D23,0) | BI23: =MAX(0,BI22*(1+BI$6/Setup!$C$13)-DG23-FE23)+IF($K23=42,$D23,0) | BJ23: =MAX(0,BJ22*(1+BJ$6/Setup!$C$13)-DH23-FF23)+IF($K23=43,$D23,0) | BK23: =MAX(0,BK22*(1+BK$6/Setup!$C$13)-DI23-FG23)+IF($K23=44,$D23,0) | BL23: =MAX(0,BL22*(1+BL$6/Setup!$C$13)-DJ23-FH23)+IF($K23=45,$D23,0) | BM23: =MAX(0,BM22*(1+BM$6/Setup!$C$13)-DK23-FI23)+IF($K23=46,$D23,0) | BN23: =MAX(0,BN22*(1+BN$6/Setup!$C$13)-DL23-FJ23)+IF($K23=47,$D23,0) | BO23: =MAX(0,BO22*(1+BO$6/Setup!$C$13)-DM23-FK23)+IF($K23=48,$D23,0) | BP23: =MAX(0,BP22*(1+BP$6/Setup!$C$13)-DN23-FL23)+IF($K23=49,$D23,0) | BQ23: =MAX(0,BQ22*(1+BQ$6/Setup!$C$13)-DO23-FM23)+IF($K23=50,$D23,0) | BR23: =MIN(T22*(1+T$6/Setup!$C$13),T$7) | BS23: =MIN(U22*(1+U$6/Setup!$C$13),U$7) | BT23: =MIN(V22*(1+V$6/Setup!$C$13),V$7) | BU23: =MIN(W22*(1+W$6/Setup!$C$13),W$7) | BV23: =MIN(X22*(1+X$6/Setup!$C$13),X$7) | BW23: =MIN(Y22*(1+Y$6/Setup!$C$13),Y$7) | BX23: =MIN(Z22*(1+Z$6/Setup!$C$13),Z$7) | BY23: =MIN(AA22*(1+AA$6/Setup!$C$13),AA$7) | ... DO23: =MIN(BQ22*(1+BQ$6/Setup!$C$13),BQ$7) | DP23: =MIN(T22*(1+T$6/Setup!$C$13)-BR23,$H23) | DQ23: =MIN(U22*(1+U$6/Setup!$C$13)-BS23,MAX(0,$H23-SUM($DP23:DP23))) | DR23: =MIN(V22*(1+V$6/Setup!$C$13)-BT23,MAX(0,$H23-SUM($DP23:DQ23))) | DS23: =MIN(W22*(1+W$6/Setup!$C$13)-BU23,MAX(0,$H23-SUM($DP23:DR23))) | DT23: =MIN(X22*(1+X$6/Setup!$C$13)-BV23,MAX(0,$H23-SUM($DP23:DS23))) | DU23: =MIN(Y22*(1+Y$6/Setup!$C$13)-BW23,MAX(0,$H23-SUM($DP23:DT23))) | DV23: =MIN(Z22*(1+Z$6/Setup!$C$13)-BX23,MAX(0,$H23-SUM($DP23:DU23))) | DW23: =MIN(AA22*(1+AA$6/Setup!$C$13)-BY23,MAX(0,$H23-SUM($DP23:DV23))) | DX23: =MIN(AB22*(1+AB$6/Setup!$C$13)-BZ23,MAX(0,$H23-SUM($DP23:DW23))) | ... FM23: =MIN(BQ22*(1+BQ$6/Setup!$C$13)-DO23,MAX(0,$H23-SUM($DP23:FL23)))
A24: =A23+1 | B24: =IF(Setup!$C$6="Every week",Setup!$C$7+7*(A24-1),IF(Setup!$C$6="Every 2 weeks",Setup!$C$7+14*(A24-1),IF(Setup!$C$6="Every month",EDATE(Setup!$C$7,A24-1),EOMONTH(Setup!$C$7,INT((A24-1+Setup!$C$20)/2)-1)+MIN(IF(MOD(A24-1+Setup!$C$20,2)=0,Setup!$C$18,Setup!$C$19),DAY(EOMONTH(Setup!$C$7,INT((A24-1+Setup!$C$20)/2))))))) | C24: =N('Paycheck Plan'!J20) | D24: =N('Paycheck Plan'!K20) | E24: =MIN(MAX(0,Setup!$C$10-F23),MAX(0,Setup!$C$8+C24-G24)) | F24: =F23+E24 | G24: =MIN(Setup!$C$14,MAX(0,Setup!$C$8+C24)) | H24: =MAX(0,Setup!$C$8+C24-G24-E24)+SUM($T$7:$BQ$7)-SUM(BR24:DO24) | I24: =SUMPRODUCT(T23:BQ23,$T$6:$BQ$6)/Setup!$C$13 | J24: =SUM(T24:BQ24) | K24: =IF(MAX(DP24:FM24)>0,MATCH(MAX(DP24:FM24),DP24:FM24,0),1) | M24: =ROUND(13*$B$2/39,0)+1 | N24: =INDEX($B$10:$B$530,MIN(M24,521)) | O24: =INDEX($J$10:$J$530,MIN(M24,521)) | T24: =MAX(0,T23*(1+T$6/Setup!$C$13)-BR24-DP24)+IF($K24=1,$D24,0) | U24: =MAX(0,U23*(1+U$6/Setup!$C$13)-BS24-DQ24)+IF($K24=2,$D24,0) | V24: =MAX(0,V23*(1+V$6/Setup!$C$13)-BT24-DR24)+IF($K24=3,$D24,0) | W24: =MAX(0,W23*(1+W$6/Setup!$C$13)-BU24-DS24)+IF($K24=4,$D24,0) | X24: =MAX(0,X23*(1+X$6/Setup!$C$13)-BV24-DT24)+IF($K24=5,$D24,0) | Y24: =MAX(0,Y23*(1+Y$6/Setup!$C$13)-BW24-DU24)+IF($K24=6,$D24,0) | Z24: =MAX(0,Z23*(1+Z$6/Setup!$C$13)-BX24-DV24)+IF($K24=7,$D24,0) | AA24: =MAX(0,AA23*(1+AA$6/Setup!$C$13)-BY24-DW24)+IF($K24=8,$D24,0) | AB24: =MAX(0,AB23*(1+AB$6/Setup!$C$13)-BZ24-DX24)+IF($K24=9,$D24,0) | AC24: =MAX(0,AC23*(1+AC$6/Setup!$C$13)-CA24-DY24)+IF($K24=10,$D24,0) | AD24: =MAX(0,AD23*(1+AD$6/Setup!$C$13)-CB24-DZ24)+IF($K24=11,$D24,0) | AE24: =MAX(0,AE23*(1+AE$6/Setup!$C$13)-CC24-EA24)+IF($K24=12,$D24,0) | AF24: =MAX(0,AF23*(1+AF$6/Setup!$C$13)-CD24-EB24)+IF($K24=13,$D24,0) | AG24: =MAX(0,AG23*(1+AG$6/Setup!$C$13)-CE24-EC24)+IF($K24=14,$D24,0) | AH24: =MAX(0,AH23*(1+AH$6/Setup!$C$13)-CF24-ED24)+IF($K24=15,$D24,0) | AI24: =MAX(0,AI23*(1+AI$6/Setup!$C$13)-CG24-EE24)+IF($K24=16,$D24,0) | AJ24: =MAX(0,AJ23*(1+AJ$6/Setup!$C$13)-CH24-EF24)+IF($K24=17,$D24,0) | AK24: =MAX(0,AK23*(1+AK$6/Setup!$C$13)-CI24-EG24)+IF($K24=18,$D24,0) | AL24: =MAX(0,AL23*(1+AL$6/Setup!$C$13)-CJ24-EH24)+IF($K24=19,$D24,0) | AM24: =MAX(0,AM23*(1+AM$6/Setup!$C$13)-CK24-EI24)+IF($K24=20,$D24,0) | AN24: =MAX(0,AN23*(1+AN$6/Setup!$C$13)-CL24-EJ24)+IF($K24=21,$D24,0) | AO24: =MAX(0,AO23*(1+AO$6/Setup!$C$13)-CM24-EK24)+IF($K24=22,$D24,0) | AP24: =MAX(0,AP23*(1+AP$6/Setup!$C$13)-CN24-EL24)+IF($K24=23,$D24,0) | AQ24: =MAX(0,AQ23*(1+AQ$6/Setup!$C$13)-CO24-EM24)+IF($K24=24,$D24,0) | AR24: =MAX(0,AR23*(1+AR$6/Setup!$C$13)-CP24-EN24)+IF($K24=25,$D24,0) | AS24: =MAX(0,AS23*(1+AS$6/Setup!$C$13)-CQ24-EO24)+IF($K24=26,$D24,0) | AT24: =MAX(0,AT23*(1+AT$6/Setup!$C$13)-CR24-EP24)+IF($K24=27,$D24,0) | AU24: =MAX(0,AU23*(1+AU$6/Setup!$C$13)-CS24-EQ24)+IF($K24=28,$D24,0) | AV24: =MAX(0,AV23*(1+AV$6/Setup!$C$13)-CT24-ER24)+IF($K24=29,$D24,0) | AW24: =MAX(0,AW23*(1+AW$6/Setup!$C$13)-CU24-ES24)+IF($K24=30,$D24,0) | AX24: =MAX(0,AX23*(1+AX$6/Setup!$C$13)-CV24-ET24)+IF($K24=31,$D24,0) | AY24: =MAX(0,AY23*(1+AY$6/Setup!$C$13)-CW24-EU24)+IF($K24=32,$D24,0) | AZ24: =MAX(0,AZ23*(1+AZ$6/Setup!$C$13)-CX24-EV24)+IF($K24=33,$D24,0) | BA24: =MAX(0,BA23*(1+BA$6/Setup!$C$13)-CY24-EW24)+IF($K24=34,$D24,0) | BB24: =MAX(0,BB23*(1+BB$6/Setup!$C$13)-CZ24-EX24)+IF($K24=35,$D24,0) | BC24: =MAX(0,BC23*(1+BC$6/Setup!$C$13)-DA24-EY24)+IF($K24=36,$D24,0) | BD24: =MAX(0,BD23*(1+BD$6/Setup!$C$13)-DB24-EZ24)+IF($K24=37,$D24,0) | BE24: =MAX(0,BE23*(1+BE$6/Setup!$C$13)-DC24-FA24)+IF($K24=38,$D24,0) | BF24: =MAX(0,BF23*(1+BF$6/Setup!$C$13)-DD24-FB24)+IF($K24=39,$D24,0) | BG24: =MAX(0,BG23*(1+BG$6/Setup!$C$13)-DE24-FC24)+IF($K24=40,$D24,0) | BH24: =MAX(0,BH23*(1+BH$6/Setup!$C$13)-DF24-FD24)+IF($K24=41,$D24,0) | BI24: =MAX(0,BI23*(1+BI$6/Setup!$C$13)-DG24-FE24)+IF($K24=42,$D24,0) | BJ24: =MAX(0,BJ23*(1+BJ$6/Setup!$C$13)-DH24-FF24)+IF($K24=43,$D24,0) | BK24: =MAX(0,BK23*(1+BK$6/Setup!$C$13)-DI24-FG24)+IF($K24=44,$D24,0) | BL24: =MAX(0,BL23*(1+BL$6/Setup!$C$13)-DJ24-FH24)+IF($K24=45,$D24,0) | BM24: =MAX(0,BM23*(1+BM$6/Setup!$C$13)-DK24-FI24)+IF($K24=46,$D24,0) | BN24: =MAX(0,BN23*(1+BN$6/Setup!$C$13)-DL24-FJ24)+IF($K24=47,$D24,0) | BO24: =MAX(0,BO23*(1+BO$6/Setup!$C$13)-DM24-FK24)+IF($K24=48,$D24,0) | BP24: =MAX(0,BP23*(1+BP$6/Setup!$C$13)-DN24-FL24)+IF($K24=49,$D24,0) | BQ24: =MAX(0,BQ23*(1+BQ$6/Setup!$C$13)-DO24-FM24)+IF($K24=50,$D24,0) | BR24: =MIN(T23*(1+T$6/Setup!$C$13),T$7) | BS24: =MIN(U23*(1+U$6/Setup!$C$13),U$7) | BT24: =MIN(V23*(1+V$6/Setup!$C$13),V$7) | BU24: =MIN(W23*(1+W$6/Setup!$C$13),W$7) | BV24: =MIN(X23*(1+X$6/Setup!$C$13),X$7) | BW24: =MIN(Y23*(1+Y$6/Setup!$C$13),Y$7) | BX24: =MIN(Z23*(1+Z$6/Setup!$C$13),Z$7) | BY24: =MIN(AA23*(1+AA$6/Setup!$C$13),AA$7) | ... DO24: =MIN(BQ23*(1+BQ$6/Setup!$C$13),BQ$7) | DP24: =MIN(T23*(1+T$6/Setup!$C$13)-BR24,$H24) | DQ24: =MIN(U23*(1+U$6/Setup!$C$13)-BS24,MAX(0,$H24-SUM($DP24:DP24))) | DR24: =MIN(V23*(1+V$6/Setup!$C$13)-BT24,MAX(0,$H24-SUM($DP24:DQ24))) | DS24: =MIN(W23*(1+W$6/Setup!$C$13)-BU24,MAX(0,$H24-SUM($DP24:DR24))) | DT24: =MIN(X23*(1+X$6/Setup!$C$13)-BV24,MAX(0,$H24-SUM($DP24:DS24))) | DU24: =MIN(Y23*(1+Y$6/Setup!$C$13)-BW24,MAX(0,$H24-SUM($DP24:DT24))) | DV24: =MIN(Z23*(1+Z$6/Setup!$C$13)-BX24,MAX(0,$H24-SUM($DP24:DU24))) | DW24: =MIN(AA23*(1+AA$6/Setup!$C$13)-BY24,MAX(0,$H24-SUM($DP24:DV24))) | DX24: =MIN(AB23*(1+AB$6/Setup!$C$13)-BZ24,MAX(0,$H24-SUM($DP24:DW24))) | ... FM24: =MIN(BQ23*(1+BQ$6/Setup!$C$13)-DO24,MAX(0,$H24-SUM($DP24:FL24)))
A25: =A24+1 | B25: =IF(Setup!$C$6="Every week",Setup!$C$7+7*(A25-1),IF(Setup!$C$6="Every 2 weeks",Setup!$C$7+14*(A25-1),IF(Setup!$C$6="Every month",EDATE(Setup!$C$7,A25-1),EOMONTH(Setup!$C$7,INT((A25-1+Setup!$C$20)/2)-1)+MIN(IF(MOD(A25-1+Setup!$C$20,2)=0,Setup!$C$18,Setup!$C$19),DAY(EOMONTH(Setup!$C$7,INT((A25-1+Setup!$C$20)/2))))))) | C25: =N('Paycheck Plan'!J21) | D25: =N('Paycheck Plan'!K21) | E25: =MIN(MAX(0,Setup!$C$10-F24),MAX(0,Setup!$C$8+C25-G25)) | F25: =F24+E25 | G25: =MIN(Setup!$C$14,MAX(0,Setup!$C$8+C25)) | H25: =MAX(0,Setup!$C$8+C25-G25-E25)+SUM($T$7:$BQ$7)-SUM(BR25:DO25) | I25: =SUMPRODUCT(T24:BQ24,$T$6:$BQ$6)/Setup!$C$13 | J25: =SUM(T25:BQ25) | K25: =IF(MAX(DP25:FM25)>0,MATCH(MAX(DP25:FM25),DP25:FM25,0),1) | M25: =ROUND(14*$B$2/39,0)+1 | N25: =INDEX($B$10:$B$530,MIN(M25,521)) | O25: =INDEX($J$10:$J$530,MIN(M25,521)) | T25: =MAX(0,T24*(1+T$6/Setup!$C$13)-BR25-DP25)+IF($K25=1,$D25,0) | U25: =MAX(0,U24*(1+U$6/Setup!$C$13)-BS25-DQ25)+IF($K25=2,$D25,0) | V25: =MAX(0,V24*(1+V$6/Setup!$C$13)-BT25-DR25)+IF($K25=3,$D25,0) | W25: =MAX(0,W24*(1+W$6/Setup!$C$13)-BU25-DS25)+IF($K25=4,$D25,0) | X25: =MAX(0,X24*(1+X$6/Setup!$C$13)-BV25-DT25)+IF($K25=5,$D25,0) | Y25: =MAX(0,Y24*(1+Y$6/Setup!$C$13)-BW25-DU25)+IF($K25=6,$D25,0) | Z25: =MAX(0,Z24*(1+Z$6/Setup!$C$13)-BX25-DV25)+IF($K25=7,$D25,0) | AA25: =MAX(0,AA24*(1+AA$6/Setup!$C$13)-BY25-DW25)+IF($K25=8,$D25,0) | AB25: =MAX(0,AB24*(1+AB$6/Setup!$C$13)-BZ25-DX25)+IF($K25=9,$D25,0) | AC25: =MAX(0,AC24*(1+AC$6/Setup!$C$13)-CA25-DY25)+IF($K25=10,$D25,0) | AD25: =MAX(0,AD24*(1+AD$6/Setup!$C$13)-CB25-DZ25)+IF($K25=11,$D25,0) | AE25: =MAX(0,AE24*(1+AE$6/Setup!$C$13)-CC25-EA25)+IF($K25=12,$D25,0) | AF25: =MAX(0,AF24*(1+AF$6/Setup!$C$13)-CD25-EB25)+IF($K25=13,$D25,0) | AG25: =MAX(0,AG24*(1+AG$6/Setup!$C$13)-CE25-EC25)+IF($K25=14,$D25,0) | AH25: =MAX(0,AH24*(1+AH$6/Setup!$C$13)-CF25-ED25)+IF($K25=15,$D25,0) | AI25: =MAX(0,AI24*(1+AI$6/Setup!$C$13)-CG25-EE25)+IF($K25=16,$D25,0) | AJ25: =MAX(0,AJ24*(1+AJ$6/Setup!$C$13)-CH25-EF25)+IF($K25=17,$D25,0) | AK25: =MAX(0,AK24*(1+AK$6/Setup!$C$13)-CI25-EG25)+IF($K25=18,$D25,0) | AL25: =MAX(0,AL24*(1+AL$6/Setup!$C$13)-CJ25-EH25)+IF($K25=19,$D25,0) | AM25: =MAX(0,AM24*(1+AM$6/Setup!$C$13)-CK25-EI25)+IF($K25=20,$D25,0) | AN25: =MAX(0,AN24*(1+AN$6/Setup!$C$13)-CL25-EJ25)+IF($K25=21,$D25,0) | AO25: =MAX(0,AO24*(1+AO$6/Setup!$C$13)-CM25-EK25)+IF($K25=22,$D25,0) | AP25: =MAX(0,AP24*(1+AP$6/Setup!$C$13)-CN25-EL25)+IF($K25=23,$D25,0) | AQ25: =MAX(0,AQ24*(1+AQ$6/Setup!$C$13)-CO25-EM25)+IF($K25=24,$D25,0) | AR25: =MAX(0,AR24*(1+AR$6/Setup!$C$13)-CP25-EN25)+IF($K25=25,$D25,0) | AS25: =MAX(0,AS24*(1+AS$6/Setup!$C$13)-CQ25-EO25)+IF($K25=26,$D25,0) | AT25: =MAX(0,AT24*(1+AT$6/Setup!$C$13)-CR25-EP25)+IF($K25=27,$D25,0) | AU25: =MAX(0,AU24*(1+AU$6/Setup!$C$13)-CS25-EQ25)+IF($K25=28,$D25,0) | AV25: =MAX(0,AV24*(1+AV$6/Setup!$C$13)-CT25-ER25)+IF($K25=29,$D25,0) | AW25: =MAX(0,AW24*(1+AW$6/Setup!$C$13)-CU25-ES25)+IF($K25=30,$D25,0) | AX25: =MAX(0,AX24*(1+AX$6/Setup!$C$13)-CV25-ET25)+IF($K25=31,$D25,0) | AY25: =MAX(0,AY24*(1+AY$6/Setup!$C$13)-CW25-EU25)+IF($K25=32,$D25,0) | AZ25: =MAX(0,AZ24*(1+AZ$6/Setup!$C$13)-CX25-EV25)+IF($K25=33,$D25,0) | BA25: =MAX(0,BA24*(1+BA$6/Setup!$C$13)-CY25-EW25)+IF($K25=34,$D25,0) | BB25: =MAX(0,BB24*(1+BB$6/Setup!$C$13)-CZ25-EX25)+IF($K25=35,$D25,0) | BC25: =MAX(0,BC24*(1+BC$6/Setup!$C$13)-DA25-EY25)+IF($K25=36,$D25,0) | BD25: =MAX(0,BD24*(1+BD$6/Setup!$C$13)-DB25-EZ25)+IF($K25=37,$D25,0) | BE25: =MAX(0,BE24*(1+BE$6/Setup!$C$13)-DC25-FA25)+IF($K25=38,$D25,0) | BF25: =MAX(0,BF24*(1+BF$6/Setup!$C$13)-DD25-FB25)+IF($K25=39,$D25,0) | BG25: =MAX(0,BG24*(1+BG$6/Setup!$C$13)-DE25-FC25)+IF($K25=40,$D25,0) | BH25: =MAX(0,BH24*(1+BH$6/Setup!$C$13)-DF25-FD25)+IF($K25=41,$D25,0) | BI25: =MAX(0,BI24*(1+BI$6/Setup!$C$13)-DG25-FE25)+IF($K25=42,$D25,0) | BJ25: =MAX(0,BJ24*(1+BJ$6/Setup!$C$13)-DH25-FF25)+IF($K25=43,$D25,0) | BK25: =MAX(0,BK24*(1+BK$6/Setup!$C$13)-DI25-FG25)+IF($K25=44,$D25,0) | BL25: =MAX(0,BL24*(1+BL$6/Setup!$C$13)-DJ25-FH25)+IF($K25=45,$D25,0) | BM25: =MAX(0,BM24*(1+BM$6/Setup!$C$13)-DK25-FI25)+IF($K25=46,$D25,0) | BN25: =MAX(0,BN24*(1+BN$6/Setup!$C$13)-DL25-FJ25)+IF($K25=47,$D25,0) | BO25: =MAX(0,BO24*(1+BO$6/Setup!$C$13)-DM25-FK25)+IF($K25=48,$D25,0) | BP25: =MAX(0,BP24*(1+BP$6/Setup!$C$13)-DN25-FL25)+IF($K25=49,$D25,0) | BQ25: =MAX(0,BQ24*(1+BQ$6/Setup!$C$13)-DO25-FM25)+IF($K25=50,$D25,0) | BR25: =MIN(T24*(1+T$6/Setup!$C$13),T$7) | BS25: =MIN(U24*(1+U$6/Setup!$C$13),U$7) | BT25: =MIN(V24*(1+V$6/Setup!$C$13),V$7) | BU25: =MIN(W24*(1+W$6/Setup!$C$13),W$7) | BV25: =MIN(X24*(1+X$6/Setup!$C$13),X$7) | BW25: =MIN(Y24*(1+Y$6/Setup!$C$13),Y$7) | BX25: =MIN(Z24*(1+Z$6/Setup!$C$13),Z$7) | BY25: =MIN(AA24*(1+AA$6/Setup!$C$13),AA$7) | ... DO25: =MIN(BQ24*(1+BQ$6/Setup!$C$13),BQ$7) | DP25: =MIN(T24*(1+T$6/Setup!$C$13)-BR25,$H25) | DQ25: =MIN(U24*(1+U$6/Setup!$C$13)-BS25,MAX(0,$H25-SUM($DP25:DP25))) | DR25: =MIN(V24*(1+V$6/Setup!$C$13)-BT25,MAX(0,$H25-SUM($DP25:DQ25))) | DS25: =MIN(W24*(1+W$6/Setup!$C$13)-BU25,MAX(0,$H25-SUM($DP25:DR25))) | DT25: =MIN(X24*(1+X$6/Setup!$C$13)-BV25,MAX(0,$H25-SUM($DP25:DS25))) | DU25: =MIN(Y24*(1+Y$6/Setup!$C$13)-BW25,MAX(0,$H25-SUM($DP25:DT25))) | DV25: =MIN(Z24*(1+Z$6/Setup!$C$13)-BX25,MAX(0,$H25-SUM($DP25:DU25))) | DW25: =MIN(AA24*(1+AA$6/Setup!$C$13)-BY25,MAX(0,$H25-SUM($DP25:DV25))) | DX25: =MIN(AB24*(1+AB$6/Setup!$C$13)-BZ25,MAX(0,$H25-SUM($DP25:DW25))) | ... FM25: =MIN(BQ24*(1+BQ$6/Setup!$C$13)-DO25,MAX(0,$H25-SUM($DP25:FL25)))
A26: =A25+1 | B26: =IF(Setup!$C$6="Every week",Setup!$C$7+7*(A26-1),IF(Setup!$C$6="Every 2 weeks",Setup!$C$7+14*(A26-1),IF(Setup!$C$6="Every month",EDATE(Setup!$C$7,A26-1),EOMONTH(Setup!$C$7,INT((A26-1+Setup!$C$20)/2)-1)+MIN(IF(MOD(A26-1+Setup!$C$20,2)=0,Setup!$C$18,Setup!$C$19),DAY(EOMONTH(Setup!$C$7,INT((A26-1+Setup!$C$20)/2))))))) | C26: =N('Paycheck Plan'!J22) | D26: =N('Paycheck Plan'!K22) | E26: =MIN(MAX(0,Setup!$C$10-F25),MAX(0,Setup!$C$8+C26-G26)) | F26: =F25+E26 | G26: =MIN(Setup!$C$14,MAX(0,Setup!$C$8+C26)) | H26: =MAX(0,Setup!$C$8+C26-G26-E26)+SUM($T$7:$BQ$7)-SUM(BR26:DO26) | I26: =SUMPRODUCT(T25:BQ25,$T$6:$BQ$6)/Setup!$C$13 | J26: =SUM(T26:BQ26) | K26: =IF(MAX(DP26:FM26)>0,MATCH(MAX(DP26:FM26),DP26:FM26,0),1) | M26: =ROUND(15*$B$2/39,0)+1 | N26: =INDEX($B$10:$B$530,MIN(M26,521)) | O26: =INDEX($J$10:$J$530,MIN(M26,521)) | T26: =MAX(0,T25*(1+T$6/Setup!$C$13)-BR26-DP26)+IF($K26=1,$D26,0) | U26: =MAX(0,U25*(1+U$6/Setup!$C$13)-BS26-DQ26)+IF($K26=2,$D26,0) | V26: =MAX(0,V25*(1+V$6/Setup!$C$13)-BT26-DR26)+IF($K26=3,$D26,0) | W26: =MAX(0,W25*(1+W$6/Setup!$C$13)-BU26-DS26)+IF($K26=4,$D26,0) | X26: =MAX(0,X25*(1+X$6/Setup!$C$13)-BV26-DT26)+IF($K26=5,$D26,0) | Y26: =MAX(0,Y25*(1+Y$6/Setup!$C$13)-BW26-DU26)+IF($K26=6,$D26,0) | Z26: =MAX(0,Z25*(1+Z$6/Setup!$C$13)-BX26-DV26)+IF($K26=7,$D26,0) | AA26: =MAX(0,AA25*(1+AA$6/Setup!$C$13)-BY26-DW26)+IF($K26=8,$D26,0) | AB26: =MAX(0,AB25*(1+AB$6/Setup!$C$13)-BZ26-DX26)+IF($K26=9,$D26,0) | AC26: =MAX(0,AC25*(1+AC$6/Setup!$C$13)-CA26-DY26)+IF($K26=10,$D26,0) | AD26: =MAX(0,AD25*(1+AD$6/Setup!$C$13)-CB26-DZ26)+IF($K26=11,$D26,0) | AE26: =MAX(0,AE25*(1+AE$6/Setup!$C$13)-CC26-EA26)+IF($K26=12,$D26,0) | AF26: =MAX(0,AF25*(1+AF$6/Setup!$C$13)-CD26-EB26)+IF($K26=13,$D26,0) | AG26: =MAX(0,AG25*(1+AG$6/Setup!$C$13)-CE26-EC26)+IF($K26=14,$D26,0) | AH26: =MAX(0,AH25*(1+AH$6/Setup!$C$13)-CF26-ED26)+IF($K26=15,$D26,0) | AI26: =MAX(0,AI25*(1+AI$6/Setup!$C$13)-CG26-EE26)+IF($K26=16,$D26,0) | AJ26: =MAX(0,AJ25*(1+AJ$6/Setup!$C$13)-CH26-EF26)+IF($K26=17,$D26,0) | AK26: =MAX(0,AK25*(1+AK$6/Setup!$C$13)-CI26-EG26)+IF($K26=18,$D26,0) | AL26: =MAX(0,AL25*(1+AL$6/Setup!$C$13)-CJ26-EH26)+IF($K26=19,$D26,0) | AM26: =MAX(0,AM25*(1+AM$6/Setup!$C$13)-CK26-EI26)+IF($K26=20,$D26,0) | AN26: =MAX(0,AN25*(1+AN$6/Setup!$C$13)-CL26-EJ26)+IF($K26=21,$D26,0) | AO26: =MAX(0,AO25*(1+AO$6/Setup!$C$13)-CM26-EK26)+IF($K26=22,$D26,0) | AP26: =MAX(0,AP25*(1+AP$6/Setup!$C$13)-CN26-EL26)+IF($K26=23,$D26,0) | AQ26: =MAX(0,AQ25*(1+AQ$6/Setup!$C$13)-CO26-EM26)+IF($K26=24,$D26,0) | AR26: =MAX(0,AR25*(1+AR$6/Setup!$C$13)-CP26-EN26)+IF($K26=25,$D26,0) | AS26: =MAX(0,AS25*(1+AS$6/Setup!$C$13)-CQ26-EO26)+IF($K26=26,$D26,0) | AT26: =MAX(0,AT25*(1+AT$6/Setup!$C$13)-CR26-EP26)+IF($K26=27,$D26,0) | AU26: =MAX(0,AU25*(1+AU$6/Setup!$C$13)-CS26-EQ26)+IF($K26=28,$D26,0) | AV26: =MAX(0,AV25*(1+AV$6/Setup!$C$13)-CT26-ER26)+IF($K26=29,$D26,0) | AW26: =MAX(0,AW25*(1+AW$6/Setup!$C$13)-CU26-ES26)+IF($K26=30,$D26,0) | AX26: =MAX(0,AX25*(1+AX$6/Setup!$C$13)-CV26-ET26)+IF($K26=31,$D26,0) | AY26: =MAX(0,AY25*(1+AY$6/Setup!$C$13)-CW26-EU26)+IF($K26=32,$D26,0) | AZ26: =MAX(0,AZ25*(1+AZ$6/Setup!$C$13)-CX26-EV26)+IF($K26=33,$D26,0) | BA26: =MAX(0,BA25*(1+BA$6/Setup!$C$13)-CY26-EW26)+IF($K26=34,$D26,0) | BB26: =MAX(0,BB25*(1+BB$6/Setup!$C$13)-CZ26-EX26)+IF($K26=35,$D26,0) | BC26: =MAX(0,BC25*(1+BC$6/Setup!$C$13)-DA26-EY26)+IF($K26=36,$D26,0) | BD26: =MAX(0,BD25*(1+BD$6/Setup!$C$13)-DB26-EZ26)+IF($K26=37,$D26,0) | BE26: =MAX(0,BE25*(1+BE$6/Setup!$C$13)-DC26-FA26)+IF($K26=38,$D26,0) | BF26: =MAX(0,BF25*(1+BF$6/Setup!$C$13)-DD26-FB26)+IF($K26=39,$D26,0) | BG26: =MAX(0,BG25*(1+BG$6/Setup!$C$13)-DE26-FC26)+IF($K26=40,$D26,0) | BH26: =MAX(0,BH25*(1+BH$6/Setup!$C$13)-DF26-FD26)+IF($K26=41,$D26,0) | BI26: =MAX(0,BI25*(1+BI$6/Setup!$C$13)-DG26-FE26)+IF($K26=42,$D26,0) | BJ26: =MAX(0,BJ25*(1+BJ$6/Setup!$C$13)-DH26-FF26)+IF($K26=43,$D26,0) | BK26: =MAX(0,BK25*(1+BK$6/Setup!$C$13)-DI26-FG26)+IF($K26=44,$D26,0) | BL26: =MAX(0,BL25*(1+BL$6/Setup!$C$13)-DJ26-FH26)+IF($K26=45,$D26,0) | BM26: =MAX(0,BM25*(1+BM$6/Setup!$C$13)-DK26-FI26)+IF($K26=46,$D26,0) | BN26: =MAX(0,BN25*(1+BN$6/Setup!$C$13)-DL26-FJ26)+IF($K26=47,$D26,0) | BO26: =MAX(0,BO25*(1+BO$6/Setup!$C$13)-DM26-FK26)+IF($K26=48,$D26,0) | BP26: =MAX(0,BP25*(1+BP$6/Setup!$C$13)-DN26-FL26)+IF($K26=49,$D26,0) | BQ26: =MAX(0,BQ25*(1+BQ$6/Setup!$C$13)-DO26-FM26)+IF($K26=50,$D26,0) | BR26: =MIN(T25*(1+T$6/Setup!$C$13),T$7) | BS26: =MIN(U25*(1+U$6/Setup!$C$13),U$7) | BT26: =MIN(V25*(1+V$6/Setup!$C$13),V$7) | BU26: =MIN(W25*(1+W$6/Setup!$C$13),W$7) | BV26: =MIN(X25*(1+X$6/Setup!$C$13),X$7) | BW26: =MIN(Y25*(1+Y$6/Setup!$C$13),Y$7) | BX26: =MIN(Z25*(1+Z$6/Setup!$C$13),Z$7) | BY26: =MIN(AA25*(1+AA$6/Setup!$C$13),AA$7) | ... DO26: =MIN(BQ25*(1+BQ$6/Setup!$C$13),BQ$7) | DP26: =MIN(T25*(1+T$6/Setup!$C$13)-BR26,$H26) | DQ26: =MIN(U25*(1+U$6/Setup!$C$13)-BS26,MAX(0,$H26-SUM($DP26:DP26))) | DR26: =MIN(V25*(1+V$6/Setup!$C$13)-BT26,MAX(0,$H26-SUM($DP26:DQ26))) | DS26: =MIN(W25*(1+W$6/Setup!$C$13)-BU26,MAX(0,$H26-SUM($DP26:DR26))) | DT26: =MIN(X25*(1+X$6/Setup!$C$13)-BV26,MAX(0,$H26-SUM($DP26:DS26))) | DU26: =MIN(Y25*(1+Y$6/Setup!$C$13)-BW26,MAX(0,$H26-SUM($DP26:DT26))) | DV26: =MIN(Z25*(1+Z$6/Setup!$C$13)-BX26,MAX(0,$H26-SUM($DP26:DU26))) | DW26: =MIN(AA25*(1+AA$6/Setup!$C$13)-BY26,MAX(0,$H26-SUM($DP26:DV26))) | DX26: =MIN(AB25*(1+AB$6/Setup!$C$13)-BZ26,MAX(0,$H26-SUM($DP26:DW26))) | ... FM26: =MIN(BQ25*(1+BQ$6/Setup!$C$13)-DO26,MAX(0,$H26-SUM($DP26:FL26)))
A27: =A26+1 | B27: =IF(Setup!$C$6="Every week",Setup!$C$7+7*(A27-1),IF(Setup!$C$6="Every 2 weeks",Setup!$C$7+14*(A27-1),IF(Setup!$C$6="Every month",EDATE(Setup!$C$7,A27-1),EOMONTH(Setup!$C$7,INT((A27-1+Setup!$C$20)/2)-1)+MIN(IF(MOD(A27-1+Setup!$C$20,2)=0,Setup!$C$18,Setup!$C$19),DAY(EOMONTH(Setup!$C$7,INT((A27-1+Setup!$C$20)/2))))))) | C27: =N('Paycheck Plan'!J23) | D27: =N('Paycheck Plan'!K23) | E27: =MIN(MAX(0,Setup!$C$10-F26),MAX(0,Setup!$C$8+C27-G27)) | F27: =F26+E27 | G27: =MIN(Setup!$C$14,MAX(0,Setup!$C$8+C27)) | H27: =MAX(0,Setup!$C$8+C27-G27-E27)+SUM($T$7:$BQ$7)-SUM(BR27:DO27) | I27: =SUMPRODUCT(T26:BQ26,$T$6:$BQ$6)/Setup!$C$13 | J27: =SUM(T27:BQ27) | K27: =IF(MAX(DP27:FM27)>0,MATCH(MAX(DP27:FM27),DP27:FM27,0),1) | M27: =ROUND(16*$B$2/39,0)+1 | N27: =INDEX($B$10:$B$530,MIN(M27,521)) | O27: =INDEX($J$10:$J$530,MIN(M27,521)) | T27: =MAX(0,T26*(1+T$6/Setup!$C$13)-BR27-DP27)+IF($K27=1,$D27,0) | U27: =MAX(0,U26*(1+U$6/Setup!$C$13)-BS27-DQ27)+IF($K27=2,$D27,0) | V27: =MAX(0,V26*(1+V$6/Setup!$C$13)-BT27-DR27)+IF($K27=3,$D27,0) | W27: =MAX(0,W26*(1+W$6/Setup!$C$13)-BU27-DS27)+IF($K27=4,$D27,0) | X27: =MAX(0,X26*(1+X$6/Setup!$C$13)-BV27-DT27)+IF($K27=5,$D27,0) | Y27: =MAX(0,Y26*(1+Y$6/Setup!$C$13)-BW27-DU27)+IF($K27=6,$D27,0) | Z27: =MAX(0,Z26*(1+Z$6/Setup!$C$13)-BX27-DV27)+IF($K27=7,$D27,0) | AA27: =MAX(0,AA26*(1+AA$6/Setup!$C$13)-BY27-DW27)+IF($K27=8,$D27,0) | AB27: =MAX(0,AB26*(1+AB$6/Setup!$C$13)-BZ27-DX27)+IF($K27=9,$D27,0) | AC27: =MAX(0,AC26*(1+AC$6/Setup!$C$13)-CA27-DY27)+IF($K27=10,$D27,0) | AD27: =MAX(0,AD26*(1+AD$6/Setup!$C$13)-CB27-DZ27)+IF($K27=11,$D27,0) | AE27: =MAX(0,AE26*(1+AE$6/Setup!$C$13)-CC27-EA27)+IF($K27=12,$D27,0) | AF27: =MAX(0,AF26*(1+AF$6/Setup!$C$13)-CD27-EB27)+IF($K27=13,$D27,0) | AG27: =MAX(0,AG26*(1+AG$6/Setup!$C$13)-CE27-EC27)+IF($K27=14,$D27,0) | AH27: =MAX(0,AH26*(1+AH$6/Setup!$C$13)-CF27-ED27)+IF($K27=15,$D27,0) | AI27: =MAX(0,AI26*(1+AI$6/Setup!$C$13)-CG27-EE27)+IF($K27=16,$D27,0) | AJ27: =MAX(0,AJ26*(1+AJ$6/Setup!$C$13)-CH27-EF27)+IF($K27=17,$D27,0) | AK27: =MAX(0,AK26*(1+AK$6/Setup!$C$13)-CI27-EG27)+IF($K27=18,$D27,0) | AL27: =MAX(0,AL26*(1+AL$6/Setup!$C$13)-CJ27-EH27)+IF($K27=19,$D27,0) | AM27: =MAX(0,AM26*(1+AM$6/Setup!$C$13)-CK27-EI27)+IF($K27=20,$D27,0) | AN27: =MAX(0,AN26*(1+AN$6/Setup!$C$13)-CL27-EJ27)+IF($K27=21,$D27,0) | AO27: =MAX(0,AO26*(1+AO$6/Setup!$C$13)-CM27-EK27)+IF($K27=22,$D27,0) | AP27: =MAX(0,AP26*(1+AP$6/Setup!$C$13)-CN27-EL27)+IF($K27=23,$D27,0) | AQ27: =MAX(0,AQ26*(1+AQ$6/Setup!$C$13)-CO27-EM27)+IF($K27=24,$D27,0) | AR27: =MAX(0,AR26*(1+AR$6/Setup!$C$13)-CP27-EN27)+IF($K27=25,$D27,0) | AS27: =MAX(0,AS26*(1+AS$6/Setup!$C$13)-CQ27-EO27)+IF($K27=26,$D27,0) | AT27: =MAX(0,AT26*(1+AT$6/Setup!$C$13)-CR27-EP27)+IF($K27=27,$D27,0) | AU27: =MAX(0,AU26*(1+AU$6/Setup!$C$13)-CS27-EQ27)+IF($K27=28,$D27,0) | AV27: =MAX(0,AV26*(1+AV$6/Setup!$C$13)-CT27-ER27)+IF($K27=29,$D27,0) | AW27: =MAX(0,AW26*(1+AW$6/Setup!$C$13)-CU27-ES27)+IF($K27=30,$D27,0) | AX27: =MAX(0,AX26*(1+AX$6/Setup!$C$13)-CV27-ET27)+IF($K27=31,$D27,0) | AY27: =MAX(0,AY26*(1+AY$6/Setup!$C$13)-CW27-EU27)+IF($K27=32,$D27,0) | AZ27: =MAX(0,AZ26*(1+AZ$6/Setup!$C$13)-CX27-EV27)+IF($K27=33,$D27,0) | BA27: =MAX(0,BA26*(1+BA$6/Setup!$C$13)-CY27-EW27)+IF($K27=34,$D27,0) | BB27: =MAX(0,BB26*(1+BB$6/Setup!$C$13)-CZ27-EX27)+IF($K27=35,$D27,0) | BC27: =MAX(0,BC26*(1+BC$6/Setup!$C$13)-DA27-EY27)+IF($K27=36,$D27,0) | BD27: =MAX(0,BD26*(1+BD$6/Setup!$C$13)-DB27-EZ27)+IF($K27=37,$D27,0) | BE27: =MAX(0,BE26*(1+BE$6/Setup!$C$13)-DC27-FA27)+IF($K27=38,$D27,0) | BF27: =MAX(0,BF26*(1+BF$6/Setup!$C$13)-DD27-FB27)+IF($K27=39,$D27,0) | BG27: =MAX(0,BG26*(1+BG$6/Setup!$C$13)-DE27-FC27)+IF($K27=40,$D27,0) | BH27: =MAX(0,BH26*(1+BH$6/Setup!$C$13)-DF27-FD27)+IF($K27=41,$D27,0) | BI27: =MAX(0,BI26*(1+BI$6/Setup!$C$13)-DG27-FE27)+IF($K27=42,$D27,0) | BJ27: =MAX(0,BJ26*(1+BJ$6/Setup!$C$13)-DH27-FF27)+IF($K27=43,$D27,0) | BK27: =MAX(0,BK26*(1+BK$6/Setup!$C$13)-DI27-FG27)+IF($K27=44,$D27,0) | BL27: =MAX(0,BL26*(1+BL$6/Setup!$C$13)-DJ27-FH27)+IF($K27=45,$D27,0) | BM27: =MAX(0,BM26*(1+BM$6/Setup!$C$13)-DK27-FI27)+IF($K27=46,$D27,0) | BN27: =MAX(0,BN26*(1+BN$6/Setup!$C$13)-DL27-FJ27)+IF($K27=47,$D27,0) | BO27: =MAX(0,BO26*(1+BO$6/Setup!$C$13)-DM27-FK27)+IF($K27=48,$D27,0) | BP27: =MAX(0,BP26*(1+BP$6/Setup!$C$13)-DN27-FL27)+IF($K27=49,$D27,0) | BQ27: =MAX(0,BQ26*(1+BQ$6/Setup!$C$13)-DO27-FM27)+IF($K27=50,$D27,0) | BR27: =MIN(T26*(1+T$6/Setup!$C$13),T$7) | BS27: =MIN(U26*(1+U$6/Setup!$C$13),U$7) | BT27: =MIN(V26*(1+V$6/Setup!$C$13),V$7) | BU27: =MIN(W26*(1+W$6/Setup!$C$13),W$7) | BV27: =MIN(X26*(1+X$6/Setup!$C$13),X$7) | BW27: =MIN(Y26*(1+Y$6/Setup!$C$13),Y$7) | BX27: =MIN(Z26*(1+Z$6/Setup!$C$13),Z$7) | BY27: =MIN(AA26*(1+AA$6/Setup!$C$13),AA$7) | ... DO27: =MIN(BQ26*(1+BQ$6/Setup!$C$13),BQ$7) | DP27: =MIN(T26*(1+T$6/Setup!$C$13)-BR27,$H27) | DQ27: =MIN(U26*(1+U$6/Setup!$C$13)-BS27,MAX(0,$H27-SUM($DP27:DP27))) | DR27: =MIN(V26*(1+V$6/Setup!$C$13)-BT27,MAX(0,$H27-SUM($DP27:DQ27))) | DS27: =MIN(W26*(1+W$6/Setup!$C$13)-BU27,MAX(0,$H27-SUM($DP27:DR27))) | DT27: =MIN(X26*(1+X$6/Setup!$C$13)-BV27,MAX(0,$H27-SUM($DP27:DS27))) | DU27: =MIN(Y26*(1+Y$6/Setup!$C$13)-BW27,MAX(0,$H27-SUM($DP27:DT27))) | DV27: =MIN(Z26*(1+Z$6/Setup!$C$13)-BX27,MAX(0,$H27-SUM($DP27:DU27))) | DW27: =MIN(AA26*(1+AA$6/Setup!$C$13)-BY27,MAX(0,$H27-SUM($DP27:DV27))) | DX27: =MIN(AB26*(1+AB$6/Setup!$C$13)-BZ27,MAX(0,$H27-SUM($DP27:DW27))) | ... FM27: =MIN(BQ26*(1+BQ$6/Setup!$C$13)-DO27,MAX(0,$H27-SUM($DP27:FL27)))
A28: =A27+1 | B28: =IF(Setup!$C$6="Every week",Setup!$C$7+7*(A28-1),IF(Setup!$C$6="Every 2 weeks",Setup!$C$7+14*(A28-1),IF(Setup!$C$6="Every month",EDATE(Setup!$C$7,A28-1),EOMONTH(Setup!$C$7,INT((A28-1+Setup!$C$20)/2)-1)+MIN(IF(MOD(A28-1+Setup!$C$20,2)=0,Setup!$C$18,Setup!$C$19),DAY(EOMONTH(Setup!$C$7,INT((A28-1+Setup!$C$20)/2))))))) | C28: =N('Paycheck Plan'!J24) | D28: =N('Paycheck Plan'!K24) | E28: =MIN(MAX(0,Setup!$C$10-F27),MAX(0,Setup!$C$8+C28-G28)) | F28: =F27+E28 | G28: =MIN(Setup!$C$14,MAX(0,Setup!$C$8+C28)) | H28: =MAX(0,Setup!$C$8+C28-G28-E28)+SUM($T$7:$BQ$7)-SUM(BR28:DO28) | I28: =SUMPRODUCT(T27:BQ27,$T$6:$BQ$6)/Setup!$C$13 | J28: =SUM(T28:BQ28) | K28: =IF(MAX(DP28:FM28)>0,MATCH(MAX(DP28:FM28),DP28:FM28,0),1) | M28: =ROUND(17*$B$2/39,0)+1 | N28: =INDEX($B$10:$B$530,MIN(M28,521)) | O28: =INDEX($J$10:$J$530,MIN(M28,521)) | T28: =MAX(0,T27*(1+T$6/Setup!$C$13)-BR28-DP28)+IF($K28=1,$D28,0) | U28: =MAX(0,U27*(1+U$6/Setup!$C$13)-BS28-DQ28)+IF($K28=2,$D28,0) | V28: =MAX(0,V27*(1+V$6/Setup!$C$13)-BT28-DR28)+IF($K28=3,$D28,0) | W28: =MAX(0,W27*(1+W$6/Setup!$C$13)-BU28-DS28)+IF($K28=4,$D28,0) | X28: =MAX(0,X27*(1+X$6/Setup!$C$13)-BV28-DT28)+IF($K28=5,$D28,0) | Y28: =MAX(0,Y27*(1+Y$6/Setup!$C$13)-BW28-DU28)+IF($K28=6,$D28,0) | Z28: =MAX(0,Z27*(1+Z$6/Setup!$C$13)-BX28-DV28)+IF($K28=7,$D28,0) | AA28: =MAX(0,AA27*(1+AA$6/Setup!$C$13)-BY28-DW28)+IF($K28=8,$D28,0) | AB28: =MAX(0,AB27*(1+AB$6/Setup!$C$13)-BZ28-DX28)+IF($K28=9,$D28,0) | AC28: =MAX(0,AC27*(1+AC$6/Setup!$C$13)-CA28-DY28)+IF($K28=10,$D28,0) | AD28: =MAX(0,AD27*(1+AD$6/Setup!$C$13)-CB28-DZ28)+IF($K28=11,$D28,0) | AE28: =MAX(0,AE27*(1+AE$6/Setup!$C$13)-CC28-EA28)+IF($K28=12,$D28,0) | AF28: =MAX(0,AF27*(1+AF$6/Setup!$C$13)-CD28-EB28)+IF($K28=13,$D28,0) | AG28: =MAX(0,AG27*(1+AG$6/Setup!$C$13)-CE28-EC28)+IF($K28=14,$D28,0) | AH28: =MAX(0,AH27*(1+AH$6/Setup!$C$13)-CF28-ED28)+IF($K28=15,$D28,0) | AI28: =MAX(0,AI27*(1+AI$6/Setup!$C$13)-CG28-EE28)+IF($K28=16,$D28,0) | AJ28: =MAX(0,AJ27*(1+AJ$6/Setup!$C$13)-CH28-EF28)+IF($K28=17,$D28,0) | AK28: =MAX(0,AK27*(1+AK$6/Setup!$C$13)-CI28-EG28)+IF($K28=18,$D28,0) | AL28: =MAX(0,AL27*(1+AL$6/Setup!$C$13)-CJ28-EH28)+IF($K28=19,$D28,0) | AM28: =MAX(0,AM27*(1+AM$6/Setup!$C$13)-CK28-EI28)+IF($K28=20,$D28,0) | AN28: =MAX(0,AN27*(1+AN$6/Setup!$C$13)-CL28-EJ28)+IF($K28=21,$D28,0) | AO28: =MAX(0,AO27*(1+AO$6/Setup!$C$13)-CM28-EK28)+IF($K28=22,$D28,0) | AP28: =MAX(0,AP27*(1+AP$6/Setup!$C$13)-CN28-EL28)+IF($K28=23,$D28,0) | AQ28: =MAX(0,AQ27*(1+AQ$6/Setup!$C$13)-CO28-EM28)+IF($K28=24,$D28,0) | AR28: =MAX(0,AR27*(1+AR$6/Setup!$C$13)-CP28-EN28)+IF($K28=25,$D28,0) | AS28: =MAX(0,AS27*(1+AS$6/Setup!$C$13)-CQ28-EO28)+IF($K28=26,$D28,0) | AT28: =MAX(0,AT27*(1+AT$6/Setup!$C$13)-CR28-EP28)+IF($K28=27,$D28,0) | AU28: =MAX(0,AU27*(1+AU$6/Setup!$C$13)-CS28-EQ28)+IF($K28=28,$D28,0) | AV28: =MAX(0,AV27*(1+AV$6/Setup!$C$13)-CT28-ER28)+IF($K28=29,$D28,0) | AW28: =MAX(0,AW27*(1+AW$6/Setup!$C$13)-CU28-ES28)+IF($K28=30,$D28,0) | AX28: =MAX(0,AX27*(1+AX$6/Setup!$C$13)-CV28-ET28)+IF($K28=31,$D28,0) | AY28: =MAX(0,AY27*(1+AY$6/Setup!$C$13)-CW28-EU28)+IF($K28=32,$D28,0) | AZ28: =MAX(0,AZ27*(1+AZ$6/Setup!$C$13)-CX28-EV28)+IF($K28=33,$D28,0) | BA28: =MAX(0,BA27*(1+BA$6/Setup!$C$13)-CY28-EW28)+IF($K28=34,$D28,0) | BB28: =MAX(0,BB27*(1+BB$6/Setup!$C$13)-CZ28-EX28)+IF($K28=35,$D28,0) | BC28: =MAX(0,BC27*(1+BC$6/Setup!$C$13)-DA28-EY28)+IF($K28=36,$D28,0) | BD28: =MAX(0,BD27*(1+BD$6/Setup!$C$13)-DB28-EZ28)+IF($K28=37,$D28,0) | BE28: =MAX(0,BE27*(1+BE$6/Setup!$C$13)-DC28-FA28)+IF($K28=38,$D28,0) | BF28: =MAX(0,BF27*(1+BF$6/Setup!$C$13)-DD28-FB28)+IF($K28=39,$D28,0) | BG28: =MAX(0,BG27*(1+BG$6/Setup!$C$13)-DE28-FC28)+IF($K28=40,$D28,0) | BH28: =MAX(0,BH27*(1+BH$6/Setup!$C$13)-DF28-FD28)+IF($K28=41,$D28,0) | BI28: =MAX(0,BI27*(1+BI$6/Setup!$C$13)-DG28-FE28)+IF($K28=42,$D28,0) | BJ28: =MAX(0,BJ27*(1+BJ$6/Setup!$C$13)-DH28-FF28)+IF($K28=43,$D28,0) | BK28: =MAX(0,BK27*(1+BK$6/Setup!$C$13)-DI28-FG28)+IF($K28=44,$D28,0) | BL28: =MAX(0,BL27*(1+BL$6/Setup!$C$13)-DJ28-FH28)+IF($K28=45,$D28,0) | BM28: =MAX(0,BM27*(1+BM$6/Setup!$C$13)-DK28-FI28)+IF($K28=46,$D28,0) | BN28: =MAX(0,BN27*(1+BN$6/Setup!$C$13)-DL28-FJ28)+IF($K28=47,$D28,0) | BO28: =MAX(0,BO27*(1+BO$6/Setup!$C$13)-DM28-FK28)+IF($K28=48,$D28,0) | BP28: =MAX(0,BP27*(1+BP$6/Setup!$C$13)-DN28-FL28)+IF($K28=49,$D28,0) | BQ28: =MAX(0,BQ27*(1+BQ$6/Setup!$C$13)-DO28-FM28)+IF($K28=50,$D28,0) | BR28: =MIN(T27*(1+T$6/Setup!$C$13),T$7) | BS28: =MIN(U27*(1+U$6/Setup!$C$13),U$7) | BT28: =MIN(V27*(1+V$6/Setup!$C$13),V$7) | BU28: =MIN(W27*(1+W$6/Setup!$C$13),W$7) | BV28: =MIN(X27*(1+X$6/Setup!$C$13),X$7) | BW28: =MIN(Y27*(1+Y$6/Setup!$C$13),Y$7) | BX28: =MIN(Z27*(1+Z$6/Setup!$C$13),Z$7) | BY28: =MIN(AA27*(1+AA$6/Setup!$C$13),AA$7) | ... DO28: =MIN(BQ27*(1+BQ$6/Setup!$C$13),BQ$7) | DP28: =MIN(T27*(1+T$6/Setup!$C$13)-BR28,$H28) | DQ28: =MIN(U27*(1+U$6/Setup!$C$13)-BS28,MAX(0,$H28-SUM($DP28:DP28))) | DR28: =MIN(V27*(1+V$6/Setup!$C$13)-BT28,MAX(0,$H28-SUM($DP28:DQ28))) | DS28: =MIN(W27*(1+W$6/Setup!$C$13)-BU28,MAX(0,$H28-SUM($DP28:DR28))) | DT28: =MIN(X27*(1+X$6/Setup!$C$13)-BV28,MAX(0,$H28-SUM($DP28:DS28))) | DU28: =MIN(Y27*(1+Y$6/Setup!$C$13)-BW28,MAX(0,$H28-SUM($DP28:DT28))) | DV28: =MIN(Z27*(1+Z$6/Setup!$C$13)-BX28,MAX(0,$H28-SUM($DP28:DU28))) | DW28: =MIN(AA27*(1+AA$6/Setup!$C$13)-BY28,MAX(0,$H28-SUM($DP28:DV28))) | DX28: =MIN(AB27*(1+AB$6/Setup!$C$13)-BZ28,MAX(0,$H28-SUM($DP28:DW28))) | ... FM28: =MIN(BQ27*(1+BQ$6/Setup!$C$13)-DO28,MAX(0,$H28-SUM($DP28:FL28)))
A29: =A28+1 | B29: =IF(Setup!$C$6="Every week",Setup!$C$7+7*(A29-1),IF(Setup!$C$6="Every 2 weeks",Setup!$C$7+14*(A29-1),IF(Setup!$C$6="Every month",EDATE(Setup!$C$7,A29-1),EOMONTH(Setup!$C$7,INT((A29-1+Setup!$C$20)/2)-1)+MIN(IF(MOD(A29-1+Setup!$C$20,2)=0,Setup!$C$18,Setup!$C$19),DAY(EOMONTH(Setup!$C$7,INT((A29-1+Setup!$C$20)/2))))))) | C29: =N('Paycheck Plan'!J25) | D29: =N('Paycheck Plan'!K25) | E29: =MIN(MAX(0,Setup!$C$10-F28),MAX(0,Setup!$C$8+C29-G29)) | F29: =F28+E29 | G29: =MIN(Setup!$C$14,MAX(0,Setup!$C$8+C29)) | H29: =MAX(0,Setup!$C$8+C29-G29-E29)+SUM($T$7:$BQ$7)-SUM(BR29:DO29) | I29: =SUMPRODUCT(T28:BQ28,$T$6:$BQ$6)/Setup!$C$13 | J29: =SUM(T29:BQ29) | K29: =IF(MAX(DP29:FM29)>0,MATCH(MAX(DP29:FM29),DP29:FM29,0),1) | M29: =ROUND(18*$B$2/39,0)+1 | N29: =INDEX($B$10:$B$530,MIN(M29,521)) | O29: =INDEX($J$10:$J$530,MIN(M29,521)) | T29: =MAX(0,T28*(1+T$6/Setup!$C$13)-BR29-DP29)+IF($K29=1,$D29,0) | U29: =MAX(0,U28*(1+U$6/Setup!$C$13)-BS29-DQ29)+IF($K29=2,$D29,0) | V29: =MAX(0,V28*(1+V$6/Setup!$C$13)-BT29-DR29)+IF($K29=3,$D29,0) | W29: =MAX(0,W28*(1+W$6/Setup!$C$13)-BU29-DS29)+IF($K29=4,$D29,0) | X29: =MAX(0,X28*(1+X$6/Setup!$C$13)-BV29-DT29)+IF($K29=5,$D29,0) | Y29: =MAX(0,Y28*(1+Y$6/Setup!$C$13)-BW29-DU29)+IF($K29=6,$D29,0) | Z29: =MAX(0,Z28*(1+Z$6/Setup!$C$13)-BX29-DV29)+IF($K29=7,$D29,0) | AA29: =MAX(0,AA28*(1+AA$6/Setup!$C$13)-BY29-DW29)+IF($K29=8,$D29,0) | AB29: =MAX(0,AB28*(1+AB$6/Setup!$C$13)-BZ29-DX29)+IF($K29=9,$D29,0) | AC29: =MAX(0,AC28*(1+AC$6/Setup!$C$13)-CA29-DY29)+IF($K29=10,$D29,0) | AD29: =MAX(0,AD28*(1+AD$6/Setup!$C$13)-CB29-DZ29)+IF($K29=11,$D29,0) | AE29: =MAX(0,AE28*(1+AE$6/Setup!$C$13)-CC29-EA29)+IF($K29=12,$D29,0) | AF29: =MAX(0,AF28*(1+AF$6/Setup!$C$13)-CD29-EB29)+IF($K29=13,$D29,0) | AG29: =MAX(0,AG28*(1+AG$6/Setup!$C$13)-CE29-EC29)+IF($K29=14,$D29,0) | AH29: =MAX(0,AH28*(1+AH$6/Setup!$C$13)-CF29-ED29)+IF($K29=15,$D29,0) | AI29: =MAX(0,AI28*(1+AI$6/Setup!$C$13)-CG29-EE29)+IF($K29=16,$D29,0) | AJ29: =MAX(0,AJ28*(1+AJ$6/Setup!$C$13)-CH29-EF29)+IF($K29=17,$D29,0) | AK29: =MAX(0,AK28*(1+AK$6/Setup!$C$13)-CI29-EG29)+IF($K29=18,$D29,0) | AL29: =MAX(0,AL28*(1+AL$6/Setup!$C$13)-CJ29-EH29)+IF($K29=19,$D29,0) | AM29: =MAX(0,AM28*(1+AM$6/Setup!$C$13)-CK29-EI29)+IF($K29=20,$D29,0) | AN29: =MAX(0,AN28*(1+AN$6/Setup!$C$13)-CL29-EJ29)+IF($K29=21,$D29,0) | AO29: =MAX(0,AO28*(1+AO$6/Setup!$C$13)-CM29-EK29)+IF($K29=22,$D29,0) | AP29: =MAX(0,AP28*(1+AP$6/Setup!$C$13)-CN29-EL29)+IF($K29=23,$D29,0) | AQ29: =MAX(0,AQ28*(1+AQ$6/Setup!$C$13)-CO29-EM29)+IF($K29=24,$D29,0) | AR29: =MAX(0,AR28*(1+AR$6/Setup!$C$13)-CP29-EN29)+IF($K29=25,$D29,0) | AS29: =MAX(0,AS28*(1+AS$6/Setup!$C$13)-CQ29-EO29)+IF($K29=26,$D29,0) | AT29: =MAX(0,AT28*(1+AT$6/Setup!$C$13)-CR29-EP29)+IF($K29=27,$D29,0) | AU29: =MAX(0,AU28*(1+AU$6/Setup!$C$13)-CS29-EQ29)+IF($K29=28,$D29,0) | AV29: =MAX(0,AV28*(1+AV$6/Setup!$C$13)-CT29-ER29)+IF($K29=29,$D29,0) | AW29: =MAX(0,AW28*(1+AW$6/Setup!$C$13)-CU29-ES29)+IF($K29=30,$D29,0) | AX29: =MAX(0,AX28*(1+AX$6/Setup!$C$13)-CV29-ET29)+IF($K29=31,$D29,0) | AY29: =MAX(0,AY28*(1+AY$6/Setup!$C$13)-CW29-EU29)+IF($K29=32,$D29,0) | AZ29: =MAX(0,AZ28*(1+AZ$6/Setup!$C$13)-CX29-EV29)+IF($K29=33,$D29,0) | BA29: =MAX(0,BA28*(1+BA$6/Setup!$C$13)-CY29-EW29)+IF($K29=34,$D29,0) | BB29: =MAX(0,BB28*(1+BB$6/Setup!$C$13)-CZ29-EX29)+IF($K29=35,$D29,0) | BC29: =MAX(0,BC28*(1+BC$6/Setup!$C$13)-DA29-EY29)+IF($K29=36,$D29,0) | BD29: =MAX(0,BD28*(1+BD$6/Setup!$C$13)-DB29-EZ29)+IF($K29=37,$D29,0) | BE29: =MAX(0,BE28*(1+BE$6/Setup!$C$13)-DC29-FA29)+IF($K29=38,$D29,0) | BF29: =MAX(0,BF28*(1+BF$6/Setup!$C$13)-DD29-FB29)+IF($K29=39,$D29,0) | BG29: =MAX(0,BG28*(1+BG$6/Setup!$C$13)-DE29-FC29)+IF($K29=40,$D29,0) | BH29: =MAX(0,BH28*(1+BH$6/Setup!$C$13)-DF29-FD29)+IF($K29=41,$D29,0) | BI29: =MAX(0,BI28*(1+BI$6/Setup!$C$13)-DG29-FE29)+IF($K29=42,$D29,0) | BJ29: =MAX(0,BJ28*(1+BJ$6/Setup!$C$13)-DH29-FF29)+IF($K29=43,$D29,0) | BK29: =MAX(0,BK28*(1+BK$6/Setup!$C$13)-DI29-FG29)+IF($K29=44,$D29,0) | BL29: =MAX(0,BL28*(1+BL$6/Setup!$C$13)-DJ29-FH29)+IF($K29=45,$D29,0) | BM29: =MAX(0,BM28*(1+BM$6/Setup!$C$13)-DK29-FI29)+IF($K29=46,$D29,0) | BN29: =MAX(0,BN28*(1+BN$6/Setup!$C$13)-DL29-FJ29)+IF($K29=47,$D29,0) | BO29: =MAX(0,BO28*(1+BO$6/Setup!$C$13)-DM29-FK29)+IF($K29=48,$D29,0) | BP29: =MAX(0,BP28*(1+BP$6/Setup!$C$13)-DN29-FL29)+IF($K29=49,$D29,0) | BQ29: =MAX(0,BQ28*(1+BQ$6/Setup!$C$13)-DO29-FM29)+IF($K29=50,$D29,0) | BR29: =MIN(T28*(1+T$6/Setup!$C$13),T$7) | BS29: =MIN(U28*(1+U$6/Setup!$C$13),U$7) | BT29: =MIN(V28*(1+V$6/Setup!$C$13),V$7) | BU29: =MIN(W28*(1+W$6/Setup!$C$13),W$7) | BV29: =MIN(X28*(1+X$6/Setup!$C$13),X$7) | BW29: =MIN(Y28*(1+Y$6/Setup!$C$13),Y$7) | BX29: =MIN(Z28*(1+Z$6/Setup!$C$13),Z$7) | BY29: =MIN(AA28*(1+AA$6/Setup!$C$13),AA$7) | ... DO29: =MIN(BQ28*(1+BQ$6/Setup!$C$13),BQ$7) | DP29: =MIN(T28*(1+T$6/Setup!$C$13)-BR29,$H29) | DQ29: =MIN(U28*(1+U$6/Setup!$C$13)-BS29,MAX(0,$H29-SUM($DP29:DP29))) | DR29: =MIN(V28*(1+V$6/Setup!$C$13)-BT29,MAX(0,$H29-SUM($DP29:DQ29))) | DS29: =MIN(W28*(1+W$6/Setup!$C$13)-BU29,MAX(0,$H29-SUM($DP29:DR29))) | DT29: =MIN(X28*(1+X$6/Setup!$C$13)-BV29,MAX(0,$H29-SUM($DP29:DS29))) | DU29: =MIN(Y28*(1+Y$6/Setup!$C$13)-BW29,MAX(0,$H29-SUM($DP29:DT29))) | DV29: =MIN(Z28*(1+Z$6/Setup!$C$13)-BX29,MAX(0,$H29-SUM($DP29:DU29))) | DW29: =MIN(AA28*(1+AA$6/Setup!$C$13)-BY29,MAX(0,$H29-SUM($DP29:DV29))) | DX29: =MIN(AB28*(1+AB$6/Setup!$C$13)-BZ29,MAX(0,$H29-SUM($DP29:DW29))) | ... FM29: =MIN(BQ28*(1+BQ$6/Setup!$C$13)-DO29,MAX(0,$H29-SUM($DP29:FL29)))
A30: =A29+1 | B30: =IF(Setup!$C$6="Every week",Setup!$C$7+7*(A30-1),IF(Setup!$C$6="Every 2 weeks",Setup!$C$7+14*(A30-1),IF(Setup!$C$6="Every month",EDATE(Setup!$C$7,A30-1),EOMONTH(Setup!$C$7,INT((A30-1+Setup!$C$20)/2)-1)+MIN(IF(MOD(A30-1+Setup!$C$20,2)=0,Setup!$C$18,Setup!$C$19),DAY(EOMONTH(Setup!$C$7,INT((A30-1+Setup!$C$20)/2))))))) | C30: =N('Paycheck Plan'!J26) | D30: =N('Paycheck Plan'!K26) | E30: =MIN(MAX(0,Setup!$C$10-F29),MAX(0,Setup!$C$8+C30-G30)) | F30: =F29+E30 | G30: =MIN(Setup!$C$14,MAX(0,Setup!$C$8+C30)) | H30: =MAX(0,Setup!$C$8+C30-G30-E30)+SUM($T$7:$BQ$7)-SUM(BR30:DO30) | I30: =SUMPRODUCT(T29:BQ29,$T$6:$BQ$6)/Setup!$C$13 | J30: =SUM(T30:BQ30) | K30: =IF(MAX(DP30:FM30)>0,MATCH(MAX(DP30:FM30),DP30:FM30,0),1) | M30: =ROUND(19*$B$2/39,0)+1 | N30: =INDEX($B$10:$B$530,MIN(M30,521)) | O30: =INDEX($J$10:$J$530,MIN(M30,521)) | T30: =MAX(0,T29*(1+T$6/Setup!$C$13)-BR30-DP30)+IF($K30=1,$D30,0) | U30: =MAX(0,U29*(1+U$6/Setup!$C$13)-BS30-DQ30)+IF($K30=2,$D30,0) | V30: =MAX(0,V29*(1+V$6/Setup!$C$13)-BT30-DR30)+IF($K30=3,$D30,0) | W30: =MAX(0,W29*(1+W$6/Setup!$C$13)-BU30-DS30)+IF($K30=4,$D30,0) | X30: =MAX(0,X29*(1+X$6/Setup!$C$13)-BV30-DT30)+IF($K30=5,$D30,0) | Y30: =MAX(0,Y29*(1+Y$6/Setup!$C$13)-BW30-DU30)+IF($K30=6,$D30,0) | Z30: =MAX(0,Z29*(1+Z$6/Setup!$C$13)-BX30-DV30)+IF($K30=7,$D30,0) | AA30: =MAX(0,AA29*(1+AA$6/Setup!$C$13)-BY30-DW30)+IF($K30=8,$D30,0) | AB30: =MAX(0,AB29*(1+AB$6/Setup!$C$13)-BZ30-DX30)+IF($K30=9,$D30,0) | AC30: =MAX(0,AC29*(1+AC$6/Setup!$C$13)-CA30-DY30)+IF($K30=10,$D30,0) | AD30: =MAX(0,AD29*(1+AD$6/Setup!$C$13)-CB30-DZ30)+IF($K30=11,$D30,0) | AE30: =MAX(0,AE29*(1+AE$6/Setup!$C$13)-CC30-EA30)+IF($K30=12,$D30,0) | AF30: =MAX(0,AF29*(1+AF$6/Setup!$C$13)-CD30-EB30)+IF($K30=13,$D30,0) | AG30: =MAX(0,AG29*(1+AG$6/Setup!$C$13)-CE30-EC30)+IF($K30=14,$D30,0) | AH30: =MAX(0,AH29*(1+AH$6/Setup!$C$13)-CF30-ED30)+IF($K30=15,$D30,0) | AI30: =MAX(0,AI29*(1+AI$6/Setup!$C$13)-CG30-EE30)+IF($K30=16,$D30,0) | AJ30: =MAX(0,AJ29*(1+AJ$6/Setup!$C$13)-CH30-EF30)+IF($K30=17,$D30,0) | AK30: =MAX(0,AK29*(1+AK$6/Setup!$C$13)-CI30-EG30)+IF($K30=18,$D30,0) | AL30: =MAX(0,AL29*(1+AL$6/Setup!$C$13)-CJ30-EH30)+IF($K30=19,$D30,0) | AM30: =MAX(0,AM29*(1+AM$6/Setup!$C$13)-CK30-EI30)+IF($K30=20,$D30,0) | AN30: =MAX(0,AN29*(1+AN$6/Setup!$C$13)-CL30-EJ30)+IF($K30=21,$D30,0) | AO30: =MAX(0,AO29*(1+AO$6/Setup!$C$13)-CM30-EK30)+IF($K30=22,$D30,0) | AP30: =MAX(0,AP29*(1+AP$6/Setup!$C$13)-CN30-EL30)+IF($K30=23,$D30,0) | AQ30: =MAX(0,AQ29*(1+AQ$6/Setup!$C$13)-CO30-EM30)+IF($K30=24,$D30,0) | AR30: =MAX(0,AR29*(1+AR$6/Setup!$C$13)-CP30-EN30)+IF($K30=25,$D30,0) | AS30: =MAX(0,AS29*(1+AS$6/Setup!$C$13)-CQ30-EO30)+IF($K30=26,$D30,0) | AT30: =MAX(0,AT29*(1+AT$6/Setup!$C$13)-CR30-EP30)+IF($K30=27,$D30,0) | AU30: =MAX(0,AU29*(1+AU$6/Setup!$C$13)-CS30-EQ30)+IF($K30=28,$D30,0) | AV30: =MAX(0,AV29*(1+AV$6/Setup!$C$13)-CT30-ER30)+IF($K30=29,$D30,0) | AW30: =MAX(0,AW29*(1+AW$6/Setup!$C$13)-CU30-ES30)+IF($K30=30,$D30,0) | AX30: =MAX(0,AX29*(1+AX$6/Setup!$C$13)-CV30-ET30)+IF($K30=31,$D30,0) | AY30: =MAX(0,AY29*(1+AY$6/Setup!$C$13)-CW30-EU30)+IF($K30=32,$D30,0) | AZ30: =MAX(0,AZ29*(1+AZ$6/Setup!$C$13)-CX30-EV30)+IF($K30=33,$D30,0) | BA30: =MAX(0,BA29*(1+BA$6/Setup!$C$13)-CY30-EW30)+IF($K30=34,$D30,0) | BB30: =MAX(0,BB29*(1+BB$6/Setup!$C$13)-CZ30-EX30)+IF($K30=35,$D30,0) | BC30: =MAX(0,BC29*(1+BC$6/Setup!$C$13)-DA30-EY30)+IF($K30=36,$D30,0) | BD30: =MAX(0,BD29*(1+BD$6/Setup!$C$13)-DB30-EZ30)+IF($K30=37,$D30,0) | BE30: =MAX(0,BE29*(1+BE$6/Setup!$C$13)-DC30-FA30)+IF($K30=38,$D30,0) | BF30: =MAX(0,BF29*(1+BF$6/Setup!$C$13)-DD30-FB30)+IF($K30=39,$D30,0) | BG30: =MAX(0,BG29*(1+BG$6/Setup!$C$13)-DE30-FC30)+IF($K30=40,$D30,0) | BH30: =MAX(0,BH29*(1+BH$6/Setup!$C$13)-DF30-FD30)+IF($K30=41,$D30,0) | BI30: =MAX(0,BI29*(1+BI$6/Setup!$C$13)-DG30-FE30)+IF($K30=42,$D30,0) | BJ30: =MAX(0,BJ29*(1+BJ$6/Setup!$C$13)-DH30-FF30)+IF($K30=43,$D30,0) | BK30: =MAX(0,BK29*(1+BK$6/Setup!$C$13)-DI30-FG30)+IF($K30=44,$D30,0) | BL30: =MAX(0,BL29*(1+BL$6/Setup!$C$13)-DJ30-FH30)+IF($K30=45,$D30,0) | BM30: =MAX(0,BM29*(1+BM$6/Setup!$C$13)-DK30-FI30)+IF($K30=46,$D30,0) | BN30: =MAX(0,BN29*(1+BN$6/Setup!$C$13)-DL30-FJ30)+IF($K30=47,$D30,0) | BO30: =MAX(0,BO29*(1+BO$6/Setup!$C$13)-DM30-FK30)+IF($K30=48,$D30,0) | BP30: =MAX(0,BP29*(1+BP$6/Setup!$C$13)-DN30-FL30)+IF($K30=49,$D30,0) | BQ30: =MAX(0,BQ29*(1+BQ$6/Setup!$C$13)-DO30-FM30)+IF($K30=50,$D30,0) | BR30: =MIN(T29*(1+T$6/Setup!$C$13),T$7) | BS30: =MIN(U29*(1+U$6/Setup!$C$13),U$7) | BT30: =MIN(V29*(1+V$6/Setup!$C$13),V$7) | BU30: =MIN(W29*(1+W$6/Setup!$C$13),W$7) | BV30: =MIN(X29*(1+X$6/Setup!$C$13),X$7) | BW30: =MIN(Y29*(1+Y$6/Setup!$C$13),Y$7) | BX30: =MIN(Z29*(1+Z$6/Setup!$C$13),Z$7) | BY30: =MIN(AA29*(1+AA$6/Setup!$C$13),AA$7) | ... DO30: =MIN(BQ29*(1+BQ$6/Setup!$C$13),BQ$7) | DP30: =MIN(T29*(1+T$6/Setup!$C$13)-BR30,$H30) | DQ30: =MIN(U29*(1+U$6/Setup!$C$13)-BS30,MAX(0,$H30-SUM($DP30:DP30))) | DR30: =MIN(V29*(1+V$6/Setup!$C$13)-BT30,MAX(0,$H30-SUM($DP30:DQ30))) | DS30: =MIN(W29*(1+W$6/Setup!$C$13)-BU30,MAX(0,$H30-SUM($DP30:DR30))) | DT30: =MIN(X29*(1+X$6/Setup!$C$13)-BV30,MAX(0,$H30-SUM($DP30:DS30))) | DU30: =MIN(Y29*(1+Y$6/Setup!$C$13)-BW30,MAX(0,$H30-SUM($DP30:DT30))) | DV30: =MIN(Z29*(1+Z$6/Setup!$C$13)-BX30,MAX(0,$H30-SUM($DP30:DU30))) | DW30: =MIN(AA29*(1+AA$6/Setup!$C$13)-BY30,MAX(0,$H30-SUM($DP30:DV30))) | DX30: =MIN(AB29*(1+AB$6/Setup!$C$13)-BZ30,MAX(0,$H30-SUM($DP30:DW30))) | ... FM30: =MIN(BQ29*(1+BQ$6/Setup!$C$13)-DO30,MAX(0,$H30-SUM($DP30:FL30)))
A31: =A30+1 | B31: =IF(Setup!$C$6="Every week",Setup!$C$7+7*(A31-1),IF(Setup!$C$6="Every 2 weeks",Setup!$C$7+14*(A31-1),IF(Setup!$C$6="Every month",EDATE(Setup!$C$7,A31-1),EOMONTH(Setup!$C$7,INT((A31-1+Setup!$C$20)/2)-1)+MIN(IF(MOD(A31-1+Setup!$C$20,2)=0,Setup!$C$18,Setup!$C$19),DAY(EOMONTH(Setup!$C$7,INT((A31-1+Setup!$C$20)/2))))))) | C31: =N('Paycheck Plan'!J27) | D31: =N('Paycheck Plan'!K27) | E31: =MIN(MAX(0,Setup!$C$10-F30),MAX(0,Setup!$C$8+C31-G31)) | F31: =F30+E31 | G31: =MIN(Setup!$C$14,MAX(0,Setup!$C$8+C31)) | H31: =MAX(0,Setup!$C$8+C31-G31-E31)+SUM($T$7:$BQ$7)-SUM(BR31:DO31) | I31: =SUMPRODUCT(T30:BQ30,$T$6:$BQ$6)/Setup!$C$13 | J31: =SUM(T31:BQ31) | K31: =IF(MAX(DP31:FM31)>0,MATCH(MAX(DP31:FM31),DP31:FM31,0),1) | M31: =ROUND(20*$B$2/39,0)+1 | N31: =INDEX($B$10:$B$530,MIN(M31,521)) | O31: =INDEX($J$10:$J$530,MIN(M31,521)) | T31: =MAX(0,T30*(1+T$6/Setup!$C$13)-BR31-DP31)+IF($K31=1,$D31,0) | U31: =MAX(0,U30*(1+U$6/Setup!$C$13)-BS31-DQ31)+IF($K31=2,$D31,0) | V31: =MAX(0,V30*(1+V$6/Setup!$C$13)-BT31-DR31)+IF($K31=3,$D31,0) | W31: =MAX(0,W30*(1+W$6/Setup!$C$13)-BU31-DS31)+IF($K31=4,$D31,0) | X31: =MAX(0,X30*(1+X$6/Setup!$C$13)-BV31-DT31)+IF($K31=5,$D31,0) | Y31: =MAX(0,Y30*(1+Y$6/Setup!$C$13)-BW31-DU31)+IF($K31=6,$D31,0) | Z31: =MAX(0,Z30*(1+Z$6/Setup!$C$13)-BX31-DV31)+IF($K31=7,$D31,0) | AA31: =MAX(0,AA30*(1+AA$6/Setup!$C$13)-BY31-DW31)+IF($K31=8,$D31,0) | AB31: =MAX(0,AB30*(1+AB$6/Setup!$C$13)-BZ31-DX31)+IF($K31=9,$D31,0) | AC31: =MAX(0,AC30*(1+AC$6/Setup!$C$13)-CA31-DY31)+IF($K31=10,$D31,0) | AD31: =MAX(0,AD30*(1+AD$6/Setup!$C$13)-CB31-DZ31)+IF($K31=11,$D31,0) | AE31: =MAX(0,AE30*(1+AE$6/Setup!$C$13)-CC31-EA31)+IF($K31=12,$D31,0) | AF31: =MAX(0,AF30*(1+AF$6/Setup!$C$13)-CD31-EB31)+IF($K31=13,$D31,0) | AG31: =MAX(0,AG30*(1+AG$6/Setup!$C$13)-CE31-EC31)+IF($K31=14,$D31,0) | AH31: =MAX(0,AH30*(1+AH$6/Setup!$C$13)-CF31-ED31)+IF($K31=15,$D31,0) | AI31: =MAX(0,AI30*(1+AI$6/Setup!$C$13)-CG31-EE31)+IF($K31=16,$D31,0) | AJ31: =MAX(0,AJ30*(1+AJ$6/Setup!$C$13)-CH31-EF31)+IF($K31=17,$D31,0) | AK31: =MAX(0,AK30*(1+AK$6/Setup!$C$13)-CI31-EG31)+IF($K31=18,$D31,0) | AL31: =MAX(0,AL30*(1+AL$6/Setup!$C$13)-CJ31-EH31)+IF($K31=19,$D31,0) | AM31: =MAX(0,AM30*(1+AM$6/Setup!$C$13)-CK31-EI31)+IF($K31=20,$D31,0) | AN31: =MAX(0,AN30*(1+AN$6/Setup!$C$13)-CL31-EJ31)+IF($K31=21,$D31,0) | AO31: =MAX(0,AO30*(1+AO$6/Setup!$C$13)-CM31-EK31)+IF($K31=22,$D31,0) | AP31: =MAX(0,AP30*(1+AP$6/Setup!$C$13)-CN31-EL31)+IF($K31=23,$D31,0) | AQ31: =MAX(0,AQ30*(1+AQ$6/Setup!$C$13)-CO31-EM31)+IF($K31=24,$D31,0) | AR31: =MAX(0,AR30*(1+AR$6/Setup!$C$13)-CP31-EN31)+IF($K31=25,$D31,0) | AS31: =MAX(0,AS30*(1+AS$6/Setup!$C$13)-CQ31-EO31)+IF($K31=26,$D31,0) | AT31: =MAX(0,AT30*(1+AT$6/Setup!$C$13)-CR31-EP31)+IF($K31=27,$D31,0) | AU31: =MAX(0,AU30*(1+AU$6/Setup!$C$13)-CS31-EQ31)+IF($K31=28,$D31,0) | AV31: =MAX(0,AV30*(1+AV$6/Setup!$C$13)-CT31-ER31)+IF($K31=29,$D31,0) | AW31: =MAX(0,AW30*(1+AW$6/Setup!$C$13)-CU31-ES31)+IF($K31=30,$D31,0) | AX31: =MAX(0,AX30*(1+AX$6/Setup!$C$13)-CV31-ET31)+IF($K31=31,$D31,0) | AY31: =MAX(0,AY30*(1+AY$6/Setup!$C$13)-CW31-EU31)+IF($K31=32,$D31,0) | AZ31: =MAX(0,AZ30*(1+AZ$6/Setup!$C$13)-CX31-EV31)+IF($K31=33,$D31,0) | BA31: =MAX(0,BA30*(1+BA$6/Setup!$C$13)-CY31-EW31)+IF($K31=34,$D31,0) | BB31: =MAX(0,BB30*(1+BB$6/Setup!$C$13)-CZ31-EX31)+IF($K31=35,$D31,0) | BC31: =MAX(0,BC30*(1+BC$6/Setup!$C$13)-DA31-EY31)+IF($K31=36,$D31,0) | BD31: =MAX(0,BD30*(1+BD$6/Setup!$C$13)-DB31-EZ31)+IF($K31=37,$D31,0) | BE31: =MAX(0,BE30*(1+BE$6/Setup!$C$13)-DC31-FA31)+IF($K31=38,$D31,0) | BF31: =MAX(0,BF30*(1+BF$6/Setup!$C$13)-DD31-FB31)+IF($K31=39,$D31,0) | BG31: =MAX(0,BG30*(1+BG$6/Setup!$C$13)-DE31-FC31)+IF($K31=40,$D31,0) | BH31: =MAX(0,BH30*(1+BH$6/Setup!$C$13)-DF31-FD31)+IF($K31=41,$D31,0) | BI31: =MAX(0,BI30*(1+BI$6/Setup!$C$13)-DG31-FE31)+IF($K31=42,$D31,0) | BJ31: =MAX(0,BJ30*(1+BJ$6/Setup!$C$13)-DH31-FF31)+IF($K31=43,$D31,0) | BK31: =MAX(0,BK30*(1+BK$6/Setup!$C$13)-DI31-FG31)+IF($K31=44,$D31,0) | BL31: =MAX(0,BL30*(1+BL$6/Setup!$C$13)-DJ31-FH31)+IF($K31=45,$D31,0) | BM31: =MAX(0,BM30*(1+BM$6/Setup!$C$13)-DK31-FI31)+IF($K31=46,$D31,0) | BN31: =MAX(0,BN30*(1+BN$6/Setup!$C$13)-DL31-FJ31)+IF($K31=47,$D31,0) | BO31: =MAX(0,BO30*(1+BO$6/Setup!$C$13)-DM31-FK31)+IF($K31=48,$D31,0) | BP31: =MAX(0,BP30*(1+BP$6/Setup!$C$13)-DN31-FL31)+IF($K31=49,$D31,0) | BQ31: =MAX(0,BQ30*(1+BQ$6/Setup!$C$13)-DO31-FM31)+IF($K31=50,$D31,0) | BR31: =MIN(T30*(1+T$6/Setup!$C$13),T$7) | BS31: =MIN(U30*(1+U$6/Setup!$C$13),U$7) | BT31: =MIN(V30*(1+V$6/Setup!$C$13),V$7) | BU31: =MIN(W30*(1+W$6/Setup!$C$13),W$7) | BV31: =MIN(X30*(1+X$6/Setup!$C$13),X$7) | BW31: =MIN(Y30*(1+Y$6/Setup!$C$13),Y$7) | BX31: =MIN(Z30*(1+Z$6/Setup!$C$13),Z$7) | BY31: =MIN(AA30*(1+AA$6/Setup!$C$13),AA$7) | ... DO31: =MIN(BQ30*(1+BQ$6/Setup!$C$13),BQ$7) | DP31: =MIN(T30*(1+T$6/Setup!$C$13)-BR31,$H31) | DQ31: =MIN(U30*(1+U$6/Setup!$C$13)-BS31,MAX(0,$H31-SUM($DP31:DP31))) | DR31: =MIN(V30*(1+V$6/Setup!$C$13)-BT31,MAX(0,$H31-SUM($DP31:DQ31))) | DS31: =MIN(W30*(1+W$6/Setup!$C$13)-BU31,MAX(0,$H31-SUM($DP31:DR31))) | DT31: =MIN(X30*(1+X$6/Setup!$C$13)-BV31,MAX(0,$H31-SUM($DP31:DS31))) | DU31: =MIN(Y30*(1+Y$6/Setup!$C$13)-BW31,MAX(0,$H31-SUM($DP31:DT31))) | DV31: =MIN(Z30*(1+Z$6/Setup!$C$13)-BX31,MAX(0,$H31-SUM($DP31:DU31))) | DW31: =MIN(AA30*(1+AA$6/Setup!$C$13)-BY31,MAX(0,$H31-SUM($DP31:DV31))) | DX31: =MIN(AB30*(1+AB$6/Setup!$C$13)-BZ31,MAX(0,$H31-SUM($DP31:DW31))) | ... FM31: =MIN(BQ30*(1+BQ$6/Setup!$C$13)-DO31,MAX(0,$H31-SUM($DP31:FL31)))
A32: =A31+1 | B32: =IF(Setup!$C$6="Every week",Setup!$C$7+7*(A32-1),IF(Setup!$C$6="Every 2 weeks",Setup!$C$7+14*(A32-1),IF(Setup!$C$6="Every month",EDATE(Setup!$C$7,A32-1),EOMONTH(Setup!$C$7,INT((A32-1+Setup!$C$20)/2)-1)+MIN(IF(MOD(A32-1+Setup!$C$20,2)=0,Setup!$C$18,Setup!$C$19),DAY(EOMONTH(Setup!$C$7,INT((A32-1+Setup!$C$20)/2))))))) | C32: =N('Paycheck Plan'!J28) | D32: =N('Paycheck Plan'!K28) | E32: =MIN(MAX(0,Setup!$C$10-F31),MAX(0,Setup!$C$8+C32-G32)) | F32: =F31+E32 | G32: =MIN(Setup!$C$14,MAX(0,Setup!$C$8+C32)) | H32: =MAX(0,Setup!$C$8+C32-G32-E32)+SUM($T$7:$BQ$7)-SUM(BR32:DO32) | I32: =SUMPRODUCT(T31:BQ31,$T$6:$BQ$6)/Setup!$C$13 | J32: =SUM(T32:BQ32) | K32: =IF(MAX(DP32:FM32)>0,MATCH(MAX(DP32:FM32),DP32:FM32,0),1) | M32: =ROUND(21*$B$2/39,0)+1 | N32: =INDEX($B$10:$B$530,MIN(M32,521)) | O32: =INDEX($J$10:$J$530,MIN(M32,521)) | T32: =MAX(0,T31*(1+T$6/Setup!$C$13)-BR32-DP32)+IF($K32=1,$D32,0) | U32: =MAX(0,U31*(1+U$6/Setup!$C$13)-BS32-DQ32)+IF($K32=2,$D32,0) | V32: =MAX(0,V31*(1+V$6/Setup!$C$13)-BT32-DR32)+IF($K32=3,$D32,0) | W32: =MAX(0,W31*(1+W$6/Setup!$C$13)-BU32-DS32)+IF($K32=4,$D32,0) | X32: =MAX(0,X31*(1+X$6/Setup!$C$13)-BV32-DT32)+IF($K32=5,$D32,0) | Y32: =MAX(0,Y31*(1+Y$6/Setup!$C$13)-BW32-DU32)+IF($K32=6,$D32,0) | Z32: =MAX(0,Z31*(1+Z$6/Setup!$C$13)-BX32-DV32)+IF($K32=7,$D32,0) | AA32: =MAX(0,AA31*(1+AA$6/Setup!$C$13)-BY32-DW32)+IF($K32=8,$D32,0) | AB32: =MAX(0,AB31*(1+AB$6/Setup!$C$13)-BZ32-DX32)+IF($K32=9,$D32,0) | AC32: =MAX(0,AC31*(1+AC$6/Setup!$C$13)-CA32-DY32)+IF($K32=10,$D32,0) | AD32: =MAX(0,AD31*(1+AD$6/Setup!$C$13)-CB32-DZ32)+IF($K32=11,$D32,0) | AE32: =MAX(0,AE31*(1+AE$6/Setup!$C$13)-CC32-EA32)+IF($K32=12,$D32,0) | AF32: =MAX(0,AF31*(1+AF$6/Setup!$C$13)-CD32-EB32)+IF($K32=13,$D32,0) | AG32: =MAX(0,AG31*(1+AG$6/Setup!$C$13)-CE32-EC32)+IF($K32=14,$D32,0) | AH32: =MAX(0,AH31*(1+AH$6/Setup!$C$13)-CF32-ED32)+IF($K32=15,$D32,0) | AI32: =MAX(0,AI31*(1+AI$6/Setup!$C$13)-CG32-EE32)+IF($K32=16,$D32,0) | AJ32: =MAX(0,AJ31*(1+AJ$6/Setup!$C$13)-CH32-EF32)+IF($K32=17,$D32,0) | AK32: =MAX(0,AK31*(1+AK$6/Setup!$C$13)-CI32-EG32)+IF($K32=18,$D32,0) | AL32: =MAX(0,AL31*(1+AL$6/Setup!$C$13)-CJ32-EH32)+IF($K32=19,$D32,0) | AM32: =MAX(0,AM31*(1+AM$6/Setup!$C$13)-CK32-EI32)+IF($K32=20,$D32,0) | AN32: =MAX(0,AN31*(1+AN$6/Setup!$C$13)-CL32-EJ32)+IF($K32=21,$D32,0) | AO32: =MAX(0,AO31*(1+AO$6/Setup!$C$13)-CM32-EK32)+IF($K32=22,$D32,0) | AP32: =MAX(0,AP31*(1+AP$6/Setup!$C$13)-CN32-EL32)+IF($K32=23,$D32,0) | AQ32: =MAX(0,AQ31*(1+AQ$6/Setup!$C$13)-CO32-EM32)+IF($K32=24,$D32,0) | AR32: =MAX(0,AR31*(1+AR$6/Setup!$C$13)-CP32-EN32)+IF($K32=25,$D32,0) | AS32: =MAX(0,AS31*(1+AS$6/Setup!$C$13)-CQ32-EO32)+IF($K32=26,$D32,0) | AT32: =MAX(0,AT31*(1+AT$6/Setup!$C$13)-CR32-EP32)+IF($K32=27,$D32,0) | AU32: =MAX(0,AU31*(1+AU$6/Setup!$C$13)-CS32-EQ32)+IF($K32=28,$D32,0) | AV32: =MAX(0,AV31*(1+AV$6/Setup!$C$13)-CT32-ER32)+IF($K32=29,$D32,0) | AW32: =MAX(0,AW31*(1+AW$6/Setup!$C$13)-CU32-ES32)+IF($K32=30,$D32,0) | AX32: =MAX(0,AX31*(1+AX$6/Setup!$C$13)-CV32-ET32)+IF($K32=31,$D32,0) | AY32: =MAX(0,AY31*(1+AY$6/Setup!$C$13)-CW32-EU32)+IF($K32=32,$D32,0) | AZ32: =MAX(0,AZ31*(1+AZ$6/Setup!$C$13)-CX32-EV32)+IF($K32=33,$D32,0) | BA32: =MAX(0,BA31*(1+BA$6/Setup!$C$13)-CY32-EW32)+IF($K32=34,$D32,0) | BB32: =MAX(0,BB31*(1+BB$6/Setup!$C$13)-CZ32-EX32)+IF($K32=35,$D32,0) | BC32: =MAX(0,BC31*(1+BC$6/Setup!$C$13)-DA32-EY32)+IF($K32=36,$D32,0) | BD32: =MAX(0,BD31*(1+BD$6/Setup!$C$13)-DB32-EZ32)+IF($K32=37,$D32,0) | BE32: =MAX(0,BE31*(1+BE$6/Setup!$C$13)-DC32-FA32)+IF($K32=38,$D32,0) | BF32: =MAX(0,BF31*(1+BF$6/Setup!$C$13)-DD32-FB32)+IF($K32=39,$D32,0) | BG32: =MAX(0,BG31*(1+BG$6/Setup!$C$13)-DE32-FC32)+IF($K32=40,$D32,0) | BH32: =MAX(0,BH31*(1+BH$6/Setup!$C$13)-DF32-FD32)+IF($K32=41,$D32,0) | BI32: =MAX(0,BI31*(1+BI$6/Setup!$C$13)-DG32-FE32)+IF($K32=42,$D32,0) | BJ32: =MAX(0,BJ31*(1+BJ$6/Setup!$C$13)-DH32-FF32)+IF($K32=43,$D32,0) | BK32: =MAX(0,BK31*(1+BK$6/Setup!$C$13)-DI32-FG32)+IF($K32=44,$D32,0) | BL32: =MAX(0,BL31*(1+BL$6/Setup!$C$13)-DJ32-FH32)+IF($K32=45,$D32,0) | BM32: =MAX(0,BM31*(1+BM$6/Setup!$C$13)-DK32-FI32)+IF($K32=46,$D32,0) | BN32: =MAX(0,BN31*(1+BN$6/Setup!$C$13)-DL32-FJ32)+IF($K32=47,$D32,0) | BO32: =MAX(0,BO31*(1+BO$6/Setup!$C$13)-DM32-FK32)+IF($K32=48,$D32,0) | BP32: =MAX(0,BP31*(1+BP$6/Setup!$C$13)-DN32-FL32)+IF($K32=49,$D32,0) | BQ32: =MAX(0,BQ31*(1+BQ$6/Setup!$C$13)-DO32-FM32)+IF($K32=50,$D32,0) | BR32: =MIN(T31*(1+T$6/Setup!$C$13),T$7) | BS32: =MIN(U31*(1+U$6/Setup!$C$13),U$7) | BT32: =MIN(V31*(1+V$6/Setup!$C$13),V$7) | BU32: =MIN(W31*(1+W$6/Setup!$C$13),W$7) | BV32: =MIN(X31*(1+X$6/Setup!$C$13),X$7) | BW32: =MIN(Y31*(1+Y$6/Setup!$C$13),Y$7) | BX32: =MIN(Z31*(1+Z$6/Setup!$C$13),Z$7) | BY32: =MIN(AA31*(1+AA$6/Setup!$C$13),AA$7) | ... DO32: =MIN(BQ31*(1+BQ$6/Setup!$C$13),BQ$7) | DP32: =MIN(T31*(1+T$6/Setup!$C$13)-BR32,$H32) | DQ32: =MIN(U31*(1+U$6/Setup!$C$13)-BS32,MAX(0,$H32-SUM($DP32:DP32))) | DR32: =MIN(V31*(1+V$6/Setup!$C$13)-BT32,MAX(0,$H32-SUM($DP32:DQ32))) | DS32: =MIN(W31*(1+W$6/Setup!$C$13)-BU32,MAX(0,$H32-SUM($DP32:DR32))) | DT32: =MIN(X31*(1+X$6/Setup!$C$13)-BV32,MAX(0,$H32-SUM($DP32:DS32))) | DU32: =MIN(Y31*(1+Y$6/Setup!$C$13)-BW32,MAX(0,$H32-SUM($DP32:DT32))) | DV32: =MIN(Z31*(1+Z$6/Setup!$C$13)-BX32,MAX(0,$H32-SUM($DP32:DU32))) | DW32: =MIN(AA31*(1+AA$6/Setup!$C$13)-BY32,MAX(0,$H32-SUM($DP32:DV32))) | DX32: =MIN(AB31*(1+AB$6/Setup!$C$13)-BZ32,MAX(0,$H32-SUM($DP32:DW32))) | ... FM32: =MIN(BQ31*(1+BQ$6/Setup!$C$13)-DO32,MAX(0,$H32-SUM($DP32:FL32)))
